{
  "type": "Feature",
  "properties": {
    "gn:admin1_code":"15.0",
    "gn:admin2_code":"3720823.0",
    "gn:asciiname":"Le Blanc",
    "gn:country_code":"HT",
    "gn:dem":409,
    "gn:feature_class":"P",
    "gn:feature_code":"PPL",
    "gn:name":"Le Blanc",
    "gn:population":0,
    "gn:timezone":"America/Port-au-Prince",
    "iso:country":"HT",
    "name:bar_x_preferred":[
        "Le Blanc"
    ],
    "name:bre_x_preferred":[
        "Le Blanc"
    ],
    "name:cat_x_preferred":[
        "Le Blanc"
    ],
    "name:ceb_x_preferred":[
        "Le Blanc"
    ],
    "name:ces_x_preferred":[
        "Le Blanc"
    ],
    "name:deu_x_preferred":[
        "Le Blanc"
    ],
    "name:epo_x_preferred":[
        "Le Blanc"
    ],
    "name:est_x_preferred":[
        "Le Blanc"
    ],
    "name:eus_x_preferred":[
        "Le Blanc"
    ],
    "name:fas_x_preferred":[
        "\u0644 \u0628\u0644\u0627\u0646"
    ],
    "name:fin_x_preferred":[
        "Le Blanc"
    ],
    "name:fra_x_preferred":[
        "Le Blanc"
    ],
    "name:hun_x_preferred":[
        "Le Blanc"
    ],
    "name:ita_x_preferred":[
        "Le Blanc"
    ],
    "name:jpn_x_preferred":[
        "\u30eb\u30fb\u30d6\u30e9\u30f3"
    ],
    "name:kor_x_preferred":[
        "\ub974\ube14\ub791"
    ],
    "name:lat_x_preferred":[
        "Oblincum"
    ],
    "name:mlg_x_preferred":[
        "Le Blanc"
    ],
    "name:msa_x_preferred":[
        "Le Blanc"
    ],
    "name:nld_x_preferred":[
        "Le Blanc"
    ],
    "name:nno_x_preferred":[
        "Le Blanc"
    ],
    "name:oci_x_preferred":[
        "Le Blanc"
    ],
    "name:pms_x_preferred":[
        "Le Blanc"
    ],
    "name:pol_x_preferred":[
        "Le Blanc"
    ],
    "name:por_x_preferred":[
        "Le Blanc"
    ],
    "name:ron_x_preferred":[
        "Le Blanc"
    ],
    "name:rus_x_preferred":[
        "\u041b\u0435-\u0411\u043b\u0430\u043d"
    ],
    "name:slk_x_preferred":[
        "Le Blanc"
    ],
    "name:slv_x_preferred":[
        "Le Blanc"
    ],
    "name:spa_x_preferred":[
        "Le Blanc"
    ],
    "name:srp_x_preferred":[
        "\u0411\u043b\u0430\u043d"
    ],
    "name:swe_x_preferred":[
        "Le Blanc"
    ],
    "name:ukr_x_preferred":[
        "\u041b\u0435-\u0411\u043b\u0430\u043d"
    ],
    "name:uzb_x_preferred":[
        "Le Blanc"
    ],
    "name:vie_x_preferred":[
        "Le Blanc"
    ],
    "name:vol_x_preferred":[
        "Le Blanc"
    ],
    "name:war_x_preferred":[
        "Le Blanc"
    ],
    "name:zho_x_preferred":[
        "\u52d2\u5e03\u6717"
    ],
    "wof:name":"Le Blanc",
    "wof:placetype":"locality"
},
  "geometry": {"coordinates":[-73.23333000000002,18.38333],"type":"Point"}
}