{
  "type": "Feature",
  "properties": {
    "gn:admin1_code":"15.0",
    "gn:asciiname":"Belivert",
    "gn:country_code":"HT",
    "gn:dem":428,
    "gn:feature_class":"P",
    "gn:feature_code":"PPL",
    "gn:name":"B\u00e9livert",
    "gn:population":0,
    "gn:timezone":"America/Port-au-Prince",
    "iso:country":"HT",
    "name:fra_x_preferred":[
        "B\u00e9livert"
    ],
    "wof:name":"Belivert",
    "wof:placetype":"locality"
},
  "geometry": {"coordinates":[-73.03482,18.30877000000001],"type":"Point"}
}