{
  "type": "Feature",
  "properties": {
    "gn:admin1_code":"3.0",
    "gn:admin2_code":"3718419.0",
    "gn:asciiname":"Mare Plate",
    "gn:country_code":"HT",
    "gn:dem":33,
    "gn:feature_class":"P",
    "gn:feature_code":"PPL",
    "gn:name":"Mare Plate",
    "gn:population":0,
    "gn:timezone":"America/Port-au-Prince",
    "iso:country":"HT",
    "name:fra_x_preferred":[
        "Mare Plate"
    ],
    "wof:name":"Mare Plate",
    "wof:placetype":"locality"
},
  "geometry": {"coordinates":[-72.96381,19.87352000000001],"type":"Point"}
}