{
  "type": "Feature",
  "properties": {
    "gn:admin1_code":"9.0",
    "gn:admin2_code":"3717545.0",
    "gn:asciiname":"Mathurin",
    "gn:country_code":"HT",
    "gn:dem":961,
    "gn:feature_class":"P",
    "gn:feature_code":"PPL",
    "gn:name":"Mathurin",
    "gn:population":0,
    "gn:timezone":"America/Port-au-Prince",
    "iso:country":"HT",
    "wof:name":"Mathurin",
    "wof:placetype":"locality"
},
  "geometry": {"coordinates":[-72.18333,19.46667],"type":"Point"}
}