{
  "type": "Feature",
  "properties": {
    "gn:admin1_code":"11.0",
    "gn:admin2_code":"3723019.0",
    "gn:asciiname":"Nan Canne",
    "gn:country_code":"HT",
    "gn:dem":583,
    "gn:feature_class":"P",
    "gn:feature_code":"PPL",
    "gn:name":"Nan Canne",
    "gn:population":0,
    "gn:timezone":"America/Port-au-Prince",
    "iso:country":"HT",
    "name:fra_x_preferred":[
        "Nan Canne"
    ],
    "wof:name":"Nan Canne",
    "wof:placetype":"locality"
},
  "geometry": {"coordinates":[-72.95418000000002,18.76035],"type":"Point"}
}