{
  "type": "Feature",
  "properties": {
    "gn:admin1_code":"6.0",
    "gn:admin2_code":"3726539.0",
    "gn:asciiname":"Borin",
    "gn:country_code":"HT",
    "gn:dem":23,
    "gn:feature_class":"P",
    "gn:feature_code":"PPL",
    "gn:name":"Borin",
    "gn:population":0,
    "gn:timezone":"America/Port-au-Prince",
    "iso:country":"HT",
    "name:fra_x_preferred":[
        "Borin"
    ],
    "wof:name":"Borin",
    "wof:placetype":"locality"
},
  "geometry": {"coordinates":[-72.49628,19.25269],"type":"Point"}
}