{
  "type": "Feature",
  "properties": {
    "gn:admin1_code":"13.0",
    "gn:admin2_code":"3730361.0",
    "gn:asciiname":"Platon Pistache",
    "gn:country_code":"HT",
    "gn:dem":1081,
    "gn:feature_class":"P",
    "gn:feature_code":"PPL",
    "gn:name":"Platon Pistache",
    "gn:population":0,
    "gn:timezone":"America/Port-au-Prince",
    "iso:country":"HT",
    "name:fra_x_preferred":[
        "Platon Pistache"
    ],
    "wof:name":"Platon Pistache",
    "wof:placetype":"locality"
},
  "geometry": {"coordinates":[-71.77253,18.23211],"type":"Point"}
}