{
  "type": "Feature",
  "properties": {
    "gn:admin1_code":"3.0",
    "gn:admin2_code":"3720764.0",
    "gn:asciiname":"Nan Remy",
    "gn:country_code":"HT",
    "gn:dem":74,
    "gn:feature_class":"P",
    "gn:feature_code":"PPL",
    "gn:name":"Nan R\u00e9my",
    "gn:population":0,
    "gn:timezone":"America/Port-au-Prince",
    "iso:country":"HT",
    "wof:name":"Nan Remy",
    "wof:placetype":"locality"
},
  "geometry": {"coordinates":[-73.00721999999998,19.85667],"type":"Point"}
}