{
  "type": "Feature",
  "properties": {
    "gn:admin1_code":"12.0",
    "gn:admin2_code":"3728096.0",
    "gn:asciiname":"Boulmier",
    "gn:country_code":"HT",
    "gn:dem":26,
    "gn:feature_class":"P",
    "gn:feature_code":"PPL",
    "gn:name":"Boulmier",
    "gn:population":0,
    "gn:timezone":"America/Port-au-Prince",
    "iso:country":"HT",
    "name:fra_x_preferred":[
        "Boulmier"
    ],
    "wof:name":"Boulmier",
    "wof:placetype":"locality"
},
  "geometry": {"coordinates":[-73.70506999999998,18.2655],"type":"Point"}
}