{
  "type": "Feature",
  "properties": {
    "gn:admin1_code":"12.0",
    "gn:admin2_code":"3727295.0",
    "gn:asciiname":"Ravine au Diable",
    "gn:country_code":"HT",
    "gn:dem":372,
    "gn:feature_class":"P",
    "gn:feature_code":"PPL",
    "gn:name":"Ravine au Diable",
    "gn:population":0,
    "gn:timezone":"America/Port-au-Prince",
    "iso:country":"HT",
    "wof:name":"Ravine au Diable",
    "wof:placetype":"locality"
},
  "geometry": {"coordinates":[-74.01666999999998,18.23333],"type":"Point"}
}