{
  "type": "Feature",
  "properties": {
    "gn:admin1_code":"13.0",
    "gn:admin2_code":"3723778.0",
    "gn:asciiname":"Michel",
    "gn:country_code":"HT",
    "gn:dem":388,
    "gn:feature_class":"P",
    "gn:feature_code":"PPL",
    "gn:name":"Michel",
    "gn:population":0,
    "gn:timezone":"America/Port-au-Prince",
    "iso:country":"HT",
    "name:ceb_x_preferred":[
        "Michel"
    ],
    "name:ces_x_preferred":[
        "Michel"
    ],
    "name:deu_x_preferred":[
        "Michel"
    ],
    "name:heb_x_preferred":[
        "\u05de\u05d9\u05e9\u05dc"
    ],
    "name:hsb_x_preferred":[
        "Michel"
    ],
    "name:ita_x_preferred":[
        "Michel"
    ],
    "name:jpn_x_preferred":[
        "\u30df\u30b7\u30a7\u30eb"
    ],
    "name:nld_x_preferred":[
        "Michel"
    ],
    "name:slv_x_preferred":[
        "Michel"
    ],
    "name:spa_x_preferred":[
        "Michel"
    ],
    "name:swe_x_preferred":[
        "Michel"
    ],
    "wof:name":"Michel",
    "wof:placetype":"locality"
},
  "geometry": {"coordinates":[-72.44083000000001,18.25722],"type":"Point"}
}