{
  "type": "Feature",
  "properties": {
    "gn:admin1_code":"12.0",
    "gn:admin2_code":"3728096.0",
    "gn:asciiname":"Sous Byran",
    "gn:country_code":"HT",
    "gn:dem":174,
    "gn:feature_class":"P",
    "gn:feature_code":"PPL",
    "gn:name":"Sous Byran",
    "gn:population":0,
    "gn:timezone":"America/Port-au-Prince",
    "iso:country":"HT",
    "wof:name":"Sous Byran",
    "wof:placetype":"locality"
},
  "geometry": {"coordinates":[-73.83333,18.31667],"type":"Point"}
}