{
  "type": "Feature",
  "properties": {
    "gn:admin1_code":"10.0",
    "gn:admin2_code":"3725169.0",
    "gn:asciiname":"Nan Cotton",
    "gn:country_code":"HT",
    "gn:dem":82,
    "gn:feature_class":"P",
    "gn:feature_code":"PPL",
    "gn:name":"Nan Cotton",
    "gn:population":0,
    "gn:timezone":"America/Port-au-Prince",
    "iso:country":"HT",
    "wof:name":"Nan Cotton",
    "wof:placetype":"locality"
},
  "geometry": {"coordinates":[-71.84999999999999,19.55],"type":"Point"}
}