{
  "type": "Feature",
  "properties": {
    "gn:admin1_code":"3.0",
    "gn:admin2_code":"3720764.0",
    "gn:asciiname":"Nan Saut",
    "gn:country_code":"HT",
    "gn:dem":229,
    "gn:feature_class":"P",
    "gn:feature_code":"PPL",
    "gn:name":"Nan Saut",
    "gn:population":0,
    "gn:timezone":"America/Port-au-Prince",
    "iso:country":"HT",
    "name:fra_x_preferred":[
        "Nan Saut"
    ],
    "wof:name":"Nan Saut",
    "wof:placetype":"locality"
},
  "geometry": {"coordinates":[-73.2201,19.81609],"type":"Point"}
}