{
  "type": "Feature",
  "properties": {
    "gn:admin1_code":"7.0",
    "gn:asciiname":"Caille Jour",
    "gn:country_code":"HT",
    "gn:dem":861,
    "gn:feature_class":"P",
    "gn:feature_code":"PPL",
    "gn:name":"Caille Jour",
    "gn:population":0,
    "gn:timezone":"America/Port-au-Prince",
    "iso:country":"HT",
    "name:fra_x_preferred":[
        "Caille Jour"
    ],
    "wof:name":"Caille Jour",
    "wof:placetype":"locality"
},
  "geometry": {"coordinates":[-72.2432,19.02195],"type":"Point"}
}