{
  "type": "Feature",
  "properties": {
    "gn:admin1_code":"15.0",
    "gn:admin2_code":"3731122.0",
    "gn:asciiname":"Paien",
    "gn:country_code":"HT",
    "gn:dem":362,
    "gn:feature_class":"P",
    "gn:feature_code":"PPL",
    "gn:name":"Pa\u00efen",
    "gn:population":0,
    "gn:timezone":"America/Port-au-Prince",
    "iso:country":"HT",
    "name:fra_x_preferred":[
        "Pa\u00efen"
    ],
    "wof:name":"Paien",
    "wof:placetype":"locality"
},
  "geometry": {"coordinates":[-73.53601999999999,18.40471],"type":"Point"}
}