{
  "type": "Feature",
  "properties": {
    "gn:admin1_code":"6.0",
    "gn:admin2_code":"3724695.0",
    "gn:asciiname":"Dumas",
    "gn:country_code":"HT",
    "gn:dem":651,
    "gn:feature_class":"P",
    "gn:feature_code":"PPL",
    "gn:name":"Dumas",
    "gn:population":0,
    "gn:timezone":"America/Port-au-Prince",
    "iso:country":"HT",
    "name:ceb_x_preferred":[
        "Dumas"
    ],
    "name:ces_x_preferred":[
        "Dumas"
    ],
    "name:dan_x_preferred":[
        "Dumas"
    ],
    "name:deu_x_preferred":[
        "Dumas"
    ],
    "name:est_x_preferred":[
        "Dumas"
    ],
    "name:fin_x_preferred":[
        "Dumas"
    ],
    "name:fra_x_preferred":[
        "Dumas"
    ],
    "name:hun_x_preferred":[
        "Dumas"
    ],
    "name:ido_x_preferred":[
        "Dumas"
    ],
    "name:ita_x_preferred":[
        "Dumas"
    ],
    "name:jpn_x_preferred":[
        "\u30c7\u30e5\u30de"
    ],
    "name:kat_x_preferred":[
        "\u10d3\u10d8\u10e3\u10db\u10d0"
    ],
    "name:nds_x_preferred":[
        "Dumas"
    ],
    "name:nld_x_preferred":[
        "Dumas"
    ],
    "name:pol_x_preferred":[
        "Dumas"
    ],
    "name:por_x_preferred":[
        "Dumas"
    ],
    "name:rus_x_preferred":[
        "\u0414\u044e\u043c\u0430"
    ],
    "name:spa_x_preferred":[
        "Dumas"
    ],
    "name:swe_x_preferred":[
        "Dumas"
    ],
    "name:tat_x_preferred":[
        "\u0414\u044e\u043c\u0430"
    ],
    "name:tgl_x_preferred":[
        "Dumas"
    ],
    "name:ukr_x_preferred":[
        "\u0414\u044e\u043c\u0430"
    ],
    "name:vol_x_preferred":[
        "Dumas"
    ],
    "wof:name":"Dumas",
    "wof:placetype":"locality"
},
  "geometry": {"coordinates":[-72.36667,19.46667],"type":"Point"}
}