{
  "type": "Feature",
  "properties": {
    "gn:admin1_code":"6.0",
    "gn:admin2_code":"3724695.0",
    "gn:asciiname":"Dumas",
    "gn:country_code":"HT",
    "gn:dem":651,
    "gn:feature_class":"P",
    "gn:feature_code":"PPL",
    "gn:name":"Dumas",
    "gn:population":0,
    "gn:timezone":"America/Port-au-Prince",
    "iso:country":"HT",
    "name:ben_x_preferred":[
        "\u09a1\u09c1\u09ae\u09be\u09b8"
    ],
    "name:ceb_x_preferred":[
        "Dumas"
    ],
    "name:ces_x_preferred":[
        "Dumas"
    ],
    "name:dan_x_preferred":[
        "Dumas"
    ],
    "name:deu_x_preferred":[
        "Dumas"
    ],
    "name:ell_x_preferred":[
        "\u039d\u03c4\u03bf\u03cd\u03bc\u03b1\u03c2"
    ],
    "name:est_x_preferred":[
        "Dumas"
    ],
    "name:fin_x_preferred":[
        "Dumas"
    ],
    "name:fra_x_preferred":[
        "Dumas"
    ],
    "name:heb_x_preferred":[
        "\u05d3\u05d5\u05de\u05d0\u05e1"
    ],
    "name:hin_x_preferred":[
        "\u0921\u094d\u092f\u0942\u092e\u0938"
    ],
    "name:hun_x_preferred":[
        "Dumas"
    ],
    "name:ido_x_preferred":[
        "Dumas"
    ],
    "name:ind_x_preferred":[
        "Dumas"
    ],
    "name:ita_x_preferred":[
        "Dumas"
    ],
    "name:jpn_x_preferred":[
        "\u30c7\u30e5\u30de"
    ],
    "name:kat_x_preferred":[
        "\u10d3\u10d8\u10e3\u10db\u10d0"
    ],
    "name:kor_x_preferred":[
        "\ub4a4\ub9c8"
    ],
    "name:nds_x_preferred":[
        "Dumas"
    ],
    "name:nld_x_preferred":[
        "Dumas"
    ],
    "name:pol_x_preferred":[
        "Dumas"
    ],
    "name:por_x_preferred":[
        "Dumas"
    ],
    "name:rus_x_preferred":[
        "\u0414\u044e\u043c\u0430"
    ],
    "name:spa_x_preferred":[
        "Dumas"
    ],
    "name:swe_x_preferred":[
        "Dumas"
    ],
    "name:tat_x_preferred":[
        "\u0414\u044e\u043c\u0430"
    ],
    "name:tgl_x_preferred":[
        "Dumas"
    ],
    "name:ukr_x_preferred":[
        "\u0414\u044e\u043c\u0430"
    ],
    "name:urd_x_preferred":[
        "\u0688\u0648\u0645\u0627\u0633"
    ],
    "name:vol_x_preferred":[
        "Dumas"
    ],
    "wof:name":"Dumas",
    "wof:placetype":"locality"
},
  "geometry": {"coordinates":[-72.36667,19.46667],"type":"Point"}
}