{
  "type": "Feature",
  "properties": {
    "gn:admin1_code":"9.0",
    "gn:admin2_code":"3728473.0",
    "gn:asciiname":"Barriere Bouteille",
    "gn:country_code":"HT",
    "gn:dem":79,
    "gn:feature_class":"P",
    "gn:feature_code":"PPL",
    "gn:name":"Barri\u00e8re Bouteille",
    "gn:population":0,
    "gn:timezone":"America/Port-au-Prince",
    "iso:country":"HT",
    "wof:name":"Barriere Bouteille",
    "wof:placetype":"locality"
},
  "geometry": {"coordinates":[-72.21306,19.75],"type":"Point"}
}