{
  "type": "Feature",
  "properties": {
    "gn:admin1_code":"11.0",
    "gn:admin2_code":"3718425.0",
    "gn:asciiname":"Bellevue",
    "gn:country_code":"HT",
    "gn:dem":414,
    "gn:feature_class":"P",
    "gn:feature_code":"PPL",
    "gn:name":"Bellevue",
    "gn:population":0,
    "gn:timezone":"America/Port-au-Prince",
    "iso:country":"HT",
    "name:fra_x_preferred":[
        "Bellevue"
    ],
    "wof:name":"Bellevue",
    "wof:placetype":"locality"
},
  "geometry": {"coordinates":[-72.44490999999999,18.48426],"type":"Point"}
}