{
  "type": "Feature",
  "properties": {
    "gn:admin1_code":"6.0",
    "gn:admin2_code":"3717587.0",
    "gn:asciiname":"Rondeau",
    "gn:country_code":"HT",
    "gn:dem":577,
    "gn:feature_class":"P",
    "gn:feature_code":"PPL",
    "gn:name":"Rondeau",
    "gn:population":0,
    "gn:timezone":"America/Port-au-Prince",
    "iso:country":"HT",
    "name:und_x_variant":[
        "Rondo",
        "Rondeau"
    ],
    "wof:name":"Rondeau",
    "wof:placetype":"locality"
},
  "geometry": {"coordinates":[-72.40562,18.93155],"type":"Point"}
}