{
  "type": "Feature",
  "properties": {
    "gn:admin1_code":"6.0",
    "gn:admin2_code":"3717587.0",
    "gn:asciiname":"Rondeau",
    "gn:country_code":"HT",
    "gn:dem":577,
    "gn:feature_class":"P",
    "gn:feature_code":"PPL",
    "gn:name":"Rondeau",
    "gn:population":0,
    "gn:timezone":"America/Port-au-Prince",
    "iso:country":"HT",
    "name:deu_x_preferred":[
        "Rondeau"
    ],
    "name:ell_x_preferred":[
        "\u03a1\u03bf\u03bd\u03c4\u03ad\u03bb\u03bf"
    ],
    "name:fra_x_preferred":[
        "Rondeau"
    ],
    "name:hye_x_preferred":[
        "\u054c\u0578\u0576\u0564\u0578"
    ],
    "name:ita_x_preferred":[
        "Rondeau"
    ],
    "name:nds_x_preferred":[
        "Rondeau"
    ],
    "name:rus_x_preferred":[
        "\u0420\u043e\u043d\u0434\u043e"
    ],
    "name:spa_x_preferred":[
        "Rondeau"
    ],
    "name:und_x_variant":[
        "Rondo"
    ],
    "wof:name":"Rondeau",
    "wof:placetype":"locality"
},
  "geometry": {"coordinates":[-72.40562,18.93155],"type":"Point"}
}