{
  "type": "Feature",
  "properties": {
    "gn:admin1_code":"7.0",
    "gn:admin2_code":"3723840.0",
    "gn:asciiname":"La Hoye",
    "gn:country_code":"HT",
    "gn:dem":263,
    "gn:feature_class":"P",
    "gn:feature_code":"PPL",
    "gn:name":"La Hoye",
    "gn:population":0,
    "gn:timezone":"America/Port-au-Prince",
    "iso:country":"HT",
    "name:fra_x_preferred":[
        "La Hoye"
    ],
    "wof:name":"La Hoye",
    "wof:placetype":"locality"
},
  "geometry": {"coordinates":[-71.93611,18.95008],"type":"Point"}
}