{
  "type": "Feature",
  "properties": {
    "gn:admin1_code":"9.0",
    "gn:admin2_code":"3722122.0",
    "gn:asciiname":"La Croix",
    "gn:country_code":"HT",
    "gn:dem":43,
    "gn:feature_class":"P",
    "gn:feature_code":"PPL",
    "gn:name":"La Croix",
    "gn:population":0,
    "gn:timezone":"America/Port-au-Prince",
    "iso:country":"HT",
    "name:fra_x_preferred":[
        "La Croix"
    ],
    "wof:name":"La Croix",
    "wof:placetype":"locality"
},
  "geometry": {"coordinates":[-72.41218000000001,19.69006],"type":"Point"}
}