{
  "type": "Feature",
  "properties": {
    "gn:admin1_code":"10.0",
    "gn:admin2_code":"3719435.0",
    "gn:asciiname":"Godin",
    "gn:country_code":"HT",
    "gn:dem":677,
    "gn:feature_class":"P",
    "gn:feature_code":"PPL",
    "gn:name":"Godin",
    "gn:population":0,
    "gn:timezone":"America/Port-au-Prince",
    "iso:country":"HT",
    "name:ceb_x_preferred":[
        "Godin"
    ],
    "name:deu_x_preferred":[
        "Godin"
    ],
    "name:fra_x_preferred":[
        "Godin"
    ],
    "name:ita_x_preferred":[
        "Godin"
    ],
    "name:lav_x_preferred":[
        "God\u0113ns"
    ],
    "name:nld_x_preferred":[
        "Godin"
    ],
    "name:pol_x_preferred":[
        "Godin"
    ],
    "name:rus_x_preferred":[
        "\u0413\u043e\u0434\u0438\u043d"
    ],
    "wof:name":"Godin",
    "wof:placetype":"locality"
},
  "geometry": {"coordinates":[-71.76666999999998,19.38333],"type":"Point"}
}