{
  "type": "Feature",
  "properties": {
    "gn:admin1_code":"15.0",
    "gn:admin2_code":"3731122.0",
    "gn:asciiname":"Morne Deboire",
    "gn:country_code":"HT",
    "gn:dem":341,
    "gn:feature_class":"P",
    "gn:feature_code":"PPL",
    "gn:name":"Morne D\u00e9boire",
    "gn:population":0,
    "gn:timezone":"America/Port-au-Prince",
    "iso:country":"HT",
    "wof:name":"Morne Deboire",
    "wof:placetype":"locality"
},
  "geometry": {"coordinates":[-73.41667,18.45],"type":"Point"}
}