{
  "type": "Feature",
  "properties": {
    "gn:admin1_code":"9.0",
    "gn:admin2_code":"3717545.0",
    "gn:asciiname":"Jean Laurent",
    "gn:country_code":"HT",
    "gn:dem":376,
    "gn:feature_class":"P",
    "gn:feature_code":"PPL",
    "gn:name":"Jean Laurent",
    "gn:population":0,
    "gn:timezone":"America/Port-au-Prince",
    "iso:country":"HT",
    "name:fra_x_preferred":[
        "Jean Laurent"
    ],
    "name:rus_x_preferred":[
        "\u041b\u043e\u0440\u0430\u043d"
    ],
    "wof:name":"Jean Laurent",
    "wof:placetype":"locality"
},
  "geometry": {"coordinates":[-72.20153000000001,19.43078],"type":"Point"}
}