{
  "type": "Feature",
  "properties": {
    "gn:admin1_code":"6.0",
    "gn:admin2_code":"3726539.0",
    "gn:asciiname":"Morisseau",
    "gn:country_code":"HT",
    "gn:dem":65,
    "gn:feature_class":"P",
    "gn:feature_code":"PPL",
    "gn:name":"Morisseau",
    "gn:population":0,
    "gn:timezone":"America/Port-au-Prince",
    "iso:country":"HT",
    "name:fra_x_preferred":[
        "Morisseau"
    ],
    "wof:name":"Morisseau",
    "wof:placetype":"locality"
},
  "geometry": {"coordinates":[-72.44552,19.08972],"type":"Point"}
}