{
  "type": "Feature",
  "properties": {
    "gn:admin1_code":"7.0",
    "gn:admin2_code":"3720809.0",
    "gn:asciiname":"Boyer",
    "gn:country_code":"HT",
    "gn:dem":123,
    "gn:feature_class":"P",
    "gn:feature_code":"PPL",
    "gn:name":"Boyer",
    "gn:population":0,
    "gn:timezone":"America/Port-au-Prince",
    "iso:country":"HT",
    "name:deu_x_preferred":[
        "Boyer"
    ],
    "wof:name":"Boyer",
    "wof:placetype":"locality"
},
  "geometry": {"coordinates":[-72.13333,18.83333],"type":"Point"}
}