{
  "type": "Feature",
  "properties": {
    "gn:admin1_code":"11.0",
    "gn:admin2_code":"3731086.0",
    "gn:asciiname":"Mantrou",
    "gn:country_code":"HT",
    "gn:dem":1110,
    "gn:feature_class":"P",
    "gn:feature_code":"PPL",
    "gn:name":"Mantrou",
    "gn:population":0,
    "gn:timezone":"America/Port-au-Prince",
    "iso:country":"HT",
    "name:fra_x_preferred":[
        "Mantrou"
    ],
    "wof:name":"Mantrou",
    "wof:placetype":"locality"
},
  "geometry": {"coordinates":[-72.45005,18.90429],"type":"Point"}
}