{
  "type": "Feature",
  "properties": {
    "gn:admin1_code":"11.0",
    "gn:admin2_code":"3722285.0",
    "gn:asciiname":"Nan Plaine",
    "gn:country_code":"HT",
    "gn:dem":345,
    "gn:feature_class":"P",
    "gn:feature_code":"PPL",
    "gn:name":"Nan Plaine",
    "gn:population":0,
    "gn:timezone":"America/Port-au-Prince",
    "iso:country":"HT",
    "name:fra_x_preferred":[
        "Nan Plaine"
    ],
    "wof:name":"Nan Plaine",
    "wof:placetype":"locality"
},
  "geometry": {"coordinates":[-73.02509999999999,18.45425],"type":"Point"}
}