{
  "type": "Feature",
  "properties": {
    "gn:admin1_code":"9.0",
    "gn:admin2_code":"3731232.0",
    "gn:asciiname":"Daut",
    "gn:country_code":"HT",
    "gn:dem":17,
    "gn:feature_class":"P",
    "gn:feature_code":"PPL",
    "gn:name":"Daut",
    "gn:population":0,
    "gn:timezone":"America/Port-au-Prince",
    "iso:country":"HT",
    "name:fra_x_preferred":[
        "Daut"
    ],
    "wof:name":"Daut",
    "wof:placetype":"locality"
},
  "geometry": {"coordinates":[-72.27342,19.67369],"type":"Point"}
}