{
  "type": "Feature",
  "properties": {
    "gn:admin1_code":"12.0",
    "gn:admin2_code":"3727295.0",
    "gn:asciiname":"Dual",
    "gn:country_code":"HT",
    "gn:dem":130,
    "gn:feature_class":"P",
    "gn:feature_code":"PPL",
    "gn:name":"Dual",
    "gn:population":0,
    "gn:timezone":"America/Port-au-Prince",
    "iso:country":"HT",
    "name:cat_x_preferred":[
        "Dual"
    ],
    "name:deu_x_preferred":[
        "Dual"
    ],
    "name:eus_x_preferred":[
        "Dual"
    ],
    "name:fra_x_preferred":[
        "Dual"
    ],
    "name:ita_x_preferred":[
        "Dual"
    ],
    "name:jpn_x_preferred":[
        "\u30c7\u30e5\u30a2\u30eb"
    ],
    "name:pol_x_preferred":[
        "Dual"
    ],
    "name:por_x_preferred":[
        "Dual"
    ],
    "name:spa_x_preferred":[
        "Dual"
    ],
    "name:swe_x_preferred":[
        "Dual"
    ],
    "name:zho_x_preferred":[
        "\u5bf9\u5076"
    ],
    "wof:name":"Dual",
    "wof:placetype":"locality"
},
  "geometry": {"coordinates":[-74.05,18.25],"type":"Point"}
}