{
  "type": "Feature",
  "properties": {
    "gn:admin1_code":"14.0",
    "gn:admin2_code":"3727381.0",
    "gn:asciiname":"Chapelet",
    "gn:country_code":"HT",
    "gn:dem":439,
    "gn:feature_class":"P",
    "gn:feature_code":"PPL",
    "gn:name":"Chapelet",
    "gn:population":0,
    "gn:timezone":"America/Port-au-Prince",
    "iso:country":"HT",
    "wof:name":"Chapelet",
    "wof:placetype":"locality"
},
  "geometry": {"coordinates":[-74.06667,18.53333],"type":"Point"}
}