{
  "type": "Feature",
  "properties": {
    "gn:admin1_code":"10.0",
    "gn:admin2_code":"3716114.0",
    "gn:asciiname":"Cigarra",
    "gn:country_code":"HT",
    "gn:dem":658,
    "gn:feature_class":"P",
    "gn:feature_code":"PPL",
    "gn:name":"Cigarra",
    "gn:population":0,
    "gn:timezone":"America/Port-au-Prince",
    "iso:country":"HT",
    "name:und_x_variant":[
        "Cigara",
        "Cigarra"
    ],
    "wof:name":"Cigarra",
    "wof:placetype":"locality"
},
  "geometry": {"coordinates":[-71.86587,19.41016],"type":"Point"}
}