{
  "type": "Feature",
  "properties": {
    "gn:admin1_code":"3.0",
    "gn:admin2_code":"3718419.0",
    "gn:asciiname":"Hemboucot",
    "gn:country_code":"HT",
    "gn:dem":64,
    "gn:feature_class":"P",
    "gn:feature_code":"PPL",
    "gn:name":"Hemboucot",
    "gn:population":0,
    "gn:timezone":"America/Port-au-Prince",
    "iso:country":"HT",
    "name:fra_x_preferred":[
        "Hemboucot"
    ],
    "wof:name":"Hemboucot",
    "wof:placetype":"locality"
},
  "geometry": {"coordinates":[-72.87006,20.0802],"type":"Point"}
}