{
  "type": "Feature",
  "properties": {
    "gn:admin1_code":"6.0",
    "gn:admin2_code":"3717563",
    "gn:asciiname":"Ananas",
    "gn:country_code":"HT",
    "gn:dem":623,
    "gn:feature_class":"P",
    "gn:feature_code":"PPL",
    "gn:name":"Ananas",
    "gn:population":0,
    "gn:timezone":"America/Port-au-Prince",
    "iso:country":"HT",
    "wof:name":"Ananas",
    "wof:placetype":"locality"
},
  "geometry": {"coordinates":[-72.33333,19.23333],"type":"Point"}
}