{
  "type": "Feature",
  "properties": {
    "gn:admin1_code":"9.0",
    "gn:admin2_code":"3717545.0",
    "gn:asciiname":"Cracaraille",
    "gn:country_code":"HT",
    "gn:dem":447,
    "gn:feature_class":"P",
    "gn:feature_code":"PPL",
    "gn:name":"Cracaraille",
    "gn:population":0,
    "gn:timezone":"America/Port-au-Prince",
    "iso:country":"HT",
    "name:fra_x_preferred":[
        "Cracaraille"
    ],
    "wof:name":"Cracaraille",
    "wof:placetype":"locality"
},
  "geometry": {"coordinates":[-72.05441999999999,19.38398],"type":"Point"}
}