{
  "type": "Feature",
  "properties": {
    "gn:admin1_code":"6.0",
    "gn:asciiname":"Dangoula",
    "gn:country_code":"HT",
    "gn:dem":833,
    "gn:feature_class":"P",
    "gn:feature_code":"PPL",
    "gn:name":"Dangoula",
    "gn:population":0,
    "gn:timezone":"America/Port-au-Prince",
    "iso:country":"HT",
    "wof:name":"Dangoula",
    "wof:placetype":"locality"
},
  "geometry": {"coordinates":[-72.35306,18.84861],"type":"Point"}
}