{
  "type": "Feature",
  "properties": {
    "gn:admin1_code":"15.0",
    "gn:admin2_code":"3730801.0",
    "gn:asciiname":"Brodequin",
    "gn:country_code":"HT",
    "gn:dem":362,
    "gn:feature_class":"P",
    "gn:feature_code":"PPL",
    "gn:name":"Brodequin",
    "gn:population":0,
    "gn:timezone":"America/Port-au-Prince",
    "iso:country":"HT",
    "wof:name":"Brodequin",
    "wof:placetype":"locality"
},
  "geometry": {"coordinates":[-73.66667,18.45],"type":"Point"}
}