{
  "type": "Feature",
  "properties": {
    "gn:admin1_code":"3.0",
    "gn:admin2_code":"3718419.0",
    "gn:asciiname":"Clair Messine",
    "gn:country_code":"HT",
    "gn:dem":51,
    "gn:feature_class":"P",
    "gn:feature_code":"PPL",
    "gn:name":"Clair Messine",
    "gn:population":0,
    "gn:timezone":"America/Port-au-Prince",
    "iso:country":"HT",
    "name:fra_x_preferred":[
        "Clair Messine"
    ],
    "wof:name":"Clair Messine",
    "wof:placetype":"locality"
},
  "geometry": {"coordinates":[-72.77076,20.06613],"type":"Point"}
}