{
  "type": "Feature",
  "properties": {
    "gn:admin1_code":"7.0",
    "gn:admin2_code":"3728053.0",
    "gn:asciiname":"Latines",
    "gn:country_code":"HT",
    "gn:dem":264,
    "gn:feature_class":"P",
    "gn:feature_code":"PPL",
    "gn:name":"Latines",
    "gn:population":0,
    "gn:timezone":"America/Port-au-Prince",
    "iso:country":"HT",
    "name:und_x_variant":[
        "Latine",
        "Latines"
    ],
    "wof:name":"Latines",
    "wof:placetype":"locality"
},
  "geometry": {"coordinates":[-71.73574000000001,19.06169],"type":"Point"}
}