{
  "type": "Feature",
  "properties": {
    "gn:admin1_code":"9.0",
    "gn:admin2_code":"3718665.0",
    "gn:asciiname":"Lorguesse",
    "gn:country_code":"HT",
    "gn:dem":722,
    "gn:feature_class":"P",
    "gn:feature_code":"PPL",
    "gn:name":"Lorguesse",
    "gn:population":0,
    "gn:timezone":"America/Port-au-Prince",
    "iso:country":"HT",
    "name:fra_x_preferred":[
        "Lorguesse"
    ],
    "wof:name":"Lorguesse",
    "wof:placetype":"locality"
},
  "geometry": {"coordinates":[-72.5372,19.60737],"type":"Point"}
}