{
  "type": "Feature",
  "properties": {
    "gn:admin1_code":"6.0",
    "gn:admin2_code":"3717587.0",
    "gn:asciiname":"Rossignol",
    "gn:country_code":"HT",
    "gn:dem":131,
    "gn:feature_class":"P",
    "gn:feature_code":"PPL",
    "gn:name":"Rossignol",
    "gn:population":0,
    "gn:timezone":"America/Port-au-Prince",
    "iso:country":"HT",
    "wof:name":"Rossignol",
    "wof:placetype":"locality"
},
  "geometry": {"coordinates":[-72.36667,18.95],"type":"Point"}
}