{
  "type": "Feature",
  "properties": {
    "gn:admin1_code":"13.0",
    "gn:admin2_code":"3730361.0",
    "gn:asciiname":"Cassourde",
    "gn:country_code":"HT",
    "gn:dem":303,
    "gn:feature_class":"P",
    "gn:feature_code":"PPL",
    "gn:name":"Cassourde",
    "gn:population":0,
    "gn:timezone":"America/Port-au-Prince",
    "iso:country":"HT",
    "name:fra_x_preferred":[
        "Cassourd\u00e9"
    ],
    "name:und_x_variant":[
        "Cassourd",
        "Cassourde"
    ],
    "wof:name":"Cassourde",
    "wof:placetype":"locality"
},
  "geometry": {"coordinates":[-71.76251999999999,18.1209],"type":"Point"}
}