{
  "type": "Feature",
  "properties": {
    "gn:admin1_code":"13.0",
    "gn:admin2_code":"3730361.0",
    "gn:asciiname":"La Fortune",
    "gn:country_code":"HT",
    "gn:dem":820,
    "gn:feature_class":"P",
    "gn:feature_code":"PPL",
    "gn:name":"La Fortune",
    "gn:population":0,
    "gn:timezone":"America/Port-au-Prince",
    "iso:country":"HT",
    "wof:name":"La Fortune",
    "wof:placetype":"locality"
},
  "geometry": {"coordinates":[-71.86667,18.25],"type":"Point"}
}