{
  "type": "Feature",
  "properties": {
    "gn:admin1_code":"14.0",
    "gn:admin2_code":"3723592",
    "gn:asciiname":"Anse d'Azur",
    "gn:country_code":"HT",
    "gn:dem":-9999,
    "gn:feature_class":"P",
    "gn:feature_code":"PPL",
    "gn:name":"Anse d\u2019Azur",
    "gn:population":0,
    "gn:timezone":"America/Port-au-Prince",
    "iso:country":"HT",
    "name:und_x_variant":[
        "Trou Cochon",
        "Anse \u00e0 Cochon",
        "Anse d\u2019Azur"
    ],
    "wof:name":"Anse d'Azur",
    "wof:placetype":"locality"
},
  "geometry": {"coordinates":[-74.14745000000001,18.66001],"type":"Point"}
}