{
  "type": "Feature",
  "properties": {
    "gn:admin1_code":"3.0",
    "gn:admin2_code":"3720764.0",
    "gn:asciiname":"Bazin",
    "gn:country_code":"HT",
    "gn:dem":188,
    "gn:feature_class":"P",
    "gn:feature_code":"PPL",
    "gn:name":"Bazin",
    "gn:population":0,
    "gn:timezone":"America/Port-au-Prince",
    "iso:country":"HT",
    "name:bre_x_preferred":[
        "Bazin"
    ],
    "name:cat_x_preferred":[
        "Bazin"
    ],
    "name:ceb_x_preferred":[
        "Bazin"
    ],
    "name:deu_x_preferred":[
        "Bazin"
    ],
    "name:fra_x_preferred":[
        "Bazin"
    ],
    "name:ita_x_preferred":[
        "Bazin"
    ],
    "name:jpn_x_preferred":[
        "\u30d0\u30b6\u30f3"
    ],
    "name:nds_x_preferred":[
        "Bazin"
    ],
    "name:ron_x_preferred":[
        "Bazin"
    ],
    "name:slv_x_preferred":[
        "Bazin"
    ],
    "name:spa_x_preferred":[
        "Bazin"
    ],
    "name:vie_x_preferred":[
        "Bazin"
    ],
    "wof:name":"Bazin",
    "wof:placetype":"locality"
},
  "geometry": {"coordinates":[-73.20471999999999,19.83833],"type":"Point"}
}