{
  "type": "Feature",
  "properties": {
    "gn:admin1_code":"13.0",
    "gn:admin2_code":"3723778.0",
    "gn:asciiname":"Grande Colline",
    "gn:country_code":"HT",
    "gn:dem":704,
    "gn:feature_class":"P",
    "gn:feature_code":"PPL",
    "gn:name":"Grande Colline",
    "gn:population":0,
    "gn:timezone":"America/Port-au-Prince",
    "iso:country":"HT",
    "name:fra_x_preferred":[
        "Grande Colline"
    ],
    "wof:name":"Grande Colline",
    "wof:placetype":"locality"
},
  "geometry": {"coordinates":[-72.69181,18.30123],"type":"Point"}
}