{
  "type": "Feature",
  "properties": {
    "gn:admin1_code":"14.0",
    "gn:asciiname":"Mais Pierre",
    "gn:country_code":"HT",
    "gn:dem":226,
    "gn:feature_class":"P",
    "gn:feature_code":"PPL",
    "gn:name":"Ma\u00efs Pierre",
    "gn:population":0,
    "gn:timezone":"America/Port-au-Prince",
    "iso:country":"HT",
    "wof:name":"Mais Pierre",
    "wof:placetype":"locality"
},
  "geometry": {"coordinates":[-73.31667,18.36667000000001],"type":"Point"}
}