{
  "type": "Feature",
  "properties": {
    "gn:admin1_code":"12.0",
    "gn:admin2_code":"3731094.0",
    "gn:asciiname":"La Cour",
    "gn:country_code":"HT",
    "gn:dem":414,
    "gn:feature_class":"P",
    "gn:feature_code":"PPL",
    "gn:name":"La Cour",
    "gn:population":0,
    "gn:timezone":"America/Port-au-Prince",
    "iso:country":"HT",
    "name:fra_x_preferred":[
        "La Cour"
    ],
    "wof:name":"La Cour",
    "wof:placetype":"locality"
},
  "geometry": {"coordinates":[-73.46635000000001,18.3193],"type":"Point"}
}