{
  "type": "Feature",
  "properties": {
    "gn:admin1_code":"10.0",
    "gn:admin2_code":"3719435.0",
    "gn:asciiname":"Doge",
    "gn:country_code":"HT",
    "gn:dem":161,
    "gn:feature_class":"P",
    "gn:feature_code":"PPL",
    "gn:name":"Doge",
    "gn:population":0,
    "gn:timezone":"America/Port-au-Prince",
    "iso:country":"HT",
    "name:aze_x_preferred":[
        "Doj"
    ],
    "name:bel_x_preferred":[
        "\u0414\u043e\u0436"
    ],
    "name:bos_x_preferred":[
        "Du\u017ed"
    ],
    "name:bul_x_preferred":[
        "\u0414\u043e\u0436"
    ],
    "name:ces_x_preferred":[
        "D\u00f3\u017ee"
    ],
    "name:deu_x_preferred":[
        "Doge"
    ],
    "name:ell_x_preferred":[
        "\u0394\u03cc\u03b3\u03b7\u03c2"
    ],
    "name:epo_x_preferred":[
        "Do\u011do"
    ],
    "name:est_x_preferred":[
        "Dood\u017e"
    ],
    "name:eus_x_preferred":[
        "Dux"
    ],
    "name:fas_x_preferred":[
        "\u062f\u0648\u062c\u0647"
    ],
    "name:fin_x_preferred":[
        "Doge"
    ],
    "name:fra_x_preferred":[
        "Doge"
    ],
    "name:fry_x_preferred":[
        "Doge"
    ],
    "name:heb_x_preferred":[
        "\u05d3\u05d5\u05d2'\u05d4"
    ],
    "name:hrv_x_preferred":[
        "Du\u017ed"
    ],
    "name:hun_x_preferred":[
        "D\u00f3zse"
    ],
    "name:hye_x_preferred":[
        "\u0534\u0578\u056a"
    ],
    "name:ido_x_preferred":[
        "Dojo"
    ],
    "name:ita_x_preferred":[
        "Doge"
    ],
    "name:jpn_x_preferred":[
        "\u30c9\u30fc\u30b8\u30a7"
    ],
    "name:kat_x_preferred":[
        "\u10d3\u10dd\u10df\u10d8"
    ],
    "name:kor_x_preferred":[
        "\ub3c4\uc81c"
    ],
    "name:lav_x_preferred":[
        "Dod\u017es"
    ],
    "name:lit_x_preferred":[
        "Do\u017eas"
    ],
    "name:nld_x_preferred":[
        "Doge"
    ],
    "name:nno_x_preferred":[
        "Doge"
    ],
    "name:nor_x_preferred":[
        "Doge"
    ],
    "name:oci_x_preferred":[
        "D\u00f2ge"
    ],
    "name:pol_x_preferred":[
        "Do\u017ca"
    ],
    "name:por_x_preferred":[
        "Doge"
    ],
    "name:ron_x_preferred":[
        "Doge"
    ],
    "name:rus_x_preferred":[
        "\u0414\u043e\u0436"
    ],
    "name:scn_x_preferred":[
        "Dogi"
    ],
    "name:slk_x_preferred":[
        "D\u00f3\u017ea"
    ],
    "name:spa_x_preferred":[
        "Dux"
    ],
    "name:srp_x_preferred":[
        "\u0414\u0443\u0436\u0434"
    ],
    "name:swe_x_preferred":[
        "Doge"
    ],
    "name:ukr_x_preferred":[
        "\u0414\u043e\u0436"
    ],
    "name:uzb_x_preferred":[
        "Doj"
    ],
    "wof:name":"Doge",
    "wof:placetype":"locality"
},
  "geometry": {"coordinates":[-71.73333000000002,19.45],"type":"Point"}
}