{
  "type": "Feature",
  "properties": {
    "gn:admin1_code":"6.0",
    "gn:admin2_code":"3717563.0",
    "gn:asciiname":"Rang",
    "gn:country_code":"HT",
    "gn:dem":516,
    "gn:feature_class":"P",
    "gn:feature_code":"PPL",
    "gn:name":"Rang",
    "gn:population":0,
    "gn:timezone":"America/Port-au-Prince",
    "iso:country":"HT",
    "name:und_x_variant":[
        "Nan Rang",
        "Pang",
        "Rang"
    ],
    "wof:name":"Rang",
    "wof:placetype":"locality"
},
  "geometry": {"coordinates":[-72.2634,19.40343],"type":"Point"}
}