{
  "type": "Feature",
  "properties": {
    "gn:admin1_code":"11.0",
    "gn:admin2_code":"3718425.0",
    "gn:asciiname":"Badio",
    "gn:country_code":"HT",
    "gn:dem":975,
    "gn:feature_class":"P",
    "gn:feature_code":"PPLL",
    "gn:name":"Badio",
    "gn:population":0,
    "gn:timezone":"America/Port-au-Prince",
    "iso:country":"HT",
    "wof:name":"Badio",
    "wof:placetype":"locality"
},
  "geometry": {"coordinates":[-72.33333,18.38333],"type":"Point"}
}