{
  "type": "Feature",
  "properties": {
    "gn:admin1_code":"9.0",
    "gn:admin2_code":"3729454.0",
    "gn:asciiname":"Dupin",
    "gn:country_code":"HT",
    "gn:dem":194,
    "gn:feature_class":"P",
    "gn:feature_code":"PPL",
    "gn:name":"Dupin",
    "gn:population":0,
    "gn:timezone":"America/Port-au-Prince",
    "iso:country":"HT",
    "name:fra_x_preferred":[
        "Dupin"
    ],
    "wof:name":"Dupin",
    "wof:placetype":"locality"
},
  "geometry": {"coordinates":[-72.49330999999999,19.7428],"type":"Point"}
}