{
  "type": "Feature",
  "properties": {
    "gn:admin1_code":"12.0",
    "gn:admin2_code":"3727295.0",
    "gn:asciiname":"Courtier",
    "gn:country_code":"HT",
    "gn:dem":143,
    "gn:feature_class":"P",
    "gn:feature_code":"PPL",
    "gn:name":"Courtier",
    "gn:population":0,
    "gn:timezone":"America/Port-au-Prince",
    "iso:country":"HT",
    "name:und_x_variant":[
        "Lourtier",
        "Courtier"
    ],
    "wof:name":"Courtier",
    "wof:placetype":"locality"
},
  "geometry": {"coordinates":[-74.02516999999997,18.22881],"type":"Point"}
}