{
  "type": "Feature",
  "properties": {
    "gn:admin1_code":"12.0",
    "gn:admin2_code":"3727295.0",
    "gn:asciiname":"Courtier",
    "gn:country_code":"HT",
    "gn:dem":143,
    "gn:feature_class":"P",
    "gn:feature_code":"PPL",
    "gn:name":"Courtier",
    "gn:population":0,
    "gn:timezone":"America/Port-au-Prince",
    "iso:country":"HT",
    "name:ces_x_preferred":[
        "Dvo\u0159an"
    ],
    "name:deu_x_preferred":[
        "H\u00f6fling"
    ],
    "name:fin_x_preferred":[
        "Hovimies"
    ],
    "name:ind_x_preferred":[
        "Abdi dalem"
    ],
    "name:isl_x_preferred":[
        "Hir\u00f0ma\u00f0ur"
    ],
    "name:ita_x_preferred":[
        "Cortigiano"
    ],
    "name:lit_x_preferred":[
        "R\u016bmininkas"
    ],
    "name:pol_x_preferred":[
        "Dworzanin"
    ],
    "name:por_x_preferred":[
        "Cortes\u00e3o"
    ],
    "name:rus_x_preferred":[
        "\u041f\u0440\u0438\u0434\u0432\u043e\u0440\u043d\u044b\u0435"
    ],
    "name:sun_x_preferred":[
        "Abdi Dalem"
    ],
    "name:tha_x_preferred":[
        "\u0e02\u0e49\u0e32\u0e23\u0e32\u0e0a\u0e2a\u0e33\u0e19\u0e31\u0e01"
    ],
    "name:ukr_x_preferred":[
        "\u041f\u0440\u0438\u0434\u0432\u043e\u0440\u043d\u0456 \u0447\u0438\u043d\u0438"
    ],
    "name:und_x_variant":[
        "Lourtier",
        "Courtier"
    ],
    "wof:name":"Courtier",
    "wof:placetype":"locality"
},
  "geometry": {"coordinates":[-74.02516999999997,18.22881],"type":"Point"}
}