{
  "type": "Feature",
  "properties": {
    "gn:admin1_code":"11.0",
    "gn:admin2_code":"3727134.0",
    "gn:asciiname":"Jacasse",
    "gn:cc2":"HT",
    "gn:country_code":"HT",
    "gn:dem":306,
    "gn:feature_class":"P",
    "gn:feature_code":"PPL",
    "gn:name":"Jacasse",
    "gn:population":0,
    "gn:timezone":"America/Port-au-Prince",
    "iso:country":"HT",
    "name:und_x_variant":[
        "Jacquasse",
        "Jacasse"
    ],
    "wof:name":"Jacasse",
    "wof:placetype":"locality"
},
  "geometry": {"coordinates":[-72.05,18.66667],"type":"Point"}
}