{
  "type": "Feature",
  "properties": {
    "gn:admin1_code":"12.0",
    "gn:admin2_code":"3718404.0",
    "gn:asciiname":"Nan Garde",
    "gn:country_code":"HT",
    "gn:dem":27,
    "gn:feature_class":"P",
    "gn:feature_code":"PPL",
    "gn:name":"Nan Garde",
    "gn:population":0,
    "gn:timezone":"America/Port-au-Prince",
    "iso:country":"HT",
    "name:fra_x_preferred":[
        "Nan Garde"
    ],
    "wof:name":"Nan Garde",
    "wof:placetype":"locality"
},
  "geometry": {"coordinates":[-73.86031,18.02891],"type":"Point"}
}