{
  "type": "Feature",
  "properties": {
    "gn:admin1_code":"3.0",
    "gn:admin2_code":"3720764.0",
    "gn:asciiname":"Rochefort",
    "gn:country_code":"HT",
    "gn:dem":44,
    "gn:feature_class":"P",
    "gn:feature_code":"PPL",
    "gn:name":"Rochefort",
    "gn:population":0,
    "gn:timezone":"America/Port-au-Prince",
    "iso:country":"HT",
    "wof:name":"Rochefort",
    "wof:placetype":"locality"
},
  "geometry": {"coordinates":[-73.40000000000001,19.65],"type":"Point"}
}