{
  "type": "Feature",
  "properties": {
    "gn:admin1_code":"3.0",
    "gn:admin2_code":"3720764.0",
    "gn:asciiname":"Rochefort",
    "gn:country_code":"HT",
    "gn:dem":44,
    "gn:feature_class":"P",
    "gn:feature_code":"PPL",
    "gn:name":"Rochefort",
    "gn:population":0,
    "gn:timezone":"America/Port-au-Prince",
    "iso:country":"HT",
    "name:als_x_preferred":[
        "Rochefort"
    ],
    "name:bel_x_preferred":[
        "\u0420\u0430\u0448\u0444\u043e\u0440"
    ],
    "name:bre_x_preferred":[
        "Rochefort"
    ],
    "name:bul_x_preferred":[
        "\u0420\u043e\u0448\u0444\u043e\u0440"
    ],
    "name:cat_x_preferred":[
        "Rochefort"
    ],
    "name:ceb_x_preferred":[
        "Rochefort"
    ],
    "name:ces_x_preferred":[
        "Rochefort"
    ],
    "name:deu_x_preferred":[
        "Rochefort"
    ],
    "name:epo_x_preferred":[
        "Rochefort"
    ],
    "name:eus_x_preferred":[
        "Rochefort"
    ],
    "name:fin_x_preferred":[
        "Rochefort"
    ],
    "name:fra_x_preferred":[
        "Rochefort"
    ],
    "name:hun_x_preferred":[
        "Rochefort"
    ],
    "name:ind_x_preferred":[
        "Rochefort"
    ],
    "name:ita_x_preferred":[
        "Rochefort"
    ],
    "name:jav_x_preferred":[
        "Rochefort"
    ],
    "name:jpn_x_preferred":[
        "\u30ed\u30b7\u30e5\u30d5\u30a9\u30fc\u30eb"
    ],
    "name:kor_x_preferred":[
        "\ub85c\uc288\ud3ec\ub974"
    ],
    "name:lmo_x_preferred":[
        "Rochefort"
    ],
    "name:ltz_x_preferred":[
        "Rochefort"
    ],
    "name:nds_x_preferred":[
        "Rochefort"
    ],
    "name:nld_x_preferred":[
        "Rochefort"
    ],
    "name:pms_x_preferred":[
        "Rochefort"
    ],
    "name:pol_x_preferred":[
        "Rochefort"
    ],
    "name:por_x_preferred":[
        "Rochefort"
    ],
    "name:ron_x_preferred":[
        "Rochefort"
    ],
    "name:rus_x_preferred":[
        "\u0420\u043e\u0448\u0444\u043e\u0440"
    ],
    "name:slk_x_preferred":[
        "Rochefort"
    ],
    "name:slv_x_preferred":[
        "Rochefort"
    ],
    "name:spa_x_preferred":[
        "Rochefort"
    ],
    "name:swe_x_preferred":[
        "Rochefort"
    ],
    "name:ukr_x_preferred":[
        "\u0420\u043e\u0448\u0444\u043e\u0440"
    ],
    "name:vol_x_preferred":[
        "Rochefort"
    ],
    "wof:name":"Rochefort",
    "wof:placetype":"locality"
},
  "geometry": {"coordinates":[-73.40000000000001,19.65],"type":"Point"}
}