{
  "type": "Feature",
  "properties": {
    "gn:admin1_code":"11.0",
    "gn:admin2_code":"3727134.0",
    "gn:asciiname":"Coupet",
    "gn:cc2":"HT",
    "gn:country_code":"HT",
    "gn:dem":1296,
    "gn:feature_class":"P",
    "gn:feature_code":"PPL",
    "gn:name":"Coupet",
    "gn:population":0,
    "gn:timezone":"America/Port-au-Prince",
    "iso:country":"HT",
    "name:und_x_variant":[
        "Coupette",
        "Coupet"
    ],
    "wof:name":"Coupet",
    "wof:placetype":"locality"
},
  "geometry": {"coordinates":[-72.13333,18.43333],"type":"Point"}
}