{
  "type": "Feature",
  "properties": {
    "gn:admin1_code":"9.0",
    "gn:admin2_code":"3729454.0",
    "gn:asciiname":"Menier",
    "gn:country_code":"HT",
    "gn:dem":558,
    "gn:feature_class":"P",
    "gn:feature_code":"PPL",
    "gn:name":"Menier",
    "gn:population":0,
    "gn:timezone":"America/Port-au-Prince",
    "iso:country":"HT",
    "wof:name":"Menier",
    "wof:placetype":"locality"
},
  "geometry": {"coordinates":[-72.48333000000002,19.78333],"type":"Point"}
}