{
  "type": "Feature",
  "properties": {
    "gn:admin1_code":"15.0",
    "gn:admin2_code":"3731122.0",
    "gn:asciiname":"Plaine aux Pins",
    "gn:country_code":"HT",
    "gn:dem":329,
    "gn:feature_class":"P",
    "gn:feature_code":"PPL",
    "gn:name":"Plaine aux Pins",
    "gn:population":0,
    "gn:timezone":"America/Port-au-Prince",
    "iso:country":"HT",
    "name:und_x_variant":[
        "Aux Pins",
        "Aux Fins",
        "Plaine aux Pins"
    ],
    "wof:name":"Plaine aux Pins",
    "wof:placetype":"locality"
},
  "geometry": {"coordinates":[-73.56314,18.44485],"type":"Point"}
}