{
  "type": "Feature",
  "properties": {
    "gn:admin1_code":"11.0",
    "gn:admin2_code":"3718425.0",
    "gn:asciiname":"Echarlotte",
    "gn:cc2":"HT",
    "gn:country_code":"HT",
    "gn:dem":173,
    "gn:feature_class":"P",
    "gn:feature_code":"PPL",
    "gn:name":"\u00c9charlotte",
    "gn:population":0,
    "gn:timezone":"America/Port-au-Prince",
    "iso:country":"HT",
    "name:und_x_variant":[
        "\u00c9chariope",
        "\u00c9charlotte"
    ],
    "wof:name":"Echarlotte",
    "wof:placetype":"locality"
},
  "geometry": {"coordinates":[-72.53333000000001,18.51667],"type":"Point"}
}