{
  "type": "Feature",
  "properties": {
    "gn:admin1_code":"11.0",
    "gn:admin2_code":"3722285.0",
    "gn:asciiname":"Vali",
    "gn:cc2":"HT",
    "gn:country_code":"HT",
    "gn:dem":700,
    "gn:feature_class":"P",
    "gn:feature_code":"PPL",
    "gn:name":"Vali",
    "gn:population":0,
    "gn:timezone":"America/Port-au-Prince",
    "iso:country":"HT",
    "name:bul_x_preferred":[
        "\u0412\u0430\u043b\u0438"
    ],
    "name:ceb_x_preferred":[
        "Vali"
    ],
    "name:deu_x_preferred":[
        "V\u00e4li"
    ],
    "name:fra_x_preferred":[
        "Vali"
    ],
    "name:heb_x_preferred":[
        "\u05d5\u05d0\u05dc\u05d9"
    ],
    "name:ita_x_preferred":[
        "Vali"
    ],
    "name:jpn_x_preferred":[
        "\u30f4\u30a1\u30fc\u30ea"
    ],
    "name:pol_x_preferred":[
        "Wali"
    ],
    "name:rus_x_preferred":[
        "\u0412\u0430\u043b\u0438"
    ],
    "name:spa_x_preferred":[
        "Vali"
    ],
    "name:srp_x_preferred":[
        "\u0412\u0430\u043b\u0438"
    ],
    "name:swe_x_preferred":[
        "Vali"
    ],
    "name:tur_x_preferred":[
        "Vali"
    ],
    "name:ukr_x_preferred":[
        "\u0412\u0430\u043b\u0456"
    ],
    "name:und_x_variant":[
        "Vally"
    ],
    "wof:name":"Vali",
    "wof:placetype":"locality"
},
  "geometry": {"coordinates":[-72.80083,18.36361],"type":"Point"}
}