{
  "type": "Feature",
  "properties": {
    "gn:admin1_code":"11.0",
    "gn:admin2_code":"3722285.0",
    "gn:asciiname":"Vali",
    "gn:cc2":"HT",
    "gn:country_code":"HT",
    "gn:dem":700,
    "gn:feature_class":"P",
    "gn:feature_code":"PPL",
    "gn:name":"Vali",
    "gn:population":0,
    "gn:timezone":"America/Port-au-Prince",
    "iso:country":"HT",
    "name:und_x_variant":[
        "Vally",
        "Vali"
    ],
    "wof:name":"Vali",
    "wof:placetype":"locality"
},
  "geometry": {"coordinates":[-72.80083,18.36361],"type":"Point"}
}