{
  "type": "Feature",
  "properties": {
    "gn:admin1_code":"14.0",
    "gn:admin2_code":"3727381.0",
    "gn:asciiname":"Borgella",
    "gn:country_code":"HT",
    "gn:dem":-9999,
    "gn:feature_class":"P",
    "gn:feature_code":"PPL",
    "gn:name":"Borgella",
    "gn:population":0,
    "gn:timezone":"America/Port-au-Prince",
    "iso:country":"HT",
    "wof:name":"Borgella",
    "wof:placetype":"locality"
},
  "geometry": {"coordinates":[-73.73333000000002,18.65],"type":"Point"}
}