{
  "type": "Feature",
  "properties": {
    "gn:admin1_code":"12.0",
    "gn:admin2_code":"3727295.0",
    "gn:asciiname":"Nan Zile",
    "gn:country_code":"HT",
    "gn:dem":583,
    "gn:feature_class":"P",
    "gn:feature_code":"PPL",
    "gn:name":"Nan Zil\u00e9",
    "gn:population":0,
    "gn:timezone":"America/Port-au-Prince",
    "iso:country":"HT",
    "name:und_x_variant":[
        "Nan Ell\u00e9",
        "Nan Zil\u00e9"
    ],
    "wof:name":"Nan Zile",
    "wof:placetype":"locality"
},
  "geometry": {"coordinates":[-74.06279000000001,18.30558],"type":"Point"}
}