{
  "type": "Feature",
  "properties": {
    "gn:admin1_code":"9.0",
    "gn:admin2_code":"3717545.0",
    "gn:asciiname":"Belle Anse",
    "gn:country_code":"HT",
    "gn:dem":742,
    "gn:feature_class":"P",
    "gn:feature_code":"PPL",
    "gn:name":"Belle Anse",
    "gn:population":0,
    "gn:timezone":"America/Port-au-Prince",
    "iso:country":"HT",
    "wof:name":"Belle Anse",
    "wof:placetype":"locality"
},
  "geometry": {"coordinates":[-72.21666999999999,19.45],"type":"Point"}
}