{
  "type": "Feature",
  "properties": {
    "gn:admin1_code":"10.0",
    "gn:admin2_code":"3716223.0",
    "gn:asciiname":"Candy",
    "gn:country_code":"HT",
    "gn:dem":638,
    "gn:feature_class":"P",
    "gn:feature_code":"PPL",
    "gn:name":"Candy",
    "gn:population":0,
    "gn:timezone":"America/Port-au-Prince",
    "iso:country":"HT",
    "name:fra_x_preferred":[
        "Candy"
    ],
    "wof:name":"Candy",
    "wof:placetype":"locality"
},
  "geometry": {"coordinates":[-72.01106999999998,19.46728],"type":"Point"}
}