{
  "type": "Feature",
  "properties": {
    "gn:admin1_code":"11.0",
    "gn:admin2_code":"3718425.0",
    "gn:asciiname":"Belle Fontaine",
    "gn:country_code":"HT",
    "gn:dem":1075,
    "gn:feature_class":"P",
    "gn:feature_code":"PPL",
    "gn:name":"Belle Fontaine",
    "gn:population":0,
    "gn:timezone":"America/Port-au-Prince",
    "iso:country":"HT",
    "wof:name":"Belle Fontaine",
    "wof:placetype":"locality"
},
  "geometry": {"coordinates":[-72.31667,18.36667000000001],"type":"Point"}
}