{
  "type": "Feature",
  "properties": {
    "gn:admin1_code":"12.0",
    "gn:admin2_code":"3727900.0",
    "gn:asciiname":"Nansinte",
    "gn:cc2":"HT",
    "gn:country_code":"HT",
    "gn:dem":33,
    "gn:feature_class":"P",
    "gn:feature_code":"PPL",
    "gn:name":"Nansinte",
    "gn:population":0,
    "gn:timezone":"America/Port-au-Prince",
    "iso:country":"HT",
    "name:und_x_variant":[
        "Cape a Four",
        "Cap Foux",
        "Nansinte"
    ],
    "wof:name":"Nansinte",
    "wof:placetype":"locality"
},
  "geometry": {"coordinates":[-74.43876999999998,18.34964],"type":"Point"}
}