{
  "type": "Feature",
  "properties": {
    "gn:admin1_code":"14.0",
    "gn:admin2_code":"3723592.0",
    "gn:asciiname":"Marfranc",
    "gn:country_code":"HT",
    "gn:dem":34,
    "gn:feature_class":"P",
    "gn:feature_code":"PPL",
    "gn:name":"Marfranc",
    "gn:population":0,
    "gn:timezone":"America/Port-au-Prince",
    "iso:country":"HT",
    "wof:name":"Marfranc",
    "wof:placetype":"locality"
},
  "geometry": {"coordinates":[-74.21819000000001,18.58247],"type":"Point"}
}