{
  "type": "Feature",
  "properties": {
    "gn:admin1_code":"7.0",
    "gn:asciiname":"Lan Citron",
    "gn:country_code":"HT",
    "gn:dem":681,
    "gn:feature_class":"P",
    "gn:feature_code":"PPL",
    "gn:name":"Lan Citron",
    "gn:population":0,
    "gn:timezone":"America/Port-au-Prince",
    "iso:country":"HT",
    "wof:name":"Lan Citron",
    "wof:placetype":"locality"
},
  "geometry": {"coordinates":[-71.96666999999999,18.73333],"type":"Point"}
}