{
  "type": "Feature",
  "properties": {
    "gn:admin1_code":"15.0",
    "gn:admin2_code":"3720823.0",
    "gn:asciiname":"Goyine",
    "gn:country_code":"HT",
    "gn:dem":584,
    "gn:feature_class":"P",
    "gn:feature_code":"PPL",
    "gn:name":"Goyine",
    "gn:population":0,
    "gn:timezone":"America/Port-au-Prince",
    "iso:country":"HT",
    "name:fra_x_preferred":[
        "Goyine"
    ],
    "wof:name":"Goyine",
    "wof:placetype":"locality"
},
  "geometry": {"coordinates":[-73.19801,18.38724],"type":"Point"}
}