{
  "type": "Feature",
  "properties": {
    "gn:admin1_code":"12.0",
    "gn:admin2_code":"3728096.0",
    "gn:asciiname":"Leger",
    "gn:country_code":"HT",
    "gn:dem":16,
    "gn:feature_class":"P",
    "gn:feature_code":"PPL",
    "gn:name":"L\u00e9ger",
    "gn:population":0,
    "gn:timezone":"America/Port-au-Prince",
    "iso:country":"HT",
    "name:deu_x_preferred":[
        "Leger"
    ],
    "name:fry_x_preferred":[
        "Leger"
    ],
    "name:nld_x_preferred":[
        "Leger"
    ],
    "wof:name":"Leger",
    "wof:placetype":"locality"
},
  "geometry": {"coordinates":[-73.84222,18.13611],"type":"Point"}
}