{
  "type": "Feature",
  "properties": {
    "gn:admin1_code":"15.0",
    "gn:asciiname":"Petite Colline",
    "gn:country_code":"HT",
    "gn:dem":507,
    "gn:feature_class":"P",
    "gn:feature_code":"PPL",
    "gn:name":"Petite Colline",
    "gn:population":0,
    "gn:timezone":"America/Port-au-Prince",
    "iso:country":"HT",
    "name:fra_x_preferred":[
        "Petite Colline"
    ],
    "wof:name":"Petite Colline",
    "wof:placetype":"locality"
},
  "geometry": {"coordinates":[-73.03026,18.35881],"type":"Point"}
}