{
  "type": "Feature",
  "properties": {
    "gn:admin1_code":"10.0",
    "gn:admin2_code":"3719435.0",
    "gn:asciiname":"Passe Cafe",
    "gn:country_code":"HT",
    "gn:dem":58,
    "gn:feature_class":"P",
    "gn:feature_code":"PPL",
    "gn:name":"Passe Caf\u00e9",
    "gn:population":0,
    "gn:timezone":"America/Port-au-Prince",
    "iso:country":"HT",
    "wof:name":"Passe Cafe",
    "wof:placetype":"locality"
},
  "geometry": {"coordinates":[-71.81667,19.55],"type":"Point"}
}