{
  "type": "Feature",
  "properties": {
    "gn:admin1_code":"6.0",
    "gn:admin2_code":"3717563.0",
    "gn:asciiname":"Nan Campeche",
    "gn:country_code":"HT",
    "gn:dem":392,
    "gn:feature_class":"P",
    "gn:feature_code":"PPL",
    "gn:name":"Nan Camp\u00eache",
    "gn:population":0,
    "gn:timezone":"America/Port-au-Prince",
    "iso:country":"HT",
    "name:fra_x_preferred":[
        "Nan Camp\u00eache"
    ],
    "wof:name":"Nan Campeche",
    "wof:placetype":"locality"
},
  "geometry": {"coordinates":[-72.33575999999999,19.31527],"type":"Point"}
}