{
  "type": "Feature",
  "properties": {
    "gn:admin1_code":"7.0",
    "gn:admin2_code":"3728053",
    "gn:asciiname":"Abricot",
    "gn:country_code":"HT",
    "gn:dem":390,
    "gn:feature_class":"P",
    "gn:feature_code":"PPL",
    "gn:name":"Abricot",
    "gn:population":0,
    "gn:timezone":"America/Port-au-Prince",
    "iso:country":"HT",
    "name:fra_x_preferred":[
        "Abricot"
    ],
    "wof:name":"Abricot",
    "wof:placetype":"locality"
},
  "geometry": {"coordinates":[-71.76701,19.1393],"type":"Point"}
}