{
  "type": "Feature",
  "properties": {
    "gn:admin1_code":"14.0",
    "gn:admin2_code":"3723592.0",
    "gn:asciiname":"Beril",
    "gn:country_code":"HT",
    "gn:dem":147,
    "gn:feature_class":"P",
    "gn:feature_code":"PPL",
    "gn:name":"B\u00e9ril",
    "gn:population":0,
    "gn:timezone":"America/Port-au-Prince",
    "iso:country":"HT",
    "name:fra_x_preferred":[
        "B\u00e9ril"
    ],
    "wof:name":"Beril",
    "wof:placetype":"locality"
},
  "geometry": {"coordinates":[-74.29824000000001,18.61091],"type":"Point"}
}