{
  "type": "Feature",
  "properties": {
    "gn:admin1_code":"10.0",
    "gn:admin2_code":"3719435.0",
    "gn:asciiname":"Guion",
    "gn:country_code":"HT",
    "gn:dem":222,
    "gn:feature_class":"P",
    "gn:feature_code":"PPL",
    "gn:name":"Guion",
    "gn:population":0,
    "gn:timezone":"America/Port-au-Prince",
    "iso:country":"HT",
    "name:deu_x_preferred":[
        "Guion"
    ],
    "name:fra_x_preferred":[
        "Guion"
    ],
    "name:glg_x_preferred":[
        "Gui\u00f3n"
    ],
    "name:pol_x_preferred":[
        "Guion"
    ],
    "name:por_x_preferred":[
        "Guion"
    ],
    "name:spa_x_preferred":[
        "Guion"
    ],
    "wof:name":"Guion",
    "wof:placetype":"locality"
},
  "geometry": {"coordinates":[-71.75,19.41667],"type":"Point"}
}