{
  "type": "Feature",
  "properties": {
    "gn:admin1_code":"6.0",
    "gn:admin2_code":"3724695.0",
    "gn:asciiname":"Danache",
    "gn:country_code":"HT",
    "gn:dem":582,
    "gn:feature_class":"P",
    "gn:feature_code":"PPL",
    "gn:name":"Danache",
    "gn:population":0,
    "gn:timezone":"America/Port-au-Prince",
    "iso:country":"HT",
    "name:fra_x_preferred":[
        "Danache"
    ],
    "wof:name":"Danache",
    "wof:placetype":"locality"
},
  "geometry": {"coordinates":[-72.5151,19.53726],"type":"Point"}
}