{
  "type": "Feature",
  "properties": {
    "gn:admin1_code":"11.0",
    "gn:asciiname":"Gros Morne",
    "gn:country_code":"HT",
    "gn:dem":607,
    "gn:feature_class":"P",
    "gn:feature_code":"PPL",
    "gn:name":"Gros Morne",
    "gn:population":0,
    "gn:timezone":"America/Port-au-Prince",
    "iso:country":"HT",
    "name:ceb_x_preferred":[
        "Gros Morne"
    ],
    "name:deu_x_preferred":[
        "Gros Morne"
    ],
    "name:fra_x_preferred":[
        "Gros Morne"
    ],
    "name:ita_x_preferred":[
        "Gros-Morne"
    ],
    "name:nld_x_preferred":[
        "Gros Morne"
    ],
    "name:pol_x_preferred":[
        "Gros-Morne"
    ],
    "name:rus_x_preferred":[
        "\u0413\u0440\u043e-\u041c\u043e\u0440\u043d"
    ],
    "name:spa_x_preferred":[
        "Gros-Morne"
    ],
    "name:swe_x_preferred":[
        "Gros Morne"
    ],
    "wof:name":"Gros Morne",
    "wof:placetype":"locality"
},
  "geometry": {"coordinates":[-72.20685999999998,18.70151],"type":"Point"}
}