{
  "type": "Feature",
  "properties": {
    "gn:admin1_code":"11.0",
    "gn:asciiname":"Gros Morne",
    "gn:country_code":"HT",
    "gn:dem":607,
    "gn:feature_class":"P",
    "gn:feature_code":"PPL",
    "gn:name":"Gros Morne",
    "gn:population":0,
    "gn:timezone":"America/Port-au-Prince",
    "iso:country":"HT",
    "name:ceb_x_preferred":[
        "Gros Morne"
    ],
    "name:deu_x_preferred":[
        "Gros Morne"
    ],
    "name:fra_x_preferred":[
        "Gros Morne"
    ],
    "name:ita_x_preferred":[
        "Gros-Morne"
    ],
    "name:nld_x_preferred":[
        "Gros Morne"
    ],
    "name:pol_x_preferred":[
        "Gros Morne"
    ],
    "name:pol_x_variant":[
        "Gros-Morne"
    ],
    "name:por_x_preferred":[
        "Gros Morne"
    ],
    "name:rus_x_preferred":[
        "\u0413\u0440\u043e-\u041c\u043e\u0440\u043d"
    ],
    "name:spa_x_preferred":[
        "Gros-Morne"
    ],
    "name:swe_x_preferred":[
        "Gros Morne"
    ],
    "name:tur_x_preferred":[
        "Gros Morne"
    ],
    "name:urd_x_preferred":[
        "\u06af\u0631\u0627\u0633 \u0645\u0648\u0631\u0646\u06d2"
    ],
    "name:vie_x_preferred":[
        "N\u00fai Gros Morne"
    ],
    "name:zho_cn_x_preferred":[
        "\u683c\u7f57\u83ab\u8bb7\u5c71"
    ],
    "name:zho_tw_x_preferred":[
        "\u683c\u7f85\u6469\u6069\u5c71"
    ],
    "wof:name":"Gros Morne",
    "wof:placetype":"locality"
},
  "geometry": {"coordinates":[-72.20686000000001,18.70151],"type":"Point"}
}