{
  "type": "Feature",
  "properties": {
    "gn:admin1_code":"12.0",
    "gn:admin2_code":"3718404.0",
    "gn:asciiname":"Valentin",
    "gn:country_code":"HT",
    "gn:dem":113,
    "gn:feature_class":"P",
    "gn:feature_code":"PPL",
    "gn:name":"Valentin",
    "gn:population":0,
    "gn:timezone":"America/Port-au-Prince",
    "iso:country":"HT",
    "wof:name":"Valentin",
    "wof:placetype":"locality"
},
  "geometry": {"coordinates":[-73.88333,18.15],"type":"Point"}
}