{
  "type": "Feature",
  "properties": {
    "gn:admin1_code":"11.0",
    "gn:admin2_code":"3727134.0",
    "gn:asciiname":"Palmiste Tampe",
    "gn:country_code":"HT",
    "gn:dem":789,
    "gn:feature_class":"P",
    "gn:feature_code":"PPL",
    "gn:name":"Palmiste Tamp\u00e9",
    "gn:population":0,
    "gn:timezone":"America/Port-au-Prince",
    "iso:country":"HT",
    "name:fra_x_preferred":[
        "Palmiste Tamp\u00e9"
    ],
    "wof:name":"Palmiste Tampe",
    "wof:placetype":"locality"
},
  "geometry": {"coordinates":[-71.85183000000001,18.42132],"type":"Point"}
}