{
  "type": "Feature",
  "properties": {
    "gn:admin1_code":"13.0",
    "gn:admin2_code":"3730361.0",
    "gn:asciiname":"Barbe Pangnol",
    "gn:country_code":"HT",
    "gn:dem":296,
    "gn:feature_class":"P",
    "gn:feature_code":"PPL",
    "gn:name":"Barbe Pangnol",
    "gn:population":0,
    "gn:timezone":"America/Port-au-Prince",
    "iso:country":"HT",
    "name:fra_x_preferred":[
        "Barbe Pangnole"
    ],
    "wof:name":"Barbe Pangnol",
    "wof:placetype":"locality"
},
  "geometry": {"coordinates":[-71.76742,18.10783],"type":"Point"}
}