{
  "type": "Feature",
  "properties": {
    "gn:admin1_code":"15.0",
    "gn:admin2_code":"3731122.0",
    "gn:asciiname":"Israel",
    "gn:country_code":"HT",
    "gn:dem":386,
    "gn:feature_class":"P",
    "gn:feature_code":"PPL",
    "gn:name":"Isra\u00ebl",
    "gn:population":0,
    "gn:timezone":"America/Port-au-Prince",
    "iso:country":"HT",
    "wof:name":"Israel",
    "wof:placetype":"locality"
},
  "geometry": {"coordinates":[-73.53471999999999,18.47806],"type":"Point"}
}