{
  "type": "Feature",
  "properties": {
    "gn:admin1_code":"10.0",
    "gn:admin2_code":"3719435.0",
    "gn:asciiname":"Bernard",
    "gn:country_code":"HT",
    "gn:dem":644,
    "gn:feature_class":"P",
    "gn:feature_code":"PPL",
    "gn:name":"Bernard",
    "gn:population":0,
    "gn:timezone":"America/Port-au-Prince",
    "iso:country":"HT",
    "name:fra_x_preferred":[
        "Bernard"
    ],
    "name:ltz_x_preferred":[
        "Bernard"
    ],
    "name:slv_x_preferred":[
        "Bernard"
    ],
    "wof:name":"Bernard",
    "wof:placetype":"locality"
},
  "geometry": {"coordinates":[-71.78545,19.39087],"type":"Point"}
}