{
  "type": "Feature",
  "properties": {
    "gn:admin1_code":"6.0",
    "gn:admin2_code":"3717563.0",
    "gn:asciiname":"Marche Louverture",
    "gn:country_code":"HT",
    "gn:dem":562,
    "gn:feature_class":"P",
    "gn:feature_code":"PPL",
    "gn:name":"March\u00e9 Louverture",
    "gn:population":0,
    "gn:timezone":"America/Port-au-Prince",
    "iso:country":"HT",
    "name:fra_x_preferred":[
        "March\u00e9 Louverture"
    ],
    "wof:name":"Marche Louverture",
    "wof:placetype":"locality"
},
  "geometry": {"coordinates":[-72.31389,19.42626],"type":"Point"}
}