{
  "type": "Feature",
  "properties": {
    "gn:admin1_code":"12.0",
    "gn:admin2_code":"3731094.0",
    "gn:asciiname":"Laroque",
    "gn:country_code":"HT",
    "gn:dem":579,
    "gn:feature_class":"P",
    "gn:feature_code":"PPL",
    "gn:name":"Laroque",
    "gn:population":0,
    "gn:timezone":"America/Port-au-Prince",
    "iso:country":"HT",
    "name:bre_x_preferred":[
        "Laroque"
    ],
    "name:ceb_x_preferred":[
        "Laroque"
    ],
    "name:deu_x_preferred":[
        "Laroque"
    ],
    "name:fra_x_preferred":[
        "Laroque"
    ],
    "name:ita_x_preferred":[
        "Laroque"
    ],
    "name:nds_x_preferred":[
        "Laroque"
    ],
    "name:nld_x_preferred":[
        "Laroque"
    ],
    "name:pms_x_preferred":[
        "Laroque"
    ],
    "name:pol_x_preferred":[
        "Laroque"
    ],
    "name:por_x_preferred":[
        "Laroque"
    ],
    "name:rus_x_preferred":[
        "\u041b\u0430\u0440\u043e\u043a"
    ],
    "name:slk_x_preferred":[
        "Laroque"
    ],
    "name:spa_x_preferred":[
        "Laroque"
    ],
    "name:swe_x_preferred":[
        "Laroque"
    ],
    "name:ukr_x_preferred":[
        "\u041b\u0430\u0440\u043e\u043a"
    ],
    "wof:name":"Laroque",
    "wof:placetype":"locality"
},
  "geometry": {"coordinates":[-73.65024,18.40492],"type":"Point"}
}