{
  "type": "Feature",
  "properties": {
    "gn:admin1_code":"6.0",
    "gn:admin2_code":"3717563.0",
    "gn:asciiname":"Libon",
    "gn:country_code":"HT",
    "gn:dem":594,
    "gn:feature_class":"P",
    "gn:feature_code":"PPL",
    "gn:name":"Libon",
    "gn:population":0,
    "gn:timezone":"America/Port-au-Prince",
    "iso:country":"HT",
    "name:fra_x_preferred":[
        "Libon"
    ],
    "wof:name":"Libon",
    "wof:placetype":"locality"
},
  "geometry": {"coordinates":[-72.39296,19.47346],"type":"Point"}
}