{
  "type": "Feature",
  "properties": {
    "gn:admin1_code":"3.0",
    "gn:admin2_code":"3720764.0",
    "gn:asciiname":"Bord-de-Mer de Jean-Rabel",
    "gn:country_code":"HT",
    "gn:dem":18,
    "gn:feature_class":"P",
    "gn:feature_code":"PPL",
    "gn:name":"Bord-de-Mer de Jean-Rabel",
    "gn:population":0,
    "gn:timezone":"America/Port-au-Prince",
    "iso:country":"HT",
    "name:und_x_variant":[
        "Magasins",
        "Almagenes",
        "Bord de Mer Jean Rabel",
        "Alma\u00e7enes",
        "Bord-de-Mer de Jean-Rabel"
    ],
    "wof:name":"Bord-de-Mer de Jean-Rabel",
    "wof:placetype":"locality"
},
  "geometry": {"coordinates":[-73.19464000000001,19.90674],"type":"Point"}
}