{
  "type": "Feature",
  "properties": {
    "gn:admin1_code":"11.0",
    "gn:admin2_code":"3722285.0",
    "gn:asciiname":"Dufort",
    "gn:country_code":"HT",
    "gn:dem":39,
    "gn:feature_class":"P",
    "gn:feature_code":"PPL",
    "gn:name":"Dufort",
    "gn:population":0,
    "gn:timezone":"America/Port-au-Prince",
    "iso:country":"HT",
    "name:fra_x_preferred":[
        "Dufort"
    ],
    "wof:name":"Dufort",
    "wof:placetype":"locality"
},
  "geometry": {"coordinates":[-72.63383,18.45777],"type":"Point"}
}