{
  "type": "Feature",
  "properties": {
    "gn:admin1_code":"9.0",
    "gn:admin2_code":"3731232.0",
    "gn:asciiname":"Baubere",
    "gn:country_code":"HT",
    "gn:dem":360,
    "gn:feature_class":"P",
    "gn:feature_code":"PPL",
    "gn:name":"Baub\u00e8re",
    "gn:population":0,
    "gn:timezone":"America/Port-au-Prince",
    "iso:country":"HT",
    "wof:name":"Baubere",
    "wof:placetype":"locality"
},
  "geometry": {"coordinates":[-72.26666999999998,19.58333],"type":"Point"}
}