{
  "type": "Feature",
  "properties": {
    "gn:admin1_code":"11.0",
    "gn:admin2_code":"3722285.0",
    "gn:asciiname":"Carlos",
    "gn:country_code":"HT",
    "gn:dem":824,
    "gn:feature_class":"P",
    "gn:feature_code":"PPL",
    "gn:name":"Carlos",
    "gn:population":0,
    "gn:timezone":"America/Port-au-Prince",
    "iso:country":"HT",
    "name:aze_x_preferred":[
        "Karlos"
    ],
    "name:ceb_x_preferred":[
        "Carlos"
    ],
    "name:ces_x_preferred":[
        "Carlos"
    ],
    "name:deu_x_preferred":[
        "Carlos"
    ],
    "name:fas_x_preferred":[
        "\u06a9\u0627\u0631\u0644\u0648\u0633"
    ],
    "name:fin_x_preferred":[
        "Carlos"
    ],
    "name:fra_x_preferred":[
        "Carlos"
    ],
    "name:heb_x_preferred":[
        "\u05e7\u05e8\u05dc\u05d5\u05e1"
    ],
    "name:hye_x_preferred":[
        "\u053f\u0561\u057c\u056c\u0578\u057d"
    ],
    "name:ita_x_preferred":[
        "Carlos"
    ],
    "name:jpn_x_preferred":[
        "\u30ab\u30eb\u30ed\u30b9"
    ],
    "name:kor_x_preferred":[
        "\uce74\ub97c\ub85c\uc2a4"
    ],
    "name:lav_x_preferred":[
        "Karloss"
    ],
    "name:ltz_x_preferred":[
        "Carlos"
    ],
    "name:nld_x_preferred":[
        "Carlos"
    ],
    "name:pol_x_preferred":[
        "Carlos"
    ],
    "name:por_x_preferred":[
        "Carlos"
    ],
    "name:ron_x_preferred":[
        "Carlos"
    ],
    "name:rus_x_preferred":[
        "\u041a\u0430\u0440\u043b\u043e\u0441"
    ],
    "name:spa_x_preferred":[
        "Carlos"
    ],
    "name:srp_x_preferred":[
        "\u041a\u0430\u0440\u043b\u043e\u0441"
    ],
    "name:swe_x_preferred":[
        "Carlos"
    ],
    "name:ukr_x_preferred":[
        "\u041a\u0430\u0440\u043b\u043e\u0441"
    ],
    "name:vie_x_preferred":[
        "Carlos"
    ],
    "name:vol_x_preferred":[
        "Carlos"
    ],
    "name:zho_x_preferred":[
        "\u5361\u6d1b\u65af"
    ],
    "wof:name":"Carlos",
    "wof:placetype":"locality"
},
  "geometry": {"coordinates":[-72.95,18.35],"type":"Point"}
}