{
  "type": "Feature",
  "properties": {
    "gn:admin1_code":"11.0",
    "gn:admin2_code":"3722285.0",
    "gn:asciiname":"Marati",
    "gn:country_code":"HT",
    "gn:dem":147,
    "gn:feature_class":"P",
    "gn:feature_code":"PPL",
    "gn:name":"Marati",
    "gn:population":0,
    "gn:timezone":"America/Port-au-Prince",
    "iso:country":"HT",
    "name:fra_x_preferred":[
        "Marati"
    ],
    "wof:name":"Marati",
    "wof:placetype":"locality"
},
  "geometry": {"coordinates":[-72.97099,18.43241],"type":"Point"}
}