{
  "type": "Feature",
  "properties": {
    "gn:admin1_code":"15.0",
    "gn:admin2_code":"3731122.0",
    "gn:asciiname":"Pini",
    "gn:country_code":"HT",
    "gn:dem":328,
    "gn:feature_class":"P",
    "gn:feature_code":"PPL",
    "gn:name":"Pini",
    "gn:population":0,
    "gn:timezone":"America/Port-au-Prince",
    "iso:country":"HT",
    "wof:name":"Pini",
    "wof:placetype":"locality"
},
  "geometry": {"coordinates":[-73.52556,18.43194],"type":"Point"}
}