{
  "type": "Feature",
  "properties": {
    "gn:admin1_code":"11.0",
    "gn:admin2_code":"3731086.0",
    "gn:asciiname":"Garicher",
    "gn:country_code":"HT",
    "gn:dem":932,
    "gn:feature_class":"P",
    "gn:feature_code":"PPL",
    "gn:name":"Garicher",
    "gn:population":0,
    "gn:timezone":"America/Port-au-Prince",
    "iso:country":"HT",
    "wof:name":"Garicher",
    "wof:placetype":"locality"
},
  "geometry": {"coordinates":[-72.56667,18.95],"type":"Point"}
}