{
  "type": "Feature",
  "properties": {
    "gn:admin1_code":"13.0",
    "gn:admin2_code":"3723778.0",
    "gn:asciiname":"Fond Nabote",
    "gn:country_code":"HT",
    "gn:dem":482,
    "gn:feature_class":"P",
    "gn:feature_code":"PPL",
    "gn:name":"Fond Nabote",
    "gn:population":0,
    "gn:timezone":"America/Port-au-Prince",
    "iso:country":"HT",
    "name:und_x_variant":[
        "Fond Habote",
        "Fond Nabote"
    ],
    "wof:name":"Fond Nabote",
    "wof:placetype":"locality"
},
  "geometry": {"coordinates":[-72.57644999999999,18.32037],"type":"Point"}
}