{
  "type": "Feature",
  "properties": {
    "gn:admin1_code":"12.0",
    "gn:admin2_code":"3718404.0",
    "gn:asciiname":"Romain",
    "gn:country_code":"HT",
    "gn:dem":260,
    "gn:feature_class":"P",
    "gn:feature_code":"PPL",
    "gn:name":"Romain",
    "gn:population":0,
    "gn:timezone":"America/Port-au-Prince",
    "iso:country":"HT",
    "name:ceb_x_preferred":[
        "Romain"
    ],
    "name:deu_x_preferred":[
        "Romain"
    ],
    "name:fra_x_preferred":[
        "Romain"
    ],
    "name:ita_x_preferred":[
        "Romain"
    ],
    "name:nds_x_preferred":[
        "Romain"
    ],
    "name:nld_x_preferred":[
        "Romain"
    ],
    "name:oci_x_preferred":[
        "Romain"
    ],
    "name:pms_x_preferred":[
        "Romain"
    ],
    "name:pol_x_preferred":[
        "Romain"
    ],
    "name:por_x_preferred":[
        "Romain"
    ],
    "name:rus_x_preferred":[
        "\u0420\u043e\u043c\u0435\u043d"
    ],
    "name:slk_x_preferred":[
        "Romain"
    ],
    "name:spa_x_preferred":[
        "Romain"
    ],
    "name:swe_x_preferred":[
        "Romain"
    ],
    "name:ukr_x_preferred":[
        "\u0420\u043e\u043c\u0435\u043d"
    ],
    "wof:name":"Romain",
    "wof:placetype":"locality"
},
  "geometry": {"coordinates":[-73.89806,18.13056],"type":"Point"}
}