{
  "type": "Feature",
  "properties": {
    "gn:admin1_code":"14.0",
    "gn:asciiname":"Morne Brice",
    "gn:country_code":"HT",
    "gn:dem":329,
    "gn:feature_class":"P",
    "gn:feature_code":"PPL",
    "gn:name":"Morne Brice",
    "gn:population":0,
    "gn:timezone":"America/Port-au-Prince",
    "iso:country":"HT",
    "wof:name":"Morne Brice",
    "wof:placetype":"locality"
},
  "geometry": {"coordinates":[-73.23333000000002,18.35],"type":"Point"}
}