{
  "type": "Feature",
  "properties": {
    "gn:admin1_code":"3.0",
    "gn:admin2_code":"3717599.0",
    "gn:asciiname":"Nan Mombin",
    "gn:country_code":"HT",
    "gn:dem":212,
    "gn:feature_class":"P",
    "gn:feature_code":"PPL",
    "gn:name":"Nan Mombin",
    "gn:population":0,
    "gn:timezone":"America/Port-au-Prince",
    "iso:country":"HT",
    "wof:name":"Nan Mombin",
    "wof:placetype":"locality"
},
  "geometry": {"coordinates":[-72.58333,19.88333],"type":"Point"}
}