{
  "type": "Feature",
  "properties": {
    "gn:admin1_code":"11.0",
    "gn:admin2_code":"3718425",
    "gn:asciiname":"Andre Libre",
    "gn:country_code":"HT",
    "gn:dem":1256,
    "gn:feature_class":"P",
    "gn:feature_code":"PPL",
    "gn:name":"Andr\u00e9 Libre",
    "gn:population":0,
    "gn:timezone":"America/Port-au-Prince",
    "iso:country":"HT",
    "wof:name":"Andre Libre",
    "wof:placetype":"locality"
},
  "geometry": {"coordinates":[-72.23333000000002,18.46667],"type":"Point"}
}