{
  "type": "Feature",
  "properties": {
    "gn:admin1_code":"11.0",
    "gn:admin2_code":"3722285.0",
    "gn:asciiname":"Vialet",
    "gn:country_code":"HT",
    "gn:dem":46,
    "gn:feature_class":"P",
    "gn:feature_code":"PPL",
    "gn:name":"Vialet",
    "gn:population":0,
    "gn:timezone":"America/Port-au-Prince",
    "iso:country":"HT",
    "name:fra_x_preferred":[
        "Vialet"
    ],
    "wof:name":"Vialet",
    "wof:placetype":"locality"
},
  "geometry": {"coordinates":[-72.93335,18.41941],"type":"Point"}
}