{
  "type": "Feature",
  "properties": {
    "gn:admin1_code":"14.0",
    "gn:admin2_code":"3731116.0",
    "gn:asciiname":"Potorien",
    "gn:country_code":"HT",
    "gn:dem":176,
    "gn:feature_class":"P",
    "gn:feature_code":"PPL",
    "gn:name":"Potorien",
    "gn:population":0,
    "gn:timezone":"America/Port-au-Prince",
    "iso:country":"HT",
    "name:fra_x_preferred":[
        "Potorien"
    ],
    "wof:name":"Potorien",
    "wof:placetype":"locality"
},
  "geometry": {"coordinates":[-74.35899000000001,18.41761],"type":"Point"}
}