{
  "type": "Feature",
  "properties": {
    "gn:admin1_code":"13.0",
    "gn:admin2_code":"3723778.0",
    "gn:asciiname":"Sable Cabaret",
    "gn:country_code":"HT",
    "gn:dem":17,
    "gn:feature_class":"P",
    "gn:feature_code":"PPL",
    "gn:name":"Sable Cabaret",
    "gn:population":0,
    "gn:timezone":"America/Port-au-Prince",
    "iso:country":"HT",
    "name:fra_x_preferred":[
        "Sable Cabaret"
    ],
    "wof:name":"Sable Cabaret",
    "wof:placetype":"locality"
},
  "geometry": {"coordinates":[-72.55461,18.22818],"type":"Point"}
}