{
  "type": "Feature",
  "properties": {
    "gn:admin1_code":"11.0",
    "gn:admin2_code":"3718425.0",
    "gn:asciiname":"Dupont",
    "gn:country_code":"HT",
    "gn:dem":429,
    "gn:feature_class":"P",
    "gn:feature_code":"PPL",
    "gn:name":"Dupont",
    "gn:population":0,
    "gn:timezone":"America/Port-au-Prince",
    "iso:country":"HT",
    "wof:name":"Dupont",
    "wof:placetype":"locality"
},
  "geometry": {"coordinates":[-72.25610999999998,18.50556],"type":"Point"}
}