{
  "type": "Feature",
  "properties": {
    "gn:admin1_code":"7.0",
    "gn:asciiname":"Pino",
    "gn:country_code":"HT",
    "gn:dem":871,
    "gn:feature_class":"P",
    "gn:feature_code":"PPL",
    "gn:name":"Pino",
    "gn:population":0,
    "gn:timezone":"America/Port-au-Prince",
    "iso:country":"HT",
    "name:cat_x_preferred":[
        "Pino"
    ],
    "name:ceb_x_preferred":[
        "Pino"
    ],
    "name:deu_x_preferred":[
        "Pino"
    ],
    "name:eus_x_preferred":[
        "Pino"
    ],
    "name:fra_x_preferred":[
        "Pino"
    ],
    "name:glg_x_preferred":[
        "Pino"
    ],
    "name:ita_x_preferred":[
        "Pino"
    ],
    "name:nld_x_preferred":[
        "Pino"
    ],
    "name:por_x_preferred":[
        "Pino"
    ],
    "name:rus_x_preferred":[
        "\u041f\u0438\u043d\u043e"
    ],
    "name:slk_x_preferred":[
        "Pino"
    ],
    "name:spa_x_preferred":[
        "Pino"
    ],
    "name:srp_x_preferred":[
        "Pino"
    ],
    "name:swe_x_preferred":[
        "Pino"
    ],
    "name:ukr_x_preferred":[
        "\u041f\u0456\u043d\u043e"
    ],
    "wof:name":"Pino",
    "wof:placetype":"locality"
},
  "geometry": {"coordinates":[-72.25,18.73333],"type":"Point"}
}