{
  "type": "Feature",
  "properties": {
    "gn:admin1_code":"11.0",
    "gn:admin2_code":"3722285.0",
    "gn:asciiname":"Chavannes",
    "gn:country_code":"HT",
    "gn:dem":69,
    "gn:feature_class":"P",
    "gn:feature_code":"PPL",
    "gn:name":"Chavannes",
    "gn:population":0,
    "gn:timezone":"America/Port-au-Prince",
    "iso:country":"HT",
    "name:als_x_preferred":[
        "Chavannes"
    ],
    "name:ceb_x_preferred":[
        "Chavannes"
    ],
    "name:deu_x_preferred":[
        "Chavannes"
    ],
    "name:epo_x_preferred":[
        "Chavannes"
    ],
    "name:fra_x_preferred":[
        "Chavannes"
    ],
    "name:ita_x_preferred":[
        "Chavannes"
    ],
    "name:jpn_x_preferred":[
        "\u30b7\u30e3\u30f4\u30a1\u30f3\u30cc"
    ],
    "name:nds_x_preferred":[
        "Chavannes"
    ],
    "name:nld_x_preferred":[
        "Chavannes"
    ],
    "name:pms_x_preferred":[
        "Chavannes"
    ],
    "name:pol_x_preferred":[
        "Chavannes"
    ],
    "name:rus_x_preferred":[
        "\u0428\u0430\u0432\u0430\u043d"
    ],
    "name:slk_x_preferred":[
        "Chavannes"
    ],
    "name:slv_x_preferred":[
        "Chavannes"
    ],
    "name:spa_x_preferred":[
        "Chavannes"
    ],
    "name:srp_x_preferred":[
        "\u0428\u0430\u0432\u0430\u043d"
    ],
    "name:swe_x_preferred":[
        "Chavannes"
    ],
    "wof:name":"Chavannes",
    "wof:placetype":"locality"
},
  "geometry": {"coordinates":[-72.86667,18.41667],"type":"Point"}
}