{
  "type": "Feature",
  "properties": {
    "gn:admin1_code":"3.0",
    "gn:admin2_code":"3718419.0",
    "gn:asciiname":"Colombier",
    "gn:country_code":"HT",
    "gn:dem":431,
    "gn:feature_class":"P",
    "gn:feature_code":"PPL",
    "gn:name":"Colombier",
    "gn:population":0,
    "gn:timezone":"America/Port-au-Prince",
    "iso:country":"HT",
    "name:als_x_preferred":[
        "Colombier"
    ],
    "name:cat_x_preferred":[
        "Colombier"
    ],
    "name:ceb_x_preferred":[
        "Colombier"
    ],
    "name:deu_x_preferred":[
        "Colombier"
    ],
    "name:epo_x_preferred":[
        "Colombier"
    ],
    "name:fra_x_preferred":[
        "Colombier"
    ],
    "name:ita_x_preferred":[
        "Colombier"
    ],
    "name:lmo_x_preferred":[
        "Colombier"
    ],
    "name:nds_x_preferred":[
        "Colombier"
    ],
    "name:nld_x_preferred":[
        "Colombier"
    ],
    "name:oci_x_preferred":[
        "Colombier"
    ],
    "name:pms_x_preferred":[
        "Colombier"
    ],
    "name:pol_x_preferred":[
        "Colombier"
    ],
    "name:por_x_preferred":[
        "Colombier"
    ],
    "name:roh_x_preferred":[
        "Colombier"
    ],
    "name:slk_x_preferred":[
        "Colombier"
    ],
    "name:spa_x_preferred":[
        "Colombier"
    ],
    "name:srp_x_preferred":[
        "\u041a\u043e\u043b\u043e\u043c\u0431\u0458\u0435"
    ],
    "name:swe_x_preferred":[
        "Colombier"
    ],
    "name:ukr_x_preferred":[
        "\u041a\u043e\u043b\u043e\u043c\u0431'\u0454"
    ],
    "wof:name":"Colombier",
    "wof:placetype":"locality"
},
  "geometry": {"coordinates":[-72.93333,19.76667],"type":"Point"}
}