{
  "type": "Feature",
  "properties": {
    "gn:admin1_code":"14.0",
    "gn:admin2_code":"3731116.0",
    "gn:asciiname":"Fond Boucan",
    "gn:country_code":"HT",
    "gn:dem":84,
    "gn:feature_class":"P",
    "gn:feature_code":"PPL",
    "gn:name":"Fond Boucan",
    "gn:population":0,
    "gn:timezone":"America/Port-au-Prince",
    "iso:country":"HT",
    "name:fra_x_preferred":[
        "Fond Boucan"
    ],
    "wof:name":"Fond Boucan",
    "wof:placetype":"locality"
},
  "geometry": {"coordinates":[-74.32739000000002,18.54386],"type":"Point"}
}