{
  "type": "Feature",
  "properties": {
    "gn:admin1_code":"6.0",
    "gn:admin2_code":"3726539.0",
    "gn:asciiname":"La Chicotte",
    "gn:country_code":"HT",
    "gn:dem":22,
    "gn:feature_class":"P",
    "gn:feature_code":"PPL",
    "gn:name":"La Chicotte",
    "gn:population":0,
    "gn:timezone":"America/Port-au-Prince",
    "iso:country":"HT",
    "wof:name":"La Chicotte",
    "wof:placetype":"locality"
},
  "geometry": {"coordinates":[-72.55,19.15],"type":"Point"}
}