{
  "type": "Feature",
  "properties": {
    "gn:admin1_code":"13.0",
    "gn:admin2_code":"3723778.0",
    "gn:asciiname":"Desmarates",
    "gn:country_code":"HT",
    "gn:dem":57,
    "gn:feature_class":"P",
    "gn:feature_code":"PPL",
    "gn:name":"Desmarates",
    "gn:population":0,
    "gn:timezone":"America/Port-au-Prince",
    "iso:country":"HT",
    "wof:name":"Desmarates",
    "wof:placetype":"locality"
},
  "geometry": {"coordinates":[-72.55583,18.24944],"type":"Point"}
}