{
  "type": "Feature",
  "properties": {
    "gn:admin1_code":"3.0",
    "gn:admin2_code":"3720764.0",
    "gn:asciiname":"Bassin Long",
    "gn:country_code":"HT",
    "gn:dem":95,
    "gn:feature_class":"P",
    "gn:feature_code":"PPL",
    "gn:name":"Bassin Long",
    "gn:population":0,
    "gn:timezone":"America/Port-au-Prince",
    "iso:country":"HT",
    "wof:name":"Bassin Long",
    "wof:placetype":"locality"
},
  "geometry": {"coordinates":[-73.15000000000001,19.66667],"type":"Point"}
}