{
  "type": "Feature",
  "properties": {
    "gn:admin1_code":"3.0",
    "gn:asciiname":"Lan Boucan",
    "gn:country_code":"HT",
    "gn:dem":12,
    "gn:feature_class":"P",
    "gn:feature_code":"PPL",
    "gn:name":"Lan Boucan",
    "gn:population":0,
    "gn:timezone":"America/Port-au-Prince",
    "iso:country":"HT",
    "wof:name":"Lan Boucan",
    "wof:placetype":"locality"
},
  "geometry": {"coordinates":[-73.10167,19.64306],"type":"Point"}
}