{
  "type": "Feature",
  "properties": {
    "gn:admin1_code":"9.0",
    "gn:admin2_code":"3718665.0",
    "gn:asciiname":"Premier",
    "gn:country_code":"HT",
    "gn:dem":1077,
    "gn:feature_class":"P",
    "gn:feature_code":"PPL",
    "gn:name":"Premier",
    "gn:population":0,
    "gn:timezone":"America/Port-au-Prince",
    "iso:country":"HT",
    "name:fas_x_preferred":[
        "\u0631\u0647\u0628\u0631 \u067e\u0627\u0631\u0644\u0645\u0627\u0646\u06cc"
    ],
    "name:ita_x_preferred":[
        "Premierato"
    ],
    "name:lim_x_preferred":[
        "Premier"
    ],
    "name:nld_x_preferred":[
        "Premier"
    ],
    "name:por_x_preferred":[
        "Premier"
    ],
    "name:spa_x_preferred":[
        "Premier"
    ],
    "name:urd_x_preferred":[
        "\u067e\u0631\u06cc\u0645\u06cc\u0626\u0631"
    ],
    "wof:name":"Premier",
    "wof:placetype":"locality"
},
  "geometry": {"coordinates":[-72.59999999999999,19.73333],"type":"Point"}
}