{
  "type": "Feature",
  "properties": {
    "gn:admin1_code":"11.0",
    "gn:admin2_code":"3722285.0",
    "gn:asciiname":"Bois Neuf",
    "gn:country_code":"HT",
    "gn:dem":595,
    "gn:feature_class":"P",
    "gn:feature_code":"PPL",
    "gn:name":"Bois Neuf",
    "gn:population":0,
    "gn:timezone":"America/Port-au-Prince",
    "iso:country":"HT",
    "wof:name":"Bois Neuf",
    "wof:placetype":"locality"
},
  "geometry": {"coordinates":[-72.59999999999999,18.36667000000001],"type":"Point"}
}