{
  "type": "Feature",
  "properties": {
    "gn:admin1_code":"12.0",
    "gn:admin2_code":"3728096.0",
    "gn:asciiname":"Musso",
    "gn:country_code":"HT",
    "gn:dem":85,
    "gn:feature_class":"P",
    "gn:feature_code":"PPL",
    "gn:name":"Musso",
    "gn:population":0,
    "gn:timezone":"America/Port-au-Prince",
    "iso:country":"HT",
    "name:ara_x_preferred":[
        "\u0645\u0648\u0633\u0648"
    ],
    "name:aze_x_preferred":[
        "Manovar Musso"
    ],
    "name:deu_x_preferred":[
        "Manowar Musso"
    ],
    "name:hye_x_preferred":[
        "\u0544\u0561\u0576\u0578\u057e\u0561\u0580 \u0544\u0578\u0582\u057d\u0578"
    ],
    "name:ind_x_preferred":[
        "Musso"
    ],
    "name:kaz_x_preferred":[
        "\u041c\u0430\u043d\u043e\u0432\u0430\u0440 \u041c\u0443\u0441\u0441\u043e"
    ],
    "name:rus_x_preferred":[
        "\u041c\u0443\u0441\u0441\u043e"
    ],
    "name:spa_x_preferred":[
        "Musso"
    ],
    "wof:name":"Musso",
    "wof:placetype":"locality"
},
  "geometry": {"coordinates":[-73.90000000000001,18.21667],"type":"Point"}
}