{
  "type": "Feature",
  "properties": {
    "gn:admin1_code":"9.0",
    "gn:admin2_code":"3722122.0",
    "gn:asciiname":"Bertrand",
    "gn:country_code":"HT",
    "gn:dem":66,
    "gn:feature_class":"P",
    "gn:feature_code":"PPL",
    "gn:name":"Bertrand",
    "gn:population":0,
    "gn:timezone":"America/Port-au-Prince",
    "iso:country":"HT",
    "name:bre_x_preferred":[
        "Bertrand"
    ],
    "name:ceb_x_preferred":[
        "Bertrand"
    ],
    "name:dan_x_preferred":[
        "Bertrand"
    ],
    "name:deu_x_preferred":[
        "Bertrand"
    ],
    "name:fra_x_preferred":[
        "Bertrand"
    ],
    "name:heb_x_preferred":[
        "\u05d1\u05e8\u05d8\u05e8\u05d0\u05df"
    ],
    "name:ita_x_preferred":[
        "Bertrand"
    ],
    "name:jpn_x_preferred":[
        "\u30d9\u30eb\u30c8\u30e9\u30f3"
    ],
    "name:kor_x_preferred":[
        "\ubca0\ub974\ud2b8\ub791"
    ],
    "name:nld_x_preferred":[
        "Bertrand"
    ],
    "name:pol_x_preferred":[
        "Bertrand"
    ],
    "name:por_x_preferred":[
        "Bertrand"
    ],
    "name:rus_x_preferred":[
        "\u0411\u0435\u0440\u0442\u0440\u0430\u043d"
    ],
    "name:spa_x_preferred":[
        "Bertrand"
    ],
    "name:srp_x_preferred":[
        "\u0411\u0435\u0440\u0442\u0440\u0430\u043d\u0434"
    ],
    "name:swe_x_preferred":[
        "Bertrand"
    ],
    "name:ukr_x_preferred":[
        "\u0411\u0435\u0440\u0442\u0440\u0430\u043d"
    ],
    "name:urd_x_preferred":[
        "\u0628\u0631\u0679\u0631\u06cc\u0646\u0688"
    ],
    "name:vol_x_preferred":[
        "Bertrand"
    ],
    "wof:name":"Bertrand",
    "wof:placetype":"locality"
},
  "geometry": {"coordinates":[-72.40000000000001,19.66667],"type":"Point"}
}