{
  "type": "Feature",
  "properties": {
    "gn:admin1_code":"13.0",
    "gn:admin2_code":"3723778.0",
    "gn:asciiname":"Castel",
    "gn:country_code":"HT",
    "gn:dem":503,
    "gn:feature_class":"P",
    "gn:feature_code":"PPL",
    "gn:name":"Castel",
    "gn:population":0,
    "gn:timezone":"America/Port-au-Prince",
    "iso:country":"HT",
    "name:ceb_x_preferred":[
        "Castel"
    ],
    "name:deu_x_preferred":[
        "Castel"
    ],
    "name:fra_x_preferred":[
        "Castel"
    ],
    "name:ita_x_preferred":[
        "Castel"
    ],
    "name:nld_x_preferred":[
        "Castel"
    ],
    "name:por_x_preferred":[
        "Castel"
    ],
    "name:ron_x_preferred":[
        "Castel"
    ],
    "name:sco_x_preferred":[
        "Castel"
    ],
    "name:swe_x_preferred":[
        "Castel"
    ],
    "wof:name":"Castel",
    "wof:placetype":"locality"
},
  "geometry": {"coordinates":[-72.5825,18.31472],"type":"Point"}
}