{
  "type": "Feature",
  "properties": {
    "gn:admin1_code":"6.0",
    "gn:admin2_code":"3724695.0",
    "gn:asciiname":"Mandrin",
    "gn:country_code":"HT",
    "gn:dem":24,
    "gn:feature_class":"P",
    "gn:feature_code":"PPL",
    "gn:name":"Mandrin",
    "gn:population":0,
    "gn:timezone":"America/Port-au-Prince",
    "iso:country":"HT",
    "name:deu_x_preferred":[
        "Mandrin"
    ],
    "name:fra_x_preferred":[
        "Mandrin"
    ],
    "name:ita_x_preferred":[
        "Mandrin"
    ],
    "wof:name":"Mandrin",
    "wof:placetype":"locality"
},
  "geometry": {"coordinates":[-72.60441999999998,19.42261],"type":"Point"}
}