{
  "type": "Feature",
  "properties": {
    "gn:admin1_code":"7.0",
    "gn:admin2_code":"3720809.0",
    "gn:asciiname":"Capucins",
    "gn:country_code":"HT",
    "gn:dem":308,
    "gn:feature_class":"P",
    "gn:feature_code":"PPL",
    "gn:name":"Capucins",
    "gn:population":0,
    "gn:timezone":"America/Port-au-Prince",
    "iso:country":"HT",
    "wof:name":"Capucins",
    "wof:placetype":"locality"
},
  "geometry": {"coordinates":[-72.23333000000002,18.98333],"type":"Point"}
}