{
  "type": "Feature",
  "properties": {
    "gn:admin1_code":"7.0",
    "gn:admin2_code":"3720809.0",
    "gn:asciiname":"Le Dier",
    "gn:country_code":"HT",
    "gn:dem":142,
    "gn:feature_class":"P",
    "gn:feature_code":"PPL",
    "gn:name":"Le Dier",
    "gn:population":0,
    "gn:timezone":"America/Port-au-Prince",
    "iso:country":"HT",
    "wof:name":"Le Dier",
    "wof:placetype":"locality"
},
  "geometry": {"coordinates":[-72.08333,18.86667000000001],"type":"Point"}
}