{
  "type": "Feature",
  "properties": {
    "gn:admin1_code":"11.0",
    "gn:admin2_code":"3723019.0",
    "gn:asciiname":"Nouvelle Cite",
    "gn:country_code":"HT",
    "gn:dem":349,
    "gn:feature_class":"P",
    "gn:feature_code":"PPL",
    "gn:name":"Nouvelle Cit\u00e9",
    "gn:population":0,
    "gn:timezone":"America/Port-au-Prince",
    "iso:country":"HT",
    "name:fra_x_preferred":[
        "Nouvelle Cit\u00e9"
    ],
    "wof:name":"Nouvelle Cite",
    "wof:placetype":"locality"
},
  "geometry": {"coordinates":[-72.84644,18.7879],"type":"Point"}
}