{
  "type": "Feature",
  "properties": {
    "gn:admin1_code":"6.0",
    "gn:admin2_code":"3726539.0",
    "gn:asciiname":"Durand",
    "gn:country_code":"HT",
    "gn:dem":74,
    "gn:feature_class":"P",
    "gn:feature_code":"PPL",
    "gn:name":"Durand",
    "gn:population":0,
    "gn:timezone":"America/Port-au-Prince",
    "iso:country":"HT",
    "name:cat_x_preferred":[
        "Durand"
    ],
    "name:ceb_x_preferred":[
        "Durand"
    ],
    "name:deu_x_preferred":[
        "Durand"
    ],
    "name:fra_x_preferred":[
        "Durand"
    ],
    "name:ita_x_preferred":[
        "Durand"
    ],
    "name:nld_x_preferred":[
        "Durand"
    ],
    "name:pol_x_preferred":[
        "Durand"
    ],
    "name:spa_x_preferred":[
        "Durand"
    ],
    "name:srp_x_preferred":[
        "\u0414\u0458\u0443\u0440\u0430\u043d\u0434"
    ],
    "name:ukr_x_preferred":[
        "\u0414\u044e\u0440\u0430\u043d"
    ],
    "name:vol_x_preferred":[
        "Durand"
    ],
    "wof:name":"Durand",
    "wof:placetype":"locality"
},
  "geometry": {"coordinates":[-72.34044,18.97892],"type":"Point"}
}