{
  "type": "Feature",
  "properties": {
    "gn:admin1_code":"11.0",
    "gn:admin2_code":"3727134.0",
    "gn:asciiname":"Cache-Cache",
    "gn:country_code":"HT",
    "gn:dem":411,
    "gn:feature_class":"P",
    "gn:feature_code":"PPL",
    "gn:name":"Cache-Cache",
    "gn:population":0,
    "gn:timezone":"America/Port-au-Prince",
    "iso:country":"HT",
    "wof:name":"Cache-Cache",
    "wof:placetype":"locality"
},
  "geometry": {"coordinates":[-72.33333,18.73333],"type":"Point"}
}