{
  "type": "Feature",
  "properties": {
    "gn:admin1_code":"13.0",
    "gn:asciiname":"Lerrer",
    "gn:country_code":"HT",
    "gn:dem":445,
    "gn:feature_class":"P",
    "gn:feature_code":"PPL",
    "gn:name":"Lerrer",
    "gn:population":0,
    "gn:timezone":"America/Port-au-Prince",
    "iso:country":"HT",
    "wof:name":"Lerrer",
    "wof:placetype":"locality"
},
  "geometry": {"coordinates":[-72.83333,18.28333],"type":"Point"}
}