{
  "type": "Feature",
  "properties": {
    "gn:admin1_code":"14.0",
    "gn:admin2_code":"3727381.0",
    "gn:asciiname":"Patate",
    "gn:country_code":"HT",
    "gn:dem":681,
    "gn:feature_class":"P",
    "gn:feature_code":"PPL",
    "gn:name":"Patate",
    "gn:population":0,
    "gn:timezone":"America/Port-au-Prince",
    "iso:country":"HT",
    "name:ces_x_preferred":[
        "Patate"
    ],
    "name:fas_x_preferred":[
        "\u067e\u0627\u062a\u0627\u062a\u0647"
    ],
    "name:fra_x_preferred":[
        "Patate"
    ],
    "name:ind_x_preferred":[
        "Patate"
    ],
    "name:lit_x_preferred":[
        "Patat\u0117"
    ],
    "name:que_x_preferred":[
        "Patate"
    ],
    "name:spa_x_preferred":[
        "Patate"
    ],
    "wof:name":"Patate",
    "wof:placetype":"locality"
},
  "geometry": {"coordinates":[-74.05,18.46667],"type":"Point"}
}