{
  "type": "Feature",
  "properties": {
    "gn:admin1_code":"9.0",
    "gn:asciiname":"Dupuy",
    "gn:country_code":"HT",
    "gn:dem":688,
    "gn:feature_class":"P",
    "gn:feature_code":"PPL",
    "gn:name":"Dupuy",
    "gn:population":0,
    "gn:timezone":"America/Port-au-Prince",
    "iso:country":"HT",
    "name:deu_x_preferred":[
        "Dupuy"
    ],
    "name:fra_x_preferred":[
        "Dupuy"
    ],
    "name:ita_x_preferred":[
        "Dupuy"
    ],
    "name:rus_x_preferred":[
        "\u0414\u044e\u043f\u044e\u0438"
    ],
    "wof:name":"Dupuy",
    "wof:placetype":"locality"
},
  "geometry": {"coordinates":[-72.33333,19.56667],"type":"Point"}
}