{
  "type": "Feature",
  "properties": {
    "gn:admin1_code":"7.0",
    "gn:admin2_code":"3723840.0",
    "gn:asciiname":"Marmont",
    "gn:country_code":"HT",
    "gn:dem":288,
    "gn:feature_class":"P",
    "gn:feature_code":"PPL",
    "gn:name":"Marmont",
    "gn:population":0,
    "gn:timezone":"America/Port-au-Prince",
    "iso:country":"HT",
    "name:fra_x_preferred":[
        "Marmont"
    ],
    "wof:name":"Marmont",
    "wof:placetype":"locality"
},
  "geometry": {"coordinates":[-71.99701,19.08956],"type":"Point"}
}