{
  "type": "Feature",
  "properties": {
    "gn:admin1_code":"11.0",
    "gn:admin2_code":"3722285.0",
    "gn:asciiname":"Pity",
    "gn:country_code":"HT",
    "gn:dem":5,
    "gn:feature_class":"P",
    "gn:feature_code":"PPL",
    "gn:name":"Pity",
    "gn:population":0,
    "gn:timezone":"America/Port-au-Prince",
    "iso:country":"HT",
    "name:und_x_variant":[
        "Piti",
        "Pity"
    ],
    "wof:name":"Pity",
    "wof:placetype":"locality"
},
  "geometry": {"coordinates":[-72.62953,18.54396],"type":"Point"}
}