{
  "type": "Feature",
  "properties": {
    "gn:admin1_code":"11.0",
    "gn:admin2_code":"3722285.0",
    "gn:asciiname":"Pity",
    "gn:country_code":"HT",
    "gn:dem":5,
    "gn:feature_class":"P",
    "gn:feature_code":"PPL",
    "gn:name":"Pity",
    "gn:population":0,
    "gn:timezone":"America/Port-au-Prince",
    "iso:country":"HT",
    "name:cat_x_preferred":[
        "Pietat"
    ],
    "name:fin_x_preferred":[
        "S\u00e4\u00e4li"
    ],
    "name:fra_x_preferred":[
        "Piti\u00e9"
    ],
    "name:glg_x_preferred":[
        "Piedade"
    ],
    "name:hun_x_preferred":[
        "Sajn\u00e1lat"
    ],
    "name:ita_x_preferred":[
        "Piet\u00e0"
    ],
    "name:kan_x_preferred":[
        "\u0c95\u0ca8\u0cbf\u0c95\u0cb0"
    ],
    "name:por_x_preferred":[
        "D\u00f3"
    ],
    "name:rus_x_preferred":[
        "\u0416\u0430\u043b\u043e\u0441\u0442\u044c"
    ],
    "name:scn_x_preferred":[
        "Piatati"
    ],
    "name:spa_x_preferred":[
        "Piedad"
    ],
    "name:tam_x_preferred":[
        "\u0b87\u0bb0\u0b95\u0bcd\u0b95\u0bae\u0bcd"
    ],
    "name:tel_x_preferred":[
        "\u0c1c\u0c3e\u0c32\u0c3f"
    ],
    "name:tur_x_preferred":[
        "Ac\u0131ma"
    ],
    "name:ukr_x_preferred":[
        "\u0416\u0430\u043b\u0456\u0441\u0442\u044c"
    ],
    "name:und_x_variant":[
        "Piti",
        "Pity"
    ],
    "wof:name":"Pity",
    "wof:placetype":"locality"
},
  "geometry": {"coordinates":[-72.62953,18.54396],"type":"Point"}
}