{
  "type": "Feature",
  "properties": {
    "gn:admin1_code":"7.0",
    "gn:admin2_code":"3722578.0",
    "gn:asciiname":"Rache Grande",
    "gn:country_code":"HT",
    "gn:dem":1039,
    "gn:feature_class":"P",
    "gn:feature_code":"PPL",
    "gn:name":"Rache Grande",
    "gn:population":0,
    "gn:timezone":"America/Port-au-Prince",
    "iso:country":"HT",
    "wof:name":"Rache Grande",
    "wof:placetype":"locality"
},
  "geometry": {"coordinates":[-71.84999999999999,18.76667],"type":"Point"}
}