{
  "type": "Feature",
  "properties": {
    "iso:country":"HT",
    "name:unk_x_variant":[
        "Carrefour Bon Repos"
    ],
    "qs:gn_country":"HT",
    "qs:gn_fcode":"PPL",
    "qs:gn_pop":0,
    "qs:name":"Bon Repos",
    "qs:name_adm0":"Ha\u00efti",
    "qs:name_adm1":"Ouest",
    "qs:photos":364,
    "qs:photos_1k":74,
    "qs:photos_9k":2,
    "qs:photos_9r":5,
    "qs:photos_all":364,
    "qs:photos_sr":6,
    "qs:placetype":"Town",
    "qs:pop_sr":"0",
    "qs:woe_adm0":23424839,
    "wof:name":"Bon Repos",
    "wof:placetype":"locality"
},
  "geometry": {"coordinates":[-72.26861,18.62583],"type":"Point"}
}