{
  "type": "Feature",
  "properties": {
    "gn:admin1_code":"12.0",
    "gn:admin2_code":"3728096.0",
    "gn:asciiname":"Lamore",
    "gn:country_code":"HT",
    "gn:dem":279,
    "gn:feature_class":"P",
    "gn:feature_code":"PPL",
    "gn:name":"Lamore",
    "gn:population":0,
    "gn:timezone":"America/Port-au-Prince",
    "iso:country":"HT",
    "name:fra_x_preferred":[
        "Lamore"
    ],
    "wof:name":"Lamore",
    "wof:placetype":"locality"
},
  "geometry": {"coordinates":[-73.77370000000001,18.32911],"type":"Point"}
}