{
  "type": "Feature",
  "properties": {
    "gn:admin1_code":"9.0",
    "gn:admin2_code":"3718665.0",
    "gn:asciiname":"Belizaire",
    "gn:country_code":"HT",
    "gn:dem":386,
    "gn:feature_class":"P",
    "gn:feature_code":"PPL",
    "gn:name":"B\u00e9lizaire",
    "gn:population":0,
    "gn:timezone":"America/Port-au-Prince",
    "iso:country":"HT",
    "wof:name":"Belizaire",
    "wof:placetype":"locality"
},
  "geometry": {"coordinates":[-72.48333000000002,19.58333],"type":"Point"}
}