{
  "type": "Feature",
  "properties": {
    "gn:admin1_code":"12.0",
    "gn:admin2_code":"3728096.0",
    "gn:asciiname":"Tuffet",
    "gn:country_code":"HT",
    "gn:dem":93,
    "gn:feature_class":"P",
    "gn:feature_code":"PPL",
    "gn:name":"Tuffet",
    "gn:population":0,
    "gn:timezone":"America/Port-au-Prince",
    "iso:country":"HT",
    "name:bul_x_preferred":[
        "\u041f\u0443\u0444"
    ],
    "name:cat_x_preferred":[
        "Puf"
    ],
    "name:eus_x_preferred":[
        "Puf"
    ],
    "name:fra_x_preferred":[
        "Pouf"
    ],
    "name:heb_x_preferred":[
        "\u05d4\u05d3\u05d5\u05dd"
    ],
    "name:ido_x_preferred":[
        "Pufo"
    ],
    "name:nno_x_preferred":[
        "Puff"
    ],
    "name:nor_x_preferred":[
        "Puff"
    ],
    "name:por_x_preferred":[
        "Escabelo"
    ],
    "name:rus_x_preferred":[
        "\u041f\u0443\u0444\u0438\u043a"
    ],
    "name:spa_x_preferred":[
        "Puf"
    ],
    "name:swe_x_preferred":[
        "Puff"
    ],
    "name:ukr_x_preferred":[
        "\u041f\u0443\u0444"
    ],
    "wof:name":"Tuffet",
    "wof:placetype":"locality"
},
  "geometry": {"coordinates":[-73.83333,18.25],"type":"Point"}
}