{
  "type": "Feature",
  "properties": {
    "gn:admin1_code":"11.0",
    "gn:admin2_code":"3731086.0",
    "gn:asciiname":"Source Matelas",
    "gn:country_code":"HT",
    "gn:dem":69,
    "gn:feature_class":"P",
    "gn:feature_code":"PPL",
    "gn:name":"Source Matelas",
    "gn:population":0,
    "gn:timezone":"America/Port-au-Prince",
    "iso:country":"HT",
    "name:fra_x_preferred":[
        "Source Matelas"
    ],
    "wof:name":"Source Matelas",
    "wof:placetype":"locality"
},
  "geometry": {"coordinates":[-72.37510999999998,18.72237],"type":"Point"}
}