{
  "type": "Feature",
  "properties": {
    "gn:admin1_code":"6.0",
    "gn:admin2_code":"3717587.0",
    "gn:asciiname":"Godan",
    "gn:country_code":"HT",
    "gn:dem":312,
    "gn:feature_class":"P",
    "gn:feature_code":"PPL",
    "gn:name":"Godan",
    "gn:population":0,
    "gn:timezone":"America/Port-au-Prince",
    "iso:country":"HT",
    "name:bar_x_preferred":[
        "Godan"
    ],
    "name:ceb_x_preferred":[
        "Godan"
    ],
    "name:hin_x_preferred":[
        "\u0917\u094b\u0926\u093e\u0928"
    ],
    "name:pan_x_preferred":[
        "\u0a17\u0a4b\u0a26\u0a3e\u0a28"
    ],
    "name:swe_x_preferred":[
        "Godan"
    ],
    "wof:name":"Godan",
    "wof:placetype":"locality"
},
  "geometry": {"coordinates":[-72.46666999999999,19.01667],"type":"Point"}
}