{
  "type": "Feature",
  "properties": {
    "gn:admin1_code":"11.0",
    "gn:admin2_code":"3723019.0",
    "gn:asciiname":"Bois Brule",
    "gn:country_code":"HT",
    "gn:dem":499,
    "gn:feature_class":"P",
    "gn:feature_code":"PPL",
    "gn:name":"Bois Br\u00fbl\u00e9",
    "gn:population":0,
    "gn:timezone":"America/Port-au-Prince",
    "iso:country":"HT",
    "name:fra_x_preferred":[
        "Bois Brul\u00e9"
    ],
    "name:und_x_variant":[
        "Bois Br\u00fbl\u00e9"
    ],
    "wof:name":"Bois Brule",
    "wof:placetype":"locality"
},
  "geometry": {"coordinates":[-72.89863000000003,18.78872],"type":"Point"}
}