{
  "type": "Feature",
  "properties": {
    "gn:admin1_code":"13.0",
    "gn:admin2_code":"3730910.0",
    "gn:asciiname":"Moreau",
    "gn:country_code":"HT",
    "gn:dem":273,
    "gn:feature_class":"P",
    "gn:feature_code":"PPL",
    "gn:name":"Moreau",
    "gn:population":0,
    "gn:timezone":"America/Port-au-Prince",
    "iso:country":"HT",
    "name:ces_x_preferred":[
        "Moreau"
    ],
    "name:deu_x_preferred":[
        "Moreau"
    ],
    "name:fin_x_preferred":[
        "Moreau"
    ],
    "name:fra_x_preferred":[
        "Moreau"
    ],
    "name:heb_x_preferred":[
        "\u05de\u05d5\u05e8\u05d5"
    ],
    "name:ita_x_preferred":[
        "Moreau"
    ],
    "name:nds_x_preferred":[
        "Moreau"
    ],
    "name:nld_x_preferred":[
        "Moreau"
    ],
    "name:pol_x_preferred":[
        "Moreau"
    ],
    "name:spa_x_preferred":[
        "Moreau"
    ],
    "name:swe_x_preferred":[
        "Moreau"
    ],
    "wof:name":"Moreau",
    "wof:placetype":"locality"
},
  "geometry": {"coordinates":[-72.93333,18.25],"type":"Point"}
}