{
  "type": "Feature",
  "properties": {
    "gn:admin1_code":"15.0",
    "gn:admin2_code":"3731122.0",
    "gn:asciiname":"Langlade",
    "gn:country_code":"HT",
    "gn:dem":197,
    "gn:feature_class":"P",
    "gn:feature_code":"PPL",
    "gn:name":"Langlade",
    "gn:population":0,
    "gn:timezone":"America/Port-au-Prince",
    "iso:country":"HT",
    "name:ceb_x_preferred":[
        "Langlade"
    ],
    "name:deu_x_preferred":[
        "Langlade"
    ],
    "name:fra_x_preferred":[
        "Langlade"
    ],
    "name:hrv_x_preferred":[
        "Langlade"
    ],
    "name:nld_x_preferred":[
        "Langlade"
    ],
    "name:pol_x_preferred":[
        "Langlade"
    ],
    "name:rus_x_preferred":[
        "\u041b\u0430\u043d\u0433\u043b\u0430\u0434"
    ],
    "name:swe_x_preferred":[
        "Langlade"
    ],
    "wof:name":"Langlade",
    "wof:placetype":"locality"
},
  "geometry": {"coordinates":[-73.43333,18.36667000000001],"type":"Point"}
}