{
  "type": "Feature",
  "properties": {
    "gn:admin1_code":"12.0",
    "gn:admin2_code":"3727900.0",
    "gn:asciiname":"Bois l'Etat",
    "gn:country_code":"HT",
    "gn:dem":766,
    "gn:feature_class":"P",
    "gn:feature_code":"PPL",
    "gn:name":"Bois l\u2019\u00c9tat",
    "gn:population":0,
    "gn:timezone":"America/Port-au-Prince",
    "iso:country":"HT",
    "wof:name":"Bois l'Etat",
    "wof:placetype":"locality"
},
  "geometry": {"coordinates":[-74.09999999999999,18.36667000000001],"type":"Point"}
}