{
  "type": "Feature",
  "properties": {
    "gn:admin1_code":"13.0",
    "gn:admin2_code":"3730361.0",
    "gn:asciiname":"Coeur Bois",
    "gn:country_code":"HT",
    "gn:dem":674,
    "gn:feature_class":"P",
    "gn:feature_code":"PPL",
    "gn:name":"Coeur Bois",
    "gn:population":0,
    "gn:timezone":"America/Port-au-Prince",
    "iso:country":"HT",
    "name:hat_x_preferred":[
        "C\u0153ur Bois"
    ],
    "wof:name":"Coeur Bois",
    "wof:placetype":"locality"
},
  "geometry": {"coordinates":[-71.88333,18.26667],"type":"Point"}
}