{
  "type": "Feature",
  "properties": {
    "gn:admin1_code":"10.0",
    "gn:admin2_code":"3716223.0",
    "gn:asciiname":"Savane Pomme",
    "gn:country_code":"HT",
    "gn:dem":54,
    "gn:feature_class":"P",
    "gn:feature_code":"PPL",
    "gn:name":"Savane Pomme",
    "gn:population":0,
    "gn:timezone":"America/Port-au-Prince",
    "iso:country":"HT",
    "name:fra_x_preferred":[
        "Savane Pomme"
    ],
    "wof:name":"Savane Pomme",
    "wof:placetype":"locality"
},
  "geometry": {"coordinates":[-71.99621999999999,19.58977],"type":"Point"}
}