{
  "type": "Feature",
  "properties": {
    "gn:admin1_code":"11.0",
    "gn:asciiname":"Decide",
    "gn:country_code":"HT",
    "gn:dem":770,
    "gn:feature_class":"P",
    "gn:feature_code":"PPL",
    "gn:name":"D\u00e9cid\u00e9",
    "gn:population":0,
    "gn:timezone":"America/Port-au-Prince",
    "iso:country":"HT",
    "name:fra_x_preferred":[
        "D\u00e9cid\u00e9"
    ],
    "wof:name":"Decide",
    "wof:placetype":"locality"
},
  "geometry": {"coordinates":[-72.87532,18.32585],"type":"Point"}
}