{
  "type": "Feature",
  "properties": {
    "gn:admin1_code":"13.0",
    "gn:admin2_code":"3730361.0",
    "gn:asciiname":"Boucan Tonton",
    "gn:country_code":"HT",
    "gn:dem":698,
    "gn:feature_class":"P",
    "gn:feature_code":"PPL",
    "gn:name":"Boucan Tonton",
    "gn:population":0,
    "gn:timezone":"America/Port-au-Prince",
    "iso:country":"HT",
    "name:fra_x_preferred":[
        "Boucan Tonton"
    ],
    "wof:name":"Boucan Tonton",
    "wof:placetype":"locality"
},
  "geometry": {"coordinates":[-71.80899000000002,18.2012],"type":"Point"}
}