{
  "type": "Feature",
  "properties": {
    "gn:admin1_code":"10.0",
    "gn:asciiname":"Douya",
    "gn:country_code":"HT",
    "gn:dem":361,
    "gn:feature_class":"P",
    "gn:feature_code":"PPL",
    "gn:name":"Douya",
    "gn:population":0,
    "gn:timezone":"America/Port-au-Prince",
    "iso:country":"HT",
    "wof:name":"Douya",
    "wof:placetype":"locality"
},
  "geometry": {"coordinates":[-72.08333,19.46667],"type":"Point"}
}