{
  "type": "Feature",
  "properties": {
    "gn:admin1_code":"12.0",
    "gn:admin2_code":"3731094",
    "gn:asciiname":"Anglade",
    "gn:country_code":"HT",
    "gn:dem":170,
    "gn:feature_class":"P",
    "gn:feature_code":"PPL",
    "gn:name":"Anglade",
    "gn:population":0,
    "gn:timezone":"America/Port-au-Prince",
    "iso:country":"HT",
    "name:bug_x_preferred":[
        "Anglade"
    ],
    "name:cat_x_preferred":[
        "Anglade"
    ],
    "name:ceb_x_preferred":[
        "Anglade"
    ],
    "name:deu_x_preferred":[
        "Anglade"
    ],
    "name:epo_x_preferred":[
        "Anglade"
    ],
    "name:eus_x_preferred":[
        "Anglade"
    ],
    "name:fra_x_preferred":[
        "Anglade"
    ],
    "name:hun_x_preferred":[
        "Anglade"
    ],
    "name:ind_x_preferred":[
        "Anglade"
    ],
    "name:ita_x_preferred":[
        "Anglade"
    ],
    "name:kaz_x_preferred":[
        "\u0410\u043d\u0433\u043b\u0430\u0434"
    ],
    "name:lat_x_preferred":[
        "Anglade"
    ],
    "name:mlg_x_preferred":[
        "Anglade"
    ],
    "name:msa_x_preferred":[
        "Anglade"
    ],
    "name:nld_x_preferred":[
        "Anglade"
    ],
    "name:nor_x_preferred":[
        "Anglade"
    ],
    "name:oci_x_preferred":[
        "Anglade"
    ],
    "name:pms_x_preferred":[
        "Anglade"
    ],
    "name:pol_x_preferred":[
        "Anglade"
    ],
    "name:por_x_preferred":[
        "Anglade"
    ],
    "name:ron_x_preferred":[
        "Anglade"
    ],
    "name:slk_x_preferred":[
        "Anglade"
    ],
    "name:spa_x_preferred":[
        "Anglade"
    ],
    "name:srp_x_preferred":[
        "\u0410\u043d\u0433\u043b\u0430\u0434"
    ],
    "name:swe_x_preferred":[
        "Anglade"
    ],
    "name:tur_x_preferred":[
        "Anglade"
    ],
    "name:ukr_x_preferred":[
        "\u0410\u043d\u0433\u043b\u0430\u0434"
    ],
    "name:uzb_x_preferred":[
        "Anglade"
    ],
    "name:vie_x_preferred":[
        "Anglade"
    ],
    "name:vol_x_preferred":[
        "Anglade"
    ],
    "name:war_x_preferred":[
        "Anglade"
    ],
    "name:zho_x_preferred":[
        "\u6602\u683c\u62c9\u5fb7"
    ],
    "wof:name":"Anglade",
    "wof:placetype":"locality"
},
  "geometry": {"coordinates":[-73.18079,18.29609],"type":"Point"}
}