{
  "type": "Feature",
  "properties": {
    "gn:admin1_code":"12.0",
    "gn:admin2_code":"3731094",
    "gn:asciiname":"Anglade",
    "gn:country_code":"HT",
    "gn:dem":170,
    "gn:feature_class":"P",
    "gn:feature_code":"PPL",
    "gn:name":"Anglade",
    "gn:population":0,
    "gn:timezone":"America/Port-au-Prince",
    "iso:country":"HT",
    "name:fra_x_preferred":[
        "Anglade"
    ],
    "wof:name":"Anglade",
    "wof:placetype":"locality"
},
  "geometry": {"coordinates":[-73.18079,18.29609],"type":"Point"}
}