{
  "type": "Feature",
  "properties": {
    "gn:admin1_code":"11.0",
    "gn:admin2_code":"3718425.0",
    "gn:asciiname":"Vieux Caille",
    "gn:country_code":"HT",
    "gn:dem":152,
    "gn:feature_class":"P",
    "gn:feature_code":"PPL",
    "gn:name":"Vieux Caille",
    "gn:population":0,
    "gn:timezone":"America/Port-au-Prince",
    "iso:country":"HT",
    "wof:name":"Vieux Caille",
    "wof:placetype":"locality"
},
  "geometry": {"coordinates":[-72.41110999999999,18.51583],"type":"Point"}
}