{
  "type": "Feature",
  "properties": {
    "gn:admin1_code":"3.0",
    "gn:admin2_code":"3720764.0",
    "gn:asciiname":"Ti Place",
    "gn:country_code":"HT",
    "gn:dem":672,
    "gn:feature_class":"P",
    "gn:feature_code":"PPL",
    "gn:name":"Ti Place",
    "gn:population":0,
    "gn:timezone":"America/Port-au-Prince",
    "iso:country":"HT",
    "wof:name":"Ti Place",
    "wof:placetype":"locality"
},
  "geometry": {"coordinates":[-73.38333,19.68333],"type":"Point"}
}