{
  "type": "Feature",
  "properties": {
    "gn:admin1_code":"10.0",
    "gn:asciiname":"De l'Eau Contree",
    "gn:country_code":"HT",
    "gn:dem":638,
    "gn:feature_class":"P",
    "gn:feature_code":"PPL",
    "gn:name":"De l\u2019Eau Contr\u00e9e",
    "gn:population":0,
    "gn:timezone":"America/Port-au-Prince",
    "iso:country":"HT",
    "name:und_x_variant":[
        "D\u2019Lo Contr\u00e9e",
        "De l\u2019Eau Contr\u00e9e"
    ],
    "wof:name":"De l'Eau Contree",
    "wof:placetype":"locality"
},
  "geometry": {"coordinates":[-71.91667,19.25],"type":"Point"}
}