{
  "type": "Feature",
  "properties": {
    "gn:admin1_code":"11.0",
    "gn:admin2_code":"3718425.0",
    "gn:asciiname":"Barriere",
    "gn:country_code":"HT",
    "gn:dem":1150,
    "gn:feature_class":"P",
    "gn:feature_code":"PPL",
    "gn:name":"Barri\u00e8re",
    "gn:population":0,
    "gn:timezone":"America/Port-au-Prince",
    "iso:country":"HT",
    "wof:name":"Barriere",
    "wof:placetype":"locality"
},
  "geometry": {"coordinates":[-72.21666999999999,18.36667000000001],"type":"Point"}
}