{
  "type": "Feature",
  "properties": {
    "gn:admin1_code":"9.0",
    "gn:admin2_code":"3728473.0",
    "gn:asciiname":"Bonnay",
    "gn:country_code":"HT",
    "gn:dem":21,
    "gn:feature_class":"P",
    "gn:feature_code":"PPL",
    "gn:name":"Bonnay",
    "gn:population":0,
    "gn:timezone":"America/Port-au-Prince",
    "iso:country":"HT",
    "name:ceb_x_preferred":[
        "Bonnay"
    ],
    "name:deu_x_preferred":[
        "Bonnay"
    ],
    "name:fra_x_preferred":[
        "Bonnay"
    ],
    "name:ita_x_preferred":[
        "Bonnay"
    ],
    "name:nds_x_preferred":[
        "Bonnay"
    ],
    "name:nld_x_preferred":[
        "Bonnay"
    ],
    "name:pms_x_preferred":[
        "Bonnay"
    ],
    "name:pol_x_preferred":[
        "Bonnay"
    ],
    "name:por_x_preferred":[
        "Bonnay"
    ],
    "name:rus_x_preferred":[
        "\u0411\u043e\u043d\u0435"
    ],
    "name:slk_x_preferred":[
        "Bonnay"
    ],
    "name:spa_x_preferred":[
        "Bonnay"
    ],
    "name:srp_x_preferred":[
        "\u0411\u043e\u043d\u0435"
    ],
    "name:swe_x_preferred":[
        "Bonnay"
    ],
    "wof:name":"Bonnay",
    "wof:placetype":"locality"
},
  "geometry": {"coordinates":[-72.17308,19.69704],"type":"Point"}
}