{
  "type": "Feature",
  "properties": {
    "gn:admin1_code":"11.0",
    "gn:asciiname":"Ca Damier",
    "gn:country_code":"HT",
    "gn:dem":871,
    "gn:feature_class":"P",
    "gn:feature_code":"PPL",
    "gn:name":"Ca Damier",
    "gn:population":0,
    "gn:timezone":"America/Port-au-Prince",
    "iso:country":"HT",
    "name:und_x_variant":[
        "Demier",
        "Ca Damier"
    ],
    "wof:name":"Ca Damier",
    "wof:placetype":"locality"
},
  "geometry": {"coordinates":[-72.24800999999999,18.75543],"type":"Point"}
}