{
  "type": "Feature",
  "properties": {
    "gn:admin1_code":"12.0",
    "gn:admin2_code":"3727295.0",
    "gn:asciiname":"Beaulier",
    "gn:country_code":"HT",
    "gn:dem":70,
    "gn:feature_class":"P",
    "gn:feature_code":"PPL",
    "gn:name":"Beaulier",
    "gn:population":0,
    "gn:timezone":"America/Port-au-Prince",
    "iso:country":"HT",
    "wof:name":"Beaulier",
    "wof:placetype":"locality"
},
  "geometry": {"coordinates":[-73.96666999999999,18.16667],"type":"Point"}
}