{
  "type": "Feature",
  "properties": {
    "gn:admin1_code":"7.0",
    "gn:admin2_code":"3720809.0",
    "gn:asciiname":"Guillaume",
    "gn:country_code":"HT",
    "gn:dem":146,
    "gn:feature_class":"P",
    "gn:feature_code":"PPL",
    "gn:name":"Guillaume",
    "gn:population":0,
    "gn:timezone":"America/Port-au-Prince",
    "iso:country":"HT",
    "name:fra_x_preferred":[
        "Guillaume"
    ],
    "wof:name":"Guillaume",
    "wof:placetype":"locality"
},
  "geometry": {"coordinates":[-72.20444999999999,18.89963],"type":"Point"}
}