{
  "type": "Feature",
  "properties": {
    "gn:admin1_code":"7.0",
    "gn:admin2_code":"3720809.0",
    "gn:asciiname":"Guillaume",
    "gn:country_code":"HT",
    "gn:dem":146,
    "gn:feature_class":"P",
    "gn:feature_code":"PPL",
    "gn:name":"Guillaume",
    "gn:population":0,
    "gn:timezone":"America/Port-au-Prince",
    "iso:country":"HT",
    "name:bre_x_preferred":[
        "Guillaume"
    ],
    "name:ces_x_preferred":[
        "Guillaume"
    ],
    "name:fra_x_preferred":[
        "Guillaume"
    ],
    "name:heb_x_preferred":[
        "\u05d2\u05d9\u05d5\u05dd"
    ],
    "name:ita_x_preferred":[
        "Guillaume"
    ],
    "name:jpn_x_preferred":[
        "\u30ae\u30e8\u30fc\u30e0"
    ],
    "name:nld_x_preferred":[
        "Guillaume"
    ],
    "name:pol_x_preferred":[
        "Guillaume"
    ],
    "name:por_x_preferred":[
        "Guillaume"
    ],
    "name:rus_x_preferred":[
        "\u0413\u0438\u0439\u043e\u043c"
    ],
    "name:slv_x_preferred":[
        "Guillaume"
    ],
    "name:spa_x_preferred":[
        "Guillaume"
    ],
    "name:ukr_x_preferred":[
        "\u0413\u0456\u0439\u043e\u043c"
    ],
    "wof:name":"Guillaume",
    "wof:placetype":"locality"
},
  "geometry": {"coordinates":[-72.20444999999999,18.89963],"type":"Point"}
}