{
  "type": "Feature",
  "properties": {
    "gn:admin1_code":"7.0",
    "gn:admin2_code":"3728053.0",
    "gn:asciiname":"Rio Hondo",
    "gn:country_code":"HT",
    "gn:dem":285,
    "gn:feature_class":"P",
    "gn:feature_code":"PPL",
    "gn:name":"Rio Hondo",
    "gn:population":0,
    "gn:timezone":"America/Port-au-Prince",
    "iso:country":"HT",
    "name:ceb_x_preferred":[
        "Rio Hondo"
    ],
    "name:deu_x_preferred":[
        "R\u00edo Hondo"
    ],
    "name:fra_x_preferred":[
        "Rio Hondo"
    ],
    "name:ita_x_preferred":[
        "Rio Hondo"
    ],
    "name:nds_x_preferred":[
        "R\u00edo Hondo"
    ],
    "name:nld_x_preferred":[
        "R\u00edo Hondo"
    ],
    "name:por_x_preferred":[
        "Rio Hondo"
    ],
    "name:spa_x_preferred":[
        "R\u00edo Hondo"
    ],
    "name:swe_x_preferred":[
        "Rio Hondo"
    ],
    "wof:name":"Rio Hondo",
    "wof:placetype":"locality"
},
  "geometry": {"coordinates":[-71.83069999999999,19.10453],"type":"Point"}
}