{
  "type": "Feature",
  "properties": {
    "gn:admin1_code":"9.0",
    "gn:admin2_code":"3731232.0",
    "gn:asciiname":"Lemou",
    "gn:country_code":"HT",
    "gn:dem":32,
    "gn:feature_class":"P",
    "gn:feature_code":"PPL",
    "gn:name":"Lemou",
    "gn:population":0,
    "gn:timezone":"America/Port-au-Prince",
    "iso:country":"HT",
    "name:fra_x_preferred":[
        "Lemou"
    ],
    "wof:name":"Lemou",
    "wof:placetype":"locality"
},
  "geometry": {"coordinates":[-72.28652,19.7161],"type":"Point"}
}