{
  "type": "Feature",
  "properties": {
    "gn:admin1_code":"12.0",
    "gn:admin2_code":"3728096.0",
    "gn:asciiname":"Figaro",
    "gn:country_code":"HT",
    "gn:dem":21,
    "gn:feature_class":"P",
    "gn:feature_code":"PPL",
    "gn:name":"Figaro",
    "gn:population":0,
    "gn:timezone":"America/Port-au-Prince",
    "iso:country":"HT",
    "name:ceb_x_preferred":[
        "Figaro"
    ],
    "name:ces_x_preferred":[
        "Figaro"
    ],
    "name:deu_x_preferred":[
        "Figaro"
    ],
    "name:est_x_preferred":[
        "Figaro"
    ],
    "name:fin_x_preferred":[
        "Figaro"
    ],
    "name:fra_x_preferred":[
        "Figaro"
    ],
    "name:heb_x_preferred":[
        "\u05e4\u05d9\u05d2\u05d0\u05e8\u05d5"
    ],
    "name:ita_x_preferred":[
        "Figaro"
    ],
    "name:jpn_x_preferred":[
        "\u30d5\u30a3\u30ac\u30ed"
    ],
    "name:kor_x_preferred":[
        "\ud53c\uac00\ub85c"
    ],
    "name:nld_x_preferred":[
        "Figaro"
    ],
    "name:nor_x_preferred":[
        "Figaro"
    ],
    "name:por_x_preferred":[
        "Figaro"
    ],
    "name:ron_x_preferred":[
        "Figaro"
    ],
    "name:rus_x_preferred":[
        "\u0424\u0438\u0433\u0430\u0440\u043e"
    ],
    "name:slk_x_preferred":[
        "Figaro"
    ],
    "name:spa_x_preferred":[
        "Figaro"
    ],
    "name:swe_x_preferred":[
        "Figaro"
    ],
    "name:tur_x_preferred":[
        "Figaro"
    ],
    "name:ukr_x_preferred":[
        "\u0424\u0456\u0433\u0430\u0440\u043e"
    ],
    "wof:name":"Figaro",
    "wof:placetype":"locality"
},
  "geometry": {"coordinates":[-73.86667,18.15],"type":"Point"}
}