{
  "type": "Feature",
  "properties": {
    "gn:admin1_code":"13.0",
    "gn:admin2_code":"3730910.0",
    "gn:asciiname":"Grande Saline",
    "gn:country_code":"HT",
    "gn:dem":274,
    "gn:feature_class":"P",
    "gn:feature_code":"PPL",
    "gn:name":"Grande Saline",
    "gn:population":0,
    "gn:timezone":"America/Port-au-Prince",
    "iso:country":"HT",
    "name:ceb_x_preferred":[
        "Grande Saline"
    ],
    "name:fra_x_preferred":[
        "Grande Saline"
    ],
    "name:swe_x_preferred":[
        "Grande Saline"
    ],
    "wof:name":"Grande Saline",
    "wof:placetype":"locality"
},
  "geometry": {"coordinates":[-72.80976,18.16632],"type":"Point"}
}