{
  "type": "Feature",
  "properties": {
    "gn:admin1_code":"7.0",
    "gn:admin2_code":"3728053.0",
    "gn:asciiname":"Guadabier",
    "gn:country_code":"HT",
    "gn:dem":648,
    "gn:feature_class":"P",
    "gn:feature_code":"PPL",
    "gn:name":"Guadabier",
    "gn:population":0,
    "gn:timezone":"America/Port-au-Prince",
    "iso:country":"HT",
    "wof:name":"Guadabier",
    "wof:placetype":"locality"
},
  "geometry": {"coordinates":[-71.76666999999998,19.23333],"type":"Point"}
}