{
  "type": "Feature",
  "properties": {
    "gn:admin1_code":"11.0",
    "gn:admin2_code":"3731086.0",
    "gn:asciiname":"Ca Dubreuil",
    "gn:country_code":"HT",
    "gn:dem":1308,
    "gn:feature_class":"P",
    "gn:feature_code":"PPL",
    "gn:name":"Ca Dubreuil",
    "gn:population":0,
    "gn:timezone":"America/Port-au-Prince",
    "iso:country":"HT",
    "name:fra_x_preferred":[
        "Ca Dubreuil"
    ],
    "wof:name":"Ca Dubreuil",
    "wof:placetype":"locality"
},
  "geometry": {"coordinates":[-72.50068,18.93101],"type":"Point"}
}