{
  "type": "Feature",
  "properties": {
    "gn:admin1_code":"6.0",
    "gn:admin2_code":"3724144.0",
    "gn:asciiname":"La Fortune",
    "gn:country_code":"HT",
    "gn:dem":383,
    "gn:feature_class":"P",
    "gn:feature_code":"PPL",
    "gn:name":"La Fortune",
    "gn:population":0,
    "gn:timezone":"America/Port-au-Prince",
    "iso:country":"HT",
    "wof:name":"La Fortune",
    "wof:placetype":"locality"
},
  "geometry": {"coordinates":[-72.71666999999999,19.63333],"type":"Point"}
}