{
  "type": "Feature",
  "properties": {
    "gn:admin1_code":"7.0",
    "gn:admin2_code":"3720809.0",
    "gn:asciiname":"La Marre",
    "gn:country_code":"HT",
    "gn:dem":160,
    "gn:feature_class":"P",
    "gn:feature_code":"PPL",
    "gn:name":"La Marre",
    "gn:population":0,
    "gn:timezone":"America/Port-au-Prince",
    "iso:country":"HT",
    "name:cat_x_preferred":[
        "La Marre"
    ],
    "name:ceb_x_preferred":[
        "La Marre"
    ],
    "name:deu_x_preferred":[
        "La Marre"
    ],
    "name:eus_x_preferred":[
        "La Marre"
    ],
    "name:fra_x_preferred":[
        "La Marre"
    ],
    "name:hun_x_preferred":[
        "La Marre"
    ],
    "name:ita_x_preferred":[
        "La Marre"
    ],
    "name:lat_x_preferred":[
        "La Marre"
    ],
    "name:msa_x_preferred":[
        "La Marre"
    ],
    "name:nld_x_preferred":[
        "La Marre"
    ],
    "name:oci_x_preferred":[
        "La Marre"
    ],
    "name:pms_x_preferred":[
        "La Marre"
    ],
    "name:pol_x_preferred":[
        "La Marre"
    ],
    "name:por_x_preferred":[
        "La Marre"
    ],
    "name:slk_x_preferred":[
        "La Marre"
    ],
    "name:spa_x_preferred":[
        "La Marre"
    ],
    "name:swe_x_preferred":[
        "La Marre"
    ],
    "name:szl_x_preferred":[
        "La Marre"
    ],
    "name:ukr_x_preferred":[
        "\u041b\u0430-\u041c\u0430\u0440\u0440"
    ],
    "name:urd_x_preferred":[
        "\u0644\u0627 \u0645\u0627\u0631\u06cc"
    ],
    "name:uzb_x_preferred":[
        "La Marre"
    ],
    "name:vie_x_preferred":[
        "La Marre"
    ],
    "name:vol_x_preferred":[
        "La Marre"
    ],
    "name:war_x_preferred":[
        "La Marre"
    ],
    "name:zho_x_preferred":[
        "\u62c9\u9a6c\u5c14"
    ],
    "wof:name":"La Marre",
    "wof:placetype":"locality"
},
  "geometry": {"coordinates":[-72.18361,18.84639],"type":"Point"}
}