{
  "type": "Feature",
  "properties": {
    "gn:admin1_code":"7.0",
    "gn:admin2_code":"3723840.0",
    "gn:asciiname":"Lan Moye",
    "gn:country_code":"HT",
    "gn:dem":326,
    "gn:feature_class":"P",
    "gn:feature_code":"PPL",
    "gn:name":"Lan Moye",
    "gn:population":0,
    "gn:timezone":"America/Port-au-Prince",
    "iso:country":"HT",
    "name:fra_x_preferred":[
        "Lan Moye"
    ],
    "wof:name":"Lan Moye",
    "wof:placetype":"locality"
},
  "geometry": {"coordinates":[-72.2332,19.18565],"type":"Point"}
}