{
  "type": "Feature",
  "properties": {
    "gn:admin1_code":"11.0",
    "gn:admin2_code":"3722285.0",
    "gn:asciiname":"Robe",
    "gn:country_code":"HT",
    "gn:dem":293,
    "gn:feature_class":"P",
    "gn:feature_code":"PPL",
    "gn:name":"Robe",
    "gn:population":0,
    "gn:timezone":"America/Port-au-Prince",
    "iso:country":"HT",
    "name:ces_x_preferred":[
        "Tal\u00e1r"
    ],
    "name:dan_x_preferred":[
        "Ornat"
    ],
    "name:deu_x_preferred":[
        "Amtstracht"
    ],
    "name:fas_x_preferred":[
        "\u0642\u0628\u0627 \u0644\u0628\u0627\u062f\u0647"
    ],
    "name:fin_x_preferred":[
        "Kaapu"
    ],
    "name:ido_x_preferred":[
        "Robo"
    ],
    "name:ind_x_preferred":[
        "Jubah"
    ],
    "name:ita_x_preferred":[
        "Roba"
    ],
    "name:jpn_x_preferred":[
        "\u30ed\u30fc\u30d6"
    ],
    "name:por_x_preferred":[
        "Beca"
    ],
    "name:rus_x_preferred":[
        "\u0422\u0430\u043b\u0430\u0440"
    ],
    "name:scn_x_preferred":[
        "Robba"
    ],
    "name:srp_x_preferred":[
        "\u041f\u043b\u0430\u0448\u0442"
    ],
    "name:swe_x_preferred":[
        "Talar"
    ],
    "wof:name":"Robe",
    "wof:placetype":"locality"
},
  "geometry": {"coordinates":[-72.55,18.45],"type":"Point"}
}