{
  "type": "Feature",
  "properties": {
    "gn:admin1_code":"7.0",
    "gn:admin2_code":"3722578.0",
    "gn:asciiname":"L'Eau Gaillee",
    "gn:country_code":"HT",
    "gn:dem":1036,
    "gn:feature_class":"P",
    "gn:feature_code":"PPL",
    "gn:name":"L\u2019Eau Gaill\u00e9e",
    "gn:population":0,
    "gn:timezone":"America/Port-au-Prince",
    "iso:country":"HT",
    "wof:name":"L'Eau Gaillee",
    "wof:placetype":"locality"
},
  "geometry": {"coordinates":[-71.82083,18.79889],"type":"Point"}
}