{
  "type": "Feature",
  "properties": {
    "gn:admin1_code":"11.0",
    "gn:admin2_code":"3727134.0",
    "gn:asciiname":"Aux Pieges",
    "gn:country_code":"HT",
    "gn:dem":1162,
    "gn:feature_class":"P",
    "gn:feature_code":"PPL",
    "gn:name":"Aux Pi\u00e8ges",
    "gn:population":0,
    "gn:timezone":"America/Port-au-Prince",
    "iso:country":"HT",
    "wof:name":"Aux Pieges",
    "wof:placetype":"locality"
},
  "geometry": {"coordinates":[-71.83333,18.65],"type":"Point"}
}