{
  "type": "Feature",
  "properties": {
    "gn:admin1_code":"10.0",
    "gn:admin2_code":"3716223.0",
    "gn:asciiname":"Belle-Tete",
    "gn:country_code":"HT",
    "gn:dem":435,
    "gn:feature_class":"P",
    "gn:feature_code":"PPL",
    "gn:name":"Belle-T\u00eate",
    "gn:population":0,
    "gn:timezone":"America/Port-au-Prince",
    "iso:country":"HT",
    "wof:name":"Belle-Tete",
    "wof:placetype":"locality"
},
  "geometry": {"coordinates":[-72.06667,19.53333],"type":"Point"}
}