{
  "type": "Feature",
  "properties": {
    "gn:admin1_code":"13.0",
    "gn:asciiname":"Cosini",
    "gn:country_code":"HT",
    "gn:dem":1061,
    "gn:feature_class":"P",
    "gn:feature_code":"PPL",
    "gn:name":"Cosini",
    "gn:population":0,
    "gn:timezone":"America/Port-au-Prince",
    "iso:country":"HT",
    "wof:name":"Cosini",
    "wof:placetype":"locality"
},
  "geometry": {"coordinates":[-71.78333000000001,18.36667000000001],"type":"Point"}
}