{
  "type": "Feature",
  "properties": {
    "gn:admin1_code":"3.0",
    "gn:admin2_code":"3717599.0",
    "gn:asciiname":"Francillette",
    "gn:country_code":"HT",
    "gn:dem":171,
    "gn:feature_class":"P",
    "gn:feature_code":"PPL",
    "gn:name":"Francillette",
    "gn:population":0,
    "gn:timezone":"America/Port-au-Prince",
    "iso:country":"HT",
    "name:fra_x_preferred":[
        "Francillette"
    ],
    "wof:name":"Francillette",
    "wof:placetype":"locality"
},
  "geometry": {"coordinates":[-72.60678,19.87493],"type":"Point"}
}