{
  "type": "Feature",
  "properties": {
    "gn:admin1_code":"9.0",
    "gn:admin2_code":"3724438.0",
    "gn:asciiname":"Zephir",
    "gn:country_code":"HT",
    "gn:dem":105,
    "gn:feature_class":"P",
    "gn:feature_code":"PPL",
    "gn:name":"Z\u00e9phir",
    "gn:population":0,
    "gn:timezone":"America/Port-au-Prince",
    "iso:country":"HT",
    "name:fra_x_preferred":[
        "Z\u00e9phir"
    ],
    "name:rus_x_preferred":[
        "Zephyr"
    ],
    "name:uzb_x_preferred":[
        "Zefir"
    ],
    "wof:name":"Zephir",
    "wof:placetype":"locality"
},
  "geometry": {"coordinates":[-72.13802,19.53888],"type":"Point"}
}