{
  "type": "Feature",
  "properties": {
    "gn:admin1_code":"11.0",
    "gn:asciiname":"Blaise",
    "gn:country_code":"HT",
    "gn:dem":889,
    "gn:feature_class":"P",
    "gn:feature_code":"PPL",
    "gn:name":"Blaise",
    "gn:population":0,
    "gn:timezone":"America/Port-au-Prince",
    "iso:country":"HT",
    "name:fra_x_preferred":[
        "Blaise"
    ],
    "wof:name":"Blaise",
    "wof:placetype":"locality"
},
  "geometry": {"coordinates":[-72.94638,18.34131],"type":"Point"}
}