{
  "type": "Feature",
  "properties": {
    "gn:admin1_code":"9.0",
    "gn:admin2_code":"3729454.0",
    "gn:asciiname":"Morlant",
    "gn:country_code":"HT",
    "gn:dem":597,
    "gn:feature_class":"P",
    "gn:feature_code":"PPL",
    "gn:name":"Morlant",
    "gn:population":0,
    "gn:timezone":"America/Port-au-Prince",
    "iso:country":"HT",
    "name:und_x_variant":[
        "Morlan",
        "Morlant"
    ],
    "wof:name":"Morlant",
    "wof:placetype":"locality"
},
  "geometry": {"coordinates":[-72.54101,19.72699],"type":"Point"}
}