{
  "type": "Feature",
  "properties": {
    "gn:admin1_code":"6.0",
    "gn:admin2_code":"3724144.0",
    "gn:asciiname":"Source Coulee",
    "gn:country_code":"HT",
    "gn:dem":480,
    "gn:feature_class":"P",
    "gn:feature_code":"PPL",
    "gn:name":"Source Coul\u00e9e",
    "gn:population":0,
    "gn:timezone":"America/Port-au-Prince",
    "iso:country":"HT",
    "wof:name":"Source Coulee",
    "wof:placetype":"locality"
},
  "geometry": {"coordinates":[-72.63333,19.68333],"type":"Point"}
}