{
  "type": "Feature",
  "properties": {
    "gn:admin1_code":"7.0",
    "gn:admin2_code":"3723840.0",
    "gn:asciiname":"Eau Carree",
    "gn:country_code":"HT",
    "gn:dem":198,
    "gn:feature_class":"P",
    "gn:feature_code":"PPL",
    "gn:name":"Eau Carr\u00e9e",
    "gn:population":0,
    "gn:timezone":"America/Port-au-Prince",
    "iso:country":"HT",
    "wof:name":"Eau Carree",
    "wof:placetype":"locality"
},
  "geometry": {"coordinates":[-71.88333,18.96667],"type":"Point"}
}