{
  "type": "Feature",
  "properties": {
    "gn:admin1_code":"3.0",
    "gn:admin2_code":"3720764.0",
    "gn:asciiname":"Port a l'Ecu",
    "gn:country_code":"HT",
    "gn:dem":13,
    "gn:feature_class":"P",
    "gn:feature_code":"PPL",
    "gn:name":"Port \u00e0 l\u2019\u00c9cu",
    "gn:population":0,
    "gn:timezone":"America/Port-au-Prince",
    "iso:country":"HT",
    "name:fra_x_preferred":[
        "Port \u00e0 l\u2019\u00c9cu"
    ],
    "wof:name":"Port a l'Ecu",
    "wof:placetype":"locality"
},
  "geometry": {"coordinates":[-73.03872,19.90652],"type":"Point"}
}