{
  "type": "Feature",
  "properties": {
    "gn:admin1_code":"12.0",
    "gn:admin2_code":"3731094.0",
    "gn:asciiname":"Delmas",
    "gn:country_code":"HT",
    "gn:dem":64,
    "gn:feature_class":"P",
    "gn:feature_code":"PPL",
    "gn:name":"Delmas",
    "gn:population":0,
    "gn:timezone":"America/Port-au-Prince",
    "iso:country":"HT",
    "name:ceb_x_preferred":[
        "Delmas"
    ],
    "name:deu_x_preferred":[
        "Delmas"
    ],
    "name:fra_x_preferred":[
        "Delmas"
    ],
    "name:nld_x_preferred":[
        "Delmas"
    ],
    "name:pol_x_preferred":[
        "Delmas"
    ],
    "name:spa_x_preferred":[
        "Delmas"
    ],
    "name:swe_x_preferred":[
        "Delmas"
    ],
    "name:ukr_x_preferred":[
        "\u0414\u0435\u043b\u044c\u043c\u0430\u0441"
    ],
    "wof:name":"Delmas",
    "wof:placetype":"locality"
},
  "geometry": {"coordinates":[-73.66667,18.31667],"type":"Point"}
}