{
  "type": "Feature",
  "properties": {
    "gn:admin1_code":"11.0",
    "gn:admin2_code":"3731086.0",
    "gn:asciiname":"Regnier",
    "gn:country_code":"HT",
    "gn:dem":1026,
    "gn:feature_class":"P",
    "gn:feature_code":"PPL",
    "gn:name":"R\u00e9gnier",
    "gn:population":0,
    "gn:timezone":"America/Port-au-Prince",
    "iso:country":"HT",
    "name:deu_x_preferred":[
        "Regnier"
    ],
    "name:fra_x_preferred":[
        "R\u00e9gnier"
    ],
    "name:jpn_x_preferred":[
        "\u30ec\u30cb\u30a8"
    ],
    "name:nds_x_preferred":[
        "Regnier"
    ],
    "name:por_x_preferred":[
        "Regnier"
    ],
    "name:rus_x_preferred":[
        "\u0420\u0435\u043d\u044c\u0435"
    ],
    "name:ukr_x_preferred":[
        "\u0420\u0435\u043d\u044c\u0454"
    ],
    "wof:name":"Regnier",
    "wof:placetype":"locality"
},
  "geometry": {"coordinates":[-72.33333,18.81667],"type":"Point"}
}