{
  "type": "Feature",
  "properties": {
    "gn:admin1_code":"6.0",
    "gn:admin2_code":"3724144.0",
    "gn:asciiname":"Lagon Brunette",
    "gn:country_code":"HT",
    "gn:dem":733,
    "gn:feature_class":"P",
    "gn:feature_code":"PPL",
    "gn:name":"Lagon Brunette",
    "gn:population":0,
    "gn:timezone":"America/Port-au-Prince",
    "iso:country":"HT",
    "name:fra_x_preferred":[
        "Lagon Brunette"
    ],
    "wof:name":"Lagon Brunette",
    "wof:placetype":"locality"
},
  "geometry": {"coordinates":[-72.63593,19.73717000000001],"type":"Point"}
}