{
  "type": "Feature",
  "properties": {
    "gn:admin1_code":"11.0",
    "gn:admin2_code":"3727134.0",
    "gn:asciiname":"Fonds Cede",
    "gn:country_code":"HT",
    "gn:dem":31,
    "gn:feature_class":"P",
    "gn:feature_code":"PPL",
    "gn:name":"Fonds Cede",
    "gn:population":0,
    "gn:timezone":"America/Port-au-Prince",
    "iso:country":"HT",
    "wof:name":"Fonds Cede",
    "wof:placetype":"locality"
},
  "geometry": {"coordinates":[-72.01389,18.63028],"type":"Point"}
}