{
  "type": "Feature",
  "properties": {
    "gn:admin1_code":"11.0",
    "gn:asciiname":"Salmador",
    "gn:country_code":"HT",
    "gn:dem":744,
    "gn:feature_class":"P",
    "gn:feature_code":"PPL",
    "gn:name":"Salmador",
    "gn:population":0,
    "gn:timezone":"America/Port-au-Prince",
    "iso:country":"HT",
    "wof:name":"Salmador",
    "wof:placetype":"locality"
},
  "geometry": {"coordinates":[-71.76666999999998,18.73333],"type":"Point"}
}