{
  "type": "Feature",
  "properties": {
    "gn:admin1_code":"11.0",
    "gn:admin2_code":"3727134.0",
    "gn:asciiname":"Paques",
    "gn:country_code":"HT",
    "gn:dem":1185,
    "gn:feature_class":"P",
    "gn:feature_code":"PPL",
    "gn:name":"P\u00e2ques",
    "gn:population":0,
    "gn:timezone":"America/Port-au-Prince",
    "iso:country":"HT",
    "name:fra_x_preferred":[
        "P\u00e2ques"
    ],
    "wof:name":"Paques",
    "wof:placetype":"locality"
},
  "geometry": {"coordinates":[-72.17728000000002,18.3612],"type":"Point"}
}