{
  "type": "Feature",
  "properties": {
    "gn:admin1_code":"15.0",
    "gn:admin2_code":"3730801.0",
    "gn:asciiname":"Dumoulin",
    "gn:country_code":"HT",
    "gn:dem":631,
    "gn:feature_class":"P",
    "gn:feature_code":"PPL",
    "gn:name":"Dumoulin",
    "gn:population":0,
    "gn:timezone":"America/Port-au-Prince",
    "iso:country":"HT",
    "wof:name":"Dumoulin",
    "wof:placetype":"locality"
},
  "geometry": {"coordinates":[-73.61333,18.455],"type":"Point"}
}