{
  "type": "Feature",
  "properties": {
    "gn:admin1_code":"10.0",
    "gn:admin2_code":"3716114.0",
    "gn:asciiname":"Ducanelle",
    "gn:country_code":"HT",
    "gn:dem":467,
    "gn:feature_class":"P",
    "gn:feature_code":"PPL",
    "gn:name":"Ducanelle",
    "gn:population":0,
    "gn:timezone":"America/Port-au-Prince",
    "iso:country":"HT",
    "name:fra_x_preferred":[
        "Ducanelle"
    ],
    "wof:name":"Ducanelle",
    "wof:placetype":"locality"
},
  "geometry": {"coordinates":[-71.9594,19.43013],"type":"Point"}
}