{
  "type": "Feature",
  "properties": {
    "gn:admin1_code":"12.0",
    "gn:admin2_code":"3731094.0",
    "gn:asciiname":"Ca Rosier",
    "gn:country_code":"HT",
    "gn:dem":19,
    "gn:feature_class":"P",
    "gn:feature_code":"PPL",
    "gn:name":"Ca Rosier",
    "gn:population":0,
    "gn:timezone":"America/Port-au-Prince",
    "iso:country":"HT",
    "name:fra_x_preferred":[
        "Ca Rosier"
    ],
    "wof:name":"Ca Rosier",
    "wof:placetype":"locality"
},
  "geometry": {"coordinates":[-73.6724,18.27744],"type":"Point"}
}