{
  "type": "Feature",
  "properties": {
    "gn:admin1_code":"10.0",
    "gn:admin2_code":"3719435.0",
    "gn:asciiname":"Florence",
    "gn:country_code":"HT",
    "gn:dem":626,
    "gn:feature_class":"P",
    "gn:feature_code":"PPL",
    "gn:name":"Florence",
    "gn:population":0,
    "gn:timezone":"America/Port-au-Prince",
    "iso:country":"HT",
    "wof:name":"Florence",
    "wof:placetype":"locality"
},
  "geometry": {"coordinates":[-71.78333000000001,19.38333],"type":"Point"}
}