{
  "type": "Feature",
  "properties": {
    "gn:admin1_code":"9.0",
    "gn:admin2_code":"3718665.0",
    "gn:asciiname":"Carber",
    "gn:country_code":"HT",
    "gn:dem":540,
    "gn:feature_class":"P",
    "gn:feature_code":"PPL",
    "gn:name":"Carber",
    "gn:population":0,
    "gn:timezone":"America/Port-au-Prince",
    "iso:country":"HT",
    "wof:name":"Carber",
    "wof:placetype":"locality"
},
  "geometry": {"coordinates":[-72.45,19.55],"type":"Point"}
}