{
  "type": "Feature",
  "properties": {
    "gn:admin1_code":"3.0",
    "gn:asciiname":"Anse-a-Foleur",
    "gn:country_code":"HT",
    "gn:dem":10,
    "gn:feature_class":"P",
    "gn:feature_code":"PPL",
    "gn:name":"Anse-\u00e0-Foleur",
    "gn:population":0,
    "gn:timezone":"America/Port-au-Prince",
    "iso:country":"HT",
    "name:und_x_variant":[
        "Ville de Anse \u00e0 Foleur",
        "Anse \u00e0 Foleur",
        "Anse-\u00e0-Foleur"
    ],
    "wof:name":"Anse-a-Foleur",
    "wof:placetype":"locality"
},
  "geometry": {"coordinates":[-72.62014000000001,19.8926],"type":"Point"}
}