{
  "type": "Feature",
  "properties": {
    "gn:admin1_code":"3.0",
    "gn:asciiname":"Anse-a-Foleur",
    "gn:country_code":"HT",
    "gn:dem":10,
    "gn:feature_class":"P",
    "gn:feature_code":"PPL",
    "gn:name":"Anse-\u00e0-Foleur",
    "gn:population":0,
    "gn:timezone":"America/Port-au-Prince",
    "iso:country":"HT",
    "name:ara_x_preferred":[
        "\u0623\u0646\u0633 \u0641\u0648\u0644\u064a\u0631"
    ],
    "name:ceb_x_preferred":[
        "Anse-\u00e0-Foleur"
    ],
    "name:fra_x_preferred":[
        "Anse-\u00e0-Foleur"
    ],
    "name:hat_x_preferred":[
        "Ansafol\u00e8"
    ],
    "name:ita_x_preferred":[
        "Anse-\u00e0-Foleur"
    ],
    "name:nld_x_preferred":[
        "Anse-\u00e0-Foleur"
    ],
    "name:por_x_preferred":[
        "Anse-\u00e0-Foleur"
    ],
    "name:ron_x_preferred":[
        "Anse-\u00e0-Foleur"
    ],
    "name:spa_x_preferred":[
        "Anse-\u00e0-Foleur"
    ],
    "name:swe_x_preferred":[
        "Anse-\u00e0-Foleur"
    ],
    "name:und_x_variant":[
        "Ville de Anse \u00e0 Foleur",
        "Anse \u00e0 Foleur"
    ],
    "wof:name":"Anse-a-Foleur",
    "wof:placetype":"locality"
},
  "geometry": {"coordinates":[-72.62014000000001,19.8926],"type":"Point"}
}