{
  "type": "Feature",
  "properties": {
    "gn:admin1_code":"12.0",
    "gn:admin2_code":"3731094.0",
    "gn:asciiname":"Lefranc",
    "gn:country_code":"HT",
    "gn:dem":1245,
    "gn:feature_class":"P",
    "gn:feature_code":"PPL",
    "gn:name":"Lefranc",
    "gn:population":0,
    "gn:timezone":"America/Port-au-Prince",
    "iso:country":"HT",
    "wof:name":"Lefranc",
    "wof:placetype":"locality"
},
  "geometry": {"coordinates":[-73.51666999999998,18.33333],"type":"Point"}
}