{
  "type": "Feature",
  "properties": {
    "gn:admin1_code":"11.0",
    "gn:admin2_code":"3723019.0",
    "gn:asciiname":"Au Parc",
    "gn:country_code":"HT",
    "gn:dem":0,
    "gn:feature_class":"P",
    "gn:feature_code":"PPL",
    "gn:name":"Au Parc",
    "gn:population":0,
    "gn:timezone":"America/Port-au-Prince",
    "iso:country":"HT",
    "name:und_x_variant":[
        "Park Bay",
        "Baie du Parc",
        "Au Parc"
    ],
    "wof:name":"Au Parc",
    "wof:placetype":"locality"
},
  "geometry": {"coordinates":[-72.83696999999999,18.72222],"type":"Point"}
}