{
  "type": "Feature",
  "properties": {
    "gn:admin1_code":"3.0",
    "gn:admin2_code":"3718419.0",
    "gn:asciiname":"La Calombe",
    "gn:country_code":"HT",
    "gn:dem":214,
    "gn:feature_class":"P",
    "gn:feature_code":"PPL",
    "gn:name":"La Calombe",
    "gn:population":0,
    "gn:timezone":"America/Port-au-Prince",
    "iso:country":"HT",
    "wof:name":"La Calombe",
    "wof:placetype":"locality"
},
  "geometry": {"coordinates":[-72.76666999999998,19.91667],"type":"Point"}
}