{
  "type": "Feature",
  "properties": {
    "gn:admin1_code":"6.0",
    "gn:admin2_code":"3724695.0",
    "gn:asciiname":"La Homane",
    "gn:country_code":"HT",
    "gn:dem":953,
    "gn:feature_class":"P",
    "gn:feature_code":"PPL",
    "gn:name":"La Homane",
    "gn:population":0,
    "gn:timezone":"America/Port-au-Prince",
    "iso:country":"HT",
    "wof:name":"La Homane",
    "wof:placetype":"locality"
},
  "geometry": {"coordinates":[-72.45,19.51667],"type":"Point"}
}