{
  "type": "Feature",
  "properties": {
    "gn:admin1_code":"7.0",
    "gn:admin2_code":"3720809.0",
    "gn:asciiname":"Bajaux",
    "gn:country_code":"HT",
    "gn:dem":185,
    "gn:feature_class":"P",
    "gn:feature_code":"PPL",
    "gn:name":"Bajaux",
    "gn:population":0,
    "gn:timezone":"America/Port-au-Prince",
    "iso:country":"HT",
    "wof:name":"Bajaux",
    "wof:placetype":"locality"
},
  "geometry": {"coordinates":[-72.19611,18.9125],"type":"Point"}
}