{
  "type": "Feature",
  "properties": {
    "gn:admin1_code":"6.0",
    "gn:admin2_code":"3717587.0",
    "gn:asciiname":"Fourneau",
    "gn:country_code":"HT",
    "gn:dem":600,
    "gn:feature_class":"P",
    "gn:feature_code":"PPL",
    "gn:name":"Fourneau",
    "gn:population":0,
    "gn:timezone":"America/Port-au-Prince",
    "iso:country":"HT",
    "name:fra_x_preferred":[
        "Fourneaux"
    ],
    "wof:name":"Fourneau",
    "wof:placetype":"locality"
},
  "geometry": {"coordinates":[-72.4729,18.99233],"type":"Point"}
}