{
  "type": "Feature",
  "properties": {
    "gn:admin1_code":"7.0",
    "gn:admin2_code":"3728053.0",
    "gn:asciiname":"Lasterre",
    "gn:country_code":"HT",
    "gn:dem":380,
    "gn:feature_class":"P",
    "gn:feature_code":"PPL",
    "gn:name":"Lasterre",
    "gn:population":0,
    "gn:timezone":"America/Port-au-Prince",
    "iso:country":"HT",
    "name:fra_x_preferred":[
        "Lasterre"
    ],
    "wof:name":"Lasterre",
    "wof:placetype":"locality"
},
  "geometry": {"coordinates":[-71.80405,19.16183],"type":"Point"}
}