{
  "type": "Feature",
  "properties": {
    "gn:admin1_code":"11.0",
    "gn:admin2_code":"3731086.0",
    "gn:asciiname":"Cotarde",
    "gn:country_code":"HT",
    "gn:dem":888,
    "gn:feature_class":"P",
    "gn:feature_code":"PPL",
    "gn:name":"Cotarde",
    "gn:population":0,
    "gn:timezone":"America/Port-au-Prince",
    "iso:country":"HT",
    "wof:name":"Cotarde",
    "wof:placetype":"locality"
},
  "geometry": {"coordinates":[-72.38333,18.85],"type":"Point"}
}