{
  "type": "Feature",
  "properties": {
    "gn:admin1_code":"13.0",
    "gn:admin2_code":"3723778.0",
    "gn:asciiname":"Brulaille",
    "gn:country_code":"HT",
    "gn:dem":241,
    "gn:feature_class":"P",
    "gn:feature_code":"PPL",
    "gn:name":"Brulaille",
    "gn:population":0,
    "gn:timezone":"America/Port-au-Prince",
    "iso:country":"HT",
    "wof:name":"Brulaille",
    "wof:placetype":"locality"
},
  "geometry": {"coordinates":[-72.48416999999998,18.34139],"type":"Point"}
}