{
  "type": "Feature",
  "properties": {
    "gn:admin1_code":"14.0",
    "gn:admin2_code":"3723592.0",
    "gn:asciiname":"Pinquiere",
    "gn:country_code":"HT",
    "gn:dem":374,
    "gn:feature_class":"P",
    "gn:feature_code":"PPL",
    "gn:name":"Pinqui\u00e8re",
    "gn:population":0,
    "gn:timezone":"America/Port-au-Prince",
    "iso:country":"HT",
    "name:fra_x_preferred":[
        "Pinqui\u00e8re"
    ],
    "wof:name":"Pinquiere",
    "wof:placetype":"locality"
},
  "geometry": {"coordinates":[-74.18338,18.51311],"type":"Point"}
}