{
  "type": "Feature",
  "properties": {
    "gn:admin1_code":"7.0",
    "gn:admin2_code":"3722578.0",
    "gn:asciiname":"La Bellevue",
    "gn:country_code":"HT",
    "gn:dem":419,
    "gn:feature_class":"P",
    "gn:feature_code":"PPL",
    "gn:name":"La Bellevue",
    "gn:population":0,
    "gn:timezone":"America/Port-au-Prince",
    "iso:country":"HT",
    "wof:name":"La Bellevue",
    "wof:placetype":"locality"
},
  "geometry": {"coordinates":[-71.78333000000001,18.93333],"type":"Point"}
}