{
  "type": "Feature",
  "properties": {
    "gn:admin1_code":"10.0",
    "gn:admin2_code":"3716223.0",
    "gn:asciiname":"Moncey",
    "gn:country_code":"HT",
    "gn:dem":126,
    "gn:feature_class":"P",
    "gn:feature_code":"PPL",
    "gn:name":"Moncey",
    "gn:population":0,
    "gn:timezone":"America/Port-au-Prince",
    "iso:country":"HT",
    "name:rus_x_preferred":[
        "\u041c\u043e\u043d\u0441\u0435"
    ],
    "name:ukr_x_preferred":[
        "\u041c\u043e\u043d\u0441\u0435"
    ],
    "wof:name":"Moncey",
    "wof:placetype":"locality"
},
  "geometry": {"coordinates":[-71.98333000000002,19.61667000000001],"type":"Point"}
}