{
  "type": "Feature",
  "properties": {
    "gn:admin1_code":"11.0",
    "gn:asciiname":"Joute",
    "gn:country_code":"HT",
    "gn:dem":460,
    "gn:feature_class":"P",
    "gn:feature_code":"PPL",
    "gn:name":"Joute",
    "gn:population":0,
    "gn:timezone":"America/Port-au-Prince",
    "iso:country":"HT",
    "wof:name":"Joute",
    "wof:placetype":"locality"
},
  "geometry": {"coordinates":[-72.81667,18.28333],"type":"Point"}
}