{
  "type": "Feature",
  "properties": {
    "gn:admin1_code":"3.0",
    "gn:admin2_code":"3718419.0",
    "gn:asciiname":"Creace",
    "gn:country_code":"HT",
    "gn:dem":275,
    "gn:feature_class":"P",
    "gn:feature_code":"PPL",
    "gn:name":"Cr\u00e9ace",
    "gn:population":0,
    "gn:timezone":"America/Port-au-Prince",
    "iso:country":"HT",
    "name:fra_x_preferred":[
        "Creace"
    ],
    "name:und_x_variant":[
        "Cr\u00e9ace"
    ],
    "wof:name":"Creace",
    "wof:placetype":"locality"
},
  "geometry": {"coordinates":[-72.89938000000002,20.05697],"type":"Point"}
}