{
  "type": "Feature",
  "properties": {
    "gn:admin1_code":"3.0",
    "gn:admin2_code":"3720764.0",
    "gn:asciiname":"Gros Bassin",
    "gn:country_code":"HT",
    "gn:dem":41,
    "gn:feature_class":"P",
    "gn:feature_code":"PPL",
    "gn:name":"Gros Bassin",
    "gn:population":0,
    "gn:timezone":"America/Port-au-Prince",
    "iso:country":"HT",
    "name:fra_x_preferred":[
        "Gros Bassin"
    ],
    "wof:name":"Gros Bassin",
    "wof:placetype":"locality"
},
  "geometry": {"coordinates":[-73.07431,19.88013],"type":"Point"}
}