{
  "type": "Feature",
  "properties": {
    "gn:admin1_code":"9.0",
    "gn:admin2_code":"3731232",
    "gn:asciiname":"Amandier",
    "gn:country_code":"HT",
    "gn:dem":533,
    "gn:feature_class":"P",
    "gn:feature_code":"PPL",
    "gn:name":"Amandier",
    "gn:population":0,
    "gn:timezone":"America/Port-au-Prince",
    "iso:country":"HT",
    "wof:name":"Amandier",
    "wof:placetype":"locality"
},
  "geometry": {"coordinates":[-72.34999999999999,19.58333],"type":"Point"}
}