{
  "type": "Feature",
  "properties": {
    "gn:admin1_code":"9.0",
    "gn:admin2_code":"3717545.0",
    "gn:asciiname":"Localite",
    "gn:country_code":"HT",
    "gn:dem":354,
    "gn:feature_class":"P",
    "gn:feature_code":"PPL",
    "gn:name":"Localit\u00e9",
    "gn:population":0,
    "gn:timezone":"America/Port-au-Prince",
    "iso:country":"HT",
    "name:und_x_variant":[
        "Logalite",
        "Localit\u00e9"
    ],
    "wof:name":"Localite",
    "wof:placetype":"locality"
},
  "geometry": {"coordinates":[-72.18238000000002,19.3614],"type":"Point"}
}