{
  "type": "Feature",
  "properties": {
    "gn:admin1_code":"3.0",
    "gn:admin2_code":"3720764.0",
    "gn:asciiname":"Ti Lagon",
    "gn:country_code":"HT",
    "gn:dem":14,
    "gn:feature_class":"P",
    "gn:feature_code":"PPL",
    "gn:name":"Ti Lagon",
    "gn:population":0,
    "gn:timezone":"America/Port-au-Prince",
    "iso:country":"HT",
    "name:fra_x_preferred":[
        "Ti Lagon"
    ],
    "wof:name":"Ti Lagon",
    "wof:placetype":"locality"
},
  "geometry": {"coordinates":[-73.12458000000002,19.63153],"type":"Point"}
}