{
  "type": "Feature",
  "properties": {
    "gn:admin1_code":"12.0",
    "gn:admin2_code":"3727900.0",
    "gn:asciiname":"Poty",
    "gn:country_code":"HT",
    "gn:dem":345,
    "gn:feature_class":"P",
    "gn:feature_code":"PPL",
    "gn:name":"Poty",
    "gn:population":0,
    "gn:timezone":"America/Port-au-Prince",
    "iso:country":"HT",
    "name:und_x_variant":[
        "Coty",
        "Poty"
    ],
    "wof:name":"Poty",
    "wof:placetype":"locality"
},
  "geometry": {"coordinates":[-74.08249000000001,18.32938],"type":"Point"}
}