{
  "type": "Feature",
  "properties": {
    "gn:admin1_code":"9.0",
    "gn:asciiname":"La Noire",
    "gn:country_code":"HT",
    "gn:dem":356,
    "gn:feature_class":"P",
    "gn:feature_code":"PPL",
    "gn:name":"La Noire",
    "gn:population":0,
    "gn:timezone":"America/Port-au-Prince",
    "iso:country":"HT",
    "wof:name":"La Noire",
    "wof:placetype":"locality"
},
  "geometry": {"coordinates":[-72.63333,19.83333],"type":"Point"}
}