{
  "type": "Feature",
  "properties": {
    "gn:country":"HT",
    "gn:fcode":"PPL",
    "gn:pop":2130,
    "iso:country":"HT",
    "name:ara_x_preferred":[
        "\u0628\u064a\u062a\u064a\u062a \u062a\u0631\u0648 \u062f\u064a \u0646\u064a\u0628\u064a\u0633"
    ],
    "name:cym_x_preferred":[
        "Petit-Trou-de-Nippes"
    ],
    "name:eng_x_preferred":[
        "Petit-Trou-de-Nippes"
    ],
    "name:fra_x_preferred":[
        "Petit-Trou-de-Nippes"
    ],
    "name:hat_x_preferred":[
        "Ti Twou de Nip"
    ],
    "name:ita_x_preferred":[
        "Petit-Trou-de-Nippes"
    ],
    "name:nld_x_preferred":[
        "Petit-Trou-de-Nippes"
    ],
    "name:pol_x_preferred":[
        "Petit-Trou-de-Nippes"
    ],
    "name:por_x_preferred":[
        "Petit Trou de Nippes"
    ],
    "name:ron_x_preferred":[
        "Petit-Trou-de-Nippes"
    ],
    "name:swe_x_preferred":[
        "Petit Trou de Nippes"
    ],
    "name:unk_x_variant":[
        "Petit Trou"
    ],
    "name:zho_x_preferred":[
        "\u4f69\u8482\u7279-\u7279\u9b6f-\u5fb7-\u5c3c\u4f69\u65af"
    ],
    "qs:name":"Petit Trou de Nippes",
    "qs:photos_9r":0,
    "qs:photos_sr":0,
    "qs:pop_sr":"4",
    "wd:wordcount":36,
    "wof:name":"Petit Trou de Nippes",
    "wof:placetype":"locality",
    "wof:population":2130
},
  "geometry": {"coordinates":[-73.50815,18.52535],"type":"Point"}
}