{
  "type": "Feature",
  "properties": {
    "gn:admin1_code":"3.0",
    "gn:admin2_code":"3718419.0",
    "gn:asciiname":"Bassin Cannotte",
    "gn:country_code":"HT",
    "gn:dem":335,
    "gn:feature_class":"P",
    "gn:feature_code":"PPL",
    "gn:name":"Bassin Cannotte",
    "gn:population":0,
    "gn:timezone":"America/Port-au-Prince",
    "iso:country":"HT",
    "wof:name":"Bassin Cannotte",
    "wof:placetype":"locality"
},
  "geometry": {"coordinates":[-72.83333,19.76667],"type":"Point"}
}