{
  "type": "Feature",
  "properties": {
    "gn:admin1_code":"14.0",
    "gn:admin2_code":"3723592.0",
    "gn:asciiname":"Grand Dolle",
    "gn:country_code":"HT",
    "gn:dem":932,
    "gn:feature_class":"P",
    "gn:feature_code":"PPL",
    "gn:name":"Grand Dolle",
    "gn:population":0,
    "gn:timezone":"America/Port-au-Prince",
    "iso:country":"HT",
    "name:fra_x_preferred":[
        "Grand Dolle"
    ],
    "wof:name":"Grand Dolle",
    "wof:placetype":"locality"
},
  "geometry": {"coordinates":[-74.18724,18.48308],"type":"Point"}
}