{
  "type": "Feature",
  "properties": {
    "gn:admin1_code":"12.0",
    "gn:admin2_code":"3727295.0",
    "gn:asciiname":"Nan Cadet",
    "gn:country_code":"HT",
    "gn:dem":186,
    "gn:feature_class":"P",
    "gn:feature_code":"PPL",
    "gn:name":"Nan Cadet",
    "gn:population":0,
    "gn:timezone":"America/Port-au-Prince",
    "iso:country":"HT",
    "name:fra_x_preferred":[
        "Nan Cadet"
    ],
    "wof:name":"Nan Cadet",
    "wof:placetype":"locality"
},
  "geometry": {"coordinates":[-74.08102,18.27887],"type":"Point"}
}