{
  "type": "Feature",
  "properties": {
    "gn:admin1_code":"7.0",
    "gn:admin2_code":"3723840.0",
    "gn:asciiname":"Epin",
    "gn:country_code":"HT",
    "gn:dem":443,
    "gn:feature_class":"P",
    "gn:feature_code":"PPL",
    "gn:name":"Epin",
    "gn:population":0,
    "gn:timezone":"America/Port-au-Prince",
    "iso:country":"HT",
    "name:fra_x_preferred":[
        "Epin"
    ],
    "wof:name":"Epin",
    "wof:placetype":"locality"
},
  "geometry": {"coordinates":[-72.03281,18.99412],"type":"Point"}
}