{
  "type": "Feature",
  "properties": {
    "gn:admin1_code":"3.0",
    "gn:admin2_code":"3720764.0",
    "gn:asciiname":"Repos",
    "gn:country_code":"HT",
    "gn:dem":360,
    "gn:feature_class":"P",
    "gn:feature_code":"PPL",
    "gn:name":"Repos",
    "gn:population":0,
    "gn:timezone":"America/Port-au-Prince",
    "iso:country":"HT",
    "wof:name":"Repos",
    "wof:placetype":"locality"
},
  "geometry": {"coordinates":[-73.13500000000001,19.76889],"type":"Point"}
}