{
  "type": "Feature",
  "properties": {
    "gn:admin1_code":"9.0",
    "gn:admin2_code":"3731232.0",
    "gn:asciiname":"Raidi",
    "gn:country_code":"HT",
    "gn:dem":16,
    "gn:feature_class":"P",
    "gn:feature_code":"PPL",
    "gn:name":"Raidi",
    "gn:population":0,
    "gn:timezone":"America/Port-au-Prince",
    "iso:country":"HT",
    "name:deu_x_preferred":[
        "Raidi"
    ],
    "name:fra_x_preferred":[
        "Raidi"
    ],
    "name:nld_x_preferred":[
        "Raidi"
    ],
    "name:nor_x_preferred":[
        "Ragdi"
    ],
    "name:swe_x_preferred":[
        "Ragdi"
    ],
    "wof:name":"Raidi",
    "wof:placetype":"locality"
},
  "geometry": {"coordinates":[-72.24757,19.67318],"type":"Point"}
}