{
  "type": "Feature",
  "properties": {
    "gn:admin1_code":"13.0",
    "gn:admin2_code":"3730361.0",
    "gn:asciiname":"Bois Pin",
    "gn:country_code":"HT",
    "gn:dem":354,
    "gn:feature_class":"P",
    "gn:feature_code":"PPL",
    "gn:name":"Bois Pin",
    "gn:population":0,
    "gn:timezone":"America/Port-au-Prince",
    "iso:country":"HT",
    "wof:name":"Bois Pin",
    "wof:placetype":"locality"
},
  "geometry": {"coordinates":[-72.11667,18.26667],"type":"Point"}
}