{
  "type": "Feature",
  "properties": {
    "gn:admin1_code":"14.0",
    "gn:asciiname":"Dumini",
    "gn:country_code":"HT",
    "gn:dem":247,
    "gn:feature_class":"P",
    "gn:feature_code":"PPL",
    "gn:name":"Dumini",
    "gn:population":0,
    "gn:timezone":"America/Port-au-Prince",
    "iso:country":"HT",
    "wof:name":"Dumini",
    "wof:placetype":"locality"
},
  "geometry": {"coordinates":[-73.34999999999999,18.36667000000001],"type":"Point"}
}