{
  "type": "Feature",
  "properties": {
    "gn:admin1_code":"7.0",
    "gn:admin2_code":"3720809.0",
    "gn:asciiname":"Zaboca",
    "gn:country_code":"HT",
    "gn:dem":1042,
    "gn:feature_class":"P",
    "gn:feature_code":"PPL",
    "gn:name":"Zaboca",
    "gn:population":0,
    "gn:timezone":"America/Port-au-Prince",
    "iso:country":"HT",
    "wof:name":"Zaboca",
    "wof:placetype":"locality"
},
  "geometry": {"coordinates":[-72.15000000000001,19.01667],"type":"Point"}
}