{
  "type": "Feature",
  "properties": {
    "gn:admin1_code":"15.0",
    "gn:admin2_code":"3731122.0",
    "gn:asciiname":"Tournade",
    "gn:country_code":"HT",
    "gn:dem":158,
    "gn:feature_class":"P",
    "gn:feature_code":"PPL",
    "gn:name":"Tournade",
    "gn:population":0,
    "gn:timezone":"America/Port-au-Prince",
    "iso:country":"HT",
    "wof:name":"Tournade",
    "wof:placetype":"locality"
},
  "geometry": {"coordinates":[-73.40000000000001,18.38333],"type":"Point"}
}