{
  "type": "Feature",
  "properties": {
    "gn:admin1_code":"12.0",
    "gn:admin2_code":"3728096.0",
    "gn:asciiname":"Etang Dole",
    "gn:country_code":"HT",
    "gn:dem":179,
    "gn:feature_class":"P",
    "gn:feature_code":"PPL",
    "gn:name":"\u00c9tang Dole",
    "gn:population":0,
    "gn:timezone":"America/Port-au-Prince",
    "iso:country":"HT",
    "wof:name":"Etang Dole",
    "wof:placetype":"locality"
},
  "geometry": {"coordinates":[-73.81667,18.33333],"type":"Point"}
}