{
  "type": "Feature",
  "properties": {
    "gn:admin1_code":"15.0",
    "gn:admin2_code":"3730801.0",
    "gn:asciiname":"Nan Renaud",
    "gn:country_code":"HT",
    "gn:dem":20,
    "gn:feature_class":"P",
    "gn:feature_code":"PPL",
    "gn:name":"Nan Renaud",
    "gn:population":0,
    "gn:timezone":"America/Port-au-Prince",
    "iso:country":"HT",
    "wof:name":"Nan Renaud",
    "wof:placetype":"locality"
},
  "geometry": {"coordinates":[-73.64778000000003,18.49139],"type":"Point"}
}