{
  "type": "Feature",
  "properties": {
    "gn:admin1_code":"6.0",
    "gn:admin2_code":"3717563.0",
    "gn:asciiname":"Dazilma",
    "gn:country_code":"HT",
    "gn:dem":372,
    "gn:feature_class":"P",
    "gn:feature_code":"PPL",
    "gn:name":"Dazilma",
    "gn:population":0,
    "gn:timezone":"America/Port-au-Prince",
    "iso:country":"HT",
    "name:fra_x_preferred":[
        "Dazilma"
    ],
    "wof:name":"Dazilma",
    "wof:placetype":"locality"
},
  "geometry": {"coordinates":[-72.28513000000002,19.31649],"type":"Point"}
}