{
  "type": "Feature",
  "properties": {
    "gn:admin1_code":"11.0",
    "gn:admin2_code":"3727134.0",
    "gn:asciiname":"Cassis",
    "gn:country_code":"HT",
    "gn:dem":26,
    "gn:feature_class":"P",
    "gn:feature_code":"PPL",
    "gn:name":"Cassis",
    "gn:population":0,
    "gn:timezone":"America/Port-au-Prince",
    "iso:country":"HT",
    "name:fra_x_preferred":[
        "Cassis"
    ],
    "wof:name":"Cassis",
    "wof:placetype":"locality"
},
  "geometry": {"coordinates":[-72.0733,18.60882],"type":"Point"}
}