{
  "type": "Feature",
  "properties": {
    "gn:admin1_code":"7.0",
    "gn:asciiname":"Bastia",
    "gn:country_code":"HT",
    "gn:dem":309,
    "gn:feature_class":"P",
    "gn:feature_code":"PPL",
    "gn:name":"Bastia",
    "gn:population":0,
    "gn:timezone":"America/Port-au-Prince",
    "iso:country":"HT",
    "name:fra_x_preferred":[
        "Bastia"
    ],
    "wof:name":"Bastia",
    "wof:placetype":"locality"
},
  "geometry": {"coordinates":[-72.19561,19.19151],"type":"Point"}
}