{
  "type": "Feature",
  "properties": {
    "gn:admin1_code":"12.0",
    "gn:admin2_code":"3727900.0",
    "gn:asciiname":"Bertrand",
    "gn:country_code":"HT",
    "gn:dem":231,
    "gn:feature_class":"P",
    "gn:feature_code":"PPL",
    "gn:name":"Bertrand",
    "gn:population":0,
    "gn:timezone":"America/Port-au-Prince",
    "iso:country":"HT",
    "name:fra_x_preferred":[
        "Bertrand"
    ],
    "wof:name":"Bertrand",
    "wof:placetype":"locality"
},
  "geometry": {"coordinates":[-74.33288,18.32902],"type":"Point"}
}