{
  "type": "Feature",
  "properties": {
    "gn:admin1_code":"11.0",
    "gn:admin2_code":"3731086.0",
    "gn:asciiname":"Dos Marotte",
    "gn:country_code":"HT",
    "gn:dem":594,
    "gn:feature_class":"P",
    "gn:feature_code":"PPL",
    "gn:name":"Dos Marotte",
    "gn:population":0,
    "gn:timezone":"America/Port-au-Prince",
    "iso:country":"HT",
    "name:fra_x_preferred":[
        "Dos Marotte"
    ],
    "wof:name":"Dos Marotte",
    "wof:placetype":"locality"
},
  "geometry": {"coordinates":[-72.56104000000001,18.86714],"type":"Point"}
}