{
  "type": "Feature",
  "properties": {
    "gn:admin1_code":"11.0",
    "gn:admin2_code":"3723019.0",
    "gn:asciiname":"Grand Pique",
    "gn:country_code":"HT",
    "gn:dem":534,
    "gn:feature_class":"P",
    "gn:feature_code":"PPL",
    "gn:name":"Grand Pique",
    "gn:population":0,
    "gn:timezone":"America/Port-au-Prince",
    "iso:country":"HT",
    "wof:name":"Grand Pique",
    "wof:placetype":"locality"
},
  "geometry": {"coordinates":[-72.90000000000001,18.78333],"type":"Point"}
}