{
  "type": "Feature",
  "properties": {
    "gn:admin1_code":"13.0",
    "gn:admin2_code":"3723778.0",
    "gn:asciiname":"Fond Fevrier",
    "gn:country_code":"HT",
    "gn:dem":42,
    "gn:feature_class":"P",
    "gn:feature_code":"PPL",
    "gn:name":"Fond F\u00e9vrier",
    "gn:population":0,
    "gn:timezone":"America/Port-au-Prince",
    "iso:country":"HT",
    "wof:name":"Fond Fevrier",
    "wof:placetype":"locality"
},
  "geometry": {"coordinates":[-72.52694,18.25417],"type":"Point"}
}