{
  "type": "Feature",
  "properties": {
    "gn:admin1_code":"7.0",
    "gn:admin2_code":"3728053.0",
    "gn:asciiname":"Los Posos",
    "gn:country_code":"HT",
    "gn:dem":321,
    "gn:feature_class":"P",
    "gn:feature_code":"PPL",
    "gn:name":"Los Posos",
    "gn:population":0,
    "gn:timezone":"America/Port-au-Prince",
    "iso:country":"HT",
    "name:fra_x_preferred":[
        "Los Posos"
    ],
    "wof:name":"Los Posos",
    "wof:placetype":"locality"
},
  "geometry": {"coordinates":[-71.75145000000001,19.1334],"type":"Point"}
}