{
  "type": "Feature",
  "properties": {
    "gn:admin1_code":"7.0",
    "gn:admin2_code":"3723840.0",
    "gn:asciiname":"Roc Blanc",
    "gn:country_code":"HT",
    "gn:dem":299,
    "gn:feature_class":"P",
    "gn:feature_code":"PPL",
    "gn:name":"Roc Blanc",
    "gn:population":0,
    "gn:timezone":"America/Port-au-Prince",
    "iso:country":"HT",
    "wof:name":"Roc Blanc",
    "wof:placetype":"locality"
},
  "geometry": {"coordinates":[-72.23333000000002,19.21667],"type":"Point"}
}