{
  "type": "Feature",
  "properties": {
    "gn:admin1_code":"14.0",
    "gn:admin2_code":"3727381.0",
    "gn:asciiname":"Mort",
    "gn:country_code":"HT",
    "gn:dem":226,
    "gn:feature_class":"P",
    "gn:feature_code":"PPL",
    "gn:name":"Mort",
    "gn:population":0,
    "gn:timezone":"America/Port-au-Prince",
    "iso:country":"HT",
    "name:bul_x_preferred":[
        "\u041c\u043e\u0440\u0442"
    ],
    "name:ces_x_preferred":[
        "Mort"
    ],
    "name:cym_x_preferred":[
        "Mort"
    ],
    "name:dan_x_preferred":[
        "D\u00f8dens L\u00e6rling"
    ],
    "name:deu_x_preferred":[
        "Gevatter Tod"
    ],
    "name:ell_x_preferred":[
        "\u0398\u03b1\u03bd\u03b1\u03c4\u03b7\u03c6\u03cc\u03c1\u03bf\u03c2 \u0392\u03bf\u03b7\u03b8\u03cc\u03c2"
    ],
    "name:fin_x_preferred":[
        "Mort"
    ],
    "name:fra_x_preferred":[
        "Mortimer"
    ],
    "name:glg_x_preferred":[
        "Mort"
    ],
    "name:heb_x_preferred":[
        "\u05ea\u05e8\u05d5\u05e2\u05ea \u05de\u05d5\u05d5\u05ea"
    ],
    "name:hun_x_preferred":[
        "Mort"
    ],
    "name:ita_x_preferred":[
        "Morty l'apprendista"
    ],
    "name:nld_x_preferred":[
        "Dunne Hein"
    ],
    "name:pol_x_preferred":[
        "Mort"
    ],
    "name:ron_x_preferred":[
        "Mort"
    ],
    "name:rus_x_preferred":[
        "\u041c\u043e\u0440"
    ],
    "name:spa_x_preferred":[
        "Mort"
    ],
    "name:srp_x_preferred":[
        "Mort"
    ],
    "name:ukr_x_preferred":[
        "\u041c\u043e\u0440\u0442"
    ],
    "wof:name":"Mort",
    "wof:placetype":"locality"
},
  "geometry": {"coordinates":[-73.98361,18.5625],"type":"Point"}
}