{
  "type": "Feature",
  "properties": {
    "gn:admin1_code":"6.0",
    "gn:admin2_code":"3717563.0",
    "gn:asciiname":"L'Ermitte",
    "gn:country_code":"HT",
    "gn:dem":350,
    "gn:feature_class":"P",
    "gn:feature_code":"PPL",
    "gn:name":"L\u2019Ermitte",
    "gn:population":0,
    "gn:timezone":"America/Port-au-Prince",
    "iso:country":"HT",
    "name:fra_x_preferred":[
        "L\u2019Ermitte"
    ],
    "name:und_x_variant":[
        "Mate L\u2019ermite",
        "L\u2019Ermite"
    ],
    "wof:name":"L'Ermitte",
    "wof:placetype":"locality"
},
  "geometry": {"coordinates":[-72.28643000000002,19.2549],"type":"Point"}
}