{
  "type": "Feature",
  "properties": {
    "gn:admin1_code":"3.0",
    "gn:admin2_code":"3720764.0",
    "gn:asciiname":"Chilotte",
    "gn:country_code":"HT",
    "gn:dem":621,
    "gn:feature_class":"P",
    "gn:feature_code":"PPL",
    "gn:name":"Chilotte",
    "gn:population":0,
    "gn:timezone":"America/Port-au-Prince",
    "iso:country":"HT",
    "name:fra_x_preferred":[
        "Chilotte"
    ],
    "wof:name":"Chilotte",
    "wof:placetype":"locality"
},
  "geometry": {"coordinates":[-73.39660000000001,19.68432],"type":"Point"}
}