{
  "type": "Feature",
  "properties": {
    "gn:admin1_code":"7.0",
    "gn:admin2_code":"3722578.0",
    "gn:asciiname":"Laurence",
    "gn:country_code":"HT",
    "gn:dem":204,
    "gn:feature_class":"P",
    "gn:feature_code":"PPL",
    "gn:name":"Laurence",
    "gn:population":0,
    "gn:timezone":"America/Port-au-Prince",
    "iso:country":"HT",
    "name:fra_x_preferred":[
        "Laurence"
    ],
    "wof:name":"Laurence",
    "wof:placetype":"locality"
},
  "geometry": {"coordinates":[-72.01201,18.89616],"type":"Point"}
}