{
  "type": "Feature",
  "properties": {
    "gn:admin1_code":"6.0",
    "gn:admin2_code":"3717587.0",
    "gn:asciiname":"Charrier",
    "gn:country_code":"HT",
    "gn:dem":94,
    "gn:feature_class":"P",
    "gn:feature_code":"PPL",
    "gn:name":"Charrier",
    "gn:population":0,
    "gn:timezone":"America/Port-au-Prince",
    "iso:country":"HT",
    "name:und_x_variant":[
        "Charier",
        "Charrier"
    ],
    "wof:name":"Charrier",
    "wof:placetype":"locality"
},
  "geometry": {"coordinates":[-72.35276,18.94447000000001],"type":"Point"}
}