{
  "type": "Feature",
  "properties": {
    "gn:admin1_code":"10.0",
    "gn:admin2_code":"3719435.0",
    "gn:asciiname":"Mont Premier",
    "gn:country_code":"HT",
    "gn:dem":105,
    "gn:feature_class":"P",
    "gn:feature_code":"PPL",
    "gn:name":"Mont Premier",
    "gn:population":0,
    "gn:timezone":"America/Port-au-Prince",
    "iso:country":"HT",
    "name:fra_x_preferred":[
        "Mont Premier"
    ],
    "wof:name":"Mont Premier",
    "wof:placetype":"locality"
},
  "geometry": {"coordinates":[-71.82254,19.5109],"type":"Point"}
}