{
  "type": "Feature",
  "properties": {
    "gn:admin1_code":"12.0",
    "gn:asciiname":"Charmant",
    "gn:country_code":"HT",
    "gn:dem":417,
    "gn:feature_class":"P",
    "gn:feature_code":"PPL",
    "gn:name":"Charmant",
    "gn:population":0,
    "gn:timezone":"America/Port-au-Prince",
    "iso:country":"HT",
    "wof:name":"Charmant",
    "wof:placetype":"locality"
},
  "geometry": {"coordinates":[-72.53333000000001,18.45],"type":"Point"}
}