{
  "type": "Feature",
  "properties": {
    "gn:admin1_code":"7.0",
    "gn:admin2_code":"3723840.0",
    "gn:asciiname":"En Bas Caimite",
    "gn:country_code":"HT",
    "gn:dem":440,
    "gn:feature_class":"P",
    "gn:feature_code":"PPL",
    "gn:name":"En Bas Caimite",
    "gn:population":0,
    "gn:timezone":"America/Port-au-Prince",
    "iso:country":"HT",
    "wof:name":"En Bas Caimite",
    "wof:placetype":"locality"
},
  "geometry": {"coordinates":[-71.96666999999999,19.25],"type":"Point"}
}