{
  "type": "Feature",
  "properties": {
    "gn:admin1_code":"6.0",
    "gn:admin2_code":"3724695.0",
    "gn:asciiname":"Ti Perisse",
    "gn:country_code":"HT",
    "gn:dem":318,
    "gn:feature_class":"P",
    "gn:feature_code":"PPL",
    "gn:name":"Ti P\u00e9risse",
    "gn:population":0,
    "gn:timezone":"America/Port-au-Prince",
    "iso:country":"HT",
    "name:und_x_variant":[
        "P\u00e9risse",
        "Ti P\u00e9risse"
    ],
    "wof:name":"Ti Perisse",
    "wof:placetype":"locality"
},
  "geometry": {"coordinates":[-72.5307,19.33168],"type":"Point"}
}