{
  "type": "Feature",
  "properties": {
    "gn:admin1_code":"13.0",
    "gn:admin2_code":"3723778.0",
    "gn:asciiname":"Depot",
    "gn:country_code":"HT",
    "gn:dem":21,
    "gn:feature_class":"P",
    "gn:feature_code":"PPL",
    "gn:name":"D\u00e9p\u00f4t",
    "gn:population":0,
    "gn:timezone":"America/Port-au-Prince",
    "iso:country":"HT",
    "name:fra_x_preferred":[
        "D\u00e9p\u00f4t"
    ],
    "wof:name":"Depot",
    "wof:placetype":"locality"
},
  "geometry": {"coordinates":[-72.29456999999999,18.22994],"type":"Point"}
}