{
  "type": "Feature",
  "properties": {
    "gn:admin1_code":"13.0",
    "gn:admin2_code":"3723778.0",
    "gn:asciiname":"Depot",
    "gn:country_code":"HT",
    "gn:dem":21,
    "gn:feature_class":"P",
    "gn:feature_code":"PPL",
    "gn:name":"D\u00e9p\u00f4t",
    "gn:population":0,
    "gn:timezone":"America/Port-au-Prince",
    "iso:country":"HT",
    "name:cat_x_preferred":[
        "Dip\u00f2sit"
    ],
    "name:dan_x_preferred":[
        "Depot"
    ],
    "name:deu_x_preferred":[
        "Depot"
    ],
    "name:est_x_preferred":[
        "Depoo"
    ],
    "name:fas_x_preferred":[
        "\u062f\u067e\u0648"
    ],
    "name:fra_x_preferred":[
        "D\u00e9p\u00f4t"
    ],
    "name:hye_x_preferred":[
        "\u0534\u0565\u057a\u0578"
    ],
    "name:nld_x_preferred":[
        "Depot"
    ],
    "name:rus_x_preferred":[
        "\u0414\u0435\u043f\u043e"
    ],
    "name:swe_x_preferred":[
        "Dep\u00e5"
    ],
    "name:ukr_x_preferred":[
        "\u0414\u0435\u043f\u043e"
    ],
    "wof:name":"Depot",
    "wof:placetype":"locality"
},
  "geometry": {"coordinates":[-72.29456999999999,18.22994],"type":"Point"}
}