{
  "type": "Feature",
  "properties": {
    "gn:admin1_code":"14.0",
    "gn:admin2_code":"3723592",
    "gn:asciiname":"Anse Joseph",
    "gn:country_code":"HT",
    "gn:dem":118,
    "gn:feature_class":"P",
    "gn:feature_code":"PPL",
    "gn:name":"Anse Joseph",
    "gn:population":0,
    "gn:timezone":"America/Port-au-Prince",
    "iso:country":"HT",
    "wof:name":"Anse Joseph",
    "wof:placetype":"locality"
},
  "geometry": {"coordinates":[-74.35259000000001,18.63804],"type":"Point"}
}