{
  "type": "Feature",
  "properties": {
    "gn:admin1_code":"14.0",
    "gn:admin2_code":"3723592.0",
    "gn:asciiname":"Petite Plaine",
    "gn:country_code":"HT",
    "gn:dem":199,
    "gn:feature_class":"P",
    "gn:feature_code":"PPL",
    "gn:name":"Petite Plaine",
    "gn:population":0,
    "gn:timezone":"America/Port-au-Prince",
    "iso:country":"HT",
    "name:fra_x_preferred":[
        "Petite Plaine"
    ],
    "wof:name":"Petite Plaine",
    "wof:placetype":"locality"
},
  "geometry": {"coordinates":[-74.23276,18.65097],"type":"Point"}
}