{
  "type": "Feature",
  "properties": {
    "gn:admin1_code":"10.0",
    "gn:admin2_code":"3716114.0",
    "gn:asciiname":"Fond Bois",
    "gn:country_code":"HT",
    "gn:dem":665,
    "gn:feature_class":"P",
    "gn:feature_code":"PPL",
    "gn:name":"Fond Bois",
    "gn:population":0,
    "gn:timezone":"America/Port-au-Prince",
    "iso:country":"HT",
    "wof:name":"Fond Bois",
    "wof:placetype":"locality"
},
  "geometry": {"coordinates":[-71.95,19.31667],"type":"Point"}
}