{
  "type": "Feature",
  "properties": {
    "gn:admin1_code":"10.0",
    "gn:asciiname":"En Bas Saline",
    "gn:country_code":"HT",
    "gn:dem":7,
    "gn:feature_class":"P",
    "gn:feature_code":"PPL",
    "gn:name":"En Bas Saline",
    "gn:population":0,
    "gn:timezone":"America/Port-au-Prince",
    "iso:country":"HT",
    "name:fra_x_preferred":[
        "En Bas Saline"
    ],
    "wof:name":"En Bas Saline",
    "wof:placetype":"locality"
},
  "geometry": {"coordinates":[-72.02450999999998,19.69215],"type":"Point"}
}