{
  "type": "Feature",
  "properties": {
    "gn:admin1_code":"6.0",
    "gn:admin2_code":"3726539.0",
    "gn:asciiname":"L'Acul",
    "gn:country_code":"HT",
    "gn:dem":39,
    "gn:feature_class":"P",
    "gn:feature_code":"PPL",
    "gn:name":"L\u2019Acul",
    "gn:population":0,
    "gn:timezone":"America/Port-au-Prince",
    "iso:country":"HT",
    "wof:name":"L'Acul",
    "wof:placetype":"locality"
},
  "geometry": {"coordinates":[-72.46666999999999,19.21667],"type":"Point"}
}