{
  "type": "Feature",
  "properties": {
    "gn:admin1_code":"14.0",
    "gn:admin2_code":"3731116.0",
    "gn:asciiname":"Breche",
    "gn:country_code":"HT",
    "gn:dem":21,
    "gn:feature_class":"P",
    "gn:feature_code":"PPL",
    "gn:name":"Br\u00e8che",
    "gn:population":0,
    "gn:timezone":"America/Port-au-Prince",
    "iso:country":"HT",
    "wof:name":"Breche",
    "wof:placetype":"locality"
},
  "geometry": {"coordinates":[-74.43207,18.53239],"type":"Point"}
}