{
  "type": "Feature",
  "properties": {
    "gn:admin1_code":"6.0",
    "gn:admin2_code":"3717587.0",
    "gn:asciiname":"Gressot",
    "gn:country_code":"HT",
    "gn:dem":565,
    "gn:feature_class":"P",
    "gn:feature_code":"PPL",
    "gn:name":"Gressot",
    "gn:population":0,
    "gn:timezone":"America/Port-au-Prince",
    "iso:country":"HT",
    "name:fra_x_preferred":[
        "Gressot"
    ],
    "wof:name":"Gressot",
    "wof:placetype":"locality"
},
  "geometry": {"coordinates":[-72.63778000000001,18.9825],"type":"Point"}
}