{
  "type": "Feature",
  "properties": {
    "gn:admin1_code":"11.0",
    "gn:admin2_code":"3722285",
    "gn:asciiname":"Abraham",
    "gn:country_code":"HT",
    "gn:dem":203,
    "gn:feature_class":"P",
    "gn:feature_code":"PPL",
    "gn:name":"Abraham",
    "gn:population":0,
    "gn:timezone":"America/Port-au-Prince",
    "iso:country":"HT",
    "wof:name":"Abraham",
    "wof:placetype":"locality"
},
  "geometry": {"coordinates":[-72.81416999999998,18.41972],"type":"Point"}
}