{
  "type": "Feature",
  "properties": {
    "gn:admin1_code":"11.0",
    "gn:admin2_code":"3718425.0",
    "gn:asciiname":"Duvivier",
    "gn:cc2":"HT",
    "gn:country_code":"HT",
    "gn:dem":14,
    "gn:feature_class":"P",
    "gn:feature_code":"PPL",
    "gn:name":"Duvivier",
    "gn:population":0,
    "gn:timezone":"America/Port-au-Prince",
    "iso:country":"HT",
    "name:und_x_variant":[
        "Duvivior",
        "Duvivier"
    ],
    "wof:name":"Duvivier",
    "wof:placetype":"locality"
},
  "geometry": {"coordinates":[-72.32083,18.60111],"type":"Point"}
}