{
  "type": "Feature",
  "properties": {
    "gn:admin1_code":"12.0",
    "gn:admin2_code":"3728096.0",
    "gn:asciiname":"Gerard",
    "gn:country_code":"HT",
    "gn:dem":71,
    "gn:feature_class":"P",
    "gn:feature_code":"PPL",
    "gn:name":"G\u00e9rard",
    "gn:population":0,
    "gn:timezone":"America/Port-au-Prince",
    "iso:country":"HT",
    "name:cat_x_preferred":[
        "Gerard"
    ],
    "name:deu_x_preferred":[
        "Gerard"
    ],
    "name:nld_x_preferred":[
        "Gerard"
    ],
    "name:pol_x_preferred":[
        "Gerard"
    ],
    "name:rus_x_preferred":[
        "\u0414\u0436\u0435\u0440\u0430\u0440\u0434"
    ],
    "wof:name":"Gerard",
    "wof:placetype":"locality"
},
  "geometry": {"coordinates":[-73.88333,18.21667],"type":"Point"}
}