{
  "type": "Feature",
  "properties": {
    "gn:country":"HT",
    "gn:fcode":"PPL",
    "gn:pop":3951,
    "iso:country":"HT",
    "name:hat_x_preferred":[
        "Kabar\u00e8"
    ],
    "name:unk_x_variant":[
        "Duvalierville"
    ],
    "qs:name":"Cabaret",
    "qs:photos_9r":0,
    "qs:photos_sr":0,
    "qs:pop_sr":"4",
    "wd:wordcount":2602,
    "wof:name":"Cabaret",
    "wof:placetype":"locality",
    "wof:population":3951
},
  "geometry": {"coordinates":[-72.4175,18.73583],"type":"Point"}
}