{
  "type": "Feature",
  "properties": {
    "gn:admin1_code":"6.0",
    "gn:admin2_code":"3717587.0",
    "gn:asciiname":"Terre Nette",
    "gn:country_code":"HT",
    "gn:dem":1105,
    "gn:feature_class":"P",
    "gn:feature_code":"PPL",
    "gn:name":"Terre Nette",
    "gn:population":0,
    "gn:timezone":"America/Port-au-Prince",
    "iso:country":"HT",
    "name:und_x_variant":[
        "Terre Net",
        "Terre Nette"
    ],
    "wof:name":"Terre Nette",
    "wof:placetype":"locality"
},
  "geometry": {"coordinates":[-72.51515999999999,18.9819],"type":"Point"}
}