{
  "type": "Feature",
  "properties": {
    "gn:admin1_code":"6.0",
    "gn:admin2_code":"3717587.0",
    "gn:asciiname":"Deschatelles",
    "gn:country_code":"HT",
    "gn:dem":19,
    "gn:feature_class":"P",
    "gn:feature_code":"PPL",
    "gn:name":"Deschatelles",
    "gn:population":0,
    "gn:timezone":"America/Port-au-Prince",
    "iso:country":"HT",
    "name:fra_x_preferred":[
        "Deschatelles"
    ],
    "wof:name":"Deschatelles",
    "wof:placetype":"locality"
},
  "geometry": {"coordinates":[-72.62753000000002,19.17699],"type":"Point"}
}