{
  "type": "Feature",
  "properties": {
    "gn:admin1_code":"14.0",
    "gn:admin2_code":"3727381.0",
    "gn:asciiname":"Durand",
    "gn:country_code":"HT",
    "gn:dem":84,
    "gn:feature_class":"P",
    "gn:feature_code":"PPL",
    "gn:name":"Durand",
    "gn:population":0,
    "gn:timezone":"America/Port-au-Prince",
    "iso:country":"HT",
    "wof:name":"Durand",
    "wof:placetype":"locality"
},
  "geometry": {"coordinates":[-74.01666999999998,18.55],"type":"Point"}
}