{
  "type": "Feature",
  "properties": {
    "gn:admin1_code":"12.0",
    "gn:admin2_code":"3731094.0",
    "gn:asciiname":"Laplante",
    "gn:country_code":"HT",
    "gn:dem":774,
    "gn:feature_class":"P",
    "gn:feature_code":"PPL",
    "gn:name":"Laplante",
    "gn:population":0,
    "gn:timezone":"America/Port-au-Prince",
    "iso:country":"HT",
    "name:fra_x_preferred":[
        "La Plante"
    ],
    "name:und_x_variant":[
        "Laplants",
        "Laplante"
    ],
    "wof:name":"Laplante",
    "wof:placetype":"locality"
},
  "geometry": {"coordinates":[-73.65689999999999,18.41493],"type":"Point"}
}