{
  "type": "Feature",
  "properties": {
    "gn:admin1_code":"6.0",
    "gn:asciiname":"Pebat",
    "gn:country_code":"HT",
    "gn:dem":1031,
    "gn:feature_class":"P",
    "gn:feature_code":"PPL",
    "gn:name":"P\u00e9bat",
    "gn:population":0,
    "gn:timezone":"America/Port-au-Prince",
    "iso:country":"HT",
    "wof:name":"Pebat",
    "wof:placetype":"locality"
},
  "geometry": {"coordinates":[-72.31667,18.81667],"type":"Point"}
}