{
  "type": "Feature",
  "properties": {
    "gn:admin1_code":"6.0",
    "gn:asciiname":"Plaine Olive",
    "gn:cc2":"HT",
    "gn:country_code":"HT",
    "gn:dem":372,
    "gn:feature_class":"P",
    "gn:feature_code":"PPL",
    "gn:name":"Plaine Olive",
    "gn:population":0,
    "gn:timezone":"America/Port-au-Prince",
    "iso:country":"HT",
    "name:und_x_variant":[
        "Plaine D\u2019Olive",
        "Plaine Olive"
    ],
    "wof:name":"Plaine Olive",
    "wof:placetype":"locality"
},
  "geometry": {"coordinates":[-72.63333,18.96667],"type":"Point"}
}