{
  "type": "Feature",
  "properties": {
    "gn:admin1_code":"6.0",
    "gn:admin2_code":"3726539.0",
    "gn:asciiname":"Vannos",
    "gn:country_code":"HT",
    "gn:dem":16,
    "gn:feature_class":"P",
    "gn:feature_code":"PPL",
    "gn:name":"Vannos",
    "gn:population":0,
    "gn:timezone":"America/Port-au-Prince",
    "iso:country":"HT",
    "name:fra_x_preferred":[
        "Vannos"
    ],
    "wof:name":"Vannos",
    "wof:placetype":"locality"
},
  "geometry": {"coordinates":[-72.52983,19.22546],"type":"Point"}
}