{
  "type": "Feature",
  "properties": {
    "gn:admin1_code":"12.0",
    "gn:admin2_code":"3727295.0",
    "gn:asciiname":"Desert",
    "gn:country_code":"HT",
    "gn:dem":505,
    "gn:feature_class":"P",
    "gn:feature_code":"PPL",
    "gn:name":"Desert",
    "gn:population":0,
    "gn:timezone":"America/Port-au-Prince",
    "iso:country":"HT",
    "wof:name":"Desert",
    "wof:placetype":"locality"
},
  "geometry": {"coordinates":[-74.01666999999998,18.28333],"type":"Point"}
}