{
  "type": "Feature",
  "properties": {
    "gn:admin1_code":"11.0",
    "gn:admin2_code":"3722285.0",
    "gn:asciiname":"Mosemberg",
    "gn:country_code":"HT",
    "gn:dem":374,
    "gn:feature_class":"P",
    "gn:feature_code":"PPL",
    "gn:name":"Mosemberg",
    "gn:population":0,
    "gn:timezone":"America/Port-au-Prince",
    "iso:country":"HT",
    "name:fra_x_preferred":[
        "Mosemberg"
    ],
    "wof:name":"Mosemberg",
    "wof:placetype":"locality"
},
  "geometry": {"coordinates":[-72.74406999999999,18.38035],"type":"Point"}
}