{
  "type": "Feature",
  "properties": {
    "gn:admin1_code":"6.0",
    "gn:admin2_code":"3717563.0",
    "gn:asciiname":"Morne Roux",
    "gn:country_code":"HT",
    "gn:dem":736,
    "gn:feature_class":"P",
    "gn:feature_code":"PPL",
    "gn:name":"Morne Roux",
    "gn:population":0,
    "gn:timezone":"America/Port-au-Prince",
    "iso:country":"HT",
    "wof:name":"Morne Roux",
    "wof:placetype":"locality"
},
  "geometry": {"coordinates":[-72.40000000000001,19.51667],"type":"Point"}
}