{
  "type": "Feature",
  "properties": {
    "gn:admin1_code":"6.0",
    "gn:admin2_code":"3717563.0",
    "gn:asciiname":"Morne Canal",
    "gn:country_code":"HT",
    "gn:dem":773,
    "gn:feature_class":"P",
    "gn:feature_code":"PPL",
    "gn:name":"Morne Canal",
    "gn:population":0,
    "gn:timezone":"America/Port-au-Prince",
    "iso:country":"HT",
    "wof:name":"Morne Canal",
    "wof:placetype":"locality"
},
  "geometry": {"coordinates":[-72.36667,19.55],"type":"Point"}
}