{
  "type": "Feature",
  "properties": {
    "gn:admin1_code":"12.0",
    "gn:admin2_code":"3728096.0",
    "gn:asciiname":"Maniche",
    "gn:country_code":"HT",
    "gn:dem":76,
    "gn:feature_class":"P",
    "gn:feature_code":"PPL",
    "gn:name":"Maniche",
    "gn:population":0,
    "gn:timezone":"America/Port-au-Prince",
    "iso:country":"HT",
    "name:hat_x_preferred":[
        "Manich"
    ],
    "name:und_x_variant":[
        "Moniche"
    ],
    "wof:name":"Maniche",
    "wof:placetype":"locality"
},
  "geometry": {"coordinates":[-73.77721,18.34501],"type":"Point"}
}