{
  "type": "Feature",
  "properties": {
    "gn:admin1_code":"12.0",
    "gn:admin2_code":"3728096.0",
    "gn:asciiname":"Maniche",
    "gn:country_code":"HT",
    "gn:dem":76,
    "gn:feature_class":"P",
    "gn:feature_code":"PPL",
    "gn:name":"Maniche",
    "gn:population":0,
    "gn:timezone":"America/Port-au-Prince",
    "iso:country":"HT",
    "name:ara_x_preferred":[
        "\u0645\u0627\u0646\u064a\u0634"
    ],
    "name:azb_x_preferred":[
        "\u0645\u0627\u0646\u06cc\u0634"
    ],
    "name:ben_x_preferred":[
        "\u09ae\u09be\u09a8\u09bf\u09b6"
    ],
    "name:ces_x_preferred":[
        "Maniche"
    ],
    "name:deu_x_preferred":[
        "Maniche"
    ],
    "name:epo_x_preferred":[
        "Maniche"
    ],
    "name:est_x_preferred":[
        "Maniche"
    ],
    "name:fas_x_preferred":[
        "\u0645\u0627\u0646\u06cc\u0634"
    ],
    "name:fin_x_preferred":[
        "Maniche"
    ],
    "name:fra_x_preferred":[
        "Maniche"
    ],
    "name:hat_x_preferred":[
        "Manich"
    ],
    "name:heb_x_preferred":[
        "\u05de\u05d0\u05e0\u05d9\u05e9"
    ],
    "name:hrv_x_preferred":[
        "Maniche"
    ],
    "name:hun_x_preferred":[
        "Maniche"
    ],
    "name:hye_x_preferred":[
        "\u0544\u0561\u0576\u056b\u0577\u0565"
    ],
    "name:ind_x_preferred":[
        "Maniche"
    ],
    "name:ita_x_preferred":[
        "Maniche"
    ],
    "name:jpn_x_preferred":[
        "\u30de\u30cb\u30b7\u30a7"
    ],
    "name:kaz_x_preferred":[
        "\u041c\u0430\u043d\u0438\u0448\u0435"
    ],
    "name:kor_x_preferred":[
        "\ub9c8\ub2c8\uc2dc"
    ],
    "name:lit_x_preferred":[
        "Maniche"
    ],
    "name:mlg_x_preferred":[
        "Maniche"
    ],
    "name:nld_x_preferred":[
        "Maniche"
    ],
    "name:nor_x_preferred":[
        "Maniche"
    ],
    "name:pol_x_preferred":[
        "Maniche"
    ],
    "name:por_x_preferred":[
        "Maniche"
    ],
    "name:que_x_preferred":[
        "Maniche"
    ],
    "name:ron_x_preferred":[
        "Maniche"
    ],
    "name:rus_x_preferred":[
        "\u041c\u0430\u043d\u0438\u0448\u0435"
    ],
    "name:slv_x_preferred":[
        "Maniche"
    ],
    "name:spa_x_preferred":[
        "Maniche"
    ],
    "name:srp_x_preferred":[
        "\u041c\u0430\u043d\u0438\u0448\u0435"
    ],
    "name:swe_x_preferred":[
        "Maniche"
    ],
    "name:tur_x_preferred":[
        "Maniche"
    ],
    "name:ukr_x_preferred":[
        "\u041c\u0430\u043d\u0456\u0448\u0435"
    ],
    "name:und_x_variant":[
        "Moniche"
    ],
    "name:zho_x_preferred":[
        "\u9a6c\u5c3c\u5207"
    ],
    "wof:name":"Maniche",
    "wof:placetype":"locality"
},
  "geometry": {"coordinates":[-73.77721,18.34501],"type":"Point"}
}