{
  "type": "Feature",
  "properties": {
    "gn:admin1_code":"6.0",
    "gn:admin2_code":"3717563.0",
    "gn:asciiname":"Boucan Sannite",
    "gn:country_code":"HT",
    "gn:dem":462,
    "gn:feature_class":"P",
    "gn:feature_code":"PPL",
    "gn:name":"Boucan Sannite",
    "gn:population":0,
    "gn:timezone":"America/Port-au-Prince",
    "iso:country":"HT",
    "wof:name":"Boucan Sannite",
    "wof:placetype":"locality"
},
  "geometry": {"coordinates":[-72.28333000000001,19.21667],"type":"Point"}
}