{
  "type": "Feature",
  "properties": {
    "gn:admin1_code":"14.0",
    "gn:admin2_code":"3723592.0",
    "gn:asciiname":"Morne Chatte",
    "gn:country_code":"HT",
    "gn:dem":381,
    "gn:feature_class":"P",
    "gn:feature_code":"PPL",
    "gn:name":"Morne Chatte",
    "gn:population":0,
    "gn:timezone":"America/Port-au-Prince",
    "iso:country":"HT",
    "wof:name":"Morne Chatte",
    "wof:placetype":"locality"
},
  "geometry": {"coordinates":[-74.34999999999999,18.58333],"type":"Point"}
}