{
  "type": "Feature",
  "properties": {
    "gn:admin1_code":"3.0",
    "gn:admin2_code":"3720764.0",
    "gn:asciiname":"Cabaret",
    "gn:country_code":"HT",
    "gn:dem":28,
    "gn:feature_class":"P",
    "gn:feature_code":"PPL",
    "gn:name":"Cabaret",
    "gn:population":0,
    "gn:timezone":"America/Port-au-Prince",
    "iso:country":"HT",
    "name:fra_x_preferred":[
        "Cabaret"
    ],
    "name:fra_x_variant":[
        "Cabare"
    ],
    "wof:name":"Cabaret",
    "wof:placetype":"locality"
},
  "geometry": {"coordinates":[-73.01459,19.87469],"type":"Point"}
}