{
  "type": "Feature",
  "properties": {
    "gn:admin1_code":"6.0",
    "gn:asciiname":"Carrefour",
    "gn:country_code":"HT",
    "gn:dem":802,
    "gn:feature_class":"P",
    "gn:feature_code":"PPL",
    "gn:name":"Carrefour",
    "gn:population":0,
    "gn:timezone":"America/Port-au-Prince",
    "iso:country":"HT",
    "wof:name":"Carrefour",
    "wof:placetype":"locality"
},
  "geometry": {"coordinates":[-72.31667,19.48333],"type":"Point"}
}