{
  "type": "Feature",
  "properties": {
    "gn:admin1_code":"7.0",
    "gn:admin2_code":"3722578.0",
    "gn:asciiname":"Colorado",
    "gn:country_code":"HT",
    "gn:dem":292,
    "gn:feature_class":"P",
    "gn:feature_code":"PPL",
    "gn:name":"Colorado",
    "gn:population":0,
    "gn:timezone":"America/Port-au-Prince",
    "iso:country":"HT",
    "name:fra_x_preferred":[
        "Colorado"
    ],
    "wof:name":"Colorado",
    "wof:placetype":"locality"
},
  "geometry": {"coordinates":[-71.85300000000002,18.94489],"type":"Point"}
}