{
  "type": "Feature",
  "properties": {
    "gn:admin1_code":"3.0",
    "gn:asciiname":"Homme de Paille",
    "gn:country_code":"HT",
    "gn:dem":12,
    "gn:feature_class":"P",
    "gn:feature_code":"PPL",
    "gn:name":"Homme de Paille",
    "gn:population":0,
    "gn:timezone":"America/Port-au-Prince",
    "iso:country":"HT",
    "wof:name":"Homme de Paille",
    "wof:placetype":"locality"
},
  "geometry": {"coordinates":[-73.09278,19.64222],"type":"Point"}
}