{
  "type": "Feature",
  "properties": {
    "gn:admin1_code":"13.0",
    "gn:admin2_code":"3723778.0",
    "gn:asciiname":"Guillaumond",
    "gn:cc2":"HT",
    "gn:country_code":"HT",
    "gn:dem":36,
    "gn:feature_class":"P",
    "gn:feature_code":"PPL",
    "gn:name":"Guillaumond",
    "gn:population":0,
    "gn:timezone":"America/Port-au-Prince",
    "iso:country":"HT",
    "name:und_x_variant":[
        "Guillaumonde",
        "Guillaumond"
    ],
    "wof:name":"Guillaumond",
    "wof:placetype":"locality"
},
  "geometry": {"coordinates":[-72.26971999999998,18.22944],"type":"Point"}
}