{
  "type": "Feature",
  "properties": {
    "gn:admin1_code":"10.0",
    "gn:admin2_code":"3716114.0",
    "gn:asciiname":"Francois Pierre",
    "gn:country_code":"HT",
    "gn:dem":642,
    "gn:feature_class":"P",
    "gn:feature_code":"PPL",
    "gn:name":"Fran\u00e7ois Pierre",
    "gn:population":0,
    "gn:timezone":"America/Port-au-Prince",
    "iso:country":"HT",
    "name:fra_x_preferred":[
        "Fran\u00e7ois Pierre"
    ],
    "wof:name":"Francois Pierre",
    "wof:placetype":"locality"
},
  "geometry": {"coordinates":[-71.78091999999999,19.29967000000001],"type":"Point"}
}