{
  "type": "Feature",
  "properties": {
    "gn:admin1_code":"6.0",
    "gn:admin2_code":"3717587.0",
    "gn:asciiname":"Dauphine",
    "gn:country_code":"HT",
    "gn:dem":460,
    "gn:feature_class":"P",
    "gn:feature_code":"PPL",
    "gn:name":"Dauphine",
    "gn:population":0,
    "gn:timezone":"America/Port-au-Prince",
    "iso:country":"HT",
    "name:deu_x_preferred":[
        "Dauphine"
    ],
    "name:fin_x_preferred":[
        "Dauphine"
    ],
    "name:fra_x_preferred":[
        "Dauphine"
    ],
    "name:ita_x_preferred":[
        "Dauphine"
    ],
    "name:nld_x_preferred":[
        "Dauphine"
    ],
    "wof:name":"Dauphine",
    "wof:placetype":"locality"
},
  "geometry": {"coordinates":[-72.45983000000003,19.01524],"type":"Point"}
}