{
  "type": "Feature",
  "properties": {
    "gn:admin1_code":"7.0",
    "gn:admin2_code":"3723840.0",
    "gn:asciiname":"De l'Eau Coq",
    "gn:country_code":"HT",
    "gn:dem":307,
    "gn:feature_class":"P",
    "gn:feature_code":"PPL",
    "gn:name":"De l\u2019Eau Coq",
    "gn:population":0,
    "gn:timezone":"America/Port-au-Prince",
    "iso:country":"HT",
    "name:fra_x_preferred":[
        "D\u2019lo Coq"
    ],
    "name:und_x_variant":[
        "D\u2019Lo Coq",
        "De l\u2019Eau Coq"
    ],
    "wof:name":"De l'Eau Coq",
    "wof:placetype":"locality"
},
  "geometry": {"coordinates":[-71.88215,19.11482],"type":"Point"}
}