{
  "type": "Feature",
  "properties": {
    "gn:admin1_code":"12.0",
    "gn:admin2_code":"3731094.0",
    "gn:asciiname":"Ducourt",
    "gn:country_code":"HT",
    "gn:dem":417,
    "gn:feature_class":"P",
    "gn:feature_code":"PPL",
    "gn:name":"Ducourt",
    "gn:population":0,
    "gn:timezone":"America/Port-au-Prince",
    "iso:country":"HT",
    "wof:name":"Ducourt",
    "wof:placetype":"locality"
},
  "geometry": {"coordinates":[-73.58333,18.41667],"type":"Point"}
}