{
  "type": "Feature",
  "properties": {
    "gn:admin1_code":"9.0",
    "gn:admin2_code":"3729454.0",
    "gn:asciiname":"Chevalier",
    "gn:country_code":"HT",
    "gn:dem":15,
    "gn:feature_class":"P",
    "gn:feature_code":"PPL",
    "gn:name":"Chevalier",
    "gn:population":0,
    "gn:timezone":"America/Port-au-Prince",
    "iso:country":"HT",
    "name:fra_x_preferred":[
        "Chevalier"
    ],
    "wof:name":"Chevalier",
    "wof:placetype":"locality"
},
  "geometry": {"coordinates":[-72.44601999999998,19.80173],"type":"Point"}
}