{
  "type": "Feature",
  "properties": {
    "gn:admin1_code":"9.0",
    "gn:admin2_code":"3729454.0",
    "gn:asciiname":"Chevalier",
    "gn:country_code":"HT",
    "gn:dem":15,
    "gn:feature_class":"P",
    "gn:feature_code":"PPL",
    "gn:name":"Chevalier",
    "gn:population":0,
    "gn:timezone":"America/Port-au-Prince",
    "iso:country":"HT",
    "name:bel_x_preferred":[
        "\u0428\u044d\u0432\u0430\u043b\u044c\u0435"
    ],
    "name:deu_x_preferred":[
        "Chevalier"
    ],
    "name:fas_x_preferred":[
        "\u0634\u0648\u0627\u0644\u06cc\u0647"
    ],
    "name:fra_x_preferred":[
        "Chevalier"
    ],
    "name:ita_x_preferred":[
        "Chevalier"
    ],
    "name:jpn_x_preferred":[
        "\u30b7\u30e5\u30f4\u30a1\u30ea\u30a8"
    ],
    "name:nld_x_preferred":[
        "Chevalier"
    ],
    "name:por_x_preferred":[
        "Chevalier"
    ],
    "name:ron_x_preferred":[
        "Chevalier"
    ],
    "name:rus_x_preferred":[
        "\u0428\u0435\u0432\u0430\u043b\u044c\u0435"
    ],
    "name:spa_x_preferred":[
        "Chevalier"
    ],
    "name:swe_x_preferred":[
        "Chevalier"
    ],
    "name:ukr_x_preferred":[
        "\u0428\u0435\u0432\u0430\u043b\u044c\u0454"
    ],
    "wof:name":"Chevalier",
    "wof:placetype":"locality"
},
  "geometry": {"coordinates":[-72.44601999999998,19.80173],"type":"Point"}
}