{
  "type": "Feature",
  "properties": {
    "gn:admin1_code":"15.0",
    "gn:admin2_code":"3731122.0",
    "gn:asciiname":"Grand Fond",
    "gn:country_code":"HT",
    "gn:dem":37,
    "gn:feature_class":"P",
    "gn:feature_code":"PPL",
    "gn:name":"Grand Fond",
    "gn:population":0,
    "gn:timezone":"America/Port-au-Prince",
    "iso:country":"HT",
    "name:fas_x_preferred":[
        "\u06af\u0631\u0646\u062f \u0641\u0648\u0646\u062f"
    ],
    "name:fra_x_preferred":[
        "Grand Fond"
    ],
    "name:oci_x_preferred":[
        "Grand Fond"
    ],
    "name:ron_x_preferred":[
        "Grand Fond"
    ],
    "wof:name":"Grand Fond",
    "wof:placetype":"locality"
},
  "geometry": {"coordinates":[-73.37456,18.50151],"type":"Point"}
}