{
  "type": "Feature",
  "properties": {
    "gn:admin1_code":"3.0",
    "gn:admin2_code":"3720764.0",
    "gn:asciiname":"La Lande",
    "gn:country_code":"HT",
    "gn:dem":555,
    "gn:feature_class":"P",
    "gn:feature_code":"PPL",
    "gn:name":"La Lande",
    "gn:population":0,
    "gn:timezone":"America/Port-au-Prince",
    "iso:country":"HT",
    "wof:name":"La Lande",
    "wof:placetype":"locality"
},
  "geometry": {"coordinates":[-73.13110999999998,19.79167],"type":"Point"}
}