{
  "type": "Feature",
  "properties": {
    "gn:admin1_code":"9.0",
    "gn:admin2_code":"3728473.0",
    "gn:asciiname":"Camp Fort",
    "gn:country_code":"HT",
    "gn:dem":11,
    "gn:feature_class":"P",
    "gn:feature_code":"PPL",
    "gn:name":"Camp Fort",
    "gn:population":0,
    "gn:timezone":"America/Port-au-Prince",
    "iso:country":"HT",
    "wof:name":"Camp Fort",
    "wof:placetype":"locality"
},
  "geometry": {"coordinates":[-72.21916999999998,19.73806],"type":"Point"}
}