{
  "type": "Feature",
  "properties": {
    "gn:admin1_code":"9.0",
    "gn:admin2_code":"3728473.0",
    "gn:asciiname":"Defraille",
    "gn:country_code":"HT",
    "gn:dem":12,
    "gn:feature_class":"P",
    "gn:feature_code":"PPL",
    "gn:name":"D\u00e9fraille",
    "gn:population":0,
    "gn:timezone":"America/Port-au-Prince",
    "iso:country":"HT",
    "name:fra_x_preferred":[
        "D\u00e9fraille"
    ],
    "wof:name":"Defraille",
    "wof:placetype":"locality"
},
  "geometry": {"coordinates":[-72.16105999999998,19.72461],"type":"Point"}
}