{
  "type": "Feature",
  "properties": {
    "gn:admin1_code":"6.0",
    "gn:admin2_code":"3717587.0",
    "gn:asciiname":"Chatelain",
    "gn:country_code":"HT",
    "gn:dem":397,
    "gn:feature_class":"P",
    "gn:feature_code":"PPL",
    "gn:name":"Chatelain",
    "gn:population":0,
    "gn:timezone":"America/Port-au-Prince",
    "iso:country":"HT",
    "name:fra_x_preferred":[
        "Chatelain"
    ],
    "wof:name":"Chatelain",
    "wof:placetype":"locality"
},
  "geometry": {"coordinates":[-72.41882,18.95767],"type":"Point"}
}