{
  "type": "Feature",
  "properties": {
    "gn:admin1_code":"10.0",
    "gn:admin2_code":"3716223.0",
    "gn:asciiname":"Sainyette",
    "gn:country_code":"HT",
    "gn:dem":375,
    "gn:feature_class":"P",
    "gn:feature_code":"PPL",
    "gn:name":"Sainyette",
    "gn:population":0,
    "gn:timezone":"America/Port-au-Prince",
    "iso:country":"HT",
    "wof:name":"Sainyette",
    "wof:placetype":"locality"
},
  "geometry": {"coordinates":[-71.98333000000002,19.53333],"type":"Point"}
}