{
  "type": "Feature",
  "properties": {
    "gn:admin1_code":"7.0",
    "gn:asciiname":"Fleurimond",
    "gn:country_code":"HT",
    "gn:dem":1262,
    "gn:feature_class":"P",
    "gn:feature_code":"PPL",
    "gn:name":"Fleurimond",
    "gn:population":0,
    "gn:timezone":"America/Port-au-Prince",
    "iso:country":"HT",
    "wof:name":"Fleurimond",
    "wof:placetype":"locality"
},
  "geometry": {"coordinates":[-71.88333,18.71667],"type":"Point"}
}