{
  "type": "Feature",
  "properties": {
    "gn:admin1_code":"6.0",
    "gn:admin2_code":"3724144.0",
    "gn:asciiname":"Ca Philippe",
    "gn:country_code":"HT",
    "gn:dem":280,
    "gn:feature_class":"P",
    "gn:feature_code":"PPL",
    "gn:name":"Ca Philippe",
    "gn:population":0,
    "gn:timezone":"America/Port-au-Prince",
    "iso:country":"HT",
    "name:und_x_variant":[
        "Ka Philippe",
        "Ca Philippe"
    ],
    "wof:name":"Ca Philippe",
    "wof:placetype":"locality"
},
  "geometry": {"coordinates":[-72.84640999999998,19.66173],"type":"Point"}
}