{
  "type": "Feature",
  "properties": {
    "gn:admin1_code":"3.0",
    "gn:admin2_code":"3718419.0",
    "gn:asciiname":"Bas Mahotiere",
    "gn:country_code":"HT",
    "gn:dem":323,
    "gn:feature_class":"P",
    "gn:feature_code":"PPL",
    "gn:name":"Bas Mahoti\u00e8re",
    "gn:population":0,
    "gn:timezone":"America/Port-au-Prince",
    "iso:country":"HT",
    "name:fra_x_preferred":[
        "Bas Mahoti\u00e8re"
    ],
    "wof:name":"Bas Mahotiere",
    "wof:placetype":"locality"
},
  "geometry": {"coordinates":[-72.96600000000002,19.783],"type":"Point"}
}