{
  "type": "Feature",
  "properties": {
    "gn:admin1_code":"3.0",
    "gn:admin2_code":"3718419.0",
    "gn:asciiname":"Pierre Tules",
    "gn:country_code":"HT",
    "gn:dem":36,
    "gn:feature_class":"P",
    "gn:feature_code":"PPL",
    "gn:name":"Pierre Tules",
    "gn:population":0,
    "gn:timezone":"America/Port-au-Prince",
    "iso:country":"HT",
    "name:fra_x_preferred":[
        "Pierre Tules"
    ],
    "wof:name":"Pierre Tules",
    "wof:placetype":"locality"
},
  "geometry": {"coordinates":[-72.75726,20.06292],"type":"Point"}
}