{
  "type": "Feature",
  "properties": {
    "gn:admin1_code":"12.0",
    "gn:admin2_code":"3727900.0",
    "gn:asciiname":"Lubin",
    "gn:country_code":"HT",
    "gn:dem":480,
    "gn:feature_class":"P",
    "gn:feature_code":"PPL",
    "gn:name":"Lubin",
    "gn:population":0,
    "gn:timezone":"America/Port-au-Prince",
    "iso:country":"HT",
    "name:bel_x_preferred":[
        "\u041b\u044e\u0431\u0456\u043d"
    ],
    "name:bul_x_preferred":[
        "\u041b\u044e\u0431\u0438\u043d"
    ],
    "name:ceb_x_preferred":[
        "Lubin"
    ],
    "name:ces_x_preferred":[
        "Lubin"
    ],
    "name:crh_x_preferred":[
        "L\u00fcbin"
    ],
    "name:csb_x_preferred":[
        "Lubin"
    ],
    "name:deu_x_preferred":[
        "Lubin"
    ],
    "name:epo_x_preferred":[
        "Lubin"
    ],
    "name:eus_x_preferred":[
        "Lubin"
    ],
    "name:fas_x_preferred":[
        "\u0644\u0648\u0628\u06cc\u0646"
    ],
    "name:fin_x_preferred":[
        "Lubin"
    ],
    "name:fra_x_preferred":[
        "Lubin"
    ],
    "name:heb_x_preferred":[
        "\u05dc\u05d5\u05d1\u05d9\u05df"
    ],
    "name:hun_x_preferred":[
        "Lubin"
    ],
    "name:hye_x_preferred":[
        "\u053c\u0575\u0578\u0582\u0562\u056b\u0576"
    ],
    "name:ind_x_preferred":[
        "Lubin"
    ],
    "name:ita_x_preferred":[
        "Lubin"
    ],
    "name:jav_x_preferred":[
        "Lubin"
    ],
    "name:jbo_x_preferred":[
        "lubin"
    ],
    "name:jpn_x_preferred":[
        "\u30eb\u30d3\u30f3"
    ],
    "name:kor_x_preferred":[
        "\ub8e8\ube48"
    ],
    "name:lav_x_preferred":[
        "Lubina"
    ],
    "name:lit_x_preferred":[
        "Liubinas"
    ],
    "name:mar_x_preferred":[
        "\u0932\u094d\u092f\u0941\u092c\u093f\u0928"
    ],
    "name:msa_x_preferred":[
        "Lubin"
    ],
    "name:new_x_preferred":[
        "\u0932\u0941\u092c\u093f\u0928"
    ],
    "name:nld_x_preferred":[
        "Lubin"
    ],
    "name:nor_x_preferred":[
        "Lubin"
    ],
    "name:pol_x_preferred":[
        "Lubin"
    ],
    "name:por_x_preferred":[
        "Lubin"
    ],
    "name:que_x_preferred":[
        "Lubin"
    ],
    "name:ron_x_preferred":[
        "Lubin"
    ],
    "name:rus_x_preferred":[
        "\u041b\u044e\u0431\u0438\u043d"
    ],
    "name:slk_x_preferred":[
        "Lubin"
    ],
    "name:spa_x_preferred":[
        "Lubin"
    ],
    "name:srp_x_preferred":[
        "\u041b\u0443\u0431\u0438\u043d"
    ],
    "name:swe_x_preferred":[
        "Lubin"
    ],
    "name:szl_x_preferred":[
        "Lubin"
    ],
    "name:tat_x_preferred":[
        "\u041b\u044e\u0431\u0438\u043d"
    ],
    "name:tur_x_preferred":[
        "Lubin"
    ],
    "name:ukr_x_preferred":[
        "\u041b\u044e\u0431\u0456\u043d"
    ],
    "name:vie_x_preferred":[
        "Lubin"
    ],
    "name:war_x_preferred":[
        "Lubin"
    ],
    "wof:name":"Lubin",
    "wof:placetype":"locality"
},
  "geometry": {"coordinates":[-74.28333000000001,18.35],"type":"Point"}
}