{
  "type": "Feature",
  "properties": {
    "gn:admin1_code":"3.0",
    "gn:admin2_code":"3718419.0",
    "gn:asciiname":"Bois Milot",
    "gn:country_code":"HT",
    "gn:dem":67,
    "gn:feature_class":"P",
    "gn:feature_code":"PPL",
    "gn:name":"Bois Milot",
    "gn:population":0,
    "gn:timezone":"America/Port-au-Prince",
    "iso:country":"HT",
    "name:fra_x_preferred":[
        "Bois Milot"
    ],
    "wof:name":"Bois Milot",
    "wof:placetype":"locality"
},
  "geometry": {"coordinates":[-72.91081,19.87497],"type":"Point"}
}