{
  "type": "Feature",
  "properties": {
    "gn:admin1_code":"10.0",
    "gn:admin2_code":"3716223.0",
    "gn:asciiname":"Lombard",
    "gn:country_code":"HT",
    "gn:dem":16,
    "gn:feature_class":"P",
    "gn:feature_code":"PPL",
    "gn:name":"Lombard",
    "gn:population":0,
    "gn:timezone":"America/Port-au-Prince",
    "iso:country":"HT",
    "name:ceb_x_preferred":[
        "Lombard"
    ],
    "name:deu_x_preferred":[
        "Lombard"
    ],
    "name:fin_x_preferred":[
        "Lombard"
    ],
    "name:fra_x_preferred":[
        "Lombard"
    ],
    "name:hun_x_preferred":[
        "Lombard"
    ],
    "name:ita_x_preferred":[
        "Lombard"
    ],
    "name:jpn_x_preferred":[
        "\u30ed\u30f3\u30d0\u30fc\u30c9"
    ],
    "name:kor_x_preferred":[
        "\ub86c\ubc14\ub4dc"
    ],
    "name:lav_x_preferred":[
        "Lombarda"
    ],
    "name:nds_x_preferred":[
        "Lombard"
    ],
    "name:nld_x_preferred":[
        "Lombard"
    ],
    "name:pms_x_preferred":[
        "Lombard"
    ],
    "name:pol_x_preferred":[
        "Lombard"
    ],
    "name:por_x_preferred":[
        "Lombard"
    ],
    "name:ron_x_preferred":[
        "Lombard"
    ],
    "name:slk_x_preferred":[
        "Lombard"
    ],
    "name:spa_x_preferred":[
        "Lombard"
    ],
    "name:swe_x_preferred":[
        "Lombard"
    ],
    "name:ukr_x_preferred":[
        "\u041b\u043e\u043c\u0431\u0430\u0440"
    ],
    "name:und_x_variant":[
        "Lombart",
        "Lombard"
    ],
    "wof:name":"Lombard",
    "wof:placetype":"locality"
},
  "geometry": {"coordinates":[-72.02004000000002,19.67098],"type":"Point"}
}