{
  "type": "Feature",
  "properties": {
    "gn:admin1_code":"12.0",
    "gn:admin2_code":"3728096.0",
    "gn:asciiname":"Melissant",
    "gn:country_code":"HT",
    "gn:dem":288,
    "gn:feature_class":"P",
    "gn:feature_code":"PPL",
    "gn:name":"M\u00e9lissant",
    "gn:population":0,
    "gn:timezone":"America/Port-au-Prince",
    "iso:country":"HT",
    "name:fra_x_preferred":[
        "Melissant"
    ],
    "name:und_x_variant":[
        "M\u00e9lissant"
    ],
    "wof:name":"Melissant",
    "wof:placetype":"locality"
},
  "geometry": {"coordinates":[-73.80285000000001,18.32826],"type":"Point"}
}