{
  "type": "Feature",
  "properties": {
    "gn:admin1_code":"9.0",
    "gn:admin2_code":"3717545.0",
    "gn:asciiname":"Zigne",
    "gn:country_code":"HT",
    "gn:dem":584,
    "gn:feature_class":"P",
    "gn:feature_code":"PPL",
    "gn:name":"Zigne",
    "gn:population":0,
    "gn:timezone":"America/Port-au-Prince",
    "iso:country":"HT",
    "wof:name":"Zigne",
    "wof:placetype":"locality"
},
  "geometry": {"coordinates":[-72.03333000000001,19.38333],"type":"Point"}
}