{
  "type": "Feature",
  "properties": {
    "gn:admin1_code":"7.0",
    "gn:admin2_code":"3723840.0",
    "gn:asciiname":"Bois Rouge",
    "gn:country_code":"HT",
    "gn:dem":1169,
    "gn:feature_class":"P",
    "gn:feature_code":"PPL",
    "gn:name":"Bois Rouge",
    "gn:population":0,
    "gn:timezone":"America/Port-au-Prince",
    "iso:country":"HT",
    "name:fra_x_preferred":[
        "Bois Rouge"
    ],
    "wof:name":"Bois Rouge",
    "wof:placetype":"locality"
},
  "geometry": {"coordinates":[-72.14686999999998,19.03036],"type":"Point"}
}