{
  "type": "Feature",
  "properties": {
    "gn:admin1_code":"6.0",
    "gn:admin2_code":"3726539.0",
    "gn:asciiname":"Bruneau",
    "gn:country_code":"HT",
    "gn:dem":24,
    "gn:feature_class":"P",
    "gn:feature_code":"PPL",
    "gn:name":"Bruneau",
    "gn:population":0,
    "gn:timezone":"America/Port-au-Prince",
    "iso:country":"HT",
    "name:deu_x_preferred":[
        "Bruneau"
    ],
    "name:fra_x_preferred":[
        "Bruneau"
    ],
    "name:nds_x_preferred":[
        "Bruneau"
    ],
    "name:nld_x_preferred":[
        "Bruneau"
    ],
    "name:rus_x_preferred":[
        "\u0411\u0440\u044e\u043d\u043e"
    ],
    "wof:name":"Bruneau",
    "wof:placetype":"locality"
},
  "geometry": {"coordinates":[-72.49916,19.16036],"type":"Point"}
}