{
  "type": "Feature",
  "properties": {
    "gn:admin1_code":"7.0",
    "gn:admin2_code":"3723840.0",
    "gn:asciiname":"Locarre",
    "gn:country_code":"HT",
    "gn:dem":267,
    "gn:feature_class":"P",
    "gn:feature_code":"PPL",
    "gn:name":"Locarr\u00e9",
    "gn:population":0,
    "gn:timezone":"America/Port-au-Prince",
    "iso:country":"HT",
    "name:und_x_variant":[
        "Locaret",
        "Locarr\u00e9"
    ],
    "wof:name":"Locarre",
    "wof:placetype":"locality"
},
  "geometry": {"coordinates":[-71.89855,18.99468],"type":"Point"}
}