{
  "type": "Feature",
  "properties": {
    "gn:admin1_code":"11.0",
    "gn:admin2_code":"3718425.0",
    "gn:asciiname":"Plaisance",
    "gn:country_code":"HT",
    "gn:dem":300,
    "gn:feature_class":"P",
    "gn:feature_code":"PPL",
    "gn:name":"Plaisance",
    "gn:population":0,
    "gn:timezone":"America/Port-au-Prince",
    "iso:country":"HT",
    "name:cat_x_preferred":[
        "Plaisance"
    ],
    "name:ceb_x_preferred":[
        "Plaisance"
    ],
    "name:deu_x_preferred":[
        "Plaisance"
    ],
    "name:fra_x_preferred":[
        "Plaisance"
    ],
    "name:ita_x_preferred":[
        "Plaisance"
    ],
    "name:nds_x_preferred":[
        "Plaisance"
    ],
    "name:nld_x_preferred":[
        "Plaisance"
    ],
    "name:pms_x_preferred":[
        "Plaisance"
    ],
    "name:pol_x_preferred":[
        "Plaisance"
    ],
    "name:por_x_preferred":[
        "Plaisance"
    ],
    "name:rus_x_preferred":[
        "\u041f\u043b\u0435\u0437\u0430\u043d\u0441"
    ],
    "name:slk_x_preferred":[
        "Plaisance"
    ],
    "name:spa_x_preferred":[
        "Plaisance"
    ],
    "name:swe_x_preferred":[
        "Plaisance"
    ],
    "name:ukr_x_preferred":[
        "\u041f\u043b\u0435\u0437\u0430\u043d\u0441"
    ],
    "name:und_x_variant":[
        "Plaissance",
        "Plaisance"
    ],
    "wof:name":"Plaisance",
    "wof:placetype":"locality"
},
  "geometry": {"coordinates":[-72.53561999999999,18.49391],"type":"Point"}
}