{
  "type": "Feature",
  "properties": {
    "gn:admin1_code":"7.0",
    "gn:admin2_code":"3723840.0",
    "gn:asciiname":"Pabdocal",
    "gn:country_code":"HT",
    "gn:dem":257,
    "gn:feature_class":"P",
    "gn:feature_code":"PPL",
    "gn:name":"Pabdocal",
    "gn:population":0,
    "gn:timezone":"America/Port-au-Prince",
    "iso:country":"HT",
    "name:fra_x_preferred":[
        "Pabdocal"
    ],
    "wof:name":"Pabdocal",
    "wof:placetype":"locality"
},
  "geometry": {"coordinates":[-71.93216,19.09755],"type":"Point"}
}