{
  "type": "Feature",
  "properties": {
    "gn:admin1_code":"7.0",
    "gn:admin2_code":"3720809.0",
    "gn:asciiname":"Matelas",
    "gn:country_code":"HT",
    "gn:dem":215,
    "gn:feature_class":"P",
    "gn:feature_code":"PPL",
    "gn:name":"Matelas",
    "gn:population":0,
    "gn:timezone":"America/Port-au-Prince",
    "iso:country":"HT",
    "wof:name":"Matelas",
    "wof:placetype":"locality"
},
  "geometry": {"coordinates":[-72.09999999999999,18.76667],"type":"Point"}
}