{
  "type": "Feature",
  "properties": {
    "gn:admin1_code":"12.0",
    "gn:admin2_code":"3728096.0",
    "gn:asciiname":"Rambeau",
    "gn:country_code":"HT",
    "gn:dem":126,
    "gn:feature_class":"P",
    "gn:feature_code":"PPL",
    "gn:name":"Rambeau",
    "gn:population":0,
    "gn:timezone":"America/Port-au-Prince",
    "iso:country":"HT",
    "name:fra_x_preferred":[
        "Rambeau"
    ],
    "wof:name":"Rambeau",
    "wof:placetype":"locality"
},
  "geometry": {"coordinates":[-73.78485999999999,18.37383],"type":"Point"}
}