{
  "type": "Feature",
  "properties": {
    "gn:admin1_code":"7.0",
    "gn:admin2_code":"3720809.0",
    "gn:asciiname":"Denizard",
    "gn:country_code":"HT",
    "gn:dem":545,
    "gn:feature_class":"P",
    "gn:feature_code":"PPL",
    "gn:name":"Denizard",
    "gn:population":0,
    "gn:timezone":"America/Port-au-Prince",
    "iso:country":"HT",
    "name:fra_x_preferred":[
        "Denizard"
    ],
    "wof:name":"Denizard",
    "wof:placetype":"locality"
},
  "geometry": {"coordinates":[-72.11279999999999,18.95917],"type":"Point"}
}