{
  "type": "Feature",
  "properties": {
    "gn:admin1_code":"10.0",
    "gn:admin2_code":"3725169.0",
    "gn:asciiname":"Romeo",
    "gn:country_code":"HT",
    "gn:dem":17,
    "gn:feature_class":"P",
    "gn:feature_code":"PPL",
    "gn:name":"Rom\u00e9o",
    "gn:population":0,
    "gn:timezone":"America/Port-au-Prince",
    "iso:country":"HT",
    "name:ara_x_preferred":[
        "\u0631\u0648\u0645\u064a\u0648"
    ],
    "name:ben_x_preferred":[
        "\u09b0\u09cb\u09ae\u09bf\u0993"
    ],
    "name:ckb_x_preferred":[
        "\u0695\u06c6\u0645\u06cc\u06c6"
    ],
    "name:ell_x_preferred":[
        "\u03a1\u03c9\u03bc\u03b1\u03af\u03bf\u03c2 \u039c\u03bf\u03bd\u03c4\u03ad\u03b3\u03bf\u03c2"
    ],
    "name:fas_x_preferred":[
        "\u0631\u0648\u0645\u0626\u0648 \u0645\u0648\u0646\u062a\u06af\u06cc\u0648"
    ],
    "name:fin_x_preferred":[
        "Romeo"
    ],
    "name:fra_x_preferred":[
        "Rom\u00e9o"
    ],
    "name:fra_x_variant":[
        "Rom\u00e9o Montaigu"
    ],
    "name:hin_x_preferred":[
        "\u0930\u094b\u092e\u093f\u092f\u094b"
    ],
    "name:ind_x_preferred":[
        "Romeo Montague"
    ],
    "name:ita_x_preferred":[
        "Romeo Montecchi"
    ],
    "name:lat_x_preferred":[
        "Romeus"
    ],
    "name:mar_x_preferred":[
        "\u0930\u094b\u092e\u093f\u092f\u094b"
    ],
    "name:mkd_x_preferred":[
        "\u0420\u043e\u043c\u0435\u043e \u041c\u043e\u043d\u0442\u0435\u0453\u0443"
    ],
    "name:nld_x_preferred":[
        "Romeo Montague"
    ],
    "name:pan_x_preferred":[
        "\u0a30\u0a4b\u0a2e\u0a40\u0a13"
    ],
    "name:pol_x_preferred":[
        "Romeo Monteki"
    ],
    "name:ron_x_preferred":[
        "Romeo Montague"
    ],
    "name:rus_x_preferred":[
        "\u0420\u043e\u043c\u0435\u043e \u041c\u043e\u043d\u0442\u0435\u043a\u043a\u0438"
    ],
    "name:spa_x_preferred":[
        "Romeo"
    ],
    "name:ukr_x_preferred":[
        "\u0420\u043e\u043c\u0435\u043e \u041c\u043e\u043d\u0442\u0435\u043a\u043a\u0456"
    ],
    "name:zho_x_preferred":[
        "\u7f85\u5bc6\u6b50\u00b7\u8499\u6cf0\u53e4"
    ],
    "wof:name":"Romeo",
    "wof:placetype":"locality"
},
  "geometry": {"coordinates":[-71.86805,19.6411],"type":"Point"}
}