{
  "type": "Feature",
  "properties": {
    "gn:admin1_code":"11.0",
    "gn:admin2_code":"3727134.0",
    "gn:asciiname":"Corail",
    "gn:country_code":"HT",
    "gn:dem":928,
    "gn:feature_class":"P",
    "gn:feature_code":"PPL",
    "gn:name":"Corail",
    "gn:population":0,
    "gn:timezone":"America/Port-au-Prince",
    "iso:country":"HT",
    "name:ceb_x_preferred":[
        "Corail"
    ],
    "name:deu_x_preferred":[
        "Corail"
    ],
    "name:fra_x_preferred":[
        "Corail"
    ],
    "name:nld_x_preferred":[
        "Corail"
    ],
    "name:spa_x_preferred":[
        "Corail"
    ],
    "name:swe_x_preferred":[
        "Corail"
    ],
    "wof:name":"Corail",
    "wof:placetype":"locality"
},
  "geometry": {"coordinates":[-72.0202,18.68325],"type":"Point"}
}