{
  "type": "Feature",
  "properties": {
    "iso:country":"HT",
    "name:ara_x_preferred":[
        "\u0622\u0643\u0644 \u062f\u0648 \u0646\u0648\u0631\u062f"
    ],
    "name:eng_x_preferred":[
        "Acul-du-Nord"
    ],
    "name:fas_x_preferred":[
        "\u0627\u06a9\u0648\u0644-\u062f\u0648-\u0646\u0648\u0631\u062f"
    ],
    "name:fra_x_preferred":[
        "Acul-du-Nord"
    ],
    "name:hat_x_preferred":[
        "Akil din\u00f2"
    ],
    "name:hat_x_variant":[
        "Akil di N\u00f2"
    ],
    "name:ita_x_preferred":[
        "Acul-du-Nord"
    ],
    "name:jpn_x_preferred":[
        "\u30a2\u30ad\u30eb\u30fb\u30c7\u30a3\u30ce\u30fc"
    ],
    "name:nld_x_preferred":[
        "Acul-du-Nord"
    ],
    "name:por_x_preferred":[
        "Acul-du-Nord"
    ],
    "name:ron_x_preferred":[
        "Acul-du-Nord"
    ],
    "name:spa_x_preferred":[
        "Acul-du-Nord"
    ],
    "name:ukr_x_preferred":[
        "\u0410\u043a\u0443\u043b-\u0434\u0443-\u041d\u043e\u0440\u0434"
    ],
    "qs:gn_country":"HT",
    "qs:gn_fcode":"PPL",
    "qs:gn_pop":3454,
    "qs:name":"Acul du Nord",
    "qs:name_adm0":"Ha\u00efti",
    "qs:name_adm1":"Nord",
    "qs:photos":15,
    "qs:photos_1k":3,
    "qs:photos_9k":1,
    "qs:photos_9r":1,
    "qs:photos_all":15,
    "qs:photos_sr":1,
    "qs:placetype":"Town",
    "qs:pop_sr":"4",
    "qs:woe_adm0":23424839,
    "wd:wordcount":76,
    "wof:name":"Acul du Nord",
    "wof:placetype":"locality",
    "wof:population":3454
},
  "geometry": {"coordinates":[-72.31667,19.68333],"type":"Point"}
}