{
  "type": "Feature",
  "properties": {
    "gn:admin1_code":"11.0",
    "gn:admin2_code":"3718425.0",
    "gn:asciiname":"Cazeau",
    "gn:country_code":"HT",
    "gn:dem":1679,
    "gn:feature_class":"P",
    "gn:feature_code":"PPL",
    "gn:name":"Cazeau",
    "gn:population":0,
    "gn:timezone":"America/Port-au-Prince",
    "iso:country":"HT",
    "wof:name":"Cazeau",
    "wof:placetype":"locality"
},
  "geometry": {"coordinates":[-72.33333,18.45],"type":"Point"}
}