{
  "type": "Feature",
  "properties": {
    "gn:admin1_code":"9.0",
    "gn:asciiname":"Bois Blanc",
    "gn:country_code":"HT",
    "gn:dem":349,
    "gn:feature_class":"P",
    "gn:feature_code":"PPL",
    "gn:name":"Bois Blanc",
    "gn:population":0,
    "gn:timezone":"America/Port-au-Prince",
    "iso:country":"HT",
    "wof:name":"Bois Blanc",
    "wof:placetype":"locality"
},
  "geometry": {"coordinates":[-72.08333,19.53333],"type":"Point"}
}