{
  "type": "Feature",
  "properties": {
    "gn:admin1_code":"13.0",
    "gn:admin2_code":"3723778.0",
    "gn:asciiname":"Dibiton",
    "gn:country_code":"HT",
    "gn:dem":240,
    "gn:feature_class":"P",
    "gn:feature_code":"PPL",
    "gn:name":"Dibiton",
    "gn:population":0,
    "gn:timezone":"America/Port-au-Prince",
    "iso:country":"HT",
    "wof:name":"Dibiton",
    "wof:placetype":"locality"
},
  "geometry": {"coordinates":[-72.53333000000001,18.35],"type":"Point"}
}