{
  "type": "Feature",
  "properties": {
    "gn:admin1_code":"14.0",
    "gn:asciiname":"Beucard",
    "gn:country_code":"HT",
    "gn:dem":246,
    "gn:feature_class":"P",
    "gn:feature_code":"PPL",
    "gn:name":"Beucard",
    "gn:population":0,
    "gn:timezone":"America/Port-au-Prince",
    "iso:country":"HT",
    "wof:name":"Beucard",
    "wof:placetype":"locality"
},
  "geometry": {"coordinates":[-73.16667,18.35],"type":"Point"}
}