{
  "type": "Feature",
  "properties": {
    "gn:admin1_code":"9.0",
    "gn:admin2_code":"3729454.0",
    "gn:asciiname":"Georges",
    "gn:country_code":"HT",
    "gn:dem":750,
    "gn:feature_class":"P",
    "gn:feature_code":"PPL",
    "gn:name":"Georges",
    "gn:population":0,
    "gn:timezone":"America/Port-au-Prince",
    "iso:country":"HT",
    "name:cat_x_preferred":[
        "Georges"
    ],
    "name:ceb_x_preferred":[
        "Georges"
    ],
    "name:fra_x_preferred":[
        "Georges"
    ],
    "name:hye_x_preferred":[
        "\u053a\u0578\u0580\u056a"
    ],
    "name:rus_x_preferred":[
        "\u0414\u0436\u043e\u0440\u0434\u0436\u0435\u0441"
    ],
    "name:spa_x_preferred":[
        "Georges"
    ],
    "name:swe_x_preferred":[
        "Georges"
    ],
    "wof:name":"Georges",
    "wof:placetype":"locality"
},
  "geometry": {"coordinates":[-72.51666999999998,19.76667],"type":"Point"}
}