{
  "type": "Feature",
  "properties": {
    "gn:admin1_code":"6.0",
    "gn:asciiname":"Laloue",
    "gn:country_code":"HT",
    "gn:dem":165,
    "gn:feature_class":"P",
    "gn:feature_code":"PPL",
    "gn:name":"Lalou\u00e9",
    "gn:population":0,
    "gn:timezone":"America/Port-au-Prince",
    "iso:country":"HT",
    "name:fra_x_preferred":[
        "Lalou\u00e9"
    ],
    "wof:name":"Laloue",
    "wof:placetype":"locality"
},
  "geometry": {"coordinates":[-72.62329,19.08722],"type":"Point"}
}