{
  "type": "Feature",
  "properties": {
    "gn:admin1_code":"7.0",
    "gn:admin2_code":"3723840.0",
    "gn:asciiname":"Callebassier",
    "gn:country_code":"HT",
    "gn:dem":302,
    "gn:feature_class":"P",
    "gn:feature_code":"PPL",
    "gn:name":"Callebassier",
    "gn:population":0,
    "gn:timezone":"America/Port-au-Prince",
    "iso:country":"HT",
    "name:fra_x_preferred":[
        "Callebassier"
    ],
    "wof:name":"Callebassier",
    "wof:placetype":"locality"
},
  "geometry": {"coordinates":[-72.24214000000001,19.23069],"type":"Point"}
}