{
  "type": "Feature",
  "properties": {
    "gn:admin1_code":"11.0",
    "gn:admin2_code":"3722285.0",
    "gn:asciiname":"La Pointe",
    "gn:country_code":"HT",
    "gn:dem":64,
    "gn:feature_class":"P",
    "gn:feature_code":"PPL",
    "gn:name":"La Pointe",
    "gn:population":0,
    "gn:timezone":"America/Port-au-Prince",
    "iso:country":"HT",
    "name:fra_x_preferred":[
        "La Pointe"
    ],
    "wof:name":"La Pointe",
    "wof:placetype":"locality"
},
  "geometry": {"coordinates":[-72.58118,18.48916],"type":"Point"}
}