{
  "type": "Feature",
  "properties": {
    "gn:admin1_code":"13.0",
    "gn:admin2_code":"3723778.0",
    "gn:asciiname":"Clemence",
    "gn:country_code":"HT",
    "gn:dem":670,
    "gn:feature_class":"P",
    "gn:feature_code":"PPL",
    "gn:name":"Cl\u00e9mence",
    "gn:population":0,
    "gn:timezone":"America/Port-au-Prince",
    "iso:country":"HT",
    "wof:name":"Clemence",
    "wof:placetype":"locality"
},
  "geometry": {"coordinates":[-72.45,18.26667],"type":"Point"}
}