{
  "type": "Feature",
  "properties": {
    "gn:admin1_code":"12.0",
    "gn:asciiname":"Ti Sale",
    "gn:cc2":"HT",
    "gn:country_code":"HT",
    "gn:dem":-9999,
    "gn:feature_class":"P",
    "gn:feature_code":"PPL",
    "gn:name":"Ti Sal\u00e9",
    "gn:population":0,
    "gn:timezone":"America/Port-au-Prince",
    "iso:country":"HT",
    "name:und_x_variant":[
        "Puit Sal\u00e9",
        "Ti Sal\u00e9"
    ],
    "wof:name":"Ti Sale",
    "wof:placetype":"locality"
},
  "geometry": {"coordinates":[-73.06667,18.18333],"type":"Point"}
}