{
  "type": "Feature",
  "properties": {
    "gn:admin1_code":"9.0",
    "gn:admin2_code":"3724438.0",
    "gn:asciiname":"Charon",
    "gn:country_code":"HT",
    "gn:dem":205,
    "gn:feature_class":"P",
    "gn:feature_code":"PPL",
    "gn:name":"Charon",
    "gn:population":0,
    "gn:timezone":"America/Port-au-Prince",
    "iso:country":"HT",
    "name:afr_x_preferred":[
        "Charon"
    ],
    "name:ara_x_preferred":[
        "\u062e\u0627\u0631\u0648\u0646"
    ],
    "name:bos_x_preferred":[
        "Haron"
    ],
    "name:bre_x_preferred":[
        "C'haron"
    ],
    "name:bul_x_preferred":[
        "\u0425\u0430\u0440\u043e\u043d"
    ],
    "name:cat_x_preferred":[
        "Caront"
    ],
    "name:ces_x_preferred":[
        "Char\u00f3n"
    ],
    "name:cos_x_preferred":[
        "Caronti"
    ],
    "name:cym_x_preferred":[
        "Charon"
    ],
    "name:dan_x_preferred":[
        "Charon"
    ],
    "name:deu_x_preferred":[
        "Charon"
    ],
    "name:ell_x_preferred":[
        "\u03a7\u03ac\u03c1\u03c9\u03bd"
    ],
    "name:epo_x_preferred":[
        "Karono"
    ],
    "name:est_x_preferred":[
        "Charon"
    ],
    "name:eus_x_preferred":[
        "Karon"
    ],
    "name:fas_x_preferred":[
        "\u062e\u0627\u0631\u0648\u0646"
    ],
    "name:fin_x_preferred":[
        "Kharon"
    ],
    "name:fra_x_preferred":[
        "Charon"
    ],
    "name:gle_x_preferred":[
        "Car\u00f3n"
    ],
    "name:glg_x_preferred":[
        "Caronte"
    ],
    "name:heb_x_preferred":[
        "\u05db\u05d0\u05e8\u05d5\u05df"
    ],
    "name:hrv_x_preferred":[
        "Haron"
    ],
    "name:hun_x_preferred":[
        "Khar\u00f3n"
    ],
    "name:hye_x_preferred":[
        "\u0554\u0561\u0580\u0578\u0576"
    ],
    "name:ind_x_preferred":[
        "Kharon"
    ],
    "name:ita_x_preferred":[
        "Caronte"
    ],
    "name:jpn_x_preferred":[
        "\u30ab\u30ed\u30fc\u30f3"
    ],
    "name:kat_x_preferred":[
        "\u10e5\u10d0\u10e0\u10dd\u10dc\u10d8"
    ],
    "name:kor_x_preferred":[
        "\uce74\ub860"
    ],
    "name:lat_x_preferred":[
        "Charon"
    ],
    "name:lij_x_preferred":[
        "Caronte"
    ],
    "name:lit_x_preferred":[
        "Charonas"
    ],
    "name:ltz_x_preferred":[
        "Charon"
    ],
    "name:nds_x_preferred":[
        "Charon"
    ],
    "name:nld_x_preferred":[
        "Charon"
    ],
    "name:nno_x_preferred":[
        "Karon"
    ],
    "name:nor_x_preferred":[
        "Kharon"
    ],
    "name:oci_x_preferred":[
        "Caront"
    ],
    "name:pol_x_preferred":[
        "Charon"
    ],
    "name:por_x_preferred":[
        "Caronte"
    ],
    "name:ron_x_preferred":[
        "Charon"
    ],
    "name:rus_x_preferred":[
        "\u0425\u0430\u0440\u043e\u043d"
    ],
    "name:scn_x_preferred":[
        "Caronti"
    ],
    "name:slk_x_preferred":[
        "Char\u00f3n"
    ],
    "name:slv_x_preferred":[
        "Haron"
    ],
    "name:spa_x_preferred":[
        "Caronte"
    ],
    "name:srp_x_preferred":[
        "\u0425\u0430\u0440\u043e\u043d"
    ],
    "name:swe_x_preferred":[
        "Charon"
    ],
    "name:tha_x_preferred":[
        "\u0e41\u0e04\u0e23\u0e2d\u0e19"
    ],
    "name:tur_x_preferred":[
        "Kharoon"
    ],
    "name:ukr_x_preferred":[
        "\u0425\u0430\u0440\u043e\u043d"
    ],
    "name:vie_x_preferred":[
        "Charon"
    ],
    "wof:name":"Charon",
    "wof:placetype":"locality"
},
  "geometry": {"coordinates":[-72.06667,19.46667],"type":"Point"}
}