{
  "type": "Feature",
  "properties": {
    "gn:admin1_code":"9.0",
    "gn:admin2_code":"3724438.0",
    "gn:asciiname":"Charon",
    "gn:country_code":"HT",
    "gn:dem":205,
    "gn:feature_class":"P",
    "gn:feature_code":"PPL",
    "gn:name":"Charon",
    "gn:population":0,
    "gn:timezone":"America/Port-au-Prince",
    "iso:country":"HT",
    "wof:name":"Charon",
    "wof:placetype":"locality"
},
  "geometry": {"coordinates":[-72.06667,19.46667],"type":"Point"}
}