{
  "type": "Feature",
  "properties": {
    "gn:admin1_code":"14.0",
    "gn:admin2_code":"3731116.0",
    "gn:asciiname":"Derriere Goyave",
    "gn:country_code":"HT",
    "gn:dem":19,
    "gn:feature_class":"P",
    "gn:feature_code":"PPL",
    "gn:name":"Derri\u00e8re Goyave",
    "gn:population":0,
    "gn:timezone":"America/Port-au-Prince",
    "iso:country":"HT",
    "wof:name":"Derriere Goyave",
    "wof:placetype":"locality"
},
  "geometry": {"coordinates":[-74.41707,18.56538],"type":"Point"}
}