{
  "type": "Feature",
  "properties": {
    "gn:admin1_code":"12.0",
    "gn:admin2_code":"3718404.0",
    "gn:asciiname":"Louroux",
    "gn:country_code":"HT",
    "gn:dem":280,
    "gn:feature_class":"P",
    "gn:feature_code":"PPL",
    "gn:name":"Louroux",
    "gn:population":0,
    "gn:timezone":"America/Port-au-Prince",
    "iso:country":"HT",
    "name:fra_x_preferred":[
        "Louroux"
    ],
    "wof:name":"Louroux",
    "wof:placetype":"locality"
},
  "geometry": {"coordinates":[-73.92211999999998,18.15759],"type":"Point"}
}