{
  "type": "Feature",
  "properties": {
    "iso:country":"HT",
    "name:ara_x_preferred":[
        "\u0643\u0648\u0627\u0631\u062a\u0631 \u0645\u0648\u0631\u064a\u0646"
    ],
    "name:ceb_x_preferred":[
        "Quartier-Morin"
    ],
    "name:ell_x_preferred":[
        "\u039a\u03b1\u03c1\u03c4\u03b9\u03ad-\u039c\u03bf\u03c1\u03ad\u03bd"
    ],
    "name:eng_x_preferred":[
        "Quartier-Morin"
    ],
    "name:fra_x_preferred":[
        "Quartier-Morin"
    ],
    "name:hat_x_preferred":[
        "Katye Moren"
    ],
    "name:ita_x_preferred":[
        "Quartier-Morin"
    ],
    "name:jpn_x_preferred":[
        "\u30ab\u30eb\u30c6\u30a3\u30a8\uff1d\u30e2\u30e9\u30f3"
    ],
    "name:nan_x_preferred":[
        "Quartier-Morin"
    ],
    "name:nld_x_preferred":[
        "Quartier-Morin"
    ],
    "name:por_x_preferred":[
        "Quartier-Morin"
    ],
    "name:ron_x_preferred":[
        "Quartier-Morin"
    ],
    "name:rus_x_preferred":[
        "\u041a\u0432\u0430\u0440\u0442\u044c\u0435-\u041c\u043e\u0440\u0435\u043d"
    ],
    "name:spa_x_preferred":[
        "Quartier-Morin"
    ],
    "name:swe_x_preferred":[
        "Quartier-Morin"
    ],
    "name:ukr_x_preferred":[
        "\u041a\u0432\u0430\u0440\u0442\u044c\u0454\u0440-\u041c\u043e\u0440\u0456\u043d"
    ],
    "name:und_x_variant":[
        "Qartier-Morin"
    ],
    "name:zho_x_preferred":[
        "\u5938\u63d0\u4e9e\u83ab\u6797"
    ],
    "qs:gn_country":"HT",
    "qs:gn_fcode":"PPL",
    "qs:gn_pop":1299,
    "qs:name":"Quartier Morin",
    "qs:name_adm0":"Ha\u00efti",
    "qs:name_adm1":"Nord",
    "qs:photos":0,
    "qs:photos_1k":0,
    "qs:photos_9k":1,
    "qs:photos_9r":1,
    "qs:photos_all":6,
    "qs:photos_sr":0,
    "qs:placetype":"Town",
    "qs:pop_sr":"3",
    "qs:woe_adm0":23424839,
    "wd:wordcount":31,
    "wof:name":"Quartier Morin",
    "wof:placetype":"locality",
    "wof:population":1299
},
  "geometry": {"coordinates":[-72.15694000000001,19.69667],"type":"Point"}
}