{
  "type": "Feature",
  "properties": {
    "gn:admin1_code":"6.0",
    "gn:admin2_code":"3724695.0",
    "gn:asciiname":"Fond Morel",
    "gn:country_code":"HT",
    "gn:dem":142,
    "gn:feature_class":"P",
    "gn:feature_code":"PPL",
    "gn:name":"Fond Morel",
    "gn:population":0,
    "gn:timezone":"America/Port-au-Prince",
    "iso:country":"HT",
    "name:fra_x_preferred":[
        "Fond Morel"
    ],
    "wof:name":"Fond Morel",
    "wof:placetype":"locality"
},
  "geometry": {"coordinates":[-72.56726,19.44665],"type":"Point"}
}