{
  "type": "Feature",
  "properties": {
    "gn:admin1_code":"14.0",
    "gn:asciiname":"Cadiac",
    "gn:country_code":"HT",
    "gn:dem":244,
    "gn:feature_class":"P",
    "gn:feature_code":"PPL",
    "gn:name":"Cadiac",
    "gn:population":0,
    "gn:timezone":"America/Port-au-Prince",
    "iso:country":"HT",
    "wof:name":"Cadiac",
    "wof:placetype":"locality"
},
  "geometry": {"coordinates":[-73.15000000000001,18.36667000000001],"type":"Point"}
}