{
  "type": "Feature",
  "properties": {
    "gn:admin1_code":"10.0",
    "gn:admin2_code":"3716223.0",
    "gn:asciiname":"Fraiche",
    "gn:country_code":"HT",
    "gn:dem":66,
    "gn:feature_class":"P",
    "gn:feature_code":"PPL",
    "gn:name":"Fra\u00eeche",
    "gn:population":0,
    "gn:timezone":"America/Port-au-Prince",
    "iso:country":"HT",
    "name:fra_x_preferred":[
        "Fra\u00eeche"
    ],
    "wof:name":"Fraiche",
    "wof:placetype":"locality"
},
  "geometry": {"coordinates":[-71.99330999999999,19.58017000000001],"type":"Point"}
}