{
  "type": "Feature",
  "properties": {
    "gn:admin1_code":"7.0",
    "gn:admin2_code":"3722578.0",
    "gn:asciiname":"Ca Laroche",
    "gn:cc2":"HT",
    "gn:country_code":"HT",
    "gn:dem":294,
    "gn:feature_class":"P",
    "gn:feature_code":"PPL",
    "gn:name":"Ca Laroche",
    "gn:population":0,
    "gn:timezone":"America/Port-au-Prince",
    "iso:country":"HT",
    "name:und_x_variant":[
        "Ka La Roche",
        "Ca Laroche"
    ],
    "wof:name":"Ca Laroche",
    "wof:placetype":"locality"
},
  "geometry": {"coordinates":[-71.81667,18.85],"type":"Point"}
}