{
  "type": "Feature",
  "properties": {
    "gn:admin1_code":"7.0",
    "gn:admin2_code":"3722578.0",
    "gn:asciiname":"Palmary",
    "gn:country_code":"HT",
    "gn:dem":188,
    "gn:feature_class":"P",
    "gn:feature_code":"PPL",
    "gn:name":"Palmary",
    "gn:population":0,
    "gn:timezone":"America/Port-au-Prince",
    "iso:country":"HT",
    "wof:name":"Palmary",
    "wof:placetype":"locality"
},
  "geometry": {"coordinates":[-71.84999999999999,18.88333],"type":"Point"}
}