{
  "type": "Feature",
  "properties": {
    "gn:admin1_code":"9.0",
    "gn:admin2_code":"3731232.0",
    "gn:asciiname":"Lombard",
    "gn:country_code":"HT",
    "gn:dem":25,
    "gn:feature_class":"P",
    "gn:feature_code":"PPL",
    "gn:name":"Lombard",
    "gn:population":0,
    "gn:timezone":"America/Port-au-Prince",
    "iso:country":"HT",
    "name:fra_x_preferred":[
        "Lombard"
    ],
    "wof:name":"Lombard",
    "wof:placetype":"locality"
},
  "geometry": {"coordinates":[-72.30568000000002,19.74225],"type":"Point"}
}