{
  "type": "Feature",
  "properties": {
    "gn:admin1_code":"12.0",
    "gn:admin2_code":"3731094.0",
    "gn:asciiname":"Vieux Bourg d'Aquin",
    "gn:country_code":"HT",
    "gn:dem":26,
    "gn:feature_class":"P",
    "gn:feature_code":"PPL",
    "gn:name":"Vieux Bourg d\u2019Aquin",
    "gn:population":0,
    "gn:timezone":"America/Port-au-Prince",
    "iso:country":"HT",
    "name:und_x_variant":[
        "Vieux Bourg",
        "Vieux Bourg d\u2019Aguin",
        "Vieux Bourg d\u2019Aquin"
    ],
    "wof:name":"Vieux Bourg d'Aquin",
    "wof:placetype":"locality"
},
  "geometry": {"coordinates":[-73.33945,18.30117000000001],"type":"Point"}
}