{
  "type": "Feature",
  "properties": {
    "gn:admin1_code":"12.0",
    "gn:admin2_code":"3728096.0",
    "gn:asciiname":"La Ferriere",
    "gn:country_code":"HT",
    "gn:dem":92,
    "gn:feature_class":"P",
    "gn:feature_code":"PPL",
    "gn:name":"La Ferri\u00e8re",
    "gn:population":0,
    "gn:timezone":"America/Port-au-Prince",
    "iso:country":"HT",
    "name:fra_x_preferred":[
        "La Ferri\u00e8re"
    ],
    "wof:name":"La Ferriere",
    "wof:placetype":"locality"
},
  "geometry": {"coordinates":[-73.92921,18.21586],"type":"Point"}
}