{
  "type": "Feature",
  "properties": {
    "gn:admin1_code":"6.0",
    "gn:admin2_code":"3717587.0",
    "gn:asciiname":"Riobe",
    "gn:country_code":"HT",
    "gn:dem":496,
    "gn:feature_class":"P",
    "gn:feature_code":"PPL",
    "gn:name":"Riob\u00e9",
    "gn:population":0,
    "gn:timezone":"America/Port-au-Prince",
    "iso:country":"HT",
    "name:fra_x_preferred":[
        "Riob\u00e9"
    ],
    "wof:name":"Riobe",
    "wof:placetype":"locality"
},
  "geometry": {"coordinates":[-72.37869000000001,18.91788],"type":"Point"}
}