{
  "type": "Feature",
  "properties": {
    "gn:admin1_code":"7.0",
    "gn:admin2_code":"3728053.0",
    "gn:asciiname":"Ravine la Salle",
    "gn:country_code":"HT",
    "gn:dem":635,
    "gn:feature_class":"P",
    "gn:feature_code":"PPL",
    "gn:name":"Ravine la Salle",
    "gn:population":0,
    "gn:timezone":"America/Port-au-Prince",
    "iso:country":"HT",
    "wof:name":"Ravine la Salle",
    "wof:placetype":"locality"
},
  "geometry": {"coordinates":[-71.66667,19.16667],"type":"Point"}
}