{
  "type": "Feature",
  "properties": {
    "gn:admin1_code":"12.0",
    "gn:asciiname":"Table au Diable",
    "gn:country_code":"HT",
    "gn:dem":45,
    "gn:feature_class":"P",
    "gn:feature_code":"PPL",
    "gn:name":"Table au Diable",
    "gn:population":0,
    "gn:timezone":"America/Port-au-Prince",
    "iso:country":"HT",
    "name:fra_x_preferred":[
        "Table au Diable"
    ],
    "wof:name":"Table au Diable",
    "wof:placetype":"locality"
},
  "geometry": {"coordinates":[-73.97311999999999,18.1649],"type":"Point"}
}