{
  "type": "Feature",
  "properties": {
    "gn:admin1_code":"7.0",
    "gn:admin2_code":"3722578.0",
    "gn:asciiname":"Platonal",
    "gn:country_code":"HT",
    "gn:dem":725,
    "gn:feature_class":"P",
    "gn:feature_code":"PPL",
    "gn:name":"Platonal",
    "gn:population":0,
    "gn:timezone":"America/Port-au-Prince",
    "iso:country":"HT",
    "name:und_x_variant":[
        "Platana",
        "Platonal"
    ],
    "wof:name":"Platonal",
    "wof:placetype":"locality"
},
  "geometry": {"coordinates":[-71.85486,18.80594],"type":"Point"}
}