{
  "type": "Feature",
  "properties": {
    "gn:admin1_code":"12.0",
    "gn:asciiname":"Grand Bois",
    "gn:country_code":"HT",
    "gn:dem":48,
    "gn:feature_class":"P",
    "gn:feature_code":"PPL",
    "gn:name":"Grand Bois",
    "gn:population":0,
    "gn:timezone":"America/Port-au-Prince",
    "iso:country":"HT",
    "name:fra_x_preferred":[
        "Grand Bois"
    ],
    "wof:name":"Grand Bois",
    "wof:placetype":"locality"
},
  "geometry": {"coordinates":[-73.64629000000002,18.22675],"type":"Point"}
}