{
  "type": "Feature",
  "properties": {
    "gn:admin1_code":"7.0",
    "gn:admin2_code":"3728053.0",
    "gn:asciiname":"Garde Augustin",
    "gn:country_code":"HT",
    "gn:dem":372,
    "gn:feature_class":"P",
    "gn:feature_code":"PPL",
    "gn:name":"Garde Augustin",
    "gn:population":0,
    "gn:timezone":"America/Port-au-Prince",
    "iso:country":"HT",
    "name:fra_x_preferred":[
        "Garde Augustin"
    ],
    "wof:name":"Garde Augustin",
    "wof:placetype":"locality"
},
  "geometry": {"coordinates":[-71.76796,19.13319],"type":"Point"}
}