{
  "type": "Feature",
  "properties": {
    "gn:admin1_code":"11.0",
    "gn:admin2_code":"3723019.0",
    "gn:asciiname":"Ti Fort Negre",
    "gn:country_code":"HT",
    "gn:dem":313,
    "gn:feature_class":"P",
    "gn:feature_code":"PPL",
    "gn:name":"Ti Fort N\u00e8gre",
    "gn:population":0,
    "gn:timezone":"America/Port-au-Prince",
    "iso:country":"HT",
    "name:fra_x_preferred":[
        "Ti Fort N\u00e8gre"
    ],
    "wof:name":"Ti Fort Negre",
    "wof:placetype":"locality"
},
  "geometry": {"coordinates":[-73.0355,18.83922],"type":"Point"}
}