{
  "type": "Feature",
  "properties": {
    "gn:admin1_code":"13.0",
    "gn:admin2_code":"3730361.0",
    "gn:asciiname":"Terlonge",
    "gn:country_code":"HT",
    "gn:dem":806,
    "gn:feature_class":"P",
    "gn:feature_code":"PPL",
    "gn:name":"Terlonge",
    "gn:population":0,
    "gn:timezone":"America/Port-au-Prince",
    "iso:country":"HT",
    "wof:name":"Terlonge",
    "wof:placetype":"locality"
},
  "geometry": {"coordinates":[-71.81667,18.21667],"type":"Point"}
}