{
  "type": "Feature",
  "properties": {
    "gn:admin1_code":"10.0",
    "gn:admin2_code":"3725169.0",
    "gn:asciiname":"Verbouc",
    "gn:country_code":"HT",
    "gn:dem":17,
    "gn:feature_class":"P",
    "gn:feature_code":"PPL",
    "gn:name":"Verbouc",
    "gn:population":0,
    "gn:timezone":"America/Port-au-Prince",
    "iso:country":"HT",
    "name:und_x_variant":[
        "Carrefour Vieux Bourg",
        "Vieux Bourg",
        "Verbouc"
    ],
    "wof:name":"Verbouc",
    "wof:placetype":"locality"
},
  "geometry": {"coordinates":[-71.82896,19.62135],"type":"Point"}
}