{
  "type": "Feature",
  "properties": {
    "gn:admin1_code":"6.0",
    "gn:admin2_code":"3724144.0",
    "gn:asciiname":"Barateau",
    "gn:country_code":"HT",
    "gn:dem":348,
    "gn:feature_class":"P",
    "gn:feature_code":"PPL",
    "gn:name":"Barateau",
    "gn:population":0,
    "gn:timezone":"America/Port-au-Prince",
    "iso:country":"HT",
    "name:fra_x_preferred":[
        "Barateau"
    ],
    "wof:name":"Barateau",
    "wof:placetype":"locality"
},
  "geometry": {"coordinates":[-72.76884,19.68439],"type":"Point"}
}