{
  "type": "Feature",
  "properties": {
    "gn:admin1_code":"13.0",
    "gn:admin2_code":"3730361.0",
    "gn:asciiname":"Ca Roseau",
    "gn:country_code":"HT",
    "gn:dem":985,
    "gn:feature_class":"P",
    "gn:feature_code":"PPL",
    "gn:name":"Ca Roseau",
    "gn:population":0,
    "gn:timezone":"America/Port-au-Prince",
    "iso:country":"HT",
    "wof:name":"Ca Roseau",
    "wof:placetype":"locality"
},
  "geometry": {"coordinates":[-71.88333,18.28333],"type":"Point"}
}