{
  "type": "Feature",
  "properties": {
    "gn:admin1_code":"14.0",
    "gn:asciiname":"Cacolo",
    "gn:country_code":"HT",
    "gn:dem":239,
    "gn:feature_class":"P",
    "gn:feature_code":"PPL",
    "gn:name":"Cacolo",
    "gn:population":0,
    "gn:timezone":"America/Port-au-Prince",
    "iso:country":"HT",
    "wof:name":"Cacolo",
    "wof:placetype":"locality"
},
  "geometry": {"coordinates":[-73.16667,18.36667000000001],"type":"Point"}
}