{
  "type": "Feature",
  "properties": {
    "gn:admin1_code":"14.0",
    "gn:admin2_code":"3731116.0",
    "gn:asciiname":"Carcasse",
    "gn:country_code":"HT",
    "gn:dem":19,
    "gn:feature_class":"P",
    "gn:feature_code":"PPL",
    "gn:name":"Carcasse",
    "gn:population":0,
    "gn:timezone":"America/Port-au-Prince",
    "iso:country":"HT",
    "wof:name":"Carcasse",
    "wof:placetype":"locality"
},
  "geometry": {"coordinates":[-74.44525,18.37033],"type":"Point"}
}