{
  "type": "Feature",
  "properties": {
    "gn:admin1_code":"11.0",
    "gn:admin2_code":"3722285.0",
    "gn:asciiname":"Martel",
    "gn:country_code":"HT",
    "gn:dem":496,
    "gn:feature_class":"P",
    "gn:feature_code":"PPL",
    "gn:name":"Martel",
    "gn:population":0,
    "gn:timezone":"America/Port-au-Prince",
    "iso:country":"HT",
    "name:deu_x_preferred":[
        "Martel"
    ],
    "name:fra_x_preferred":[
        "Martel"
    ],
    "name:heb_x_preferred":[
        "\u05de\u05e8\u05d8\u05dc"
    ],
    "name:ita_x_preferred":[
        "Martel"
    ],
    "name:jpn_x_preferred":[
        "\u30de\u30eb\u30c6\u30eb"
    ],
    "name:lmo_x_preferred":[
        "Mart\u00e8l"
    ],
    "name:nld_x_preferred":[
        "Martel"
    ],
    "name:rus_x_preferred":[
        "\u041c\u0430\u0440\u0442\u0435\u043b\u044c"
    ],
    "name:slk_x_preferred":[
        "Martel"
    ],
    "name:srp_x_preferred":[
        "\u041c\u0430\u0440\u0442\u0435\u043b"
    ],
    "name:swe_x_preferred":[
        "Martel"
    ],
    "name:ukr_x_preferred":[
        "\u041c\u0430\u0440\u0442\u0435\u043b"
    ],
    "wof:name":"Martel",
    "wof:placetype":"locality"
},
  "geometry": {"coordinates":[-72.69119000000001,18.36432000000001],"type":"Point"}
}