{
  "type": "Feature",
  "properties": {
    "gn:admin1_code":"11.0",
    "gn:admin2_code":"3722285.0",
    "gn:asciiname":"Martel",
    "gn:country_code":"HT",
    "gn:dem":496,
    "gn:feature_class":"P",
    "gn:feature_code":"PPL",
    "gn:name":"Martel",
    "gn:population":0,
    "gn:timezone":"America/Port-au-Prince",
    "iso:country":"HT",
    "name:fra_x_preferred":[
        "Martel"
    ],
    "wof:name":"Martel",
    "wof:placetype":"locality"
},
  "geometry": {"coordinates":[-72.69119000000001,18.36432000000001],"type":"Point"}
}