{
  "type": "Feature",
  "properties": {
    "gn:admin1_code":"12.0",
    "gn:admin2_code":"3727900.0",
    "gn:asciiname":"Chapelon",
    "gn:country_code":"HT",
    "gn:dem":43,
    "gn:feature_class":"P",
    "gn:feature_code":"PPL",
    "gn:name":"Chapelon",
    "gn:population":0,
    "gn:timezone":"America/Port-au-Prince",
    "iso:country":"HT",
    "name:cat_x_preferred":[
        "Chapelon"
    ],
    "name:ceb_x_preferred":[
        "Chapelon"
    ],
    "name:ces_x_preferred":[
        "Chapelon"
    ],
    "name:deu_x_preferred":[
        "Chapelon"
    ],
    "name:eus_x_preferred":[
        "Chapelon"
    ],
    "name:fra_x_preferred":[
        "Chapelon"
    ],
    "name:hun_x_preferred":[
        "Chapelon"
    ],
    "name:ita_x_preferred":[
        "Chapelon"
    ],
    "name:lat_x_preferred":[
        "Chapelon"
    ],
    "name:msa_x_preferred":[
        "Chapelon"
    ],
    "name:nld_x_preferred":[
        "Chapelon"
    ],
    "name:oci_x_preferred":[
        "Chapelon"
    ],
    "name:pms_x_preferred":[
        "Chapelon"
    ],
    "name:pol_x_preferred":[
        "Chapelon"
    ],
    "name:por_x_preferred":[
        "Chapelon"
    ],
    "name:ron_x_preferred":[
        "Chapelon"
    ],
    "name:slk_x_preferred":[
        "Chapelon"
    ],
    "name:spa_x_preferred":[
        "Chapelon"
    ],
    "name:srp_x_preferred":[
        "\u0428\u0430\u043f\u0435\u043b\u043e\u043d"
    ],
    "name:swe_x_preferred":[
        "Chapelon"
    ],
    "name:ukr_x_preferred":[
        "\u0428\u0430\u043f\u043b\u043e\u043d"
    ],
    "name:uzb_x_preferred":[
        "Chapelon"
    ],
    "name:vie_x_preferred":[
        "Chapelon"
    ],
    "name:vol_x_preferred":[
        "Chapelon"
    ],
    "name:war_x_preferred":[
        "Chapelon"
    ],
    "name:zho_x_preferred":[
        "\u6c99\u4f69\u9686"
    ],
    "wof:name":"Chapelon",
    "wof:placetype":"locality"
},
  "geometry": {"coordinates":[-74.09999999999999,18.26667],"type":"Point"}
}