{
  "type": "Feature",
  "properties": {
    "gn:admin1_code":"12.0",
    "gn:admin2_code":"3727900.0",
    "gn:asciiname":"Chapelon",
    "gn:country_code":"HT",
    "gn:dem":43,
    "gn:feature_class":"P",
    "gn:feature_code":"PPL",
    "gn:name":"Chapelon",
    "gn:population":0,
    "gn:timezone":"America/Port-au-Prince",
    "iso:country":"HT",
    "wof:name":"Chapelon",
    "wof:placetype":"locality"
},
  "geometry": {"coordinates":[-74.09999999999999,18.26667],"type":"Point"}
}