{
  "type": "Feature",
  "properties": {
    "gn:admin1_code":"11.0",
    "gn:admin2_code":"3718425.0",
    "gn:asciiname":"Mahotieres",
    "gn:country_code":"HT",
    "gn:dem":803,
    "gn:feature_class":"P",
    "gn:feature_code":"PPL",
    "gn:name":"Mahoti\u00e8res",
    "gn:population":0,
    "gn:timezone":"America/Port-au-Prince",
    "iso:country":"HT",
    "wof:name":"Mahotieres",
    "wof:placetype":"locality"
},
  "geometry": {"coordinates":[-72.21666999999999,18.41667],"type":"Point"}
}