{
  "type": "Feature",
  "properties": {
    "gn:admin1_code":"6.0",
    "gn:admin2_code":"3717563.0",
    "gn:asciiname":"Sainte-Marthe",
    "gn:country_code":"HT",
    "gn:dem":737,
    "gn:feature_class":"P",
    "gn:feature_code":"PPL",
    "gn:name":"Sainte-Marthe",
    "gn:population":0,
    "gn:timezone":"America/Port-au-Prince",
    "iso:country":"HT",
    "name:ceb_x_preferred":[
        "Sainte-Marthe"
    ],
    "name:deu_x_preferred":[
        "Sainte-Marthe"
    ],
    "name:fra_x_preferred":[
        "Sainte-Marthe"
    ],
    "name:ita_x_preferred":[
        "Sainte-Marthe"
    ],
    "name:nds_x_preferred":[
        "Sainte-Marthe"
    ],
    "name:nld_x_preferred":[
        "Sainte-Marthe"
    ],
    "name:oci_x_preferred":[
        "Sainte-Marthe"
    ],
    "name:pms_x_preferred":[
        "Sainte-Marthe"
    ],
    "name:pol_x_preferred":[
        "Sainte-Marthe"
    ],
    "name:por_x_preferred":[
        "Sainte-Marthe"
    ],
    "name:rus_x_preferred":[
        "\u0421\u0435\u043d\u0442-\u041c\u0430\u0440\u0442"
    ],
    "name:slk_x_preferred":[
        "Sainte-Marthe"
    ],
    "name:spa_x_preferred":[
        "Sainte-Marthe"
    ],
    "name:swe_x_preferred":[
        "Sainte-Marthe"
    ],
    "name:ukr_x_preferred":[
        "\u0421\u0435\u043d\u0442-\u041c\u0430\u0440\u0442"
    ],
    "wof:name":"Sainte-Marthe",
    "wof:placetype":"locality"
},
  "geometry": {"coordinates":[-72.25,19.41667],"type":"Point"}
}