{
  "type": "Feature",
  "properties": {
    "gn:admin1_code":"15.0",
    "gn:admin2_code":"3731122.0",
    "gn:asciiname":"Nan Campeche",
    "gn:country_code":"HT",
    "gn:dem":260,
    "gn:feature_class":"P",
    "gn:feature_code":"PPL",
    "gn:name":"Nan Camp\u00eache",
    "gn:population":0,
    "gn:timezone":"America/Port-au-Prince",
    "iso:country":"HT",
    "name:fra_x_preferred":[
        "Nan Camp\u00eache"
    ],
    "wof:name":"Nan Campeche",
    "wof:placetype":"locality"
},
  "geometry": {"coordinates":[-73.48014000000001,18.39143],"type":"Point"}
}