{
  "type": "Feature",
  "properties": {
    "gn:admin1_code":"6.0",
    "gn:admin2_code":"3717563.0",
    "gn:asciiname":"Pierrot",
    "gn:country_code":"HT",
    "gn:dem":749,
    "gn:feature_class":"P",
    "gn:feature_code":"PPL",
    "gn:name":"Pierrot",
    "gn:population":0,
    "gn:timezone":"America/Port-au-Prince",
    "iso:country":"HT",
    "name:fra_x_preferred":[
        "Pierrot"
    ],
    "wof:name":"Pierrot",
    "wof:placetype":"locality"
},
  "geometry": {"coordinates":[-72.35395,19.48698],"type":"Point"}
}