{
  "type": "Feature",
  "properties": {
    "gn:admin1_code":"6.0",
    "gn:admin2_code":"3717563.0",
    "gn:asciiname":"Pierrot",
    "gn:country_code":"HT",
    "gn:dem":749,
    "gn:feature_class":"P",
    "gn:feature_code":"PPL",
    "gn:name":"Pierrot",
    "gn:population":0,
    "gn:timezone":"America/Port-au-Prince",
    "iso:country":"HT",
    "name:als_x_preferred":[
        "Pierrot"
    ],
    "name:bul_x_preferred":[
        "\u041f\u0438\u0435\u0440\u043e"
    ],
    "name:cat_x_preferred":[
        "Pierrot"
    ],
    "name:ces_x_preferred":[
        "Pierot"
    ],
    "name:dan_x_preferred":[
        "Pjerrot"
    ],
    "name:deu_x_preferred":[
        "Pierrot"
    ],
    "name:epo_x_preferred":[
        "Pieroto"
    ],
    "name:eus_x_preferred":[
        "Pierrot"
    ],
    "name:fra_x_preferred":[
        "Pierrot"
    ],
    "name:heb_x_preferred":[
        "\u05e4\u05d9\u05d9\u05e8\u05d5"
    ],
    "name:ind_x_preferred":[
        "Pierrot"
    ],
    "name:ita_x_preferred":[
        "Pierrot"
    ],
    "name:kaz_x_preferred":[
        "\u041f\u044c\u0435\u0440\u043e"
    ],
    "name:kor_x_preferred":[
        "\ud53c\uc5d0\ub85c"
    ],
    "name:mkd_x_preferred":[
        "\u041f\u0458\u0435\u0440\u043e"
    ],
    "name:nld_x_preferred":[
        "Pierrot"
    ],
    "name:pol_x_preferred":[
        "Pierrot"
    ],
    "name:por_x_preferred":[
        "Pierrot"
    ],
    "name:rus_x_preferred":[
        "\u041f\u044c\u0435\u0440\u043e"
    ],
    "name:spa_x_preferred":[
        "Pierrot"
    ],
    "name:sqi_x_preferred":[
        "Pierino"
    ],
    "name:swe_x_preferred":[
        "Pierrot"
    ],
    "name:ukr_x_preferred":[
        "\u041f'\u0454\u0440\u043e"
    ],
    "wof:name":"Pierrot",
    "wof:placetype":"locality"
},
  "geometry": {"coordinates":[-72.35395,19.48698],"type":"Point"}
}