{
  "type": "Feature",
  "properties": {
    "gn:admin1_code":"13.0",
    "gn:admin2_code":"3723778.0",
    "gn:asciiname":"Pointe Jean Louis",
    "gn:country_code":"HT",
    "gn:dem":666,
    "gn:feature_class":"P",
    "gn:feature_code":"PPL",
    "gn:name":"Pointe Jean Louis",
    "gn:population":0,
    "gn:timezone":"America/Port-au-Prince",
    "iso:country":"HT",
    "wof:name":"Pointe Jean Louis",
    "wof:placetype":"locality"
},
  "geometry": {"coordinates":[-72.68000000000001,18.26917000000001],"type":"Point"}
}