{
  "type": "Feature",
  "properties": {
    "gn:admin1_code":"12.0",
    "gn:admin2_code":"3727900.0",
    "gn:asciiname":"Gauvry",
    "gn:country_code":"HT",
    "gn:dem":229,
    "gn:feature_class":"P",
    "gn:feature_code":"PPL",
    "gn:name":"Gauvry",
    "gn:population":0,
    "gn:timezone":"America/Port-au-Prince",
    "iso:country":"HT",
    "wof:name":"Gauvry",
    "wof:placetype":"locality"
},
  "geometry": {"coordinates":[-74.33333,18.31667],"type":"Point"}
}