{
  "type": "Feature",
  "properties": {
    "gn:admin1_code":"12.0",
    "gn:admin2_code":"3728096.0",
    "gn:asciiname":"Langlois",
    "gn:country_code":"HT",
    "gn:dem":40,
    "gn:feature_class":"P",
    "gn:feature_code":"PPL",
    "gn:name":"Langlois",
    "gn:population":0,
    "gn:timezone":"America/Port-au-Prince",
    "iso:country":"HT",
    "wof:name":"Langlois",
    "wof:placetype":"locality"
},
  "geometry": {"coordinates":[-73.76666999999998,18.26667],"type":"Point"}
}