{
  "type": "Feature",
  "properties": {
    "gn:admin1_code":"6.0",
    "gn:admin2_code":"3724144.0",
    "gn:asciiname":"Carrefour Figuier",
    "gn:cc2":"HT",
    "gn:country_code":"HT",
    "gn:dem":76,
    "gn:feature_class":"P",
    "gn:feature_code":"PPL",
    "gn:name":"Carrefour Figuier",
    "gn:population":0,
    "gn:timezone":"America/Port-au-Prince",
    "iso:country":"HT",
    "name:und_x_variant":[
        "Figuier",
        "Carrefour Figuier"
    ],
    "wof:name":"Carrefour Figuier",
    "wof:placetype":"locality"
},
  "geometry": {"coordinates":[-72.88889,19.59833],"type":"Point"}
}