{
  "type": "Feature",
  "properties": {
    "gn:admin1_code":"6.0",
    "gn:admin2_code":"3724695.0",
    "gn:asciiname":"Bayonnais",
    "gn:country_code":"HT",
    "gn:dem":806,
    "gn:feature_class":"P",
    "gn:feature_code":"PPL",
    "gn:name":"Bayonnais",
    "gn:population":0,
    "gn:timezone":"America/Port-au-Prince",
    "iso:country":"HT",
    "name:fra_x_preferred":[
        "Bayonnais"
    ],
    "wof:name":"Bayonnais",
    "wof:placetype":"locality"
},
  "geometry": {"coordinates":[-72.47774,19.4085],"type":"Point"}
}