{
  "type": "Feature",
  "properties": {
    "gn:admin1_code":"6.0",
    "gn:admin2_code":"3724144.0",
    "gn:asciiname":"Perdutemps",
    "gn:country_code":"HT",
    "gn:dem":600,
    "gn:feature_class":"P",
    "gn:feature_code":"PPL",
    "gn:name":"Perdutemps",
    "gn:population":0,
    "gn:timezone":"America/Port-au-Prince",
    "iso:country":"HT",
    "name:fra_x_preferred":[
        "Perdutemps"
    ],
    "wof:name":"Perdutemps",
    "wof:placetype":"locality"
},
  "geometry": {"coordinates":[-72.73697,19.60706],"type":"Point"}
}