{
  "type": "Feature",
  "properties": {
    "gn:admin1_code":"11.0",
    "gn:admin2_code":"3718425.0",
    "gn:asciiname":"Tubereuse",
    "gn:country_code":"HT",
    "gn:dem":396,
    "gn:feature_class":"P",
    "gn:feature_code":"PPL",
    "gn:name":"Tub\u00e9reuse",
    "gn:population":0,
    "gn:timezone":"America/Port-au-Prince",
    "iso:country":"HT",
    "wof:name":"Tubereuse",
    "wof:placetype":"locality"
},
  "geometry": {"coordinates":[-72.16944000000002,18.46417000000001],"type":"Point"}
}