{
  "type": "Feature",
  "properties": {
    "gn:admin1_code":"11.0",
    "gn:admin2_code":"3722285.0",
    "gn:asciiname":"Carrefour Baussan",
    "gn:country_code":"HT",
    "gn:dem":15,
    "gn:feature_class":"P",
    "gn:feature_code":"PPL",
    "gn:name":"Carrefour Baussan",
    "gn:population":0,
    "gn:timezone":"America/Port-au-Prince",
    "iso:country":"HT",
    "wof:name":"Carrefour Baussan",
    "wof:placetype":"locality"
},
  "geometry": {"coordinates":[-72.63333,18.51667],"type":"Point"}
}