{
  "type": "Feature",
  "properties": {
    "gn:admin1_code":"9.0",
    "gn:admin2_code":"3731232.0",
    "gn:asciiname":"Bailly",
    "gn:country_code":"HT",
    "gn:dem":220,
    "gn:feature_class":"P",
    "gn:feature_code":"PPL",
    "gn:name":"Bailly",
    "gn:population":0,
    "gn:timezone":"America/Port-au-Prince",
    "iso:country":"HT",
    "name:ceb_x_preferred":[
        "Bailly"
    ],
    "name:deu_x_preferred":[
        "Bailly"
    ],
    "name:fra_x_preferred":[
        "Bailly"
    ],
    "name:ita_x_preferred":[
        "Bailly"
    ],
    "name:jpn_x_preferred":[
        "\u30d0\u30a4\u30a4"
    ],
    "name:ltz_x_preferred":[
        "Bailly"
    ],
    "name:nds_x_preferred":[
        "Bailly"
    ],
    "name:nld_x_preferred":[
        "Bailly"
    ],
    "name:oci_x_preferred":[
        "Bailly"
    ],
    "name:pol_x_preferred":[
        "Bailly"
    ],
    "name:por_x_preferred":[
        "Bailly"
    ],
    "name:scn_x_preferred":[
        "Bailly"
    ],
    "name:slk_x_preferred":[
        "Bailly"
    ],
    "name:slv_x_preferred":[
        "Bailly"
    ],
    "name:spa_x_preferred":[
        "Bailly"
    ],
    "name:swe_x_preferred":[
        "Bailly"
    ],
    "name:ukr_x_preferred":[
        "\u0411\u0430\u0457"
    ],
    "wof:name":"Bailly",
    "wof:placetype":"locality"
},
  "geometry": {"coordinates":[-72.33333,19.63333],"type":"Point"}
}