{
  "type": "Feature",
  "properties": {
    "gn:admin1_code":"11.0",
    "gn:admin2_code":"3723019.0",
    "gn:asciiname":"La Cour Joseph",
    "gn:country_code":"HT",
    "gn:dem":252,
    "gn:feature_class":"P",
    "gn:feature_code":"PPL",
    "gn:name":"La Cour Joseph",
    "gn:population":0,
    "gn:timezone":"America/Port-au-Prince",
    "iso:country":"HT",
    "name:fra_x_preferred":[
        "La Cour Joseph"
    ],
    "wof:name":"La Cour Joseph",
    "wof:placetype":"locality"
},
  "geometry": {"coordinates":[-72.88399,18.81943],"type":"Point"}
}