{
  "type": "Feature",
  "properties": {
    "gn:admin1_code":"10.0",
    "gn:admin2_code":"3716223.0",
    "gn:asciiname":"Cocoloco",
    "gn:country_code":"HT",
    "gn:dem":411,
    "gn:feature_class":"P",
    "gn:feature_code":"PPL",
    "gn:name":"Cocoloco",
    "gn:population":0,
    "gn:timezone":"America/Port-au-Prince",
    "iso:country":"HT",
    "wof:name":"Cocoloco",
    "wof:placetype":"locality"
},
  "geometry": {"coordinates":[-72.05,19.55],"type":"Point"}
}