{
  "type": "Feature",
  "properties": {
    "gn:admin1_code":"9.0",
    "gn:admin2_code":"3728473.0",
    "gn:asciiname":"Haut du Cap",
    "gn:country_code":"HT",
    "gn:dem":13,
    "gn:feature_class":"P",
    "gn:feature_code":"PPL",
    "gn:name":"Haut du Cap",
    "gn:population":0,
    "gn:timezone":"America/Port-au-Prince",
    "iso:country":"HT",
    "wof:name":"Haut du Cap",
    "wof:placetype":"locality"
},
  "geometry": {"coordinates":[-72.22889000000001,19.72333],"type":"Point"}
}