{
  "type": "Feature",
  "properties": {
    "gn:admin1_code":"11.0",
    "gn:admin2_code":"3731086.0",
    "gn:asciiname":"Garotte",
    "gn:country_code":"HT",
    "gn:dem":44,
    "gn:feature_class":"P",
    "gn:feature_code":"PPL",
    "gn:name":"Garotte",
    "gn:population":0,
    "gn:timezone":"America/Port-au-Prince",
    "iso:country":"HT",
    "name:fra_x_preferred":[
        "Garotte"
    ],
    "wof:name":"Garotte",
    "wof:placetype":"locality"
},
  "geometry": {"coordinates":[-72.54315,18.80979],"type":"Point"}
}