{
  "type": "Feature",
  "properties": {
    "gn:admin1_code":"14.0",
    "gn:admin2_code":"3723592.0",
    "gn:asciiname":"La Seringue",
    "gn:cc2":"HT",
    "gn:country_code":"HT",
    "gn:dem":23,
    "gn:feature_class":"P",
    "gn:feature_code":"PPL",
    "gn:name":"La Seringue",
    "gn:population":0,
    "gn:timezone":"America/Port-au-Prince",
    "iso:country":"HT",
    "name:und_x_variant":[
        "Habitation Seringue",
        "La Seringue"
    ],
    "wof:name":"La Seringue",
    "wof:placetype":"locality"
},
  "geometry": {"coordinates":[-74.38800000000001,18.63764],"type":"Point"}
}