{
  "type": "Feature",
  "properties": {
    "gn:admin1_code":"9.0",
    "gn:admin2_code":"3728473.0",
    "gn:asciiname":"La Chevalerie",
    "gn:country_code":"HT",
    "gn:dem":11,
    "gn:feature_class":"P",
    "gn:feature_code":"PPL",
    "gn:name":"La Chevalerie",
    "gn:population":0,
    "gn:timezone":"America/Port-au-Prince",
    "iso:country":"HT",
    "name:fra_x_preferred":[
        "La Chevalerie"
    ],
    "wof:name":"La Chevalerie",
    "wof:placetype":"locality"
},
  "geometry": {"coordinates":[-72.10550000000001,19.69983],"type":"Point"}
}