{
  "type": "Feature",
  "properties": {
    "gn:admin1_code":"11.0",
    "gn:asciiname":"Jonc",
    "gn:country_code":"HT",
    "gn:dem":1347,
    "gn:feature_class":"P",
    "gn:feature_code":"PPL",
    "gn:name":"Jonc",
    "gn:population":0,
    "gn:timezone":"America/Port-au-Prince",
    "iso:country":"HT",
    "wof:name":"Jonc",
    "wof:placetype":"locality"
},
  "geometry": {"coordinates":[-72.06667,18.31667],"type":"Point"}
}