{
  "type": "Feature",
  "properties": {
    "gn:admin1_code":"14.0",
    "gn:asciiname":"Bahon",
    "gn:country_code":"HT",
    "gn:dem":360,
    "gn:feature_class":"P",
    "gn:feature_code":"PPL",
    "gn:name":"Bahon",
    "gn:population":0,
    "gn:timezone":"America/Port-au-Prince",
    "iso:country":"HT",
    "wof:name":"Bahon",
    "wof:placetype":"locality"
},
  "geometry": {"coordinates":[-73.21666999999999,18.36667000000001],"type":"Point"}
}