{
  "type": "Feature",
  "properties": {
    "gn:admin1_code":"14.0",
    "gn:asciiname":"Bahon",
    "gn:country_code":"HT",
    "gn:dem":360,
    "gn:feature_class":"P",
    "gn:feature_code":"PPL",
    "gn:name":"Bahon",
    "gn:population":0,
    "gn:timezone":"America/Port-au-Prince",
    "iso:country":"HT",
    "name:ara_x_preferred":[
        "\u0628\u0627\u0647\u0648\u0646"
    ],
    "name:ceb_x_preferred":[
        "Bahon"
    ],
    "name:fra_x_preferred":[
        "Bahon"
    ],
    "name:hat_x_preferred":[
        "Bawon"
    ],
    "name:ita_x_preferred":[
        "Bahon"
    ],
    "name:nld_x_preferred":[
        "Bahon"
    ],
    "name:por_x_preferred":[
        "Bahon"
    ],
    "name:ron_x_preferred":[
        "Bahon"
    ],
    "name:spa_x_preferred":[
        "Bahon"
    ],
    "name:swe_x_preferred":[
        "Bahon"
    ],
    "wof:name":"Bahon",
    "wof:placetype":"locality"
},
  "geometry": {"coordinates":[-73.21666999999999,18.36667000000001],"type":"Point"}
}