{
  "type": "Feature",
  "properties": {
    "gn:admin1_code":"15.0",
    "gn:admin2_code":"3730801.0",
    "gn:asciiname":"Mathon",
    "gn:country_code":"HT",
    "gn:dem":23,
    "gn:feature_class":"P",
    "gn:feature_code":"PPL",
    "gn:name":"Mathon",
    "gn:population":0,
    "gn:timezone":"America/Port-au-Prince",
    "iso:country":"HT",
    "name:ceb_x_preferred":[
        "Mathon"
    ],
    "name:deu_x_preferred":[
        "Mathon"
    ],
    "name:epo_x_preferred":[
        "Mathon"
    ],
    "name:eus_x_preferred":[
        "Mathon"
    ],
    "name:fra_x_preferred":[
        "Mathon"
    ],
    "name:swe_x_preferred":[
        "Mathon"
    ],
    "wof:name":"Mathon",
    "wof:placetype":"locality"
},
  "geometry": {"coordinates":[-73.59999999999999,18.56667],"type":"Point"}
}