{
  "type": "Feature",
  "properties": {
    "gn:admin1_code":"9.0",
    "gn:admin2_code":"3729454.0",
    "gn:asciiname":"Jeannette",
    "gn:country_code":"HT",
    "gn:dem":110,
    "gn:feature_class":"P",
    "gn:feature_code":"PPL",
    "gn:name":"Jeannette",
    "gn:population":0,
    "gn:timezone":"America/Port-au-Prince",
    "iso:country":"HT",
    "name:fra_x_preferred":[
        "Jeannette"
    ],
    "wof:name":"Jeannette",
    "wof:placetype":"locality"
},
  "geometry": {"coordinates":[-72.47041,19.7132],"type":"Point"}
}