{
  "type": "Feature",
  "properties": {
    "gn:admin1_code":"10.0",
    "gn:admin2_code":"3719435.0",
    "gn:asciiname":"Duller",
    "gn:country_code":"HT",
    "gn:dem":205,
    "gn:feature_class":"P",
    "gn:feature_code":"PPL",
    "gn:name":"Duller",
    "gn:population":0,
    "gn:timezone":"America/Port-au-Prince",
    "iso:country":"HT",
    "name:fra_x_preferred":[
        "Duller"
    ],
    "wof:name":"Duller",
    "wof:placetype":"locality"
},
  "geometry": {"coordinates":[-71.83190999999999,19.48311],"type":"Point"}
}