{
  "type": "Feature",
  "properties": {
    "gn:admin1_code":"6.0",
    "gn:admin2_code":"3724144.0",
    "gn:asciiname":"Derriere Anse Rouge",
    "gn:country_code":"HT",
    "gn:dem":99,
    "gn:feature_class":"P",
    "gn:feature_code":"PPL",
    "gn:name":"Derri\u00e8re Anse Rouge",
    "gn:population":0,
    "gn:timezone":"America/Port-au-Prince",
    "iso:country":"HT",
    "wof:name":"Derriere Anse Rouge",
    "wof:placetype":"locality"
},
  "geometry": {"coordinates":[-73.07278000000002,19.65],"type":"Point"}
}