{
  "type": "Feature",
  "properties": {
    "gn:admin1_code":"11.0",
    "gn:admin2_code":"3727134.0",
    "gn:asciiname":"Ducabon",
    "gn:country_code":"HT",
    "gn:dem":1185,
    "gn:feature_class":"P",
    "gn:feature_code":"PPL",
    "gn:name":"Ducabon",
    "gn:population":0,
    "gn:timezone":"America/Port-au-Prince",
    "iso:country":"HT",
    "name:fra_x_preferred":[
        "Ducabon"
    ],
    "wof:name":"Ducabon",
    "wof:placetype":"locality"
},
  "geometry": {"coordinates":[-71.88114,18.65191],"type":"Point"}
}