{
  "type": "Feature",
  "properties": {
    "gn:admin1_code":"6.0",
    "gn:admin2_code":"3726539.0",
    "gn:asciiname":"La Couline",
    "gn:country_code":"HT",
    "gn:dem":459,
    "gn:feature_class":"P",
    "gn:feature_code":"PPL",
    "gn:name":"La Couline",
    "gn:population":0,
    "gn:timezone":"America/Port-au-Prince",
    "iso:country":"HT",
    "name:fra_x_preferred":[
        "La Couline"
    ],
    "wof:name":"La Couline",
    "wof:placetype":"locality"
},
  "geometry": {"coordinates":[-72.31184,18.98376],"type":"Point"}
}