{
  "type": "Feature",
  "properties": {
    "gn:admin1_code":"9.0",
    "gn:admin2_code":"3728473",
    "gn:asciiname":"Pont Parois",
    "gn:country_code":"HT",
    "gn:dem":19,
    "gn:feature_class":"P",
    "gn:feature_code":"PPL",
    "gn:name":"Pont Parois",
    "gn:population":0,
    "gn:timezone":"America/Port-au-Prince",
    "iso:country":"HT",
    "wof:name":"Pont Parois",
    "wof:placetype":"locality"
},
  "geometry": {"coordinates":[-72.1425,19.68722],"type":"Point"}
}