{
  "type": "Feature",
  "properties": {
    "gn:admin1_code":"6.0",
    "gn:asciiname":"Descambe",
    "gn:country_code":"HT",
    "gn:dem":635,
    "gn:feature_class":"P",
    "gn:feature_code":"PPL",
    "gn:name":"Descambe",
    "gn:population":0,
    "gn:timezone":"America/Port-au-Prince",
    "iso:country":"HT",
    "name:fra_x_preferred":[
        "Descambe"
    ],
    "wof:name":"Descambe",
    "wof:placetype":"locality"
},
  "geometry": {"coordinates":[-72.70844,19.79351],"type":"Point"}
}