{
  "type": "Feature",
  "properties": {
    "gn:admin1_code":"10.0",
    "gn:admin2_code":"3716114.0",
    "gn:asciiname":"Brochard",
    "gn:country_code":"HT",
    "gn:dem":470,
    "gn:feature_class":"P",
    "gn:feature_code":"PPL",
    "gn:name":"Brochard",
    "gn:population":0,
    "gn:timezone":"America/Port-au-Prince",
    "iso:country":"HT",
    "wof:name":"Brochard",
    "wof:placetype":"locality"
},
  "geometry": {"coordinates":[-72.01666999999998,19.41667],"type":"Point"}
}