{
  "type": "Feature",
  "properties": {
    "gn:admin1_code":"9.0",
    "gn:admin2_code":"3729454.0",
    "gn:asciiname":"Nan Plaisir",
    "gn:country_code":"HT",
    "gn:dem":515,
    "gn:feature_class":"P",
    "gn:feature_code":"PPL",
    "gn:name":"Nan Plaisir",
    "gn:population":0,
    "gn:timezone":"America/Port-au-Prince",
    "iso:country":"HT",
    "wof:name":"Nan Plaisir",
    "wof:placetype":"locality"
},
  "geometry": {"coordinates":[-72.56667,19.85],"type":"Point"}
}