{
  "type": "Feature",
  "properties": {
    "gn:admin1_code":"6.0",
    "gn:admin2_code":"3726539.0",
    "gn:asciiname":"Dandouin",
    "gn:country_code":"HT",
    "gn:dem":1432,
    "gn:feature_class":"P",
    "gn:feature_code":"PPL",
    "gn:name":"Dandouin",
    "gn:population":0,
    "gn:timezone":"America/Port-au-Prince",
    "iso:country":"HT",
    "wof:name":"Dandouin",
    "wof:placetype":"locality"
},
  "geometry": {"coordinates":[-72.26666999999998,19.06667],"type":"Point"}
}