{
  "type": "Feature",
  "properties": {
    "gn:admin1_code":"3.0",
    "gn:admin2_code":"3720764.0",
    "gn:asciiname":"La Riviere",
    "gn:country_code":"HT",
    "gn:dem":49,
    "gn:feature_class":"P",
    "gn:feature_code":"PPL",
    "gn:name":"La Rivi\u00e8re",
    "gn:population":0,
    "gn:timezone":"America/Port-au-Prince",
    "iso:country":"HT",
    "wof:name":"La Riviere",
    "wof:placetype":"locality"
},
  "geometry": {"coordinates":[-73.03806,19.86944],"type":"Point"}
}