{
  "type": "Feature",
  "properties": {
    "gn:admin1_code":"3.0",
    "gn:admin2_code":"3720764.0",
    "gn:asciiname":"Bassin Bleu",
    "gn:country_code":"HT",
    "gn:dem":241,
    "gn:feature_class":"P",
    "gn:feature_code":"PPL",
    "gn:name":"Bassin Bleu",
    "gn:population":0,
    "gn:timezone":"America/Port-au-Prince",
    "iso:country":"HT",
    "name:fra_x_preferred":[
        "Bassin Bleu"
    ],
    "wof:name":"Bassin Bleu",
    "wof:placetype":"locality"
},
  "geometry": {"coordinates":[-73.17158000000001,19.81257],"type":"Point"}
}