{
  "type": "Feature",
  "properties": {
    "gn:admin1_code":"11.0",
    "gn:admin2_code":"3731086.0",
    "gn:asciiname":"Sophie",
    "gn:country_code":"HT",
    "gn:dem":156,
    "gn:feature_class":"P",
    "gn:feature_code":"PPL",
    "gn:name":"Sophie",
    "gn:population":0,
    "gn:timezone":"America/Port-au-Prince",
    "iso:country":"HT",
    "name:bre_x_preferred":[
        "Sophie"
    ],
    "name:fra_x_preferred":[
        "Sophie"
    ],
    "name:heb_x_preferred":[
        "\u05e1\u05d5\u05e4\u05d9"
    ],
    "name:nds_x_preferred":[
        "Sophie"
    ],
    "name:nld_x_preferred":[
        "Sophie"
    ],
    "name:spa_x_preferred":[
        "Sophie"
    ],
    "wof:name":"Sophie",
    "wof:placetype":"locality"
},
  "geometry": {"coordinates":[-72.38809000000001,18.78113],"type":"Point"}
}