{
  "type": "Feature",
  "properties": {
    "gn:admin1_code":"10.0",
    "gn:admin2_code":"3716114.0",
    "gn:asciiname":"Paques",
    "gn:country_code":"HT",
    "gn:dem":517,
    "gn:feature_class":"P",
    "gn:feature_code":"PPL",
    "gn:name":"P\u00e2ques",
    "gn:population":0,
    "gn:timezone":"America/Port-au-Prince",
    "iso:country":"HT",
    "name:und_x_variant":[
        "Nan Paques",
        "P\u00e2ques"
    ],
    "wof:name":"Paques",
    "wof:placetype":"locality"
},
  "geometry": {"coordinates":[-71.9862,19.37198],"type":"Point"}
}