{
  "type": "Feature",
  "properties": {
    "gn:admin1_code":"14.0",
    "gn:admin2_code":"3727381.0",
    "gn:asciiname":"Fond Deron",
    "gn:country_code":"HT",
    "gn:dem":458,
    "gn:feature_class":"P",
    "gn:feature_code":"PPL",
    "gn:name":"Fond D\u00e9ron",
    "gn:population":0,
    "gn:timezone":"America/Port-au-Prince",
    "iso:country":"HT",
    "name:und_x_variant":[
        "Fonderon",
        "Fond D\u00e9ron"
    ],
    "wof:name":"Fond Deron",
    "wof:placetype":"locality"
},
  "geometry": {"coordinates":[-73.86918,18.45466],"type":"Point"}
}