{
  "type": "Feature",
  "properties": {
    "gn:admin1_code":"15.0",
    "gn:admin2_code":"3731122.0",
    "gn:asciiname":"Source Crabe",
    "gn:country_code":"HT",
    "gn:dem":791,
    "gn:feature_class":"P",
    "gn:feature_code":"PPL",
    "gn:name":"Source Crabe",
    "gn:population":0,
    "gn:timezone":"America/Port-au-Prince",
    "iso:country":"HT",
    "wof:name":"Source Crabe",
    "wof:placetype":"locality"
},
  "geometry": {"coordinates":[-73.61833,18.44667],"type":"Point"}
}