{
  "type": "Feature",
  "properties": {
    "gn:admin1_code":"9.0",
    "gn:admin2_code":"3729454.0",
    "gn:asciiname":"Freto",
    "gn:country_code":"HT",
    "gn:dem":474,
    "gn:feature_class":"P",
    "gn:feature_code":"PPL",
    "gn:name":"Fr\u00e9to",
    "gn:population":0,
    "gn:timezone":"America/Port-au-Prince",
    "iso:country":"HT",
    "name:und_x_variant":[
        "Foueto",
        "Fr\u00e9to"
    ],
    "wof:name":"Freto",
    "wof:placetype":"locality"
},
  "geometry": {"coordinates":[-72.60405,19.79297],"type":"Point"}
}