{
  "type": "Feature",
  "properties": {
    "gn:admin1_code":"13.0",
    "gn:admin2_code":"3723778.0",
    "gn:asciiname":"Ti Riviere",
    "gn:country_code":"HT",
    "gn:dem":791,
    "gn:feature_class":"P",
    "gn:feature_code":"PPL",
    "gn:name":"Ti Rivi\u00e8re",
    "gn:population":0,
    "gn:timezone":"America/Port-au-Prince",
    "iso:country":"HT",
    "name:fra_x_preferred":[
        "Ti Rivi\u00e8re"
    ],
    "wof:name":"Ti Riviere",
    "wof:placetype":"locality"
},
  "geometry": {"coordinates":[-72.48828,18.36537],"type":"Point"}
}