{
  "type": "Feature",
  "properties": {
    "gn:admin1_code":"12.0",
    "gn:admin2_code":"3727900.0",
    "gn:asciiname":"Samedi",
    "gn:country_code":"HT",
    "gn:dem":66,
    "gn:feature_class":"P",
    "gn:feature_code":"PPL",
    "gn:name":"Samedi",
    "gn:population":0,
    "gn:timezone":"America/Port-au-Prince",
    "iso:country":"HT",
    "name:fra_x_preferred":[
        "Samedi"
    ],
    "wof:name":"Samedi",
    "wof:placetype":"locality"
},
  "geometry": {"coordinates":[-74.14331,18.28707],"type":"Point"}
}