{
  "type": "Feature",
  "properties": {
    "gn:country":"HT",
    "gn:fcode":"PPL",
    "gn:population":18256,
    "iso:country":"HT",
    "name:ceb_x_preferred":[
        "Fond Parisien"
    ],
    "name:deu_x_preferred":[
        "Fonds-Parisien"
    ],
    "name:eng_x_preferred":[
        "Fonds-Parisien"
    ],
    "name:fra_x_preferred":[
        "Fonds-Parisien"
    ],
    "name:nld_x_preferred":[
        "Fonds-Parisien"
    ],
    "name:pol_x_preferred":[
        "Fonds-Parisien"
    ],
    "name:ron_x_preferred":[
        "Fonds-Parisien"
    ],
    "name:spa_x_preferred":[
        "Fond Parisien"
    ],
    "name:swe_x_preferred":[
        "Fond Parisien"
    ],
    "qs:name":"Fond Parisien",
    "qs:photos_9r":0,
    "qs:photos_sr":0,
    "qs:pop_sr":"6",
    "wof:name":"Fond Parisien",
    "wof:placetype":"locality",
    "wof:population":18256
},
  "geometry": {"coordinates":[-71.97667,18.50583],"type":"Point"}
}