{
  "type": "Feature",
  "properties": {
    "gn:admin1_code":"11.0",
    "gn:admin2_code":"3727134.0",
    "gn:asciiname":"Bois Neptune",
    "gn:country_code":"HT",
    "gn:dem":998,
    "gn:feature_class":"P",
    "gn:feature_code":"PPL",
    "gn:name":"Bois Neptune",
    "gn:population":0,
    "gn:timezone":"America/Port-au-Prince",
    "iso:country":"HT",
    "wof:name":"Bois Neptune",
    "wof:placetype":"locality"
},
  "geometry": {"coordinates":[-71.86667,18.66667],"type":"Point"}
}