{
  "type": "Feature",
  "properties": {
    "gn:admin1_code":"9.0",
    "gn:asciiname":"Vogues",
    "gn:country_code":"HT",
    "gn:dem":46,
    "gn:feature_class":"P",
    "gn:feature_code":"PPL",
    "gn:name":"Vogues",
    "gn:population":0,
    "gn:timezone":"America/Port-au-Prince",
    "iso:country":"HT",
    "wof:name":"Vogues",
    "wof:placetype":"locality"
},
  "geometry": {"coordinates":[-72.06667,19.63333],"type":"Point"}
}