{
  "type": "Feature",
  "properties": {
    "gn:admin1_code":"7.0",
    "gn:admin2_code":"3720809.0",
    "gn:asciiname":"Ca Ibe",
    "gn:country_code":"HT",
    "gn:dem":473,
    "gn:feature_class":"P",
    "gn:feature_code":"PPL",
    "gn:name":"Ca Ibe",
    "gn:population":0,
    "gn:timezone":"America/Port-au-Prince",
    "iso:country":"HT",
    "wof:name":"Ca Ibe",
    "wof:placetype":"locality"
},
  "geometry": {"coordinates":[-72.08333,18.95],"type":"Point"}
}