{
  "type": "Feature",
  "properties": {
    "gn:admin1_code":"15.0",
    "gn:admin2_code":"3731122.0",
    "gn:asciiname":"Gastel",
    "gn:country_code":"HT",
    "gn:dem":391,
    "gn:feature_class":"P",
    "gn:feature_code":"PPL",
    "gn:name":"Gastel",
    "gn:population":0,
    "gn:timezone":"America/Port-au-Prince",
    "iso:country":"HT",
    "name:ceb_x_preferred":[
        "Gastel"
    ],
    "name:fra_x_preferred":[
        "Gastel"
    ],
    "name:nld_x_preferred":[
        "Gastel"
    ],
    "wof:name":"Gastel",
    "wof:placetype":"locality"
},
  "geometry": {"coordinates":[-73.52778000000001,18.47139],"type":"Point"}
}