{
  "type": "Feature",
  "properties": {
    "gn:admin1_code":"11.0",
    "gn:admin2_code":"3722285.0",
    "gn:asciiname":"Grand Bois",
    "gn:country_code":"HT",
    "gn:dem":526,
    "gn:feature_class":"P",
    "gn:feature_code":"PPL",
    "gn:name":"Grand Bois",
    "gn:population":0,
    "gn:timezone":"America/Port-au-Prince",
    "iso:country":"HT",
    "name:ceb_x_preferred":[
        "Grand Bois"
    ],
    "name:swe_x_preferred":[
        "Grand Bois"
    ],
    "wof:name":"Grand Bois",
    "wof:placetype":"locality"
},
  "geometry": {"coordinates":[-72.58333,18.38333],"type":"Point"}
}