{
  "type": "Feature",
  "properties": {
    "gn:admin1_code":"3.0",
    "gn:admin2_code":"3720764",
    "gn:asciiname":"Abricot",
    "gn:country_code":"HT",
    "gn:dem":300,
    "gn:feature_class":"P",
    "gn:feature_code":"PPL",
    "gn:name":"Abricot",
    "gn:population":0,
    "gn:timezone":"America/Port-au-Prince",
    "iso:country":"HT",
    "name:fra_x_preferred":[
        "Abricot"
    ],
    "wof:name":"Abricot",
    "wof:placetype":"locality"
},
  "geometry": {"coordinates":[-73.13946999999997,19.82709],"type":"Point"}
}