{
  "type": "Feature",
  "properties": {
    "gn:admin1_code":"6.0",
    "gn:admin2_code":"3726539.0",
    "gn:asciiname":"Marinette",
    "gn:country_code":"HT",
    "gn:dem":587,
    "gn:feature_class":"P",
    "gn:feature_code":"PPL",
    "gn:name":"Marinette",
    "gn:population":0,
    "gn:timezone":"America/Port-au-Prince",
    "iso:country":"HT",
    "name:ben_x_preferred":[
        "\u09ae\u09cd\u09af\u09b0\u09bf\u09a8\u09c7\u099f"
    ],
    "name:deu_x_preferred":[
        "Marinette"
    ],
    "name:ell_x_preferred":[
        "\u039c\u03b1\u03c1\u03b9\u03bd\u03ad\u03c4"
    ],
    "name:fra_x_preferred":[
        "Marinette"
    ],
    "name:heb_x_preferred":[
        "\u05de\u05e8\u05d9\u05e0\u05d8"
    ],
    "name:hin_x_preferred":[
        "\u092e\u0948\u0930\u0940\u0928\u0947\u091f"
    ],
    "name:ind_x_preferred":[
        "Marinette"
    ],
    "name:kor_x_preferred":[
        "\ub9c8\ub9ac\ub124\ub728"
    ],
    "name:pol_x_preferred":[
        "Marinette"
    ],
    "name:por_x_preferred":[
        "Marinette"
    ],
    "name:rus_x_preferred":[
        "\u041c\u044d\u0440\u0438\u043d\u0435\u0442\u0442"
    ],
    "name:srp_x_preferred":[
        "\u041c\u0430\u0440\u0438\u043d\u0435\u0442"
    ],
    "name:urd_x_preferred":[
        "\u0645\u06cc\u0631\u06cc\u0646\u06cc\u0679"
    ],
    "name:zho_cn_x_preferred":[
        "\u9a6c\u91cc\u5185\u7279"
    ],
    "name:zho_tw_x_preferred":[
        "\u99ac\u91cc\u5167\u7279"
    ],
    "wof:name":"Marinette",
    "wof:placetype":"locality"
},
  "geometry": {"coordinates":[-72.28333000000001,18.98333],"type":"Point"}
}