{
  "type": "Feature",
  "properties": {
    "gn:admin1_code":"9.0",
    "gn:admin2_code":"3717545.0",
    "gn:asciiname":"Nan Cienne",
    "gn:country_code":"HT",
    "gn:dem":848,
    "gn:feature_class":"P",
    "gn:feature_code":"PPL",
    "gn:name":"Nan Cienne",
    "gn:population":0,
    "gn:timezone":"America/Port-au-Prince",
    "iso:country":"HT",
    "name:fra_x_preferred":[
        "Nan Cienne"
    ],
    "wof:name":"Nan Cienne",
    "wof:placetype":"locality"
},
  "geometry": {"coordinates":[-72.24243,19.48147],"type":"Point"}
}