{
  "type": "Feature",
  "properties": {
    "gn:admin1_code":"3.0",
    "gn:admin2_code":"3720764.0",
    "gn:asciiname":"Malabe",
    "gn:country_code":"HT",
    "gn:dem":103,
    "gn:feature_class":"P",
    "gn:feature_code":"PPL",
    "gn:name":"Malabe",
    "gn:population":0,
    "gn:timezone":"America/Port-au-Prince",
    "iso:country":"HT",
    "name:sin_x_preferred":[
        "\u0db8\u0dcf\u0dbd\u0db6\u0dda"
    ],
    "name:und_x_variant":[
        "Malable",
        "Malabe"
    ],
    "wof:name":"Malabe",
    "wof:placetype":"locality"
},
  "geometry": {"coordinates":[-73.01968000000002,19.84058],"type":"Point"}
}