{
  "type": "Feature",
  "properties": {
    "gn:admin1_code":"14.0",
    "gn:admin2_code":"3727381.0",
    "gn:asciiname":"Lamentin",
    "gn:country_code":"HT",
    "gn:dem":113,
    "gn:feature_class":"P",
    "gn:feature_code":"PPL",
    "gn:name":"Lamentin",
    "gn:population":0,
    "gn:timezone":"America/Port-au-Prince",
    "iso:country":"HT",
    "name:ara_x_preferred":[
        "\u0644\u0627\u0645\u0646\u062a\u064a\u0646"
    ],
    "name:bug_x_preferred":[
        "Lamentin"
    ],
    "name:cat_x_preferred":[
        "Lamentin"
    ],
    "name:ceb_x_preferred":[
        "Lamentin"
    ],
    "name:deu_x_preferred":[
        "Lamentin"
    ],
    "name:fra_x_preferred":[
        "Lamentin"
    ],
    "name:ind_x_preferred":[
        "Lamentin"
    ],
    "name:ita_x_preferred":[
        "Lamentin"
    ],
    "name:lat_x_preferred":[
        "Lamentin"
    ],
    "name:msa_x_preferred":[
        "Lamentin"
    ],
    "name:nld_x_preferred":[
        "Lamentin"
    ],
    "name:oci_x_preferred":[
        "Lamentin"
    ],
    "name:pms_x_preferred":[
        "Lamentin"
    ],
    "name:pol_x_preferred":[
        "Lamentin"
    ],
    "name:por_x_preferred":[
        "Lamentin"
    ],
    "name:slk_x_preferred":[
        "Lamentin"
    ],
    "name:spa_x_preferred":[
        "Lamentin"
    ],
    "name:swe_x_preferred":[
        "Lamentin"
    ],
    "name:ukr_x_preferred":[
        "\u041b\u0430\u043c\u0430\u043d\u0442\u0435\u043d"
    ],
    "name:urd_x_preferred":[
        "\u0644\u0627\u0645\u06cc\u0646\u0679\u06cc\u0646"
    ],
    "name:vie_x_preferred":[
        "Lamentin"
    ],
    "name:war_x_preferred":[
        "Lamentin"
    ],
    "wof:name":"Lamentin",
    "wof:placetype":"locality"
},
  "geometry": {"coordinates":[-73.82470000000001,18.55225],"type":"Point"}
}