{
  "type": "Feature",
  "properties": {
    "gn:admin1_code":"12.0",
    "gn:admin2_code":"3728096.0",
    "gn:asciiname":"Valere",
    "gn:country_code":"HT",
    "gn:dem":15,
    "gn:feature_class":"P",
    "gn:feature_code":"PPL",
    "gn:name":"Val\u00e8re",
    "gn:population":0,
    "gn:timezone":"America/Port-au-Prince",
    "iso:country":"HT",
    "name:und_x_variant":[
        "Carrefour Val\u00e9re",
        "Val\u00e8re"
    ],
    "wof:name":"Valere",
    "wof:placetype":"locality"
},
  "geometry": {"coordinates":[-73.8556,18.12782],"type":"Point"}
}