{
  "type": "Feature",
  "properties": {
    "gn:admin1_code":"7.0",
    "gn:admin2_code":"3720809.0",
    "gn:asciiname":"Fond Laporte",
    "gn:country_code":"HT",
    "gn:dem":976,
    "gn:feature_class":"P",
    "gn:feature_code":"PPL",
    "gn:name":"Fond Laporte",
    "gn:population":0,
    "gn:timezone":"America/Port-au-Prince",
    "iso:country":"HT",
    "name:fra_x_preferred":[
        "Fond Laporte"
    ],
    "wof:name":"Fond Laporte",
    "wof:placetype":"locality"
},
  "geometry": {"coordinates":[-72.14503000000001,19.01583],"type":"Point"}
}