{
  "type": "Feature",
  "properties": {
    "gn:admin1_code":"7.0",
    "gn:admin2_code":"3728053.0",
    "gn:asciiname":"La Tablie",
    "gn:country_code":"HT",
    "gn:dem":702,
    "gn:feature_class":"P",
    "gn:feature_code":"PPL",
    "gn:name":"La Tablie",
    "gn:population":0,
    "gn:timezone":"America/Port-au-Prince",
    "iso:country":"HT",
    "wof:name":"La Tablie",
    "wof:placetype":"locality"
},
  "geometry": {"coordinates":[-71.76666999999998,19.26667],"type":"Point"}
}