{
  "type": "Feature",
  "properties": {
    "gn:country":"HT",
    "gn:fcode":"PPL",
    "gn:population":10569,
    "iso:country":"HT",
    "name:ara_x_preferred":[
        "\u062a\u0631\u0648 \u0627\u0644\u0634\u0645\u0627\u0644\u064a\u0629"
    ],
    "name:aze_x_preferred":[
        "Tru-dyu-Nor"
    ],
    "name:cat_x_preferred":[
        "Trou-du-Nord"
    ],
    "name:ceb_x_preferred":[
        "Trou du Nord"
    ],
    "name:dan_x_preferred":[
        "Trou-du-Nord"
    ],
    "name:ell_x_preferred":[
        "\u03a4\u03c1\u03bf\u03c5-\u03bd\u03c4\u03c5-\u039d\u03bf\u03c1"
    ],
    "name:eng_x_preferred":[
        "Trou-du-Nord"
    ],
    "name:fra_x_preferred":[
        "Trou-du-Nord"
    ],
    "name:gle_x_preferred":[
        "Trou-du-Nord"
    ],
    "name:hat_x_preferred":[
        "Trou di N\u00f2"
    ],
    "name:hat_x_variant":[
        "Twou din\u00f2"
    ],
    "name:heb_x_preferred":[
        "\u05d8\u05e8\u05d5-\u05d3\u05d9-\u05e0\u05d5\u05e8"
    ],
    "name:ita_x_preferred":[
        "Trou-du-Nord"
    ],
    "name:jpn_x_preferred":[
        "\u30c8\u30a5\u30eb\u30fb\u30c7\u30e5\u30fb\u30ce\u30fc\u30eb"
    ],
    "name:ltz_x_preferred":[
        "Trou-du-Nord"
    ],
    "name:nan_x_preferred":[
        "Trou-du-Nord"
    ],
    "name:nld_x_preferred":[
        "Trou-du-Nord"
    ],
    "name:pol_x_preferred":[
        "Trou-du-Nord"
    ],
    "name:por_x_preferred":[
        "Trou-du-Nord"
    ],
    "name:ron_x_preferred":[
        "Trou-du-Nord"
    ],
    "name:rus_x_preferred":[
        "\u0422\u0440\u0443-\u0434\u044e-\u041d\u043e\u0440"
    ],
    "name:spa_x_preferred":[
        "Trou-du-Nord"
    ],
    "name:swe_x_preferred":[
        "Trou du Nord"
    ],
    "name:szl_x_preferred":[
        "Trou-du-Nord"
    ],
    "name:tgk_x_preferred":[
        "\u0422\u0440\u0443-\u0434\u044e-\u041d\u043e\u0440\u0434"
    ],
    "name:und_x_variant":[
        "Le Trou"
    ],
    "name:zho_x_preferred":[
        "\u7279\u9b6f\u675c\u5317"
    ],
    "qs:name":"Trou du Nord",
    "qs:photos_9r":0,
    "qs:photos_sr":0,
    "qs:pop_sr":"6",
    "wd:wordcount":58,
    "wof:name":"Trou du Nord",
    "wof:placetype":"locality",
    "wof:population":10569
},
  "geometry": {"coordinates":[-72.01667,19.63333],"type":"Point"}
}