{
  "type": "Feature",
  "properties": {
    "gn:country":"HT",
    "gn:fcode":"PPL",
    "gn:pop":10569,
    "iso:country":"HT",
    "name:ara_x_preferred":[
        "\u062a\u0631\u0648 \u0627\u0644\u0634\u0645\u0627\u0644\u064a\u0629"
    ],
    "name:eng_x_preferred":[
        "Trou-du-Nord"
    ],
    "name:fra_x_preferred":[
        "Trou-du-Nord"
    ],
    "name:hat_x_preferred":[
        "Trou di N\u00f2"
    ],
    "name:ita_x_preferred":[
        "Trou-du-Nord"
    ],
    "name:nld_x_preferred":[
        "Trou-du-Nord"
    ],
    "name:pol_x_preferred":[
        "Trou-du-Nord"
    ],
    "name:por_x_preferred":[
        "Trou-du-Nord"
    ],
    "name:ron_x_preferred":[
        "Trou-du-Nord"
    ],
    "name:rus_x_preferred":[
        "\u0422\u0440\u0443-\u0434\u044e-\u041d\u043e\u0440"
    ],
    "name:unk_x_variant":[
        "Le Trou"
    ],
    "name:zho_x_preferred":[
        "\u7279\u9b6f\u675c\u5317"
    ],
    "qs:name":"Trou du Nord",
    "qs:photos_9r":0,
    "qs:photos_sr":0,
    "qs:pop_sr":"6",
    "wd:wordcount":58,
    "wof:name":"Trou du Nord",
    "wof:placetype":"locality",
    "wof:population":10569
},
  "geometry": {"coordinates":[-72.01667,19.63333],"type":"Point"}
}