{
  "type": "Feature",
  "properties": {
    "gn:admin1_code":"10.0",
    "gn:admin2_code":"3716223.0",
    "gn:asciiname":"La Tres Sainte",
    "gn:country_code":"HT",
    "gn:dem":348,
    "gn:feature_class":"P",
    "gn:feature_code":"PPL",
    "gn:name":"La Tr\u00e8s Sainte",
    "gn:population":0,
    "gn:timezone":"America/Port-au-Prince",
    "iso:country":"HT",
    "wof:name":"La Tres Sainte",
    "wof:placetype":"locality"
},
  "geometry": {"coordinates":[-72.09999999999999,19.58333],"type":"Point"}
}