{
  "type": "Feature",
  "properties": {
    "gn:admin1_code":"6.0",
    "gn:admin2_code":"3717587.0",
    "gn:asciiname":"Bellon",
    "gn:country_code":"HT",
    "gn:dem":456,
    "gn:feature_class":"P",
    "gn:feature_code":"PPL",
    "gn:name":"Bellon",
    "gn:population":0,
    "gn:timezone":"America/Port-au-Prince",
    "iso:country":"HT",
    "name:fra_x_preferred":[
        "Bellon"
    ],
    "wof:name":"Bellon",
    "wof:placetype":"locality"
},
  "geometry": {"coordinates":[-72.34578,18.88669],"type":"Point"}
}