{
  "type": "Feature",
  "properties": {
    "gn:admin1_code":"7.0",
    "gn:admin2_code":"3723840.0",
    "gn:asciiname":"Mauric",
    "gn:country_code":"HT",
    "gn:dem":243,
    "gn:feature_class":"P",
    "gn:feature_code":"PPL",
    "gn:name":"Mauric",
    "gn:population":0,
    "gn:timezone":"America/Port-au-Prince",
    "iso:country":"HT",
    "wof:name":"Mauric",
    "wof:placetype":"locality"
},
  "geometry": {"coordinates":[-72.01666999999998,19.16667],"type":"Point"}
}