{
  "type": "Feature",
  "properties": {
    "gn:admin1_code":"12.0",
    "gn:admin2_code":"3731094.0",
    "gn:asciiname":"Charles Roy",
    "gn:country_code":"HT",
    "gn:dem":568,
    "gn:feature_class":"P",
    "gn:feature_code":"PPL",
    "gn:name":"Charles Roy",
    "gn:population":0,
    "gn:timezone":"America/Port-au-Prince",
    "iso:country":"HT",
    "wof:name":"Charles Roy",
    "wof:placetype":"locality"
},
  "geometry": {"coordinates":[-73.56667,18.35],"type":"Point"}
}