{
  "type": "Feature",
  "properties": {
    "gn:admin1_code":"12.0",
    "gn:admin2_code":"3728096.0",
    "gn:asciiname":"Pour",
    "gn:country_code":"HT",
    "gn:dem":298,
    "gn:feature_class":"P",
    "gn:feature_code":"PPL",
    "gn:name":"Pour",
    "gn:population":0,
    "gn:timezone":"America/Port-au-Prince",
    "iso:country":"HT",
    "name:ces_x_preferred":[
        "Pour"
    ],
    "name:deu_x_preferred":[
        "Pour"
    ],
    "name:fra_x_preferred":[
        "Pour"
    ],
    "wof:name":"Pour",
    "wof:placetype":"locality"
},
  "geometry": {"coordinates":[-73.91667,18.23333],"type":"Point"}
}