{
  "type": "Feature",
  "properties": {
    "gn:admin1_code":"11.0",
    "gn:admin2_code":"3723019.0",
    "gn:asciiname":"Trou Jacques",
    "gn:country_code":"HT",
    "gn:dem":5,
    "gn:feature_class":"P",
    "gn:feature_code":"PPL",
    "gn:name":"Trou Jacques",
    "gn:population":0,
    "gn:timezone":"America/Port-au-Prince",
    "iso:country":"HT",
    "name:fra_x_preferred":[
        "Trou Jacques"
    ],
    "wof:name":"Trou Jacques",
    "wof:placetype":"locality"
},
  "geometry": {"coordinates":[-72.91632,18.73913],"type":"Point"}
}