{
  "type": "Feature",
  "properties": {
    "gn:admin1_code":"7.0",
    "gn:asciiname":"Bodian",
    "gn:country_code":"HT",
    "gn:dem":248,
    "gn:feature_class":"P",
    "gn:feature_code":"PPL",
    "gn:name":"Bodian",
    "gn:population":0,
    "gn:timezone":"America/Port-au-Prince",
    "iso:country":"HT",
    "name:fra_x_preferred":[
        "Bodian"
    ],
    "wof:name":"Bodian",
    "wof:placetype":"locality"
},
  "geometry": {"coordinates":[-72.2239,18.92693],"type":"Point"}
}