{
  "type": "Feature",
  "properties": {
    "gn:admin1_code":"6.0",
    "gn:admin2_code":"3726539.0",
    "gn:asciiname":"Martin",
    "gn:country_code":"HT",
    "gn:dem":28,
    "gn:feature_class":"P",
    "gn:feature_code":"PPL",
    "gn:name":"Martin",
    "gn:population":0,
    "gn:timezone":"America/Port-au-Prince",
    "iso:country":"HT",
    "name:und_x_variant":[
        "Martio",
        "Martin"
    ],
    "wof:name":"Martin",
    "wof:placetype":"locality"
},
  "geometry": {"coordinates":[-72.47306,19.1812],"type":"Point"}
}