{
  "type": "Feature",
  "properties": {
    "gn:admin1_code":"13.0",
    "gn:admin2_code":"3723778.0",
    "gn:asciiname":"L'Eau Calme",
    "gn:country_code":"HT",
    "gn:dem":11,
    "gn:feature_class":"P",
    "gn:feature_code":"PPL",
    "gn:name":"L\u2019Eau Calme",
    "gn:population":0,
    "gn:timezone":"America/Port-au-Prince",
    "iso:country":"HT",
    "wof:name":"L'Eau Calme",
    "wof:placetype":"locality"
},
  "geometry": {"coordinates":[-72.55,18.23167],"type":"Point"}
}