{
  "type": "Feature",
  "properties": {
    "gn:admin1_code":"3.0",
    "gn:admin2_code":"3720764.0",
    "gn:asciiname":"Nan Digo",
    "gn:country_code":"HT",
    "gn:dem":23,
    "gn:feature_class":"P",
    "gn:feature_code":"PPL",
    "gn:name":"Nan Digo",
    "gn:population":0,
    "gn:timezone":"America/Port-au-Prince",
    "iso:country":"HT",
    "wof:name":"Nan Digo",
    "wof:placetype":"locality"
},
  "geometry": {"coordinates":[-73.26666999999998,19.86667000000001],"type":"Point"}
}