{
  "type": "Feature",
  "properties": {
    "gn:admin1_code":"7.0",
    "gn:asciiname":"Bois Neuf",
    "gn:cc2":"HT",
    "gn:country_code":"HT",
    "gn:dem":733,
    "gn:feature_class":"P",
    "gn:feature_code":"PPL",
    "gn:name":"Bois Neuf",
    "gn:population":0,
    "gn:timezone":"America/Port-au-Prince",
    "iso:country":"HT",
    "name:und_x_variant":[
        "Bois Neut",
        "Bois Neuf"
    ],
    "wof:name":"Bois Neuf",
    "wof:placetype":"locality"
},
  "geometry": {"coordinates":[-72.31667,19.15],"type":"Point"}
}