{
  "type": "Feature",
  "properties": {
    "gn:admin1_code":"10.0",
    "gn:asciiname":"Gramand",
    "gn:country_code":"HT",
    "gn:dem":632,
    "gn:feature_class":"P",
    "gn:feature_code":"PPL",
    "gn:name":"Gramand",
    "gn:population":0,
    "gn:timezone":"America/Port-au-Prince",
    "iso:country":"HT",
    "wof:name":"Gramand",
    "wof:placetype":"locality"
},
  "geometry": {"coordinates":[-71.98333000000002,19.35],"type":"Point"}
}