{
  "type": "Feature",
  "properties": {
    "gn:admin1_code":"7.0",
    "gn:asciiname":"Bourgeois",
    "gn:country_code":"HT",
    "gn:dem":488,
    "gn:feature_class":"P",
    "gn:feature_code":"PPL",
    "gn:name":"Bourgeois",
    "gn:population":0,
    "gn:timezone":"America/Port-au-Prince",
    "iso:country":"HT",
    "name:fra_x_preferred":[
        "Bourgeois"
    ],
    "wof:name":"Bourgeois",
    "wof:placetype":"locality"
},
  "geometry": {"coordinates":[-71.92371,19.27645],"type":"Point"}
}