{
  "type": "Feature",
  "properties": {
    "gn:admin1_code":"6.0",
    "gn:admin2_code":"3717563.0",
    "gn:asciiname":"Ravine Fond",
    "gn:country_code":"HT",
    "gn:dem":410,
    "gn:feature_class":"P",
    "gn:feature_code":"PPL",
    "gn:name":"Ravine Fond",
    "gn:population":0,
    "gn:timezone":"America/Port-au-Prince",
    "iso:country":"HT",
    "wof:name":"Ravine Fond",
    "wof:placetype":"locality"
},
  "geometry": {"coordinates":[-72.31667,19.35],"type":"Point"}
}