{
  "type": "Feature",
  "properties": {
    "gn:admin1_code":"3.0",
    "gn:admin2_code":"3720764.0",
    "gn:asciiname":"Trou Jules",
    "gn:country_code":"HT",
    "gn:dem":84,
    "gn:feature_class":"P",
    "gn:feature_code":"PPL",
    "gn:name":"Trou Jules",
    "gn:population":0,
    "gn:timezone":"America/Port-au-Prince",
    "iso:country":"HT",
    "wof:name":"Trou Jules",
    "wof:placetype":"locality"
},
  "geometry": {"coordinates":[-73.15056,19.86639],"type":"Point"}
}