{
  "type": "Feature",
  "properties": {
    "gn:admin1_code":"9.0",
    "gn:admin2_code":"3728473.0",
    "gn:asciiname":"Pica",
    "gn:country_code":"HT",
    "gn:dem":362,
    "gn:feature_class":"P",
    "gn:feature_code":"PPL",
    "gn:name":"Pica",
    "gn:population":0,
    "gn:timezone":"America/Port-au-Prince",
    "iso:country":"HT",
    "wof:name":"Pica",
    "wof:placetype":"locality"
},
  "geometry": {"coordinates":[-72.21805999999999,19.76194],"type":"Point"}
}