{
  "type": "Feature",
  "properties": {
    "gn:admin1_code":"9.0",
    "gn:admin2_code":"3718665.0",
    "gn:asciiname":"Bellande",
    "gn:country_code":"HT",
    "gn:dem":356,
    "gn:feature_class":"P",
    "gn:feature_code":"PPL",
    "gn:name":"Bellande",
    "gn:population":0,
    "gn:timezone":"America/Port-au-Prince",
    "iso:country":"HT",
    "name:fra_x_preferred":[
        "Bellande"
    ],
    "wof:name":"Bellande",
    "wof:placetype":"locality"
},
  "geometry": {"coordinates":[-72.55394,19.68532],"type":"Point"}
}