{
  "type": "Feature",
  "properties": {
    "iso:country":"HT",
    "name:ara_x_preferred":[
        "\u0644\u064a\u0633 \u0623\u0646\u062c\u0644\u064a\u0633"
    ],
    "name:cat_x_preferred":[
        "Les Anglais"
    ],
    "name:ceb_x_preferred":[
        "Les Anglais"
    ],
    "name:eng_x_preferred":[
        "Les Anglais"
    ],
    "name:fra_x_preferred":[
        "Les Anglais"
    ],
    "name:hat_x_preferred":[
        "Zangl\u00e8"
    ],
    "name:hun_x_preferred":[
        "Les Anglais"
    ],
    "name:ita_x_preferred":[
        "Les Anglais"
    ],
    "name:nld_x_preferred":[
        "Les Anglais"
    ],
    "name:por_x_preferred":[
        "Les Anglais"
    ],
    "name:ron_x_preferred":[
        "Les Anglais"
    ],
    "name:spa_x_preferred":[
        "Les Anglais"
    ],
    "name:swe_x_preferred":[
        "Les Anglais"
    ],
    "name:unk_x_variant":[
        "Anglais"
    ],
    "name:zho_x_preferred":[
        "\u82f1\u4eba\u6751"
    ],
    "qs:gn_country":"HT",
    "qs:gn_fcode":"PPL",
    "qs:gn_pop":8247,
    "qs:name":"Les Anglais",
    "qs:name_adm0":"Ha\u00efti",
    "qs:name_adm1":"Sud",
    "qs:photos":0,
    "qs:photos_1k":0,
    "qs:photos_9k":1,
    "qs:photos_9r":1,
    "qs:photos_all":3,
    "qs:photos_sr":0,
    "qs:placetype":"Town",
    "qs:pop_sr":"5",
    "qs:woe_adm0":23424839,
    "wd:wordcount":41,
    "wof:name":"Les Anglais",
    "wof:placetype":"locality",
    "wof:population":8247
},
  "geometry": {"coordinates":[-74.21968,18.3054],"type":"Point"}
}