{
  "type": "Feature",
  "properties": {
    "gn:admin1_code":"12.0",
    "gn:asciiname":"Lacour",
    "gn:country_code":"HT",
    "gn:dem":16,
    "gn:feature_class":"P",
    "gn:feature_code":"PPL",
    "gn:name":"Lacour",
    "gn:population":0,
    "gn:timezone":"America/Port-au-Prince",
    "iso:country":"HT",
    "name:ceb_x_preferred":[
        "Lacour"
    ],
    "name:deu_x_preferred":[
        "Lacour"
    ],
    "name:eus_x_preferred":[
        "Lacour"
    ],
    "name:fra_x_preferred":[
        "Lacour"
    ],
    "name:hun_x_preferred":[
        "Lacour"
    ],
    "name:ita_x_preferred":[
        "Lacour"
    ],
    "name:lat_x_preferred":[
        "Lacour"
    ],
    "name:mlg_x_preferred":[
        "Lacour"
    ],
    "name:msa_x_preferred":[
        "Lacour"
    ],
    "name:nld_x_preferred":[
        "Lacour"
    ],
    "name:oci_x_preferred":[
        "La Cort"
    ],
    "name:pms_x_preferred":[
        "Lacour"
    ],
    "name:pol_x_preferred":[
        "Lacour"
    ],
    "name:por_x_preferred":[
        "Lacour"
    ],
    "name:ron_x_preferred":[
        "Lacour"
    ],
    "name:slk_x_preferred":[
        "Lacour"
    ],
    "name:spa_x_preferred":[
        "Lacour"
    ],
    "name:swe_x_preferred":[
        "Lacour"
    ],
    "name:ukr_x_preferred":[
        "\u041b\u0430\u043a\u0443\u0440"
    ],
    "name:urd_x_preferred":[
        "\u0644\u0627\u06a9\u0648\u0631"
    ],
    "name:vie_x_preferred":[
        "Lacour"
    ],
    "name:vol_x_preferred":[
        "Lacour"
    ],
    "name:war_x_preferred":[
        "Lacour"
    ],
    "wof:name":"Lacour",
    "wof:placetype":"locality"
},
  "geometry": {"coordinates":[-73.66667,18.23333],"type":"Point"}
}