{
  "type": "Feature",
  "properties": {
    "gn:admin1_code":"11.0",
    "gn:admin2_code":"3727134.0",
    "gn:asciiname":"Grand Rack",
    "gn:country_code":"HT",
    "gn:dem":801,
    "gn:feature_class":"P",
    "gn:feature_code":"PPL",
    "gn:name":"Grand Rack",
    "gn:population":0,
    "gn:timezone":"America/Port-au-Prince",
    "iso:country":"HT",
    "name:fra_x_preferred":[
        "Grand Rock"
    ],
    "wof:name":"Grand Rack",
    "wof:placetype":"locality"
},
  "geometry": {"coordinates":[-72.08381999999997,18.44756],"type":"Point"}
}