{
  "type": "Feature",
  "properties": {
    "gn:admin1_code":"9.0",
    "gn:admin2_code":"3731232.0",
    "gn:asciiname":"Beloten",
    "gn:country_code":"HT",
    "gn:dem":14,
    "gn:feature_class":"P",
    "gn:feature_code":"PPL",
    "gn:name":"Beloten",
    "gn:population":0,
    "gn:timezone":"America/Port-au-Prince",
    "iso:country":"HT",
    "name:fra_x_preferred":[
        "Beloten"
    ],
    "wof:name":"Beloten",
    "wof:placetype":"locality"
},
  "geometry": {"coordinates":[-72.3301,19.70998],"type":"Point"}
}