{
  "type": "Feature",
  "properties": {
    "gn:admin1_code":"11.0",
    "gn:admin2_code":"3722285.0",
    "gn:asciiname":"Carrefour Fauche",
    "gn:cc2":"HT",
    "gn:country_code":"HT",
    "gn:dem":130,
    "gn:feature_class":"P",
    "gn:feature_code":"PPL",
    "gn:name":"Carrefour Fauch\u00e9",
    "gn:population":0,
    "gn:timezone":"America/Port-au-Prince",
    "iso:country":"HT",
    "name:und_x_variant":[
        "Carrefour Faucheux",
        "Carrefour Fauch\u00e9"
    ],
    "wof:name":"Carrefour Fauche",
    "wof:placetype":"locality"
},
  "geometry": {"coordinates":[-72.71666999999999,18.41667],"type":"Point"}
}