{
  "type": "Feature",
  "properties": {
    "gn:admin1_code":"14.0",
    "gn:admin2_code":"3727381.0",
    "gn:asciiname":"Nan Latanier",
    "gn:country_code":"HT",
    "gn:dem":573,
    "gn:feature_class":"P",
    "gn:feature_code":"PPL",
    "gn:name":"Nan Latanier",
    "gn:population":0,
    "gn:timezone":"America/Port-au-Prince",
    "iso:country":"HT",
    "name:fra_x_preferred":[
        "Nan Latanier"
    ],
    "wof:name":"Nan Latanier",
    "wof:placetype":"locality"
},
  "geometry": {"coordinates":[-73.87113000000002,18.47776],"type":"Point"}
}