{
  "type": "Feature",
  "properties": {
    "gn:admin1_code":"10.0",
    "gn:asciiname":"Roche Plate",
    "gn:country_code":"HT",
    "gn:dem":74,
    "gn:feature_class":"P",
    "gn:feature_code":"PPL",
    "gn:name":"Roche Plate",
    "gn:population":0,
    "gn:timezone":"America/Port-au-Prince",
    "iso:country":"HT",
    "name:fra_x_preferred":[
        "Roche Plate"
    ],
    "wof:name":"Roche Plate",
    "wof:placetype":"locality"
},
  "geometry": {"coordinates":[-71.98498000000002,19.56227],"type":"Point"}
}