{
  "type": "Feature",
  "properties": {
    "gn:admin1_code":"14.0",
    "gn:admin2_code":"3723592.0",
    "gn:asciiname":"Lavalace",
    "gn:country_code":"HT",
    "gn:dem":313,
    "gn:feature_class":"P",
    "gn:feature_code":"PPL",
    "gn:name":"Lavalace",
    "gn:population":0,
    "gn:timezone":"America/Port-au-Prince",
    "iso:country":"HT",
    "name:fra_x_preferred":[
        "Lavalace"
    ],
    "wof:name":"Lavalace",
    "wof:placetype":"locality"
},
  "geometry": {"coordinates":[-74.25135,18.58011],"type":"Point"}
}