{
  "type": "Feature",
  "properties": {
    "gn:admin1_code":"9.0",
    "gn:admin2_code":"3718665.0",
    "gn:asciiname":"Place",
    "gn:country_code":"HT",
    "gn:dem":393,
    "gn:feature_class":"P",
    "gn:feature_code":"PPL",
    "gn:name":"Place",
    "gn:population":0,
    "gn:timezone":"America/Port-au-Prince",
    "iso:country":"HT",
    "name:ceb_x_preferred":[
        "Place"
    ],
    "name:deu_x_preferred":[
        "Place"
    ],
    "name:fra_x_preferred":[
        "Place"
    ],
    "name:heb_x_preferred":[
        "\u05de\u05e7\u05d5\u05dd"
    ],
    "name:kor_x_preferred":[
        "\ud50c\ub808\uc774\uc2a4"
    ],
    "name:nld_x_preferred":[
        "Place"
    ],
    "name:por_x_preferred":[
        "Place"
    ],
    "name:swe_x_preferred":[
        "Place"
    ],
    "name:ukr_x_preferred":[
        "\u041c\u0456\u0441\u0446\u0435"
    ],
    "wof:name":"Place",
    "wof:placetype":"locality"
},
  "geometry": {"coordinates":[-72.51666999999998,19.63333],"type":"Point"}
}