{
  "type": "Feature",
  "properties": {
    "gn:admin1_code":"10.0",
    "gn:admin2_code":"3725169.0",
    "gn:asciiname":"Casimir",
    "gn:country_code":"HT",
    "gn:dem":24,
    "gn:feature_class":"P",
    "gn:feature_code":"PPL",
    "gn:name":"Casimir",
    "gn:population":0,
    "gn:timezone":"America/Port-au-Prince",
    "iso:country":"HT",
    "name:fra_x_preferred":[
        "Casimir"
    ],
    "wof:name":"Casimir",
    "wof:placetype":"locality"
},
  "geometry": {"coordinates":[-71.78870999999999,19.60191],"type":"Point"}
}