{
  "type": "Feature",
  "properties": {
    "gn:admin1_code":"10.0",
    "gn:admin2_code":"3725169.0",
    "gn:asciiname":"Casimir",
    "gn:country_code":"HT",
    "gn:dem":24,
    "gn:feature_class":"P",
    "gn:feature_code":"PPL",
    "gn:name":"Casimir",
    "gn:population":0,
    "gn:timezone":"America/Port-au-Prince",
    "iso:country":"HT",
    "name:bel_x_preferred":[
        "\u041a\u0430\u0437\u0456\u043c\u0456\u0440"
    ],
    "name:deu_x_preferred":[
        "Kasimir"
    ],
    "name:fin_x_preferred":[
        "Kasimir"
    ],
    "name:fra_x_preferred":[
        "Casimir"
    ],
    "name:jpn_x_preferred":[
        "\u30ab\u30b8\u30df\u30fc\u30eb"
    ],
    "name:nld_x_preferred":[
        "Casimir"
    ],
    "name:rus_x_preferred":[
        "\u041a\u0430\u0437\u0438\u043c\u0438\u0440"
    ],
    "name:swe_x_preferred":[
        "Kasimir"
    ],
    "name:ukr_x_preferred":[
        "\u041a\u0430\u0437\u0438\u043c\u0438\u0440"
    ],
    "name:zho_x_preferred":[
        "\u5361\u9f50\u7c73\u65e5"
    ],
    "wof:name":"Casimir",
    "wof:placetype":"locality"
},
  "geometry": {"coordinates":[-71.78870999999999,19.60191],"type":"Point"}
}