{
  "type": "Feature",
  "properties": {
    "gn:admin1_code":"6.0",
    "gn:admin2_code":"3724695.0",
    "gn:asciiname":"La Coupe",
    "gn:country_code":"HT",
    "gn:dem":164,
    "gn:feature_class":"P",
    "gn:feature_code":"PPL",
    "gn:name":"La Coupe",
    "gn:population":0,
    "gn:timezone":"America/Port-au-Prince",
    "iso:country":"HT",
    "name:fra_x_preferred":[
        "La Coupe"
    ],
    "wof:name":"La Coupe",
    "wof:placetype":"locality"
},
  "geometry": {"coordinates":[-72.58660999999999,19.53207],"type":"Point"}
}