{
  "type": "Feature",
  "properties": {
    "gn:country":"HT",
    "gn:fcode":"PPL",
    "gn:pop":1528,
    "iso:country":"HT",
    "name:ara_x_preferred":[
        "\u0633\u0627\u0646\u062a \u0644\u0648\u064a\u0633 \u0627\u0644\u062c\u0646\u0648\u0628\u064a\u0629"
    ],
    "name:eng_x_preferred":[
        "Saint-Louis-du-Sud"
    ],
    "name:fra_x_preferred":[
        "Saint-Louis-du-Sud"
    ],
    "name:hat_x_preferred":[
        "Sen Lwi di Sid"
    ],
    "name:hat_x_variant":[
        "Sen Lwi disid"
    ],
    "name:ita_x_preferred":[
        "Saint-Louis-du-Sud"
    ],
    "name:jpn_x_preferred":[
        "\u30b5\u30f3\uff1d\u30eb\u30a4\uff1d\u30c7\u30e5\uff1d\u30b7\u30e5\u30c9"
    ],
    "name:nld_x_preferred":[
        "Saint-Louis-du-Sud"
    ],
    "name:pol_x_preferred":[
        "Saint-Louis-du-Sud"
    ],
    "name:ron_x_preferred":[
        "Saint-Louis-du-Sud"
    ],
    "name:spa_x_preferred":[
        "Saint-Louis-du-Sud"
    ],
    "name:unk_x_variant":[
        "Saint Louis"
    ],
    "name:urd_x_preferred":[
        "\u0633\u06cc\u0646\u0679-\u0644\u0648\u0626\u06cc\u0633-\u062f\u0648-\u0633\u0648\u062f"
    ],
    "qs:name":"Saint-Louis du Sud",
    "qs:photos_9r":0,
    "qs:photos_sr":0,
    "qs:pop_sr":"3",
    "wd:wordcount":60,
    "wof:name":"Saint-Louis du Sud",
    "wof:placetype":"locality",
    "wof:population":1528
},
  "geometry": {"coordinates":[-73.55,18.26667],"type":"Point"}
}