{
  "type": "Feature",
  "properties": {
    "gn:country":"HT",
    "gn:fcode":"PPL",
    "gn:pop":1528,
    "iso:country":"HT",
    "name:hat_x_preferred":[
        "Sen Lwi di Sid"
    ],
    "name:unk_x_variant":[
        "Saint Louis"
    ],
    "qs:name":"Saint-Louis du Sud",
    "qs:photos_9r":0,
    "qs:photos_sr":0,
    "qs:pop_sr":"3",
    "wd:wordcount":60,
    "wof:name":"Saint-Louis du Sud",
    "wof:placetype":"locality",
    "wof:population":1528
},
  "geometry": {"coordinates":[-73.55,18.26667],"type":"Point"}
}