{
  "type": "Feature",
  "properties": {
    "gn:admin1_code":"11.0",
    "gn:admin2_code":"3722285.0",
    "gn:asciiname":"Mardi Gras",
    "gn:country_code":"HT",
    "gn:dem":254,
    "gn:feature_class":"P",
    "gn:feature_code":"PPL",
    "gn:name":"Mardi Gras",
    "gn:population":0,
    "gn:timezone":"America/Port-au-Prince",
    "iso:country":"HT",
    "wof:name":"Mardi Gras",
    "wof:placetype":"locality"
},
  "geometry": {"coordinates":[-72.53333000000001,18.46667],"type":"Point"}
}