{
  "type": "Feature",
  "properties": {
    "gn:admin1_code":"13.0",
    "gn:admin2_code":"3730361.0",
    "gn:asciiname":"Blecke",
    "gn:cc2":"HT",
    "gn:country_code":"HT",
    "gn:dem":762,
    "gn:feature_class":"P",
    "gn:feature_code":"PPL",
    "gn:name":"Blecke",
    "gn:population":0,
    "gn:timezone":"America/Port-au-Prince",
    "iso:country":"HT",
    "name:und_x_variant":[
        "Bleck",
        "Blecke"
    ],
    "wof:name":"Blecke",
    "wof:placetype":"locality"
},
  "geometry": {"coordinates":[-71.84999999999999,18.21667],"type":"Point"}
}