{
  "type": "Feature",
  "properties": {
    "gn:admin1_code":"3.0",
    "gn:asciiname":"La Tendrie",
    "gn:country_code":"HT",
    "gn:dem":7,
    "gn:feature_class":"P",
    "gn:feature_code":"PPL",
    "gn:name":"La Tendrie",
    "gn:population":0,
    "gn:timezone":"America/Port-au-Prince",
    "iso:country":"HT",
    "name:fra_x_preferred":[
        "La Tendric"
    ],
    "wof:name":"La Tendrie",
    "wof:placetype":"locality"
},
  "geometry": {"coordinates":[-72.84989,19.94048],"type":"Point"}
}