{
  "type": "Feature",
  "properties": {
    "gn:admin1_code":"12.0",
    "gn:admin2_code":"3718404.0",
    "gn:asciiname":"Bassin",
    "gn:country_code":"HT",
    "gn:dem":261,
    "gn:feature_class":"P",
    "gn:feature_code":"PPL",
    "gn:name":"Bassin",
    "gn:population":0,
    "gn:timezone":"America/Port-au-Prince",
    "iso:country":"HT",
    "name:fra_x_preferred":[
        "Bassin"
    ],
    "name:nld_x_preferred":[
        "Bassin"
    ],
    "name:spa_x_preferred":[
        "Bassin"
    ],
    "wof:name":"Bassin",
    "wof:placetype":"locality"
},
  "geometry": {"coordinates":[-73.89333000000001,18.13889],"type":"Point"}
}