{
  "type": "Feature",
  "properties": {
    "gn:admin1_code":"6.0",
    "gn:admin2_code":"3724144.0",
    "gn:asciiname":"Ti Fond",
    "gn:country_code":"HT",
    "gn:dem":418,
    "gn:feature_class":"P",
    "gn:feature_code":"PPL",
    "gn:name":"Ti Fond",
    "gn:population":0,
    "gn:timezone":"America/Port-au-Prince",
    "iso:country":"HT",
    "name:fra_x_preferred":[
        "Ti Fond"
    ],
    "wof:name":"Ti Fond",
    "wof:placetype":"locality"
},
  "geometry": {"coordinates":[-72.76082,19.63605],"type":"Point"}
}