{
  "type": "Feature",
  "properties": {
    "gn:admin1_code":"10.0",
    "gn:admin2_code":"3716114.0",
    "gn:asciiname":"Maledemon",
    "gn:country_code":"HT",
    "gn:dem":656,
    "gn:feature_class":"P",
    "gn:feature_code":"PPL",
    "gn:name":"Maledemon",
    "gn:population":0,
    "gn:timezone":"America/Port-au-Prince",
    "iso:country":"HT",
    "wof:name":"Maledemon",
    "wof:placetype":"locality"
},
  "geometry": {"coordinates":[-71.88333,19.45],"type":"Point"}
}