{
  "type": "Feature",
  "properties": {
    "gn:admin1_code":"3.0",
    "gn:admin2_code":"3717599.0",
    "gn:asciiname":"Desgranges",
    "gn:country_code":"HT",
    "gn:dem":20,
    "gn:feature_class":"P",
    "gn:feature_code":"PPL",
    "gn:name":"Desgranges",
    "gn:population":0,
    "gn:timezone":"America/Port-au-Prince",
    "iso:country":"HT",
    "name:fra_x_preferred":[
        "Desgranges"
    ],
    "wof:name":"Desgranges",
    "wof:placetype":"locality"
},
  "geometry": {"coordinates":[-72.70768000000002,19.92448],"type":"Point"}
}