{
  "type": "Feature",
  "properties": {
    "gn:admin1_code":"9.0",
    "gn:admin2_code":"3718665.0",
    "gn:asciiname":"Laporte",
    "gn:country_code":"HT",
    "gn:dem":631,
    "gn:feature_class":"P",
    "gn:feature_code":"PPL",
    "gn:name":"Laporte",
    "gn:population":0,
    "gn:timezone":"America/Port-au-Prince",
    "iso:country":"HT",
    "name:cat_x_preferred":[
        "Laporte"
    ],
    "name:ceb_x_preferred":[
        "Laporte"
    ],
    "name:deu_x_preferred":[
        "Laporte"
    ],
    "name:fra_x_preferred":[
        "Laporte"
    ],
    "name:ita_x_preferred":[
        "Laporte"
    ],
    "name:pol_x_preferred":[
        "Laporte"
    ],
    "name:por_x_preferred":[
        "Laporte"
    ],
    "name:rus_x_preferred":[
        "\u041b\u0430\u043f\u043e\u0440\u0442"
    ],
    "name:spa_x_preferred":[
        "Laporte"
    ],
    "name:srp_x_preferred":[
        "\u041b\u0430 \u041f\u043e\u0440\u0442"
    ],
    "name:ukr_x_preferred":[
        "\u041b\u0430\u043f\u043e\u0440\u0442"
    ],
    "name:vol_x_preferred":[
        "Laporte"
    ],
    "wof:name":"Laporte",
    "wof:placetype":"locality"
},
  "geometry": {"coordinates":[-72.58403,19.73388],"type":"Point"}
}