{
  "type": "Feature",
  "properties": {
    "gn:admin1_code":"6.0",
    "gn:admin2_code":"3726539.0",
    "gn:asciiname":"Noailles",
    "gn:country_code":"HT",
    "gn:dem":74,
    "gn:feature_class":"P",
    "gn:feature_code":"PPL",
    "gn:name":"Noailles",
    "gn:population":0,
    "gn:timezone":"America/Port-au-Prince",
    "iso:country":"HT",
    "name:cat_x_preferred":[
        "Noailles"
    ],
    "name:ceb_x_preferred":[
        "Noailles"
    ],
    "name:deu_x_preferred":[
        "Noailles"
    ],
    "name:eus_x_preferred":[
        "Noailles"
    ],
    "name:fra_x_preferred":[
        "Noailles"
    ],
    "name:ita_x_preferred":[
        "Noailles"
    ],
    "name:jpn_x_preferred":[
        "\u30ce\u30a2\u30a4\u30e6"
    ],
    "name:nds_x_preferred":[
        "Noailles"
    ],
    "name:nld_x_preferred":[
        "Noailles"
    ],
    "name:oci_x_preferred":[
        "Noailles"
    ],
    "name:pms_x_preferred":[
        "Noailles"
    ],
    "name:pol_x_preferred":[
        "Noailles"
    ],
    "name:por_x_preferred":[
        "Noailles"
    ],
    "name:rus_x_preferred":[
        "\u041d\u043e\u0430\u0439"
    ],
    "name:slk_x_preferred":[
        "Noailles"
    ],
    "name:spa_x_preferred":[
        "Noailles"
    ],
    "name:swe_x_preferred":[
        "Noailles"
    ],
    "name:ukr_x_preferred":[
        "\u041d\u043e\u0430\u0439"
    ],
    "wof:name":"Noailles",
    "wof:placetype":"locality"
},
  "geometry": {"coordinates":[-72.41667,19.05],"type":"Point"}
}