{
  "type": "Feature",
  "properties": {
    "gn:admin1_code":"11.0",
    "gn:admin2_code":"3722285.0",
    "gn:asciiname":"Cabaret",
    "gn:country_code":"HT",
    "gn:dem":427,
    "gn:feature_class":"P",
    "gn:feature_code":"PPL",
    "gn:name":"Cabaret",
    "gn:population":0,
    "gn:timezone":"America/Port-au-Prince",
    "iso:country":"HT",
    "name:fra_x_preferred":[
        "Cabaret"
    ],
    "wof:name":"Cabaret",
    "wof:placetype":"locality"
},
  "geometry": {"coordinates":[-72.60111999999999,18.3994],"type":"Point"}
}