{
  "type": "Feature",
  "properties": {
    "gn:admin1_code":"6.0",
    "gn:admin2_code":"3724144.0",
    "gn:asciiname":"Ti Moulin",
    "gn:country_code":"HT",
    "gn:dem":278,
    "gn:feature_class":"P",
    "gn:feature_code":"PPL",
    "gn:name":"Ti Moulin",
    "gn:population":0,
    "gn:timezone":"America/Port-au-Prince",
    "iso:country":"HT",
    "name:fra_x_preferred":[
        "Ti Moulin"
    ],
    "wof:name":"Ti Moulin",
    "wof:placetype":"locality"
},
  "geometry": {"coordinates":[-72.69580000000001,19.64961],"type":"Point"}
}