{
  "type": "Feature",
  "properties": {
    "gn:admin1_code":"11.0",
    "gn:admin2_code":"3722285.0",
    "gn:asciiname":"Bois Chandel",
    "gn:cc2":"HT",
    "gn:country_code":"HT",
    "gn:dem":201,
    "gn:feature_class":"P",
    "gn:feature_code":"PPL",
    "gn:name":"Bois Chandel",
    "gn:population":0,
    "gn:timezone":"America/Port-au-Prince",
    "iso:country":"HT",
    "name:und_x_variant":[
        "Bois Chandelle",
        "Bois Chandel"
    ],
    "wof:name":"Bois Chandel",
    "wof:placetype":"locality"
},
  "geometry": {"coordinates":[-72.93333,18.45],"type":"Point"}
}