{
  "type": "Feature",
  "properties": {
    "gn:admin1_code":"9.0",
    "gn:admin2_code":"3724438.0",
    "gn:asciiname":"Poudriere",
    "gn:country_code":"HT",
    "gn:dem":206,
    "gn:feature_class":"P",
    "gn:feature_code":"PPL",
    "gn:name":"Poudri\u00e8re",
    "gn:population":0,
    "gn:timezone":"America/Port-au-Prince",
    "iso:country":"HT",
    "wof:name":"Poudriere",
    "wof:placetype":"locality"
},
  "geometry": {"coordinates":[-72.18333,19.56667],"type":"Point"}
}