{
  "type": "Feature",
  "properties": {
    "gn:admin1_code":"13.0",
    "gn:admin2_code":"3730910.0",
    "gn:asciiname":"Ca Laneau",
    "gn:cc2":"HT",
    "gn:country_code":"HT",
    "gn:dem":388,
    "gn:feature_class":"P",
    "gn:feature_code":"PPL",
    "gn:name":"Ca Laneau",
    "gn:population":0,
    "gn:timezone":"America/Port-au-Prince",
    "iso:country":"HT",
    "name:und_x_variant":[
        "Laneau",
        "Ca Laneau"
    ],
    "wof:name":"Ca Laneau",
    "wof:placetype":"locality"
},
  "geometry": {"coordinates":[-72.75444,18.25139],"type":"Point"}
}