{
  "type": "Feature",
  "properties": {
    "gn:admin1_code":"14.0",
    "gn:admin2_code":"3723592.0",
    "gn:asciiname":"Chameau",
    "gn:country_code":"HT",
    "gn:dem":371,
    "gn:feature_class":"P",
    "gn:feature_code":"PPL",
    "gn:name":"Chameau",
    "gn:population":0,
    "gn:timezone":"America/Port-au-Prince",
    "iso:country":"HT",
    "name:fra_x_preferred":[
        "Chameau"
    ],
    "name:spa_x_preferred":[
        "Chameau"
    ],
    "wof:name":"Chameau",
    "wof:placetype":"locality"
},
  "geometry": {"coordinates":[-74.23333000000002,18.51667],"type":"Point"}
}