{
  "type": "Feature",
  "properties": {
    "gn:admin1_code":"9.0",
    "gn:admin2_code":"3722122.0",
    "gn:asciiname":"Roche Haleine",
    "gn:country_code":"HT",
    "gn:dem":78,
    "gn:feature_class":"P",
    "gn:feature_code":"PPL",
    "gn:name":"Roche Haleine",
    "gn:population":0,
    "gn:timezone":"America/Port-au-Prince",
    "iso:country":"HT",
    "wof:name":"Roche Haleine",
    "wof:placetype":"locality"
},
  "geometry": {"coordinates":[-72.41667,19.65],"type":"Point"}
}