{
  "type": "Feature",
  "properties": {
    "gn:admin1_code":"12.0",
    "gn:admin2_code":"3731094.0",
    "gn:asciiname":"Mission",
    "gn:country_code":"HT",
    "gn:dem":97,
    "gn:feature_class":"P",
    "gn:feature_code":"PPL",
    "gn:name":"Mission",
    "gn:population":0,
    "gn:timezone":"America/Port-au-Prince",
    "iso:country":"HT",
    "name:cat_x_preferred":[
        "Mission"
    ],
    "name:ceb_x_preferred":[
        "Mission"
    ],
    "name:dan_x_preferred":[
        "Mission"
    ],
    "name:deu_x_preferred":[
        "Mission"
    ],
    "name:est_x_preferred":[
        "Missioon"
    ],
    "name:fra_x_preferred":[
        "Mission"
    ],
    "name:ita_x_preferred":[
        "Mission"
    ],
    "name:jpn_x_preferred":[
        "\u30df\u30c3\u30b7\u30e7\u30f3"
    ],
    "name:kaz_x_preferred":[
        "\u041c\u0438\u0441\u0441\u0438\u044f"
    ],
    "name:nld_x_preferred":[
        "Mission"
    ],
    "name:pol_x_preferred":[
        "Mission"
    ],
    "name:por_x_preferred":[
        "Mission"
    ],
    "name:ron_x_preferred":[
        "Misiune"
    ],
    "name:rus_x_preferred":[
        "\u041c\u0438\u0441\u0441\u0438\u044f"
    ],
    "name:srp_x_preferred":[
        "\u041c\u0438\u0448\u043e\u043d"
    ],
    "name:swe_x_preferred":[
        "Mission"
    ],
    "name:ukr_x_preferred":[
        "\u041c\u0456\u0441\u0456\u044f"
    ],
    "name:urd_x_preferred":[
        "\u0645\u0634\u0646"
    ],
    "name:vol_x_preferred":[
        "Mission"
    ],
    "wof:name":"Mission",
    "wof:placetype":"locality"
},
  "geometry": {"coordinates":[-73.67917,18.36667000000001],"type":"Point"}
}