{
  "type": "Feature",
  "properties": {
    "gn:admin1_code":"11.0",
    "gn:admin2_code":"3723019.0",
    "gn:asciiname":"Des Pauvres",
    "gn:country_code":"HT",
    "gn:dem":70,
    "gn:feature_class":"P",
    "gn:feature_code":"PPL",
    "gn:name":"Des Pauvres",
    "gn:population":0,
    "gn:timezone":"America/Port-au-Prince",
    "iso:country":"HT",
    "wof:name":"Des Pauvres",
    "wof:placetype":"locality"
},
  "geometry": {"coordinates":[-73.13333,18.91667],"type":"Point"}
}