{
  "type": "Feature",
  "properties": {
    "gn:admin1_code":"10.0",
    "gn:admin2_code":"3725169.0",
    "gn:asciiname":"Briel",
    "gn:country_code":"HT",
    "gn:dem":68,
    "gn:feature_class":"P",
    "gn:feature_code":"PPL",
    "gn:name":"Briel",
    "gn:population":0,
    "gn:timezone":"America/Port-au-Prince",
    "iso:country":"HT",
    "name:deu_x_preferred":[
        "Briel"
    ],
    "name:fra_x_preferred":[
        "Briel"
    ],
    "name:ita_x_preferred":[
        "Briel"
    ],
    "wof:name":"Briel",
    "wof:placetype":"locality"
},
  "geometry": {"coordinates":[-71.88825,19.58715],"type":"Point"}
}