{
  "type": "Feature",
  "properties": {
    "gn:admin1_code":"12.0",
    "gn:admin2_code":"3728096.0",
    "gn:asciiname":"Nicolas",
    "gn:country_code":"HT",
    "gn:dem":64,
    "gn:feature_class":"P",
    "gn:feature_code":"PPL",
    "gn:name":"Nicolas",
    "gn:population":0,
    "gn:timezone":"America/Port-au-Prince",
    "iso:country":"HT",
    "name:ceb_x_preferred":[
        "Nicolas"
    ],
    "name:deu_x_preferred":[
        "Nicolas"
    ],
    "name:fin_x_preferred":[
        "Nicolas"
    ],
    "name:fra_x_preferred":[
        "Nicolas"
    ],
    "name:ita_x_preferred":[
        "Nicolas"
    ],
    "name:jpn_x_preferred":[
        "\u30cb\u30b3\u30e9\u30b9"
    ],
    "name:nld_x_preferred":[
        "Nicolas"
    ],
    "name:ron_x_preferred":[
        "Nicolas"
    ],
    "name:swe_x_preferred":[
        "Nicolas"
    ],
    "name:zho_x_preferred":[
        "\u5c3c\u53e4\u62c9\u65af"
    ],
    "wof:name":"Nicolas",
    "wof:placetype":"locality"
},
  "geometry": {"coordinates":[-73.81667,18.23333],"type":"Point"}
}