{
  "type": "Feature",
  "properties": {
    "gn:admin1_code":"12.0",
    "gn:admin2_code":"3727295.0",
    "gn:asciiname":"Nan Fourneau",
    "gn:country_code":"HT",
    "gn:dem":195,
    "gn:feature_class":"P",
    "gn:feature_code":"PPL",
    "gn:name":"Nan Fourneau",
    "gn:population":0,
    "gn:timezone":"America/Port-au-Prince",
    "iso:country":"HT",
    "name:fra_x_preferred":[
        "Nan Fourneau"
    ],
    "wof:name":"Nan Fourneau",
    "wof:placetype":"locality"
},
  "geometry": {"coordinates":[-73.95374,18.1655],"type":"Point"}
}