{
  "type": "Feature",
  "properties": {
    "gn:country":"HT",
    "gn:fcode":"PPL",
    "gn:pop":134190,
    "iso:country":"HT",
    "name:ara_x_preferred":[
        "\u064a\u0648\u063a\u0627\u0646"
    ],
    "name:ben_x_preferred":[
        "\u09b2\u09bf\u0993\u0997\u09c7\u09a8"
    ],
    "name:dan_x_preferred":[
        "L\u00e9og\u00e2ne"
    ],
    "name:deu_x_preferred":[
        "L\u00e9og\u00e2ne"
    ],
    "name:ell_x_preferred":[
        "\u039b\u03b5\u03bf\u03b6\u03ac\u03bd"
    ],
    "name:eng_x_preferred":[
        "L\u00e9og\u00e2ne"
    ],
    "name:epo_x_preferred":[
        "L\u00e9og\u00e2ne"
    ],
    "name:fin_x_preferred":[
        "L\u00e9og\u00e2ne"
    ],
    "name:fra_x_preferred":[
        "L\u00e9og\u00e2ne"
    ],
    "name:guj_x_preferred":[
        "\u0ab2\u0abf\u0a93\u0a97\u0abe\u0aa8"
    ],
    "name:hat_x_preferred":[
        "Leyog\u00e0n"
    ],
    "name:hin_x_preferred":[
        "\u0932\u093f\u092f\u094b\u0917\u0947\u0928"
    ],
    "name:ind_x_preferred":[
        "L\u00e9og\u00e2ne"
    ],
    "name:ita_x_preferred":[
        "L\u00e9og\u00e2ne"
    ],
    "name:jpn_x_preferred":[
        "\u30ec\u30aa\u30ac\u30f3"
    ],
    "name:kan_x_preferred":[
        "\u0cb2\u0cc0\u0c97\u0cca\u0ca8\u0ccd"
    ],
    "name:kor_x_preferred":[
        "\ub808\uc624\uac04"
    ],
    "name:lav_x_preferred":[
        "Leogane"
    ],
    "name:lit_x_preferred":[
        "Leogan\u0117"
    ],
    "name:mar_x_preferred":[
        "\u0932\u094b\u0917\u093e\u0907\u0928"
    ],
    "name:msa_x_preferred":[
        "Leogane"
    ],
    "name:nld_x_preferred":[
        "L\u00e9og\u00e2ne"
    ],
    "name:nob_x_preferred":[
        "L\u00e9og\u00e2ne"
    ],
    "name:pol_x_preferred":[
        "L\u00e9og\u00e2ne"
    ],
    "name:por_x_preferred":[
        "L\u00e9og\u00e2ne"
    ],
    "name:ron_x_preferred":[
        "L\u00e9og\u00e2ne"
    ],
    "name:rus_x_preferred":[
        "\u041b\u0435\u043e\u0433\u0430\u043d"
    ],
    "name:sin_x_preferred":[
        "\u0dbd\u0dd2\u0dba\u0ddd\u0d9c\u0dcf\u0db1\u0dda"
    ],
    "name:spa_x_preferred":[
        "Leog\u00e1ne"
    ],
    "name:swe_x_preferred":[
        "L\u00e9og\u00e2ne"
    ],
    "name:tam_x_preferred":[
        "\u0bb2\u0bc6\u0baf\u0bcb\u0b95\u0ba9\u0bc7"
    ],
    "name:tel_x_preferred":[
        "\u0c32\u0c3f\u0c2f\u0c4b \u0c17\u0c47\u0c28\u0c4d"
    ],
    "name:tha_x_preferred":[
        "\u0e25\u0e35\u0e42\u0e2d\u0e41\u0e01\u0e07"
    ],
    "name:tur_x_preferred":[
        "Leogane"
    ],
    "name:ukr_x_preferred":[
        "\u041b\u0435\u043e\u0433\u0430\u043d"
    ],
    "name:unk_x_variant":[
        "Yaguana"
    ],
    "name:urd_x_preferred":[
        "\u0644\u06cc\u0648\u062c\u0627\u0646\u06cc"
    ],
    "name:vie_x_preferred":[
        "Leogane"
    ],
    "name:zho_x_preferred":[
        "\u840a\u5967\u7518"
    ],
    "qs:name":"L\u00e9og\u00e2ne",
    "qs:photos_9r":0,
    "qs:photos_sr":0,
    "qs:pop_sr":"9",
    "wd:wordcount":4502,
    "wof:name":"L\u00e9og\u00e2ne",
    "wof:placetype":"locality",
    "wof:population":134190
},
  "geometry": {"coordinates":[-72.63388999999999,18.51083],"type":"Point"}
}