{
  "type": "Feature",
  "properties": {
    "gn:admin1_code":"10.0",
    "gn:admin2_code":"3716114.0",
    "gn:asciiname":"Jaloule",
    "gn:country_code":"HT",
    "gn:dem":443,
    "gn:feature_class":"P",
    "gn:feature_code":"PPL",
    "gn:name":"Jaloule",
    "gn:population":0,
    "gn:timezone":"America/Port-au-Prince",
    "iso:country":"HT",
    "wof:name":"Jaloule",
    "wof:placetype":"locality"
},
  "geometry": {"coordinates":[-71.96666999999999,19.45],"type":"Point"}
}