{
  "type": "Feature",
  "properties": {
    "gn:admin1_code":"6.0",
    "gn:admin2_code":"3717563.0",
    "gn:asciiname":"Savane Salee",
    "gn:country_code":"HT",
    "gn:dem":553,
    "gn:feature_class":"P",
    "gn:feature_code":"PPL",
    "gn:name":"Savane Sal\u00e9e",
    "gn:population":0,
    "gn:timezone":"America/Port-au-Prince",
    "iso:country":"HT",
    "wof:name":"Savane Salee",
    "wof:placetype":"locality"
},
  "geometry": {"coordinates":[-72.28333000000001,19.43333],"type":"Point"}
}