{
  "type": "Feature",
  "properties": {
    "gn:admin1_code":"13.0",
    "gn:admin2_code":"3723778.0",
    "gn:asciiname":"Bellevue",
    "gn:country_code":"HT",
    "gn:dem":745,
    "gn:feature_class":"P",
    "gn:feature_code":"PPL",
    "gn:name":"Bellevue",
    "gn:population":0,
    "gn:timezone":"America/Port-au-Prince",
    "iso:country":"HT",
    "wof:name":"Bellevue",
    "wof:placetype":"locality"
},
  "geometry": {"coordinates":[-72.46666999999999,18.28333],"type":"Point"}
}