{
  "type": "Feature",
  "properties": {
    "gn:admin1_code":"12.0",
    "gn:admin2_code":"3731094.0",
    "gn:asciiname":"Leger",
    "gn:cc2":"HT",
    "gn:country_code":"HT",
    "gn:dem":586,
    "gn:feature_class":"P",
    "gn:feature_code":"PPL",
    "gn:name":"L\u00e9ger",
    "gn:population":0,
    "gn:timezone":"America/Port-au-Prince",
    "iso:country":"HT",
    "name:deu_x_preferred":[
        "Leger"
    ],
    "name:fry_x_preferred":[
        "Leger"
    ],
    "name:nld_x_preferred":[
        "Leger"
    ],
    "name:und_x_variant":[
        "Lager",
        "L\u00e9ger"
    ],
    "wof:name":"Leger",
    "wof:placetype":"locality"
},
  "geometry": {"coordinates":[-73.55,18.37528],"type":"Point"}
}