{
  "type": "Feature",
  "properties": {
    "gn:admin1_code":"3.0",
    "gn:admin2_code":"3720764.0",
    "gn:asciiname":"Jasmin",
    "gn:country_code":"HT",
    "gn:dem":414,
    "gn:feature_class":"P",
    "gn:feature_code":"PPL",
    "gn:name":"Jasmin",
    "gn:population":0,
    "gn:timezone":"America/Port-au-Prince",
    "iso:country":"HT",
    "name:bos_x_preferred":[
        "Jasmin"
    ],
    "name:deu_x_preferred":[
        "Jasmin"
    ],
    "name:est_x_preferred":[
        "Jasmin"
    ],
    "name:fra_x_preferred":[
        "Jasmin"
    ],
    "name:nld_x_preferred":[
        "Jasmin"
    ],
    "name:nor_x_preferred":[
        "Jasmin"
    ],
    "name:pol_x_preferred":[
        "Jasmin"
    ],
    "name:ron_x_preferred":[
        "Jasmin"
    ],
    "name:spa_x_preferred":[
        "Jasmin"
    ],
    "name:swe_x_preferred":[
        "Jasmin"
    ],
    "wof:name":"Jasmin",
    "wof:placetype":"locality"
},
  "geometry": {"coordinates":[-73.28798,19.70079],"type":"Point"}
}