{
  "type": "Feature",
  "properties": {
    "gn:admin1_code":"11.0",
    "gn:asciiname":"Platon",
    "gn:country_code":"HT",
    "gn:dem":468,
    "gn:feature_class":"P",
    "gn:feature_code":"PPL",
    "gn:name":"Platon",
    "gn:population":0,
    "gn:timezone":"America/Port-au-Prince",
    "iso:country":"HT",
    "wof:name":"Platon",
    "wof:placetype":"locality"
},
  "geometry": {"coordinates":[-72.61667,18.33333],"type":"Point"}
}