{
  "type": "Feature",
  "properties": {
    "gn:admin1_code":"10.0",
    "gn:asciiname":"Roche Tempee",
    "gn:country_code":"HT",
    "gn:dem":587,
    "gn:feature_class":"P",
    "gn:feature_code":"PPL",
    "gn:name":"Roche Temp\u00e9e",
    "gn:population":0,
    "gn:timezone":"America/Port-au-Prince",
    "iso:country":"HT",
    "name:und_x_variant":[
        "Roche Tempe",
        "Roche Temp\u00e9e"
    ],
    "wof:name":"Roche Tempee",
    "wof:placetype":"locality"
},
  "geometry": {"coordinates":[-71.90834,19.29953],"type":"Point"}
}