{
  "type": "Feature",
  "properties": {
    "gn:admin1_code":"6.0",
    "gn:admin2_code":"3724695.0",
    "gn:asciiname":"Dolant",
    "gn:country_code":"HT",
    "gn:dem":656,
    "gn:feature_class":"P",
    "gn:feature_code":"PPL",
    "gn:name":"Dolant",
    "gn:population":0,
    "gn:timezone":"America/Port-au-Prince",
    "iso:country":"HT",
    "name:und_x_variant":[
        "Dolan",
        "Dolette",
        "Dolant"
    ],
    "wof:name":"Dolant",
    "wof:placetype":"locality"
},
  "geometry": {"coordinates":[-72.54518,19.5799],"type":"Point"}
}