{
  "type": "Feature",
  "properties": {
    "gn:admin1_code":"11.0",
    "gn:asciiname":"Bodin",
    "gn:cc2":"HT",
    "gn:country_code":"HT",
    "gn:dem":845,
    "gn:feature_class":"P",
    "gn:feature_code":"PPL",
    "gn:name":"Bodin",
    "gn:population":0,
    "gn:timezone":"America/Port-au-Prince",
    "iso:country":"HT",
    "name:nno_x_preferred":[
        "Bodin"
    ],
    "name:nor_x_preferred":[
        "Bodin"
    ],
    "name:rus_x_preferred":[
        "\u0411\u0443\u0434\u0438\u043d"
    ],
    "name:und_x_variant":[
        "Baudin"
    ],
    "wof:name":"Bodin",
    "wof:placetype":"locality"
},
  "geometry": {"coordinates":[-72.70028000000001,18.30778],"type":"Point"}
}