{
  "type": "Feature",
  "properties": {
    "gn:admin1_code":"15.0",
    "gn:asciiname":"Baptiste",
    "gn:country_code":"HT",
    "gn:dem":261,
    "gn:feature_class":"P",
    "gn:feature_code":"PPL",
    "gn:name":"Baptiste",
    "gn:population":0,
    "gn:timezone":"America/Port-au-Prince",
    "iso:country":"HT",
    "name:bre_x_preferred":[
        "Baptiste"
    ],
    "name:deu_x_preferred":[
        "Baptiste"
    ],
    "name:epo_x_preferred":[
        "Baptisto"
    ],
    "name:fra_x_preferred":[
        "Baptiste"
    ],
    "name:jpn_x_preferred":[
        "\u30d0\u30c6\u30a3\u30b9\u30c8"
    ],
    "name:pol_x_preferred":[
        "Baptysta"
    ],
    "name:por_x_preferred":[
        "Baptiste"
    ],
    "wof:name":"Baptiste",
    "wof:placetype":"locality"
},
  "geometry": {"coordinates":[-73.31114000000002,18.37235],"type":"Point"}
}