{
  "type": "Feature",
  "properties": {
    "gn:admin1_code":"11.0",
    "gn:admin2_code":"3722285.0",
    "gn:asciiname":"Lafleur",
    "gn:country_code":"HT",
    "gn:dem":493,
    "gn:feature_class":"P",
    "gn:feature_code":"PPL",
    "gn:name":"Lafleur",
    "gn:population":0,
    "gn:timezone":"America/Port-au-Prince",
    "iso:country":"HT",
    "name:deu_x_preferred":[
        "Lafleur"
    ],
    "name:fra_x_preferred":[
        "Lafleur"
    ],
    "name:ita_x_preferred":[
        "Lafleur"
    ],
    "name:pol_x_preferred":[
        "Lafleur"
    ],
    "name:rus_x_preferred":[
        "\u041b\u0430\u0444\u043b\u0451\u0440"
    ],
    "name:ukr_x_preferred":[
        "\u041b\u0430\u0444\u043b\u0435\u0440"
    ],
    "wof:name":"Lafleur",
    "wof:placetype":"locality"
},
  "geometry": {"coordinates":[-72.48333000000002,18.46667],"type":"Point"}
}