{
  "type": "Feature",
  "properties": {
    "gn:admin1_code":"9.0",
    "gn:admin2_code":"3731232.0",
    "gn:asciiname":"Normand",
    "gn:country_code":"HT",
    "gn:dem":58,
    "gn:feature_class":"P",
    "gn:feature_code":"PPL",
    "gn:name":"Normand",
    "gn:population":0,
    "gn:timezone":"America/Port-au-Prince",
    "iso:country":"HT",
    "name:fra_x_preferred":[
        "Normand"
    ],
    "name:pol_x_preferred":[
        "Normand"
    ],
    "wof:name":"Normand",
    "wof:placetype":"locality"
},
  "geometry": {"coordinates":[-72.25865,19.72208],"type":"Point"}
}