{
  "type": "Feature",
  "properties": {
    "gn:admin1_code":"6.0",
    "gn:admin2_code":"3724144.0",
    "gn:asciiname":"Magasin Degan",
    "gn:country_code":"HT",
    "gn:dem":3,
    "gn:feature_class":"P",
    "gn:feature_code":"PPL",
    "gn:name":"Magasin D\u00e9gan",
    "gn:population":0,
    "gn:timezone":"America/Port-au-Prince",
    "iso:country":"HT",
    "wof:name":"Magasin Degan",
    "wof:placetype":"locality"
},
  "geometry": {"coordinates":[-73.03663,19.61889],"type":"Point"}
}