{
  "type": "Feature",
  "properties": {
    "gn:admin1_code":"9.0",
    "gn:admin2_code":"3731232.0",
    "gn:asciiname":"Dubre",
    "gn:country_code":"HT",
    "gn:dem":23,
    "gn:feature_class":"P",
    "gn:feature_code":"PPL",
    "gn:name":"Dubr\u00e9",
    "gn:population":0,
    "gn:timezone":"America/Port-au-Prince",
    "iso:country":"HT",
    "name:fra_x_preferred":[
        "Dubr\u00e9"
    ],
    "wof:name":"Dubre",
    "wof:placetype":"locality"
},
  "geometry": {"coordinates":[-72.23484000000001,19.65726],"type":"Point"}
}