{
  "type": "Feature",
  "properties": {
    "gn:admin1_code":"3.0",
    "gn:admin2_code":"3718419.0",
    "gn:asciiname":"Terre Cassee",
    "gn:country_code":"HT",
    "gn:dem":593,
    "gn:feature_class":"P",
    "gn:feature_code":"PPL",
    "gn:name":"Terre Cass\u00e9e",
    "gn:population":0,
    "gn:timezone":"America/Port-au-Prince",
    "iso:country":"HT",
    "name:fra_x_preferred":[
        "Terre Cass\u00e9e"
    ],
    "wof:name":"Terre Cassee",
    "wof:placetype":"locality"
},
  "geometry": {"coordinates":[-72.83896,19.74223],"type":"Point"}
}