{
  "type": "Feature",
  "properties": {
    "gn:admin1_code":"6.0",
    "gn:admin2_code":"3724695.0",
    "gn:asciiname":"Ti Coupe Nandrin",
    "gn:country_code":"HT",
    "gn:dem":22,
    "gn:feature_class":"P",
    "gn:feature_code":"PPL",
    "gn:name":"Ti Coupe Nandrin",
    "gn:population":0,
    "gn:timezone":"America/Port-au-Prince",
    "iso:country":"HT",
    "name:fra_x_preferred":[
        "Ti Coupe Nandrin"
    ],
    "wof:name":"Ti Coupe Nandrin",
    "wof:placetype":"locality"
},
  "geometry": {"coordinates":[-72.60294,19.44799],"type":"Point"}
}