{
  "type": "Feature",
  "properties": {
    "gn:admin1_code":"13.0",
    "gn:admin2_code":"3730361.0",
    "gn:asciiname":"Garreau",
    "gn:country_code":"HT",
    "gn:dem":1414,
    "gn:feature_class":"P",
    "gn:feature_code":"PPL",
    "gn:name":"Garreau",
    "gn:population":0,
    "gn:timezone":"America/Port-au-Prince",
    "iso:country":"HT",
    "name:fra_x_preferred":[
        "Garreau"
    ],
    "wof:name":"Garreau",
    "wof:placetype":"locality"
},
  "geometry": {"coordinates":[-71.77948000000001,18.26684],"type":"Point"}
}