{
  "type": "Feature",
  "properties": {
    "gn:admin1_code":"7.0",
    "gn:admin2_code":"3720809.0",
    "gn:asciiname":"Marche Canard",
    "gn:country_code":"HT",
    "gn:dem":180,
    "gn:feature_class":"P",
    "gn:feature_code":"PPL",
    "gn:name":"March\u00e9 Canard",
    "gn:population":0,
    "gn:timezone":"America/Port-au-Prince",
    "iso:country":"HT",
    "wof:name":"Marche Canard",
    "wof:placetype":"locality"
},
  "geometry": {"coordinates":[-72.03333000000001,18.78333],"type":"Point"}
}