{
  "type": "Feature",
  "properties": {
    "gn:admin1_code":"6.0",
    "gn:admin2_code":"3717563.0",
    "gn:asciiname":"Mapou",
    "gn:country_code":"HT",
    "gn:dem":357,
    "gn:feature_class":"P",
    "gn:feature_code":"PPL",
    "gn:name":"Mapou",
    "gn:population":0,
    "gn:timezone":"America/Port-au-Prince",
    "iso:country":"HT",
    "name:ceb_x_preferred":[
        "Mapou"
    ],
    "name:deu_x_preferred":[
        "Mapou"
    ],
    "name:fra_x_preferred":[
        "Mapou"
    ],
    "name:nld_x_preferred":[
        "Mapou"
    ],
    "name:swe_x_preferred":[
        "Mapou"
    ],
    "wof:name":"Mapou",
    "wof:placetype":"locality"
},
  "geometry": {"coordinates":[-72.28333000000001,19.23333],"type":"Point"}
}