{
  "type": "Feature",
  "properties": {
    "gn:admin1_code":"13.0",
    "gn:admin2_code":"3730910.0",
    "gn:asciiname":"Zabo",
    "gn:country_code":"HT",
    "gn:dem":313,
    "gn:feature_class":"P",
    "gn:feature_code":"PPL",
    "gn:name":"Zabo",
    "gn:population":0,
    "gn:timezone":"America/Port-au-Prince",
    "iso:country":"HT",
    "name:fra_x_preferred":[
        "Zabo"
    ],
    "wof:name":"Zabo",
    "wof:placetype":"locality"
},
  "geometry": {"coordinates":[-72.90000000000001,18.18333],"type":"Point"}
}