{
  "type": "Feature",
  "properties": {
    "gn:admin1_code":"10.0",
    "gn:admin2_code":"3725169.0",
    "gn:asciiname":"Gerard",
    "gn:country_code":"HT",
    "gn:dem":20,
    "gn:feature_class":"P",
    "gn:feature_code":"PPL",
    "gn:name":"G\u00e9rard",
    "gn:population":0,
    "gn:timezone":"America/Port-au-Prince",
    "iso:country":"HT",
    "name:fra_x_preferred":[
        "G\u00e9rard"
    ],
    "wof:name":"Gerard",
    "wof:placetype":"locality"
},
  "geometry": {"coordinates":[-71.77115999999999,19.59447],"type":"Point"}
}