{
  "type": "Feature",
  "properties": {
    "gn:admin1_code":"14.0",
    "gn:admin2_code":"3727381.0",
    "gn:asciiname":"Lamentier",
    "gn:country_code":"HT",
    "gn:dem":682,
    "gn:feature_class":"P",
    "gn:feature_code":"PPL",
    "gn:name":"Lamentier",
    "gn:population":0,
    "gn:timezone":"America/Port-au-Prince",
    "iso:country":"HT",
    "wof:name":"Lamentier",
    "wof:placetype":"locality"
},
  "geometry": {"coordinates":[-73.93333,18.45],"type":"Point"}
}