{
  "type": "Feature",
  "properties": {
    "gn:admin1_code":"9.0",
    "gn:admin2_code":"3731232.0",
    "gn:asciiname":"Rojetin",
    "gn:country_code":"HT",
    "gn:dem":450,
    "gn:feature_class":"P",
    "gn:feature_code":"PPL",
    "gn:name":"Rojetin",
    "gn:population":0,
    "gn:timezone":"America/Port-au-Prince",
    "iso:country":"HT",
    "wof:name":"Rojetin",
    "wof:placetype":"locality"
},
  "geometry": {"coordinates":[-72.40000000000001,19.56667],"type":"Point"}
}