{
  "type": "Feature",
  "properties": {
    "gn:admin1_code":"13.0",
    "gn:asciiname":"Ca Jacques",
    "gn:country_code":"HT",
    "gn:dem":2046,
    "gn:feature_class":"P",
    "gn:feature_code":"PPL",
    "gn:name":"Ca Jacques",
    "gn:population":0,
    "gn:timezone":"America/Port-au-Prince",
    "iso:country":"HT",
    "wof:name":"Ca Jacques",
    "wof:placetype":"locality"
},
  "geometry": {"coordinates":[-72.28333000000001,18.35],"type":"Point"}
}