{
  "type": "Feature",
  "properties": {
    "gn:admin1_code":"3.0",
    "gn:admin2_code":"3718419.0",
    "gn:asciiname":"L'Hopital",
    "gn:country_code":"HT",
    "gn:dem":287,
    "gn:feature_class":"P",
    "gn:feature_code":"PPL",
    "gn:name":"L\u2019H\u00f4pital",
    "gn:population":0,
    "gn:timezone":"America/Port-au-Prince",
    "iso:country":"HT",
    "name:fra_x_preferred":[
        "L\u2019Hopital"
    ],
    "name:und_x_variant":[
        "L\u2019H\u00f4pital"
    ],
    "wof:name":"L'Hopital",
    "wof:placetype":"locality"
},
  "geometry": {"coordinates":[-72.89593000000001,20.05639],"type":"Point"}
}