{
  "type": "Feature",
  "properties": {
    "gn:admin1_code":"6.0",
    "gn:admin2_code":"3724144.0",
    "gn:asciiname":"Nan Fort",
    "gn:country_code":"HT",
    "gn:dem":8,
    "gn:feature_class":"P",
    "gn:feature_code":"PPL",
    "gn:name":"Nan Fort",
    "gn:population":0,
    "gn:timezone":"America/Port-au-Prince",
    "iso:country":"HT",
    "name:fra_x_preferred":[
        "Nan Fort"
    ],
    "wof:name":"Nan Fort",
    "wof:placetype":"locality"
},
  "geometry": {"coordinates":[-73.00613,19.6132],"type":"Point"}
}