{
  "type": "Feature",
  "properties": {
    "gn:admin1_code":"12.0",
    "gn:admin2_code":"3728096.0",
    "gn:asciiname":"Ca Durand",
    "gn:country_code":"HT",
    "gn:dem":272,
    "gn:feature_class":"P",
    "gn:feature_code":"PPL",
    "gn:name":"Ca Durand",
    "gn:population":0,
    "gn:timezone":"America/Port-au-Prince",
    "iso:country":"HT",
    "name:fra_x_preferred":[
        "Ca Durand"
    ],
    "wof:name":"Ca Durand",
    "wof:placetype":"locality"
},
  "geometry": {"coordinates":[-73.82571,18.32166],"type":"Point"}
}