{
  "type": "Feature",
  "properties": {
    "gn:admin1_code":"7.0",
    "gn:admin2_code":"3723840.0",
    "gn:asciiname":"Savane Baptiste",
    "gn:country_code":"HT",
    "gn:dem":351,
    "gn:feature_class":"P",
    "gn:feature_code":"PPL",
    "gn:name":"Savane Baptiste",
    "gn:population":0,
    "gn:timezone":"America/Port-au-Prince",
    "iso:country":"HT",
    "wof:name":"Savane Baptiste",
    "wof:placetype":"locality"
},
  "geometry": {"coordinates":[-71.97721999999997,18.99722],"type":"Point"}
}