{
  "type": "Feature",
  "properties": {
    "gn:admin1_code":"6.0",
    "gn:admin2_code":"3717563.0",
    "gn:asciiname":"Nan Bois Pin",
    "gn:country_code":"HT",
    "gn:dem":386,
    "gn:feature_class":"P",
    "gn:feature_code":"PPL",
    "gn:name":"Nan Bois Pin",
    "gn:population":0,
    "gn:timezone":"America/Port-au-Prince",
    "iso:country":"HT",
    "wof:name":"Nan Bois Pin",
    "wof:placetype":"locality"
},
  "geometry": {"coordinates":[-72.28333000000001,19.33333],"type":"Point"}
}