{
  "type": "Feature",
  "properties": {
    "gn:admin1_code":"3.0",
    "gn:admin2_code":"3718419.0",
    "gn:asciiname":"Tete a l'Ile",
    "gn:country_code":"HT",
    "gn:dem":8,
    "gn:feature_class":"P",
    "gn:feature_code":"PPL",
    "gn:name":"T\u00eate \u00e0 l\u2019\u00cele",
    "gn:population":0,
    "gn:timezone":"America/Port-au-Prince",
    "iso:country":"HT",
    "name:und_x_variant":[
        "Tete Ligne",
        "T\u00eate \u00e0 l\u2019\u00cele"
    ],
    "wof:name":"Tete a l'Ile",
    "wof:placetype":"locality"
},
  "geometry": {"coordinates":[-72.64057,19.99384],"type":"Point"}
}