{
  "type": "Feature",
  "properties": {
    "gn:admin1_code":"11.0",
    "gn:asciiname":"Trou Canari",
    "gn:country_code":"HT",
    "gn:dem":924,
    "gn:feature_class":"P",
    "gn:feature_code":"PPL",
    "gn:name":"Trou Canari",
    "gn:population":0,
    "gn:timezone":"America/Port-au-Prince",
    "iso:country":"HT",
    "name:fra_x_preferred":[
        "Trou Canari"
    ],
    "wof:name":"Trou Canari",
    "wof:placetype":"locality"
},
  "geometry": {"coordinates":[-72.94407,18.3495],"type":"Point"}
}