{
  "type": "Feature",
  "properties": {
    "gn:admin1_code":"10.0",
    "gn:admin2_code":"3719435.0",
    "gn:asciiname":"Duvignal",
    "gn:country_code":"HT",
    "gn:dem":704,
    "gn:feature_class":"P",
    "gn:feature_code":"PPL",
    "gn:name":"Duvignal",
    "gn:population":0,
    "gn:timezone":"America/Port-au-Prince",
    "iso:country":"HT",
    "wof:name":"Duvignal",
    "wof:placetype":"locality"
},
  "geometry": {"coordinates":[-71.84999999999999,19.41667],"type":"Point"}
}