{
  "type": "Feature",
  "properties": {
    "iso:country":"HT",
    "name:ara_x_preferred":[
        "\u062c\u0627\u0646 \u0631\u0627\u0628\u064a\u0644"
    ],
    "name:eng_x_preferred":[
        "Jean-Rabel"
    ],
    "name:fra_x_preferred":[
        "Jean-Rabel"
    ],
    "name:hat_x_preferred":[
        "Jan Rab\u00e8l"
    ],
    "name:ita_x_preferred":[
        "Jean-Rabel"
    ],
    "name:jpn_x_preferred":[
        "\u30b8\u30e3\u30f3\uff1d\u30e9\u30d9\u30eb"
    ],
    "name:kor_x_preferred":[
        "\uc7a5\ub77c\ubca8"
    ],
    "name:nld_x_preferred":[
        "Jean-Rabel"
    ],
    "name:nno_x_preferred":[
        "Jean-Rabel"
    ],
    "name:por_x_preferred":[
        "Jean-Rabel"
    ],
    "name:ron_x_preferred":[
        "Jean-Rabel"
    ],
    "name:swe_x_preferred":[
        "Jean-Rabel"
    ],
    "name:unk_x_variant":[
        "Ville de Jean Rabel"
    ],
    "qs:gn_country":"HT",
    "qs:gn_fcode":"PPL",
    "qs:gn_pop":5419,
    "qs:name":"Jean-Rabel",
    "qs:name_adm0":"Ha\u00efti",
    "qs:name_adm1":"Nord-Ouest",
    "qs:photos":0,
    "qs:photos_1k":0,
    "qs:photos_9k":1,
    "qs:photos_9r":1,
    "qs:photos_all":1,
    "qs:photos_sr":0,
    "qs:placetype":"Town",
    "qs:pop_sr":"5",
    "qs:woe_adm0":23424839,
    "wd:wordcount":411,
    "wof:name":"Jean-Rabel",
    "wof:placetype":"locality",
    "wof:population":5419
},
  "geometry": {"coordinates":[-73.19167,19.85333],"type":"Point"}
}