{
  "type": "Feature",
  "properties": {
    "gn:admin1_code":"12.0",
    "gn:admin2_code":"3728096.0",
    "gn:asciiname":"Lamonge",
    "gn:country_code":"HT",
    "gn:dem":400,
    "gn:feature_class":"P",
    "gn:feature_code":"PPL",
    "gn:name":"Lamonge",
    "gn:population":0,
    "gn:timezone":"America/Port-au-Prince",
    "iso:country":"HT",
    "name:fra_x_preferred":[
        "Lamonge"
    ],
    "wof:name":"Lamonge",
    "wof:placetype":"locality"
},
  "geometry": {"coordinates":[-73.92551,18.31588],"type":"Point"}
}