{
  "type": "Feature",
  "properties": {
    "gn:admin1_code":"12.0",
    "gn:admin2_code":"3731094.0",
    "gn:asciiname":"Mingrette",
    "gn:country_code":"HT",
    "gn:dem":61,
    "gn:feature_class":"P",
    "gn:feature_code":"PPL",
    "gn:name":"Mingrette",
    "gn:population":0,
    "gn:timezone":"America/Port-au-Prince",
    "iso:country":"HT",
    "wof:name":"Mingrette",
    "wof:placetype":"locality"
},
  "geometry": {"coordinates":[-73.34999999999999,18.31667],"type":"Point"}
}