{
  "type": "Feature",
  "properties": {
    "gn:admin1_code":"10.0",
    "gn:admin2_code":"3716114.0",
    "gn:asciiname":"La Cyplaine",
    "gn:country_code":"HT",
    "gn:dem":790,
    "gn:feature_class":"P",
    "gn:feature_code":"PPL",
    "gn:name":"La Cypla\u00eene",
    "gn:population":0,
    "gn:timezone":"America/Port-au-Prince",
    "iso:country":"HT",
    "name:und_x_variant":[
        "La Chaine",
        "La Cypla\u00eene"
    ],
    "wof:name":"La Cyplaine",
    "wof:placetype":"locality"
},
  "geometry": {"coordinates":[-71.88761,19.37876],"type":"Point"}
}