{
  "type": "Feature",
  "properties": {
    "gn:admin1_code":"11.0",
    "gn:admin2_code":"3722285.0",
    "gn:asciiname":"Brache",
    "gn:country_code":"HT",
    "gn:dem":36,
    "gn:feature_class":"P",
    "gn:feature_code":"PPL",
    "gn:name":"Brache",
    "gn:population":0,
    "gn:timezone":"America/Port-au-Prince",
    "iso:country":"HT",
    "wof:name":"Brache",
    "wof:placetype":"locality"
},
  "geometry": {"coordinates":[-72.58750000000001,18.52194],"type":"Point"}
}