{
  "type": "Feature",
  "properties": {
    "gn:admin1_code":"11.0",
    "gn:admin2_code":"3727134.0",
    "gn:asciiname":"Nan Tete Source",
    "gn:country_code":"HT",
    "gn:dem":42,
    "gn:feature_class":"P",
    "gn:feature_code":"PPL",
    "gn:name":"Nan T\u00eate Source",
    "gn:population":0,
    "gn:timezone":"America/Port-au-Prince",
    "iso:country":"HT",
    "wof:name":"Nan Tete Source",
    "wof:placetype":"locality"
},
  "geometry": {"coordinates":[-72.05,18.65],"type":"Point"}
}