{
  "type": "Feature",
  "properties": {
    "gn:admin1_code":"7.0",
    "gn:asciiname":"Diable Aube",
    "gn:country_code":"HT",
    "gn:dem":562,
    "gn:feature_class":"P",
    "gn:feature_code":"PPL",
    "gn:name":"Diable Aub\u00e9",
    "gn:population":0,
    "gn:timezone":"America/Port-au-Prince",
    "iso:country":"HT",
    "name:fra_x_preferred":[
        "Diable Aub\u00e9"
    ],
    "wof:name":"Diable Aube",
    "wof:placetype":"locality"
},
  "geometry": {"coordinates":[-71.82449,19.23499],"type":"Point"}
}