{
  "type": "Feature",
  "properties": {
    "gn:admin1_code":"11.0",
    "gn:admin2_code":"3727134.0",
    "gn:asciiname":"Theron",
    "gn:country_code":"HT",
    "gn:dem":826,
    "gn:feature_class":"P",
    "gn:feature_code":"PPL",
    "gn:name":"Theron",
    "gn:population":0,
    "gn:timezone":"America/Port-au-Prince",
    "iso:country":"HT",
    "name:afr_x_preferred":[
        "Theron"
    ],
    "name:ceb_x_preferred":[
        "Theron"
    ],
    "name:deu_x_preferred":[
        "Theron"
    ],
    "name:fra_x_preferred":[
        "Theron"
    ],
    "name:nds_x_preferred":[
        "Theron"
    ],
    "name:rus_x_preferred":[
        "\u0422\u0435\u0440\u043e\u043d"
    ],
    "name:slv_x_preferred":[
        "Theron"
    ],
    "wof:name":"Theron",
    "wof:placetype":"locality"
},
  "geometry": {"coordinates":[-72.25,18.75],"type":"Point"}
}