{
  "type": "Feature",
  "properties": {
    "gn:admin1_code":"12.0",
    "gn:admin2_code":"3728096.0",
    "gn:asciiname":"Le Pinay",
    "gn:country_code":"HT",
    "gn:dem":140,
    "gn:feature_class":"P",
    "gn:feature_code":"PPL",
    "gn:name":"Le Pinay",
    "gn:population":0,
    "gn:timezone":"America/Port-au-Prince",
    "iso:country":"HT",
    "name:und_x_variant":[
        "L\u2019Pine",
        "Le Pinay"
    ],
    "wof:name":"Le Pinay",
    "wof:placetype":"locality"
},
  "geometry": {"coordinates":[-73.80119000000001,18.3454],"type":"Point"}
}