{
  "type": "Feature",
  "properties": {
    "gn:admin1_code":"12.0",
    "gn:admin2_code":"3728096.0",
    "gn:asciiname":"Dollin",
    "gn:country_code":"HT",
    "gn:dem":74,
    "gn:feature_class":"P",
    "gn:feature_code":"PPL",
    "gn:name":"Dollin",
    "gn:population":0,
    "gn:timezone":"America/Port-au-Prince",
    "iso:country":"HT",
    "name:fra_x_preferred":[
        "Dollin"
    ],
    "wof:name":"Dollin",
    "wof:placetype":"locality"
},
  "geometry": {"coordinates":[-73.78649,18.28538],"type":"Point"}
}