{
  "type": "Feature",
  "properties": {
    "gn:admin1_code":"7.0",
    "gn:admin2_code":"3720809.0",
    "gn:asciiname":"Guibert",
    "gn:cc2":"HT",
    "gn:country_code":"HT",
    "gn:dem":333,
    "gn:feature_class":"P",
    "gn:feature_code":"PPL",
    "gn:name":"Guibert",
    "gn:population":0,
    "gn:timezone":"America/Port-au-Prince",
    "iso:country":"HT",
    "name:deu_x_preferred":[
        "Guibert"
    ],
    "name:fra_x_preferred":[
        "Guibert"
    ],
    "name:rus_x_preferred":[
        "\u0413\u0438\u0431\u0435\u0440"
    ],
    "name:und_x_variant":[
        "Guilbert",
        "Guibert"
    ],
    "wof:name":"Guibert",
    "wof:placetype":"locality"
},
  "geometry": {"coordinates":[-72.21167,18.80111],"type":"Point"}
}