{
  "type": "Feature",
  "properties": {
    "gn:admin1_code":"11.0",
    "gn:admin2_code":"3731086.0",
    "gn:asciiname":"Perrier",
    "gn:country_code":"HT",
    "gn:dem":1305,
    "gn:feature_class":"P",
    "gn:feature_code":"PPL",
    "gn:name":"Perrier",
    "gn:population":0,
    "gn:timezone":"America/Port-au-Prince",
    "iso:country":"HT",
    "name:fra_x_preferred":[
        "Perrier"
    ],
    "wof:name":"Perrier",
    "wof:placetype":"locality"
},
  "geometry": {"coordinates":[-72.57963000000002,18.91811],"type":"Point"}
}