{
  "type": "Feature",
  "properties": {
    "gn:admin1_code":"11.0",
    "gn:admin2_code":"3731086.0",
    "gn:asciiname":"Perrier",
    "gn:country_code":"HT",
    "gn:dem":1305,
    "gn:feature_class":"P",
    "gn:feature_code":"PPL",
    "gn:name":"Perrier",
    "gn:population":0,
    "gn:timezone":"America/Port-au-Prince",
    "iso:country":"HT",
    "name:ben_x_preferred":[
        "\u09aa\u09c7\u09b0\u09bf\u09af\u09bc\u09c7"
    ],
    "name:deu_x_preferred":[
        "Perrier"
    ],
    "name:eus_x_preferred":[
        "Perrier"
    ],
    "name:fra_x_preferred":[
        "Perrier"
    ],
    "name:ita_x_preferred":[
        "Perrier"
    ],
    "name:jpn_x_preferred":[
        "\u30da\u30ea\u30a8"
    ],
    "name:kor_x_preferred":[
        "\ud398\ub9ac\uc5d0"
    ],
    "name:nld_x_preferred":[
        "Perrier"
    ],
    "name:nor_x_preferred":[
        "Perrier"
    ],
    "name:oci_x_preferred":[
        "Perrier"
    ],
    "name:pol_x_preferred":[
        "Perrier"
    ],
    "name:por_x_preferred":[
        "Perrier"
    ],
    "name:rus_x_preferred":[
        "Perrier"
    ],
    "name:spa_x_preferred":[
        "Perrier"
    ],
    "name:swe_x_preferred":[
        "Perrier"
    ],
    "name:zho_x_preferred":[
        "\u6c9b\u7da0\u96c5"
    ],
    "wof:name":"Perrier",
    "wof:placetype":"locality"
},
  "geometry": {"coordinates":[-72.57963000000002,18.91811],"type":"Point"}
}