{
  "type": "Feature",
  "properties": {
    "gn:admin1_code":"14.0",
    "gn:asciiname":"Torbeck",
    "gn:country_code":"HT",
    "gn:dem":-9999,
    "gn:feature_class":"P",
    "gn:feature_code":"PPL",
    "gn:name":"Torbeck",
    "gn:population":0,
    "gn:timezone":"America/Port-au-Prince",
    "iso:country":"HT",
    "name:ara_x_preferred":[
        "\u062a\u0648\u0631\u0628\u064a\u0643"
    ],
    "name:ceb_x_preferred":[
        "Torbeck"
    ],
    "name:fra_x_preferred":[
        "Torbeck"
    ],
    "name:hat_x_preferred":[
        "T\u00f2b\u00e8k"
    ],
    "name:ita_x_preferred":[
        "Torbeck"
    ],
    "name:nld_x_preferred":[
        "Torbeck"
    ],
    "name:por_x_preferred":[
        "Torbeck"
    ],
    "name:ron_x_preferred":[
        "Torbeck"
    ],
    "name:spa_x_preferred":[
        "Torbeck"
    ],
    "name:swe_x_preferred":[
        "Torbeck"
    ],
    "wof:name":"Torbeck",
    "wof:placetype":"locality"
},
  "geometry": {"coordinates":[-74.21666999999999,18.68333],"type":"Point"}
}