{
  "type": "Feature",
  "properties": {
    "gn:admin1_code":"13.0",
    "gn:admin2_code":"3723778.0",
    "gn:asciiname":"Meyer",
    "gn:country_code":"HT",
    "gn:dem":53,
    "gn:feature_class":"P",
    "gn:feature_code":"PPL",
    "gn:name":"Meyer",
    "gn:population":0,
    "gn:timezone":"America/Port-au-Prince",
    "iso:country":"HT",
    "name:bel_x_preferred":[
        "\u041c\u0435\u0435\u0440"
    ],
    "name:bul_x_preferred":[
        "\u041c\u0430\u0439\u0435\u0440"
    ],
    "name:cat_x_preferred":[
        "Meyer"
    ],
    "name:ceb_x_preferred":[
        "Meyer"
    ],
    "name:ces_x_preferred":[
        "Meyer"
    ],
    "name:dan_x_preferred":[
        "Meyer"
    ],
    "name:deu_x_preferred":[
        "Meyer"
    ],
    "name:epo_x_preferred":[
        "Meyer"
    ],
    "name:est_x_preferred":[
        "Meyer"
    ],
    "name:fin_x_preferred":[
        "Meyer"
    ],
    "name:fra_x_preferred":[
        "M\u00e9yer"
    ],
    "name:fra_x_variant":[
        "Meyer"
    ],
    "name:heb_x_preferred":[
        "\u05de\u05d0\u05d9\u05d9\u05e8"
    ],
    "name:ita_x_preferred":[
        "Meyer"
    ],
    "name:jpn_x_preferred":[
        "\u30de\u30a4\u30e4\u30fc"
    ],
    "name:kor_x_preferred":[
        "\ub9c8\uc774\uc5b4"
    ],
    "name:lav_x_preferred":[
        "Meyer"
    ],
    "name:lit_x_preferred":[
        "Meyer"
    ],
    "name:pol_x_preferred":[
        "Meyer"
    ],
    "name:por_x_preferred":[
        "Meyer"
    ],
    "name:ron_x_preferred":[
        "Meyer"
    ],
    "name:rus_x_preferred":[
        "\u041c\u0435\u0439\u0435\u0440"
    ],
    "name:spa_x_preferred":[
        "Meyer"
    ],
    "name:swe_x_preferred":[
        "Meyer"
    ],
    "name:tur_x_preferred":[
        "Meyer"
    ],
    "name:ukr_x_preferred":[
        "\u041c\u0435\u0454\u0440"
    ],
    "name:und_x_variant":[
        "Meyerre",
        "Meyer"
    ],
    "wof:name":"Meyer",
    "wof:placetype":"locality"
},
  "geometry": {"coordinates":[-72.48265000000001,18.2308],"type":"Point"}
}