{
  "type": "Feature",
  "properties": {
    "gn:admin1_code":"13.0",
    "gn:admin2_code":"3723778.0",
    "gn:asciiname":"Meyer",
    "gn:country_code":"HT",
    "gn:dem":53,
    "gn:feature_class":"P",
    "gn:feature_code":"PPL",
    "gn:name":"Meyer",
    "gn:population":0,
    "gn:timezone":"America/Port-au-Prince",
    "iso:country":"HT",
    "name:fra_x_preferred":[
        "M\u00e9yer"
    ],
    "name:und_x_variant":[
        "Meyerre",
        "Meyer"
    ],
    "wof:name":"Meyer",
    "wof:placetype":"locality"
},
  "geometry": {"coordinates":[-72.48265000000001,18.2308],"type":"Point"}
}