{
  "type": "Feature",
  "properties": {
    "gn:admin1_code":"3.0",
    "gn:admin2_code":"3720764.0",
    "gn:asciiname":"Nan Picho",
    "gn:country_code":"HT",
    "gn:dem":42,
    "gn:feature_class":"P",
    "gn:feature_code":"PPL",
    "gn:name":"Nan Picho",
    "gn:population":0,
    "gn:timezone":"America/Port-au-Prince",
    "iso:country":"HT",
    "name:fra_x_preferred":[
        "Nan Picho"
    ],
    "wof:name":"Nan Picho",
    "wof:placetype":"locality"
},
  "geometry": {"coordinates":[-73.08405,19.88695],"type":"Point"}
}