{
  "type": "Feature",
  "properties": {
    "gn:admin1_code":"9.0",
    "gn:admin2_code":"3724438.0",
    "gn:asciiname":"L'Anneau",
    "gn:country_code":"HT",
    "gn:dem":618,
    "gn:feature_class":"P",
    "gn:feature_code":"PPL",
    "gn:name":"L\u2019Anneau",
    "gn:population":0,
    "gn:timezone":"America/Port-au-Prince",
    "iso:country":"HT",
    "wof:name":"L'Anneau",
    "wof:placetype":"locality"
},
  "geometry": {"coordinates":[-72.21666999999999,19.53333],"type":"Point"}
}