{
  "type": "Feature",
  "properties": {
    "gn:admin1_code":"6.0",
    "gn:asciiname":"Pierre Paul",
    "gn:country_code":"HT",
    "gn:dem":193,
    "gn:feature_class":"P",
    "gn:feature_code":"PPL",
    "gn:name":"Pierre Paul",
    "gn:population":0,
    "gn:timezone":"America/Port-au-Prince",
    "iso:country":"HT",
    "name:fra_x_preferred":[
        "Pierre Paul"
    ],
    "wof:name":"Pierre Paul",
    "wof:placetype":"locality"
},
  "geometry": {"coordinates":[-72.26111,18.89203],"type":"Point"}
}