{
  "type": "Feature",
  "properties": {
    "gn:admin1_code":"10.0",
    "gn:admin2_code":"3719435.0",
    "gn:asciiname":"Vieux Gaille",
    "gn:country_code":"HT",
    "gn:dem":244,
    "gn:feature_class":"P",
    "gn:feature_code":"PPL",
    "gn:name":"Vieux Gaille",
    "gn:population":0,
    "gn:timezone":"America/Port-au-Prince",
    "iso:country":"HT",
    "name:und_x_variant":[
        "Vieux Calle",
        "Vieux Gaille"
    ],
    "wof:name":"Vieux Gaille",
    "wof:placetype":"locality"
},
  "geometry": {"coordinates":[-71.83126999999998,19.45589],"type":"Point"}
}