{
  "type": "Feature",
  "properties": {
    "gn:admin1_code":"13.0",
    "gn:asciiname":"Chapotin",
    "gn:country_code":"HT",
    "gn:dem":1601,
    "gn:feature_class":"P",
    "gn:feature_code":"PPL",
    "gn:name":"Chapotin",
    "gn:population":0,
    "gn:timezone":"America/Port-au-Prince",
    "iso:country":"HT",
    "wof:name":"Chapotin",
    "wof:placetype":"locality"
},
  "geometry": {"coordinates":[-71.71666999999999,18.31667],"type":"Point"}
}