{
  "type": "Feature",
  "properties": {
    "gn:admin1_code":"12.0",
    "gn:admin2_code":"3718404.0",
    "gn:asciiname":"Mont Gerard",
    "gn:country_code":"HT",
    "gn:dem":258,
    "gn:feature_class":"P",
    "gn:feature_code":"PPL",
    "gn:name":"Mont G\u00e9rard",
    "gn:population":0,
    "gn:timezone":"America/Port-au-Prince",
    "iso:country":"HT",
    "wof:name":"Mont Gerard",
    "wof:placetype":"locality"
},
  "geometry": {"coordinates":[-73.90278000000001,18.135],"type":"Point"}
}