{
  "type": "Feature",
  "properties": {
    "gn:admin1_code":"12.0",
    "gn:admin2_code":"3718404.0",
    "gn:asciiname":"Brieux",
    "gn:country_code":"HT",
    "gn:dem":148,
    "gn:feature_class":"P",
    "gn:feature_code":"PPL",
    "gn:name":"Brieux",
    "gn:population":0,
    "gn:timezone":"America/Port-au-Prince",
    "iso:country":"HT",
    "name:fra_x_preferred":[
        "Brieux"
    ],
    "wof:name":"Brieux",
    "wof:placetype":"locality"
},
  "geometry": {"coordinates":[-73.85349000000002,18.10457],"type":"Point"}
}