{
  "type": "Feature",
  "properties": {
    "gn:admin1_code":"12.0",
    "gn:admin2_code":"3718404.0",
    "gn:asciiname":"Brieux",
    "gn:country_code":"HT",
    "gn:dem":148,
    "gn:feature_class":"P",
    "gn:feature_code":"PPL",
    "gn:name":"Brieux",
    "gn:population":0,
    "gn:timezone":"America/Port-au-Prince",
    "iso:country":"HT",
    "name:cat_x_preferred":[
        "Brieux"
    ],
    "name:ceb_x_preferred":[
        "Brieux"
    ],
    "name:deu_x_preferred":[
        "Brieux"
    ],
    "name:eus_x_preferred":[
        "Brieux"
    ],
    "name:fas_x_preferred":[
        "\u0628\u0631\u0648\u06cc\u06a9\u0633"
    ],
    "name:fra_x_preferred":[
        "Brieux"
    ],
    "name:hun_x_preferred":[
        "Brieux"
    ],
    "name:ind_x_preferred":[
        "Brieux"
    ],
    "name:ita_x_preferred":[
        "Brieux"
    ],
    "name:kaz_x_preferred":[
        "\u0411\u0440\u0438\u0435"
    ],
    "name:lat_x_preferred":[
        "Brieux"
    ],
    "name:mlg_x_preferred":[
        "Brieux"
    ],
    "name:msa_x_preferred":[
        "Brieux"
    ],
    "name:nld_x_preferred":[
        "Brieux"
    ],
    "name:oci_x_preferred":[
        "Brieux"
    ],
    "name:pms_x_preferred":[
        "Brieux"
    ],
    "name:pol_x_preferred":[
        "Brieux"
    ],
    "name:por_x_preferred":[
        "Brieux"
    ],
    "name:ron_x_preferred":[
        "Brieux"
    ],
    "name:slk_x_preferred":[
        "Brieux"
    ],
    "name:spa_x_preferred":[
        "Brieux"
    ],
    "name:srp_x_preferred":[
        "\u0411\u0440\u0438\u0458\u0435"
    ],
    "name:swe_x_preferred":[
        "Brieux"
    ],
    "name:ukr_x_preferred":[
        "\u0411\u0440\u0456\u0454"
    ],
    "name:uzb_x_preferred":[
        "Brieux"
    ],
    "name:vie_x_preferred":[
        "Brieux"
    ],
    "name:vol_x_preferred":[
        "Brieux"
    ],
    "name:war_x_preferred":[
        "Brieux"
    ],
    "name:zho_x_preferred":[
        "\u5e03\u91cc\u5384"
    ],
    "wof:name":"Brieux",
    "wof:placetype":"locality"
},
  "geometry": {"coordinates":[-73.85349000000002,18.10457],"type":"Point"}
}