{
  "type": "Feature",
  "properties": {
    "gn:admin1_code":"6.0",
    "gn:admin2_code":"3717587.0",
    "gn:asciiname":"Marecage",
    "gn:country_code":"HT",
    "gn:dem":44,
    "gn:feature_class":"P",
    "gn:feature_code":"PPL",
    "gn:name":"Mar\u00e9cage",
    "gn:population":0,
    "gn:timezone":"America/Port-au-Prince",
    "iso:country":"HT",
    "name:fra_x_preferred":[
        "Mar\u00e9cage"
    ],
    "wof:name":"Marecage",
    "wof:placetype":"locality"
},
  "geometry": {"coordinates":[-72.51430000000001,19.09867],"type":"Point"}
}