{
  "type": "Feature",
  "properties": {
    "gn:admin1_code":"7.0",
    "gn:admin2_code":"3720809.0",
    "gn:asciiname":"Du Parc",
    "gn:country_code":"HT",
    "gn:dem":611,
    "gn:feature_class":"P",
    "gn:feature_code":"PPL",
    "gn:name":"Du Parc",
    "gn:population":0,
    "gn:timezone":"America/Port-au-Prince",
    "iso:country":"HT",
    "name:fra_x_preferred":[
        "Duparc"
    ],
    "wof:name":"Du Parc",
    "wof:placetype":"locality"
},
  "geometry": {"coordinates":[-72.06515,18.95143],"type":"Point"}
}