{
  "type": "Feature",
  "properties": {
    "gn:admin1_code":"9.0",
    "gn:admin2_code":"3729454.0",
    "gn:asciiname":"Mathurin",
    "gn:country_code":"HT",
    "gn:dem":33,
    "gn:feature_class":"P",
    "gn:feature_code":"PPL",
    "gn:name":"Mathurin",
    "gn:population":0,
    "gn:timezone":"America/Port-au-Prince",
    "iso:country":"HT",
    "name:bre_x_preferred":[
        "Matelin"
    ],
    "name:deu_x_preferred":[
        "Mathurin"
    ],
    "name:fra_x_preferred":[
        "Mathurin"
    ],
    "name:ita_x_preferred":[
        "Maturino"
    ],
    "name:pol_x_preferred":[
        "Mathurin"
    ],
    "wof:name":"Mathurin",
    "wof:placetype":"locality"
},
  "geometry": {"coordinates":[-72.42655999999999,19.76026],"type":"Point"}
}