{
  "type": "Feature",
  "properties": {
    "gn:admin1_code":"6.0",
    "gn:admin2_code":"3717587.0",
    "gn:asciiname":"Baille",
    "gn:country_code":"HT",
    "gn:dem":441,
    "gn:feature_class":"P",
    "gn:feature_code":"PPL",
    "gn:name":"Baille",
    "gn:population":0,
    "gn:timezone":"America/Port-au-Prince",
    "iso:country":"HT",
    "name:fra_x_preferred":[
        "Baille"
    ],
    "name:nld_x_preferred":[
        "Baille"
    ],
    "wof:name":"Baille",
    "wof:placetype":"locality"
},
  "geometry": {"coordinates":[-72.35514000000001,18.89916],"type":"Point"}
}