{
  "type": "Feature",
  "properties": {
    "gn:admin1_code":"14.0",
    "gn:admin2_code":"3723592.0",
    "gn:asciiname":"Cafetiere",
    "gn:country_code":"HT",
    "gn:dem":19,
    "gn:feature_class":"P",
    "gn:feature_code":"PPL",
    "gn:name":"Cafeti\u00e8re",
    "gn:population":0,
    "gn:timezone":"America/Port-au-Prince",
    "iso:country":"HT",
    "wof:name":"Cafetiere",
    "wof:placetype":"locality"
},
  "geometry": {"coordinates":[-74.32969,18.65456],"type":"Point"}
}