{
  "type": "Feature",
  "properties": {
    "gn:admin1_code":"6.0",
    "gn:admin2_code":"3717563.0",
    "gn:asciiname":"Deja",
    "gn:country_code":"HT",
    "gn:dem":568,
    "gn:feature_class":"P",
    "gn:feature_code":"PPL",
    "gn:name":"Dej\u00e1",
    "gn:population":0,
    "gn:timezone":"America/Port-au-Prince",
    "iso:country":"HT",
    "name:ceb_x_preferred":[
        "Deja"
    ],
    "name:deu_x_preferred":[
        "Deja"
    ],
    "name:swe_x_preferred":[
        "Deja"
    ],
    "wof:name":"Deja",
    "wof:placetype":"locality"
},
  "geometry": {"coordinates":[-72.40000000000001,19.38333],"type":"Point"}
}