{
  "type": "Feature",
  "properties": {
    "gn:admin1_code":"7.0",
    "gn:admin2_code":"3728053.0",
    "gn:asciiname":"Lamielle",
    "gn:country_code":"HT",
    "gn:dem":521,
    "gn:feature_class":"P",
    "gn:feature_code":"PPL",
    "gn:name":"Lamielle",
    "gn:population":0,
    "gn:timezone":"America/Port-au-Prince",
    "iso:country":"HT",
    "name:und_x_variant":[
        "La Miel"
    ],
    "wof:name":"Lamielle",
    "wof:placetype":"locality"
},
  "geometry": {"coordinates":[-71.72878,19.24319],"type":"Point"}
}