{
  "type": "Feature",
  "properties": {
    "gn:admin1_code":"11.0",
    "gn:admin2_code":"3718425.0",
    "gn:asciiname":"Macon",
    "gn:country_code":"HT",
    "gn:dem":768,
    "gn:feature_class":"P",
    "gn:feature_code":"PPL",
    "gn:name":"Ma\u00e7on",
    "gn:population":0,
    "gn:timezone":"America/Port-au-Prince",
    "iso:country":"HT",
    "name:bre_x_preferred":[
        "Macon"
    ],
    "name:cat_x_preferred":[
        "Macon"
    ],
    "name:ceb_x_preferred":[
        "Macon"
    ],
    "name:ces_x_preferred":[
        "Macon"
    ],
    "name:deu_x_preferred":[
        "Macon"
    ],
    "name:epo_x_preferred":[
        "Macon"
    ],
    "name:fra_x_preferred":[
        "Macon"
    ],
    "name:hun_x_preferred":[
        "Macon"
    ],
    "name:ita_x_preferred":[
        "Macon"
    ],
    "name:jpn_x_preferred":[
        "\u30e1\u30a4\u30b3\u30f3"
    ],
    "name:kor_x_preferred":[
        "\uba54\uc774\ucee8"
    ],
    "name:nld_x_preferred":[
        "Macon"
    ],
    "name:pol_x_preferred":[
        "Macon"
    ],
    "name:por_x_preferred":[
        "Macon"
    ],
    "name:ron_x_preferred":[
        "Macon"
    ],
    "name:rus_x_preferred":[
        "\u041c\u0430\u043a\u043e\u043d"
    ],
    "name:spa_x_preferred":[
        "Macon"
    ],
    "name:srp_x_preferred":[
        "\u041c\u0435\u0458\u043a\u043e\u043d"
    ],
    "name:swe_x_preferred":[
        "Macon"
    ],
    "name:ukr_x_preferred":[
        "\u041c\u0435\u0439\u043a\u043e\u043d"
    ],
    "name:vol_x_preferred":[
        "Macon"
    ],
    "wof:name":"Macon",
    "wof:placetype":"locality"
},
  "geometry": {"coordinates":[-72.38333,18.45],"type":"Point"}
}