{
  "type": "Feature",
  "properties": {
    "gn:admin1_code":"11.0",
    "gn:admin2_code":"3723019.0",
    "gn:asciiname":"Platon Trou Bigaille",
    "gn:country_code":"HT",
    "gn:dem":200,
    "gn:feature_class":"P",
    "gn:feature_code":"PPL",
    "gn:name":"Platon Trou Bigaille",
    "gn:population":0,
    "gn:timezone":"America/Port-au-Prince",
    "iso:country":"HT",
    "name:und_x_variant":[
        "Trou Bigaille",
        "Platon Trou Bigaille"
    ],
    "wof:name":"Platon Trou Bigaille",
    "wof:placetype":"locality"
},
  "geometry": {"coordinates":[-73.08291,18.8158],"type":"Point"}
}