{
  "type": "Feature",
  "properties": {
    "gn:admin1_code":"7.0",
    "gn:admin2_code":"3722578.0",
    "gn:asciiname":"Decouverte",
    "gn:country_code":"HT",
    "gn:dem":1280,
    "gn:feature_class":"P",
    "gn:feature_code":"PPL",
    "gn:name":"D\u00e9couverte",
    "gn:population":0,
    "gn:timezone":"America/Port-au-Prince",
    "iso:country":"HT",
    "name:fra_x_preferred":[
        "D\u00e9couverte"
    ],
    "wof:name":"Decouverte",
    "wof:placetype":"locality"
},
  "geometry": {"coordinates":[-71.74275,18.7375],"type":"Point"}
}