{
  "type": "Feature",
  "properties": {
    "gn:admin1_code":"10.0",
    "gn:admin2_code":"3725169.0",
    "gn:asciiname":"Delpeche",
    "gn:country_code":"HT",
    "gn:dem":612,
    "gn:feature_class":"P",
    "gn:feature_code":"PPL",
    "gn:name":"Delp\u00e8che",
    "gn:population":0,
    "gn:timezone":"America/Port-au-Prince",
    "iso:country":"HT",
    "name:fra_x_preferred":[
        "Delp\u00e8che"
    ],
    "wof:name":"Delpeche",
    "wof:placetype":"locality"
},
  "geometry": {"coordinates":[-71.92350999999999,19.4657],"type":"Point"}
}