{
  "type": "Feature",
  "properties": {
    "gn:admin1_code":"3.0",
    "gn:admin2_code":"3720764.0",
    "gn:asciiname":"Nan Bantier",
    "gn:country_code":"HT",
    "gn:dem":12,
    "gn:feature_class":"P",
    "gn:feature_code":"PPL",
    "gn:name":"Nan Bantier",
    "gn:population":0,
    "gn:timezone":"America/Port-au-Prince",
    "iso:country":"HT",
    "wof:name":"Nan Bantier",
    "wof:placetype":"locality"
},
  "geometry": {"coordinates":[-73.06028000000001,19.90083],"type":"Point"}
}