{
  "type": "Feature",
  "properties": {
    "gn:admin1_code":"6.0",
    "gn:admin2_code":"3726539.0",
    "gn:asciiname":"Poux",
    "gn:country_code":"HT",
    "gn:dem":71,
    "gn:feature_class":"P",
    "gn:feature_code":"PPL",
    "gn:name":"Poux",
    "gn:population":0,
    "gn:timezone":"America/Port-au-Prince",
    "iso:country":"HT",
    "name:fra_x_preferred":[
        "Poux"
    ],
    "wof:name":"Poux",
    "wof:placetype":"locality"
},
  "geometry": {"coordinates":[-72.37168,19.01803],"type":"Point"}
}