{
  "type": "Feature",
  "properties": {
    "gn:admin1_code":"9.0",
    "gn:admin2_code":"3722122.0",
    "gn:asciiname":"Calumette",
    "gn:country_code":"HT",
    "gn:dem":275,
    "gn:feature_class":"P",
    "gn:feature_code":"PPL",
    "gn:name":"Calumette",
    "gn:population":0,
    "gn:timezone":"America/Port-au-Prince",
    "iso:country":"HT",
    "wof:name":"Calumette",
    "wof:placetype":"locality"
},
  "geometry": {"coordinates":[-72.43333,19.68333],"type":"Point"}
}