{
  "type": "Feature",
  "properties": {
    "gn:admin1_code":"11.0",
    "gn:admin2_code":"3731086.0",
    "gn:asciiname":"Leger",
    "gn:country_code":"HT",
    "gn:dem":1208,
    "gn:feature_class":"P",
    "gn:feature_code":"PPL",
    "gn:name":"L\u00e9ger",
    "gn:population":0,
    "gn:timezone":"America/Port-au-Prince",
    "iso:country":"HT",
    "name:deu_x_preferred":[
        "Leger"
    ],
    "name:fry_x_preferred":[
        "Leger"
    ],
    "name:nld_x_preferred":[
        "Leger"
    ],
    "wof:name":"Leger",
    "wof:placetype":"locality"
},
  "geometry": {"coordinates":[-72.45,18.91667],"type":"Point"}
}