{
  "type": "Feature",
  "properties": {
    "gn:admin1_code":"6.0",
    "gn:admin2_code":"3717587.0",
    "gn:asciiname":"Popotte",
    "gn:country_code":"HT",
    "gn:dem":603,
    "gn:feature_class":"P",
    "gn:feature_code":"PPL",
    "gn:name":"Popotte",
    "gn:population":0,
    "gn:timezone":"America/Port-au-Prince",
    "iso:country":"HT",
    "name:fra_x_preferred":[
        "Popotte"
    ],
    "wof:name":"Popotte",
    "wof:placetype":"locality"
},
  "geometry": {"coordinates":[-72.58452,19.04076],"type":"Point"}
}