{
  "type": "Feature",
  "properties": {
    "gn:admin1_code":"13.0",
    "gn:admin2_code":"3730910.0",
    "gn:asciiname":"Jo Fourneau",
    "gn:cc2":"HT",
    "gn:country_code":"HT",
    "gn:dem":359,
    "gn:feature_class":"P",
    "gn:feature_code":"PPL",
    "gn:name":"Jo Fourneau",
    "gn:population":0,
    "gn:timezone":"America/Port-au-Prince",
    "iso:country":"HT",
    "name:fra_x_preferred":[
        "La Fourneau"
    ],
    "name:und_x_variant":[
        "La Forneau",
        "Jo Forneau",
        "Jo Fourneau"
    ],
    "wof:name":"Jo Fourneau",
    "wof:placetype":"locality"
},
  "geometry": {"coordinates":[-72.83667,18.18611],"type":"Point"}
}