{
  "type": "Feature",
  "properties": {
    "gn:admin1_code":"13.0",
    "gn:admin2_code":"3730361.0",
    "gn:asciiname":"Nan Noel",
    "gn:country_code":"HT",
    "gn:dem":868,
    "gn:feature_class":"P",
    "gn:feature_code":"PPL",
    "gn:name":"Nan No\u00ebl",
    "gn:population":0,
    "gn:timezone":"America/Port-au-Prince",
    "iso:country":"HT",
    "name:fra_x_preferred":[
        "Nan No\u00ebl"
    ],
    "wof:name":"Nan Noel",
    "wof:placetype":"locality"
},
  "geometry": {"coordinates":[-72.20618,18.25899],"type":"Point"}
}