{
  "type": "Feature",
  "properties": {
    "gn:admin1_code":"6.0",
    "gn:asciiname":"Plaine Bassin",
    "gn:country_code":"HT",
    "gn:dem":654,
    "gn:feature_class":"P",
    "gn:feature_code":"PPL",
    "gn:name":"Plaine Bassin",
    "gn:population":0,
    "gn:timezone":"America/Port-au-Prince",
    "iso:country":"HT",
    "name:fra_x_preferred":[
        "Plaine Bassin"
    ],
    "wof:name":"Plaine Bassin",
    "wof:placetype":"locality"
},
  "geometry": {"coordinates":[-72.37444000000001,19.53575],"type":"Point"}
}