{
  "type": "Feature",
  "properties": {
    "gn:admin1_code":"15.0",
    "gn:asciiname":"Brea",
    "gn:country_code":"HT",
    "gn:dem":-9999,
    "gn:feature_class":"P",
    "gn:feature_code":"PPL",
    "gn:name":"Br\u00e9a",
    "gn:population":0,
    "gn:timezone":"America/Port-au-Prince",
    "iso:country":"HT",
    "name:cat_x_preferred":[
        "Brea"
    ],
    "name:ceb_x_preferred":[
        "Brea"
    ],
    "name:deu_x_preferred":[
        "Brea"
    ],
    "name:fin_x_preferred":[
        "Brea"
    ],
    "name:fra_x_preferred":[
        "Br\u00e9a"
    ],
    "name:glg_x_preferred":[
        "Brea"
    ],
    "name:ita_x_preferred":[
        "Brea"
    ],
    "name:kor_x_preferred":[
        "\ube0c\ub808\uc544"
    ],
    "name:nld_x_preferred":[
        "Brea"
    ],
    "name:pol_x_preferred":[
        "Brea"
    ],
    "name:por_x_preferred":[
        "Brea"
    ],
    "name:rus_x_preferred":[
        "\u0411\u0440\u0435\u0430"
    ],
    "name:spa_x_preferred":[
        "Brea"
    ],
    "name:swe_x_preferred":[
        "Brea"
    ],
    "wof:name":"Brea",
    "wof:placetype":"locality"
},
  "geometry": {"coordinates":[-73.65000000000001,18.55],"type":"Point"}
}