{
  "type": "Feature",
  "properties": {
    "gn:admin1_code":"13.0",
    "gn:admin2_code":"3730361.0",
    "gn:asciiname":"Ratier",
    "gn:country_code":"HT",
    "gn:dem":706,
    "gn:feature_class":"P",
    "gn:feature_code":"PPL",
    "gn:name":"Ratier",
    "gn:population":0,
    "gn:timezone":"America/Port-au-Prince",
    "iso:country":"HT",
    "name:deu_x_preferred":[
        "Ratier-Figeac"
    ],
    "name:fra_x_preferred":[
        "Ratier"
    ],
    "wof:name":"Ratier",
    "wof:placetype":"locality"
},
  "geometry": {"coordinates":[-71.91667,18.26667],"type":"Point"}
}