{
  "type": "Feature",
  "properties": {
    "gn:admin1_code":"11.0",
    "gn:admin2_code":"3722285.0",
    "gn:asciiname":"Lamy",
    "gn:country_code":"HT",
    "gn:dem":813,
    "gn:feature_class":"P",
    "gn:feature_code":"PPL",
    "gn:name":"Lamy",
    "gn:population":0,
    "gn:timezone":"America/Port-au-Prince",
    "iso:country":"HT",
    "name:ces_x_preferred":[
        "Lamy"
    ],
    "name:deu_x_preferred":[
        "Lamy"
    ],
    "name:fra_x_preferred":[
        "Lamy"
    ],
    "name:ita_x_preferred":[
        "Lamy"
    ],
    "name:jpn_x_preferred":[
        "\u30e9\u30df\u30fc"
    ],
    "name:lav_x_preferred":[
        "Lamy"
    ],
    "name:swe_x_preferred":[
        "Lamy"
    ],
    "name:tha_x_preferred":[
        "\u0e25\u0e32\u0e21\u0e35\u0e48"
    ],
    "wof:name":"Lamy",
    "wof:placetype":"locality"
},
  "geometry": {"coordinates":[-72.98333000000002,18.35],"type":"Point"}
}