{
  "type": "Feature",
  "properties": {
    "gn:admin1_code":"11.0",
    "gn:admin2_code":"3718425.0",
    "gn:asciiname":"Grande Riviere",
    "gn:country_code":"HT",
    "gn:dem":588,
    "gn:feature_class":"P",
    "gn:feature_code":"PPL",
    "gn:name":"Grande Rivi\u00e8re",
    "gn:population":0,
    "gn:timezone":"America/Port-au-Prince",
    "iso:country":"HT",
    "wof:name":"Grande Riviere",
    "wof:placetype":"locality"
},
  "geometry": {"coordinates":[-72.43333,18.46667],"type":"Point"}
}