{
  "type": "Feature",
  "properties": {
    "gn:admin1_code":"11.0",
    "gn:admin2_code":"3731086.0",
    "gn:asciiname":"Hatte Robert",
    "gn:country_code":"HT",
    "gn:dem":60,
    "gn:feature_class":"P",
    "gn:feature_code":"PPL",
    "gn:name":"Hatte Robert",
    "gn:population":0,
    "gn:timezone":"America/Port-au-Prince",
    "iso:country":"HT",
    "name:und_x_variant":[
        "Robert",
        "Hatte Robert"
    ],
    "wof:name":"Hatte Robert",
    "wof:placetype":"locality"
},
  "geometry": {"coordinates":[-72.49856,18.79181],"type":"Point"}
}