{
  "type": "Feature",
  "properties": {
    "gn:admin1_code":"11.0",
    "gn:admin2_code":"3727134.0",
    "gn:asciiname":"Risque",
    "gn:country_code":"HT",
    "gn:dem":131,
    "gn:feature_class":"P",
    "gn:feature_code":"PPL",
    "gn:name":"Risque",
    "gn:population":0,
    "gn:timezone":"America/Port-au-Prince",
    "iso:country":"HT",
    "name:fra_x_preferred":[
        "Risque"
    ],
    "name:fra_x_variant":[
        "Risqu\u00e9"
    ],
    "wof:name":"Risque",
    "wof:placetype":"locality"
},
  "geometry": {"coordinates":[-72.11688000000002,18.53883],"type":"Point"}
}