{
  "type": "Feature",
  "properties": {
    "gn:admin1_code":"10.0",
    "gn:admin2_code":"3716223.0",
    "gn:asciiname":"Bercera",
    "gn:country_code":"HT",
    "gn:dem":78,
    "gn:feature_class":"P",
    "gn:feature_code":"PPL",
    "gn:name":"Bercera",
    "gn:population":0,
    "gn:timezone":"America/Port-au-Prince",
    "iso:country":"HT",
    "name:und_x_variant":[
        "Bercery",
        "Bercera"
    ],
    "wof:name":"Bercera",
    "wof:placetype":"locality"
},
  "geometry": {"coordinates":[-71.97638000000001,19.61991],"type":"Point"}
}