{
  "type": "Feature",
  "properties": {
    "gn:admin1_code":"6.0",
    "gn:admin2_code":"3724695.0",
    "gn:asciiname":"Desire",
    "gn:country_code":"HT",
    "gn:dem":103,
    "gn:feature_class":"P",
    "gn:feature_code":"PPL",
    "gn:name":"D\u00e9sir\u00e9",
    "gn:population":0,
    "gn:timezone":"America/Port-au-Prince",
    "iso:country":"HT",
    "name:ara_x_preferred":[
        "\u0631\u063a\u0628\u0629"
    ],
    "name:bul_x_preferred":[
        "\u0416\u0435\u043b\u0430\u043d\u0438\u0435"
    ],
    "name:ces_x_preferred":[
        "Touha"
    ],
    "name:deu_x_preferred":[
        "Begierde"
    ],
    "name:epo_x_preferred":[
        "Avido"
    ],
    "name:est_x_preferred":[
        "Himu"
    ],
    "name:eus_x_preferred":[
        "Desira"
    ],
    "name:fin_x_preferred":[
        "Halu"
    ],
    "name:fra_x_preferred":[
        "D\u00e9sir"
    ],
    "name:gle_x_preferred":[
        "Fonn"
    ],
    "name:heb_x_preferred":[
        "\u05db\u05de\u05d9\u05d4\u05d4"
    ],
    "name:hin_x_preferred":[
        "\u0907\u0915\u094d\u0937\u093e"
    ],
    "name:hun_x_preferred":[
        "V\u00e1gy"
    ],
    "name:kan_x_preferred":[
        "\u0cac\u0caf\u0c95\u0cc6"
    ],
    "name:lit_x_preferred":[
        "Tro\u0161kimas"
    ],
    "name:new_x_preferred":[
        "\u0907\u091a\u094d\u091b\u093e"
    ],
    "name:nor_x_preferred":[
        "Lyst"
    ],
    "name:oci_x_preferred":[
        "Desir"
    ],
    "name:pan_x_preferred":[
        "\u0a1a\u0a3e\u0a39\u0a24"
    ],
    "name:ron_x_preferred":[
        "Dorin\u021b\u0103"
    ],
    "name:slk_x_preferred":[
        "T\u00fa\u017eba"
    ],
    "name:tam_x_preferred":[
        "\u0b85\u0bb5\u0bbe"
    ],
    "name:tel_x_preferred":[
        "\u0c15\u0c4b\u0c30\u0c3f\u0c15"
    ],
    "name:tgl_x_preferred":[
        "Nais"
    ],
    "wof:name":"Desire",
    "wof:placetype":"locality"
},
  "geometry": {"coordinates":[-72.55,19.35],"type":"Point"}
}