{
  "type": "Feature",
  "properties": {
    "gn:admin1_code":"12.0",
    "gn:admin2_code":"3728096.0",
    "gn:asciiname":"Mahotiere",
    "gn:country_code":"HT",
    "gn:dem":261,
    "gn:feature_class":"P",
    "gn:feature_code":"PPL",
    "gn:name":"Mahoti\u00e8re",
    "gn:population":0,
    "gn:timezone":"America/Port-au-Prince",
    "iso:country":"HT",
    "name:fra_x_preferred":[
        "Mahoti\u00e8re"
    ],
    "wof:name":"Mahotiere",
    "wof:placetype":"locality"
},
  "geometry": {"coordinates":[-73.83811,18.37005],"type":"Point"}
}