{
  "type": "Feature",
  "properties": {
    "gn:admin1_code":"14.0",
    "gn:admin2_code":"3723592.0",
    "gn:asciiname":"Dayere",
    "gn:country_code":"HT",
    "gn:dem":445,
    "gn:feature_class":"P",
    "gn:feature_code":"PPL",
    "gn:name":"Dayere",
    "gn:population":0,
    "gn:timezone":"America/Port-au-Prince",
    "iso:country":"HT",
    "wof:name":"Dayere",
    "wof:placetype":"locality"
},
  "geometry": {"coordinates":[-74.18333,18.51667],"type":"Point"}
}