{
  "type": "Feature",
  "properties": {
    "gn:admin1_code":"13.0",
    "gn:admin2_code":"3723778.0",
    "gn:asciiname":"Nan Bellale",
    "gn:country_code":"HT",
    "gn:dem":753,
    "gn:feature_class":"P",
    "gn:feature_code":"PPL",
    "gn:name":"Nan Bellale",
    "gn:population":0,
    "gn:timezone":"America/Port-au-Prince",
    "iso:country":"HT",
    "wof:name":"Nan Bellale",
    "wof:placetype":"locality"
},
  "geometry": {"coordinates":[-72.43333,18.36667000000001],"type":"Point"}
}