{
  "type": "Feature",
  "properties": {
    "gn:admin1_code":"12.0",
    "gn:admin2_code":"3731094.0",
    "gn:asciiname":"Vibert",
    "gn:country_code":"HT",
    "gn:dem":148,
    "gn:feature_class":"P",
    "gn:feature_code":"PPL",
    "gn:name":"Vibert",
    "gn:population":0,
    "gn:timezone":"America/Port-au-Prince",
    "iso:country":"HT",
    "name:ces_x_preferred":[
        "Vibert"
    ],
    "name:deu_x_preferred":[
        "Vibert"
    ],
    "name:fra_x_preferred":[
        "Vibert"
    ],
    "name:rus_x_preferred":[
        "\u0412\u0438\u0431\u0435\u0440"
    ],
    "name:und_x_variant":[
        "Puits Vibert"
    ],
    "wof:name":"Vibert",
    "wof:placetype":"locality"
},
  "geometry": {"coordinates":[-73.11171999999998,18.23164],"type":"Point"}
}