{
  "type": "Feature",
  "properties": {
    "gn:admin1_code":"7.0",
    "gn:admin2_code":"3720809.0",
    "gn:asciiname":"Chevrie",
    "gn:country_code":"HT",
    "gn:dem":97,
    "gn:feature_class":"P",
    "gn:feature_code":"PPL",
    "gn:name":"Chevrie",
    "gn:population":0,
    "gn:timezone":"America/Port-au-Prince",
    "iso:country":"HT",
    "name:fra_x_preferred":[
        "Chevrie"
    ],
    "wof:name":"Chevrie",
    "wof:placetype":"locality"
},
  "geometry": {"coordinates":[-72.20623000000001,18.88215],"type":"Point"}
}