{
  "type": "Feature",
  "properties": {
    "gn:admin1_code":"13.0",
    "gn:admin2_code":"3730361.0",
    "gn:asciiname":"Commandant",
    "gn:country_code":"HT",
    "gn:dem":404,
    "gn:feature_class":"P",
    "gn:feature_code":"PPL",
    "gn:name":"Commandant",
    "gn:population":0,
    "gn:timezone":"America/Port-au-Prince",
    "iso:country":"HT",
    "name:bel_x_preferred":[
        "\u041a\u0430\u043c\u0435\u043d\u0434\u0430\u043d\u0442"
    ],
    "name:bos_x_preferred":[
        "Komandant"
    ],
    "name:deu_x_preferred":[
        "Kommandant"
    ],
    "name:fra_x_preferred":[
        "Commandant"
    ],
    "name:fry_x_preferred":[
        "Kommandant"
    ],
    "name:ind_x_preferred":[
        "Komandan"
    ],
    "name:kaz_x_preferred":[
        "\u041a\u043e\u043c\u0435\u043d\u0434\u0430\u043d\u0442"
    ],
    "name:kir_x_preferred":[
        "\u041a\u043e\u043c\u0435\u043d\u0434\u0430\u043d\u0442"
    ],
    "name:lit_x_preferred":[
        "Komandantas"
    ],
    "name:msa_x_preferred":[
        "Komandan"
    ],
    "name:nld_x_preferred":[
        "Commandant"
    ],
    "name:nno_x_preferred":[
        "Befalingsmann"
    ],
    "name:nor_x_preferred":[
        "Befal"
    ],
    "name:oss_x_preferred":[
        "\u041a\u043e\u043c\u0430\u043d\u0434\u0430\u043d\u0442\u0435"
    ],
    "name:pol_x_preferred":[
        "Komendant"
    ],
    "name:rus_x_preferred":[
        "\u041a\u043e\u043c\u0435\u043d\u0434\u0430\u043d\u0442"
    ],
    "name:slv_x_preferred":[
        "Komandant"
    ],
    "name:swe_x_preferred":[
        "Bef\u00e4l"
    ],
    "name:ukr_x_preferred":[
        "\u041a\u043e\u043c\u0435\u043d\u0434\u0430\u043d\u0442"
    ],
    "wof:name":"Commandant",
    "wof:placetype":"locality"
},
  "geometry": {"coordinates":[-72.09999999999999,18.26667],"type":"Point"}
}