{
  "type": "Feature",
  "properties": {
    "gn:admin1_code":"11.0",
    "gn:admin2_code":"3722285.0",
    "gn:asciiname":"Cormier",
    "gn:country_code":"HT",
    "gn:dem":437,
    "gn:feature_class":"P",
    "gn:feature_code":"PPL",
    "gn:name":"Cormier",
    "gn:population":0,
    "gn:timezone":"America/Port-au-Prince",
    "iso:country":"HT",
    "name:deu_x_preferred":[
        "Cormier"
    ],
    "name:fra_x_preferred":[
        "Cormier"
    ],
    "name:rus_x_preferred":[
        "\u041a\u043e\u0440\u043c\u044c\u0435"
    ],
    "wof:name":"Cormier",
    "wof:placetype":"locality"
},
  "geometry": {"coordinates":[-72.64022,18.41949],"type":"Point"}
}