{
  "type": "Feature",
  "properties": {
    "gn:admin1_code":"6.0",
    "gn:admin2_code":"3717563.0",
    "gn:asciiname":"Grande Plaine",
    "gn:country_code":"HT",
    "gn:dem":431,
    "gn:feature_class":"P",
    "gn:feature_code":"PPL",
    "gn:name":"Grande Plaine",
    "gn:population":0,
    "gn:timezone":"America/Port-au-Prince",
    "iso:country":"HT",
    "wof:name":"Grande Plaine",
    "wof:placetype":"locality"
},
  "geometry": {"coordinates":[-72.34999999999999,19.36667000000001],"type":"Point"}
}