{
  "type": "Feature",
  "properties": {
    "gn:admin1_code":"11.0",
    "gn:admin2_code":"3723019.0",
    "gn:asciiname":"Tresor",
    "gn:country_code":"HT",
    "gn:dem":384,
    "gn:feature_class":"P",
    "gn:feature_code":"PPL",
    "gn:name":"Tr\u00e9sor",
    "gn:population":0,
    "gn:timezone":"America/Port-au-Prince",
    "iso:country":"HT",
    "name:fra_x_preferred":[
        "Tr\u00e9sor"
    ],
    "wof:name":"Tresor",
    "wof:placetype":"locality"
},
  "geometry": {"coordinates":[-72.86828,18.79592],"type":"Point"}
}