{
  "type": "Feature",
  "properties": {
    "gn:admin1_code":"6.0",
    "gn:admin2_code":"3726539.0",
    "gn:asciiname":"Vedery",
    "gn:country_code":"HT",
    "gn:dem":18,
    "gn:feature_class":"P",
    "gn:feature_code":"PPL",
    "gn:name":"V\u00e9dery",
    "gn:population":0,
    "gn:timezone":"America/Port-au-Prince",
    "iso:country":"HT",
    "name:fra_x_preferred":[
        "V\u00e9dery"
    ],
    "wof:name":"Vedery",
    "wof:placetype":"locality"
},
  "geometry": {"coordinates":[-72.56801,19.18595],"type":"Point"}
}