{
  "type": "Feature",
  "properties": {
    "gn:country":"HT",
    "gn:fcode":"PPL",
    "gn:pop":1609,
    "iso:country":"HT",
    "name:ara_x_preferred":[
        "\u0643\u0627\u064a\u0633 \u062c\u0627\u0643\u0645\u064a\u0644"
    ],
    "name:eng_x_preferred":[
        "Cayes-Jacmel"
    ],
    "name:fra_x_preferred":[
        "Cayes-Jacmel"
    ],
    "name:hat_x_preferred":[
        "Kay Jakm\u00e8l"
    ],
    "name:ita_x_preferred":[
        "Cayes-Jacmel"
    ],
    "name:nld_x_preferred":[
        "Cayes-Jacmel"
    ],
    "name:por_x_preferred":[
        "Cayes-Jacmel"
    ],
    "name:ron_x_preferred":[
        "Cayes-Jacmel"
    ],
    "name:spa_x_preferred":[
        "Cayes-Jacmel"
    ],
    "name:unk_x_variant":[
        "Cayes de Jacmel"
    ],
    "qs:name":"Cayes Jacmel",
    "qs:photos_9r":0,
    "qs:photos_sr":0,
    "qs:pop_sr":"3",
    "wd:wordcount":91,
    "wof:name":"Cayes Jacmel",
    "wof:placetype":"locality",
    "wof:population":1609
},
  "geometry": {"coordinates":[-72.39610999999999,18.23028],"type":"Point"}
}