{
  "type": "Feature",
  "properties": {
    "gn:admin1_code":"11.0",
    "gn:asciiname":"Merger",
    "gn:country_code":"HT",
    "gn:dem":52,
    "gn:feature_class":"P",
    "gn:feature_code":"PPL",
    "gn:name":"Merger",
    "gn:population":0,
    "gn:timezone":"America/Port-au-Prince",
    "iso:country":"HT",
    "name:fra_x_preferred":[
        "Merger"
    ],
    "wof:name":"Merger",
    "wof:placetype":"locality"
},
  "geometry": {"coordinates":[-72.49021,18.54151],"type":"Point"}
}