{
  "type": "Feature",
  "properties": {
    "gn:admin1_code":"6.0",
    "gn:admin2_code":"3717563.0",
    "gn:asciiname":"Mare Blanche",
    "gn:country_code":"HT",
    "gn:dem":686,
    "gn:feature_class":"P",
    "gn:feature_code":"PPL",
    "gn:name":"Mare Blanche",
    "gn:population":0,
    "gn:timezone":"America/Port-au-Prince",
    "iso:country":"HT",
    "wof:name":"Mare Blanche",
    "wof:placetype":"locality"
},
  "geometry": {"coordinates":[-72.40000000000001,19.48333],"type":"Point"}
}