{
  "type": "Feature",
  "properties": {
    "gn:admin1_code":"6.0",
    "gn:admin2_code":"3717587.0",
    "gn:asciiname":"Charlet",
    "gn:country_code":"HT",
    "gn:dem":149,
    "gn:feature_class":"P",
    "gn:feature_code":"PPL",
    "gn:name":"Charlet",
    "gn:population":0,
    "gn:timezone":"America/Port-au-Prince",
    "iso:country":"HT",
    "wof:name":"Charlet",
    "wof:placetype":"locality"
},
  "geometry": {"coordinates":[-72.48333000000002,19.05],"type":"Point"}
}