{
  "type": "Feature",
  "properties": {
    "gn:admin1_code":"7.0",
    "gn:admin2_code":"3723840.0",
    "gn:asciiname":"Caimites",
    "gn:country_code":"HT",
    "gn:dem":434,
    "gn:feature_class":"P",
    "gn:feature_code":"PPL",
    "gn:name":"Ca\u00efmites",
    "gn:population":0,
    "gn:timezone":"America/Port-au-Prince",
    "iso:country":"HT",
    "name:und_x_variant":[
        "Caimite",
        "Ca\u00efmites"
    ],
    "wof:name":"Caimites",
    "wof:placetype":"locality"
},
  "geometry": {"coordinates":[-71.96531,19.23507],"type":"Point"}
}