{
  "type": "Feature",
  "properties": {
    "gn:admin1_code":"6.0",
    "gn:admin2_code":"3726539.0",
    "gn:asciiname":"Boulaillo",
    "gn:country_code":"HT",
    "gn:dem":694,
    "gn:feature_class":"P",
    "gn:feature_code":"PPL",
    "gn:name":"Boulaillo",
    "gn:population":0,
    "gn:timezone":"America/Port-au-Prince",
    "iso:country":"HT",
    "wof:name":"Boulaillo",
    "wof:placetype":"locality"
},
  "geometry": {"coordinates":[-72.31667,19.13333],"type":"Point"}
}