{
  "type": "Feature",
  "properties": {
    "gn:admin1_code":"9.0",
    "gn:admin2_code":"3731232.0",
    "gn:asciiname":"Bordes",
    "gn:country_code":"HT",
    "gn:dem":162,
    "gn:feature_class":"P",
    "gn:feature_code":"PPL",
    "gn:name":"Bordes",
    "gn:population":0,
    "gn:timezone":"America/Port-au-Prince",
    "iso:country":"HT",
    "name:arg_x_preferred":[
        "Bordes"
    ],
    "name:cat_x_preferred":[
        "Bordes"
    ],
    "name:ceb_x_preferred":[
        "Bordes"
    ],
    "name:deu_x_preferred":[
        "Bordes"
    ],
    "name:fra_x_preferred":[
        "Bordes"
    ],
    "name:ita_x_preferred":[
        "Bordes"
    ],
    "name:nds_x_preferred":[
        "Bordes"
    ],
    "name:nld_x_preferred":[
        "Bordes"
    ],
    "name:pms_x_preferred":[
        "Bordes"
    ],
    "name:pol_x_preferred":[
        "Bordes"
    ],
    "name:por_x_preferred":[
        "Bordes"
    ],
    "name:rus_x_preferred":[
        "\u0411\u043e\u0440\u0434\u0435\u0441"
    ],
    "name:slk_x_preferred":[
        "Bordes"
    ],
    "name:spa_x_preferred":[
        "Bordes"
    ],
    "name:swe_x_preferred":[
        "Bordes"
    ],
    "wof:name":"Bordes",
    "wof:placetype":"locality"
},
  "geometry": {"coordinates":[-72.23333000000002,19.61667000000001],"type":"Point"}
}