{
  "type": "Feature",
  "properties": {
    "gn:admin1_code":"6.0",
    "gn:asciiname":"Lourou",
    "gn:country_code":"HT",
    "gn:dem":254,
    "gn:feature_class":"P",
    "gn:feature_code":"PPL",
    "gn:name":"Lourou",
    "gn:population":0,
    "gn:timezone":"America/Port-au-Prince",
    "iso:country":"HT",
    "name:fra_x_preferred":[
        "Lourou"
    ],
    "wof:name":"Lourou",
    "wof:placetype":"locality"
},
  "geometry": {"coordinates":[-72.60526999999998,19.67568],"type":"Point"}
}