{
  "type": "Feature",
  "properties": {
    "gn:admin1_code":"9.0",
    "gn:admin2_code":"3731232.0",
    "gn:asciiname":"Gallifet",
    "gn:country_code":"HT",
    "gn:dem":28,
    "gn:feature_class":"P",
    "gn:feature_code":"PPL",
    "gn:name":"Gallifet",
    "gn:population":0,
    "gn:timezone":"America/Port-au-Prince",
    "iso:country":"HT",
    "name:und_x_variant":[
        "Galiffet",
        "Gallifet"
    ],
    "wof:name":"Gallifet",
    "wof:placetype":"locality"
},
  "geometry": {"coordinates":[-72.20520999999999,19.66395],"type":"Point"}
}