{
  "type": "Feature",
  "properties": {
    "gn:admin1_code":"7.0",
    "gn:admin2_code":"3723840.0",
    "gn:asciiname":"La Guardiane",
    "gn:country_code":"HT",
    "gn:dem":314,
    "gn:feature_class":"P",
    "gn:feature_code":"PPL",
    "gn:name":"La Guardiane",
    "gn:population":0,
    "gn:timezone":"America/Port-au-Prince",
    "iso:country":"HT",
    "name:fra_x_preferred":[
        "La Guardiane"
    ],
    "name:fra_x_variant":[
        "Laguardiane"
    ],
    "wof:name":"La Guardiane",
    "wof:placetype":"locality"
},
  "geometry": {"coordinates":[-71.89397,19.13748],"type":"Point"}
}