{
  "type": "Feature",
  "properties": {
    "gn:admin1_code":"11.0",
    "gn:admin2_code":"3727134.0",
    "gn:asciiname":"Mare Dejeune",
    "gn:country_code":"HT",
    "gn:dem":471,
    "gn:feature_class":"P",
    "gn:feature_code":"PPL",
    "gn:name":"Mare D\u00e9jeune",
    "gn:population":0,
    "gn:timezone":"America/Port-au-Prince",
    "iso:country":"HT",
    "name:fra_x_preferred":[
        "Mare D\u00e9jeune"
    ],
    "wof:name":"Mare Dejeune",
    "wof:placetype":"locality"
},
  "geometry": {"coordinates":[-72.05086999999997,18.68292000000001],"type":"Point"}
}