{
  "type": "Feature",
  "properties": {
    "gn:admin1_code":"6.0",
    "gn:admin2_code":"3726539.0",
    "gn:asciiname":"Plasac",
    "gn:country_code":"HT",
    "gn:dem":119,
    "gn:feature_class":"P",
    "gn:feature_code":"PPL",
    "gn:name":"Plasac",
    "gn:population":0,
    "gn:timezone":"America/Port-au-Prince",
    "iso:country":"HT",
    "name:fra_x_preferred":[
        "Plasac"
    ],
    "wof:name":"Plasac",
    "wof:placetype":"locality"
},
  "geometry": {"coordinates":[-72.40389999999999,19.07315],"type":"Point"}
}