{
  "type": "Feature",
  "properties": {
    "gn:admin1_code":"15.0",
    "gn:admin2_code":"3731122.0",
    "gn:asciiname":"Dolette",
    "gn:country_code":"HT",
    "gn:dem":512,
    "gn:feature_class":"P",
    "gn:feature_code":"PPL",
    "gn:name":"Dolette",
    "gn:population":0,
    "gn:timezone":"America/Port-au-Prince",
    "iso:country":"HT",
    "name:und_x_variant":[
        "Dorlette",
        "Dolette"
    ],
    "wof:name":"Dolette",
    "wof:placetype":"locality"
},
  "geometry": {"coordinates":[-73.54639,18.39944],"type":"Point"}
}