{
  "type": "Feature",
  "properties": {
    "gn:admin1_code":"9.0",
    "gn:admin2_code":"3731232.0",
    "gn:asciiname":"Belair",
    "gn:country_code":"HT",
    "gn:dem":316,
    "gn:feature_class":"P",
    "gn:feature_code":"PPL",
    "gn:name":"Belair",
    "gn:population":0,
    "gn:timezone":"America/Port-au-Prince",
    "iso:country":"HT",
    "name:deu_x_preferred":[
        "Belair"
    ],
    "name:fra_x_preferred":[
        "Belair"
    ],
    "name:ltz_x_preferred":[
        "Belair"
    ],
    "name:nld_x_preferred":[
        "Belair"
    ],
    "name:pol_x_preferred":[
        "Belair"
    ],
    "wof:name":"Belair",
    "wof:placetype":"locality"
},
  "geometry": {"coordinates":[-72.26666999999998,19.73333],"type":"Point"}
}