{
  "type": "Feature",
  "properties": {
    "gn:admin1_code":"15.0",
    "gn:admin2_code":"3731122.0",
    "gn:asciiname":"Landry",
    "gn:country_code":"HT",
    "gn:dem":272,
    "gn:feature_class":"P",
    "gn:feature_code":"PPL",
    "gn:name":"Landry",
    "gn:population":0,
    "gn:timezone":"America/Port-au-Prince",
    "iso:country":"HT",
    "name:deu_x_preferred":[
        "Landry"
    ],
    "name:fra_x_preferred":[
        "Landry"
    ],
    "name:jpn_x_preferred":[
        "\u30e9\u30f3\u30c9\u30ea\u30fc"
    ],
    "name:rus_x_preferred":[
        "\u041b\u0430\u043d\u0434\u0440\u0438"
    ],
    "wof:name":"Landry",
    "wof:placetype":"locality"
},
  "geometry": {"coordinates":[-73.31667,18.43333],"type":"Point"}
}