{
  "type": "Feature",
  "properties": {
    "gn:admin1_code":"6.0",
    "gn:admin2_code":"3717587.0",
    "gn:asciiname":"Gresseau",
    "gn:country_code":"HT",
    "gn:dem":522,
    "gn:feature_class":"P",
    "gn:feature_code":"PPL",
    "gn:name":"Gresseau",
    "gn:population":0,
    "gn:timezone":"America/Port-au-Prince",
    "iso:country":"HT",
    "name:fra_x_preferred":[
        "Gresseau"
    ],
    "wof:name":"Gresseau",
    "wof:placetype":"locality"
},
  "geometry": {"coordinates":[-72.61984,18.98098],"type":"Point"}
}