{
  "type": "Feature",
  "properties": {
    "gn:country":"HT",
    "gn:fcode":"PPL",
    "gn:population":1698,
    "iso:country":"HT",
    "name:ara_x_preferred":[
        "\u0645\u0627\u0631\u064a\u063a\u0648"
    ],
    "name:ceb_x_preferred":[
        "Marigot"
    ],
    "name:deu_x_preferred":[
        "Marigot"
    ],
    "name:eng_x_preferred":[
        "Marigot"
    ],
    "name:fra_x_preferred":[
        "Marigot"
    ],
    "name:hat_x_preferred":[
        "Marigo"
    ],
    "name:ita_x_preferred":[
        "Marigot"
    ],
    "name:nld_x_preferred":[
        "Marigot"
    ],
    "name:por_x_preferred":[
        "Marigot"
    ],
    "name:ron_x_preferred":[
        "Marigot"
    ],
    "name:spa_x_preferred":[
        "Marigot"
    ],
    "name:swe_x_preferred":[
        "Marigot"
    ],
    "qs:name":"Marigot",
    "qs:photos_9r":0,
    "qs:photos_sr":0,
    "qs:pop_sr":"3",
    "wd:wordcount":64,
    "wof:name":"Marigot",
    "wof:placetype":"locality",
    "wof:population":1698
},
  "geometry": {"coordinates":[-72.31667,18.23389],"type":"Point"}
}