{
  "type": "Feature",
  "properties": {
    "gn:admin1_code":"6.0",
    "gn:admin2_code":"3724695.0",
    "gn:asciiname":"Nevil",
    "gn:country_code":"HT",
    "gn:dem":428,
    "gn:feature_class":"P",
    "gn:feature_code":"PPL",
    "gn:name":"Nevil",
    "gn:population":0,
    "gn:timezone":"America/Port-au-Prince",
    "iso:country":"HT",
    "wof:name":"Nevil",
    "wof:placetype":"locality"
},
  "geometry": {"coordinates":[-72.48333000000002,19.46667],"type":"Point"}
}