{
  "type": "Feature",
  "properties": {
    "gn:admin1_code":"12.0",
    "gn:admin2_code":"3731094.0",
    "gn:asciiname":"Marc",
    "gn:country_code":"HT",
    "gn:dem":582,
    "gn:feature_class":"P",
    "gn:feature_code":"PPL",
    "gn:name":"Marc",
    "gn:population":0,
    "gn:timezone":"America/Port-au-Prince",
    "iso:country":"HT",
    "name:cat_x_preferred":[
        "Marc"
    ],
    "name:ces_x_preferred":[
        "Marc"
    ],
    "name:deu_x_preferred":[
        "Marc"
    ],
    "name:fin_x_preferred":[
        "Marc"
    ],
    "name:fra_x_preferred":[
        "Marc"
    ],
    "name:glg_x_preferred":[
        "Marc"
    ],
    "name:heb_x_preferred":[
        "\u05de\u05d0\u05e8\u05e7"
    ],
    "name:ita_x_preferred":[
        "Marc"
    ],
    "name:nld_x_preferred":[
        "Marc"
    ],
    "name:nno_x_preferred":[
        "Marc"
    ],
    "name:pol_x_preferred":[
        "Marc"
    ],
    "name:rus_x_preferred":[
        "Marc"
    ],
    "name:spa_x_preferred":[
        "Marc"
    ],
    "name:swe_x_preferred":[
        "Marc"
    ],
    "wof:name":"Marc",
    "wof:placetype":"locality"
},
  "geometry": {"coordinates":[-73.65000000000001,18.41667],"type":"Point"}
}