{
  "type": "Feature",
  "properties": {
    "gn:admin1_code":"12.0",
    "gn:asciiname":"La Mercie",
    "gn:country_code":"HT",
    "gn:dem":414,
    "gn:feature_class":"P",
    "gn:feature_code":"PPL",
    "gn:name":"La Mercie",
    "gn:population":0,
    "gn:timezone":"America/Port-au-Prince",
    "iso:country":"HT",
    "wof:name":"La Mercie",
    "wof:placetype":"locality"
},
  "geometry": {"coordinates":[-72.95,18.21667],"type":"Point"}
}