{
  "type": "Feature",
  "properties": {
    "gn:admin1_code":"6.0",
    "gn:admin2_code":"3717587.0",
    "gn:asciiname":"Pierre Payen",
    "gn:country_code":"HT",
    "gn:dem":28,
    "gn:feature_class":"P",
    "gn:feature_code":"PPL",
    "gn:name":"Pierre Payen",
    "gn:population":0,
    "gn:timezone":"America/Port-au-Prince",
    "iso:country":"HT",
    "name:fra_x_preferred":[
        "Pierre Payen"
    ],
    "wof:name":"Pierre Payen",
    "wof:placetype":"locality"
},
  "geometry": {"coordinates":[-72.73765,18.99797],"type":"Point"}
}