{
  "type": "Feature",
  "properties": {
    "gn:admin1_code":"11.0",
    "gn:admin2_code":"3718425.0",
    "gn:asciiname":"La Source",
    "gn:country_code":"HT",
    "gn:dem":593,
    "gn:feature_class":"P",
    "gn:feature_code":"PPL",
    "gn:name":"La Source",
    "gn:population":0,
    "gn:timezone":"America/Port-au-Prince",
    "iso:country":"HT",
    "name:fra_x_preferred":[
        "La Source"
    ],
    "wof:name":"La Source",
    "wof:placetype":"locality"
},
  "geometry": {"coordinates":[-72.4806,18.49604],"type":"Point"}
}