{
  "type": "Feature",
  "properties": {
    "gn:admin1_code":"3.0",
    "gn:admin2_code":"3717599.0",
    "gn:asciiname":"Chene",
    "gn:country_code":"HT",
    "gn:dem":146,
    "gn:feature_class":"P",
    "gn:feature_code":"PPL",
    "gn:name":"Ch\u00eane",
    "gn:population":0,
    "gn:timezone":"America/Port-au-Prince",
    "iso:country":"HT",
    "wof:name":"Chene",
    "wof:placetype":"locality"
},
  "geometry": {"coordinates":[-72.73333000000002,19.91667],"type":"Point"}
}