{
  "type": "Feature",
  "properties": {
    "gn:admin1_code":"11.0",
    "gn:admin2_code":"3718425.0",
    "gn:asciiname":"Clemenceau",
    "gn:cc2":"HT",
    "gn:country_code":"HT",
    "gn:dem":1185,
    "gn:feature_class":"P",
    "gn:feature_code":"PPL",
    "gn:name":"Cl\u00e9menceau",
    "gn:population":0,
    "gn:timezone":"America/Port-au-Prince",
    "iso:country":"HT",
    "name:ara_x_preferred":[
        "\u0643\u0644\u064a\u0645\u0646\u0635\u0648"
    ],
    "name:deu_x_preferred":[
        "Clemenceau"
    ],
    "name:fra_x_preferred":[
        "Clemenceau"
    ],
    "name:jpn_x_preferred":[
        "\u30af\u30ec\u30de\u30f3\u30bd\u30fc"
    ],
    "name:kor_x_preferred":[
        "\ud074\ub808\ub9dd\uc18c"
    ],
    "name:nld_x_preferred":[
        "Clemenceau"
    ],
    "name:pol_x_preferred":[
        "Clemenceau"
    ],
    "name:por_x_preferred":[
        "Clemenceau"
    ],
    "name:spa_x_preferred":[
        "Clemenceau"
    ],
    "name:und_x_variant":[
        "Cl\u00e9mansso",
        "Cl\u00e9menceau"
    ],
    "wof:name":"Clemenceau",
    "wof:placetype":"locality"
},
  "geometry": {"coordinates":[-72.36667,18.45],"type":"Point"}
}