{
  "type": "Feature",
  "properties": {
    "gn:admin1_code":"11.0",
    "gn:admin2_code":"3718425.0",
    "gn:asciiname":"Clemenceau",
    "gn:cc2":"HT",
    "gn:country_code":"HT",
    "gn:dem":1185,
    "gn:feature_class":"P",
    "gn:feature_code":"PPL",
    "gn:name":"Cl\u00e9menceau",
    "gn:population":0,
    "gn:timezone":"America/Port-au-Prince",
    "iso:country":"HT",
    "name:und_x_variant":[
        "Cl\u00e9mansso",
        "Cl\u00e9menceau"
    ],
    "wof:name":"Clemenceau",
    "wof:placetype":"locality"
},
  "geometry": {"coordinates":[-72.36667,18.45],"type":"Point"}
}