{
  "type": "Feature",
  "properties": {
    "gn:admin1_code":"6.0",
    "gn:admin2_code":"3726539.0",
    "gn:asciiname":"Morne Goman",
    "gn:country_code":"HT",
    "gn:dem":83,
    "gn:feature_class":"P",
    "gn:feature_code":"PPL",
    "gn:name":"Morne Goman",
    "gn:population":0,
    "gn:timezone":"America/Port-au-Prince",
    "iso:country":"HT",
    "wof:name":"Morne Goman",
    "wof:placetype":"locality"
},
  "geometry": {"coordinates":[-72.43333,19.11667000000001],"type":"Point"}
}