{
  "type": "Feature",
  "properties": {
    "gn:admin1_code":"6.0",
    "gn:admin2_code":"3726539.0",
    "gn:asciiname":"Duclos",
    "gn:country_code":"HT",
    "gn:dem":10,
    "gn:feature_class":"P",
    "gn:feature_code":"PPL",
    "gn:name":"Duclos",
    "gn:population":0,
    "gn:timezone":"America/Port-au-Prince",
    "iso:country":"HT",
    "name:fra_x_preferred":[
        "Duclos"
    ],
    "wof:name":"Duclos",
    "wof:placetype":"locality"
},
  "geometry": {"coordinates":[-72.65763000000003,19.2807],"type":"Point"}
}