{
  "type": "Feature",
  "properties": {
    "iso:country":"HT",
    "name:fra_x_preferred":[
        "Tiburon"
    ],
    "name:hat_x_preferred":[
        "Tibiwon"
    ],
    "name:ita_x_preferred":[
        "Tiburon"
    ],
    "name:nld_x_preferred":[
        "Tiburon"
    ],
    "name:por_x_preferred":[
        "Tiburon"
    ],
    "name:ron_x_preferred":[
        "Tiburon"
    ],
    "name:swe_x_preferred":[
        "Tiburon"
    ],
    "qs:gn_country":"HT",
    "qs:gn_fcode":"PPL",
    "qs:gn_pop":3054,
    "qs:name":"Tiburon",
    "qs:name_adm0":"Ha\u00efti",
    "qs:name_adm1":"Sud",
    "qs:photos":0,
    "qs:photos_1k":0,
    "qs:photos_9k":1,
    "qs:photos_9r":1,
    "qs:photos_all":25,
    "qs:photos_sr":0,
    "qs:placetype":"Town",
    "qs:pop_sr":"4",
    "qs:woe_adm0":23424839,
    "wd:wordcount":55,
    "wof:name":"Tiburon",
    "wof:placetype":"locality",
    "wof:population":3054
},
  "geometry": {"coordinates":[-74.40000000000001,18.33333],"type":"Point"}
}