{
  "type": "Feature",
  "properties": {
    "gn:admin1_code":"11.0",
    "gn:admin2_code":"3722285.0",
    "gn:asciiname":"La Vache",
    "gn:country_code":"HT",
    "gn:dem":519,
    "gn:feature_class":"P",
    "gn:feature_code":"PPL",
    "gn:name":"La Vache",
    "gn:population":0,
    "gn:timezone":"America/Port-au-Prince",
    "iso:country":"HT",
    "name:fra_x_preferred":[
        "La Vache"
    ],
    "wof:name":"La Vache",
    "wof:placetype":"locality"
},
  "geometry": {"coordinates":[-72.63988000000001,18.34689],"type":"Point"}
}