{
  "type": "Feature",
  "properties": {
    "gn:admin1_code":"11.0",
    "gn:admin2_code":"3731086.0",
    "gn:asciiname":"Leveque",
    "gn:country_code":"HT",
    "gn:dem":24,
    "gn:feature_class":"P",
    "gn:feature_code":"PPL",
    "gn:name":"L\u00e9v\u00eaque",
    "gn:population":0,
    "gn:timezone":"America/Port-au-Prince",
    "iso:country":"HT",
    "name:fra_x_preferred":[
        "L\u00e9v\u00eaque"
    ],
    "wof:name":"Leveque",
    "wof:placetype":"locality"
},
  "geometry": {"coordinates":[-72.45138,18.75707],"type":"Point"}
}