{
  "type": "Feature",
  "properties": {
    "gn:admin1_code":"11.0",
    "gn:admin2_code":"3722285.0",
    "gn:asciiname":"La Hatte",
    "gn:country_code":"HT",
    "gn:dem":25,
    "gn:feature_class":"P",
    "gn:feature_code":"PPL",
    "gn:name":"La Hatte",
    "gn:population":0,
    "gn:timezone":"America/Port-au-Prince",
    "iso:country":"HT",
    "wof:name":"La Hatte",
    "wof:placetype":"locality"
},
  "geometry": {"coordinates":[-72.85722,18.43778],"type":"Point"}
}