{
  "type": "Feature",
  "properties": {
    "gn:admin1_code":"7.0",
    "gn:admin2_code":"3720809.0",
    "gn:asciiname":"Gumerin",
    "gn:country_code":"HT",
    "gn:dem":209,
    "gn:feature_class":"P",
    "gn:feature_code":"PPL",
    "gn:name":"Gum\u00e9rin",
    "gn:population":0,
    "gn:timezone":"America/Port-au-Prince",
    "iso:country":"HT",
    "name:fra_x_preferred":[
        "Gum\u00e9rin"
    ],
    "wof:name":"Gumerin",
    "wof:placetype":"locality"
},
  "geometry": {"coordinates":[-72.10254999999999,18.93692],"type":"Point"}
}