{
  "type": "Feature",
  "properties": {
    "gn:admin1_code":"6.0",
    "gn:admin2_code":"3724144.0",
    "gn:asciiname":"Savane Longue",
    "gn:country_code":"HT",
    "gn:dem":331,
    "gn:feature_class":"P",
    "gn:feature_code":"PPL",
    "gn:name":"Savane Longue",
    "gn:population":0,
    "gn:timezone":"America/Port-au-Prince",
    "iso:country":"HT",
    "name:fra_x_preferred":[
        "Savane Longue"
    ],
    "wof:name":"Savane Longue",
    "wof:placetype":"locality"
},
  "geometry": {"coordinates":[-72.81305,19.61821],"type":"Point"}
}