{
  "type": "Feature",
  "properties": {
    "gn:admin1_code":"11.0",
    "gn:admin2_code":"3718425.0",
    "gn:asciiname":"Ferte",
    "gn:country_code":"HT",
    "gn:dem":559,
    "gn:feature_class":"P",
    "gn:feature_code":"PPL",
    "gn:name":"Ferte",
    "gn:population":0,
    "gn:timezone":"America/Port-au-Prince",
    "iso:country":"HT",
    "wof:name":"Ferte",
    "wof:placetype":"locality"
},
  "geometry": {"coordinates":[-72.40000000000001,18.43333],"type":"Point"}
}