{
  "type": "Feature",
  "properties": {
    "gn:admin1_code":"11.0",
    "gn:admin2_code":"3723019.0",
    "gn:asciiname":"La Cour Longue",
    "gn:country_code":"HT",
    "gn:dem":127,
    "gn:feature_class":"P",
    "gn:feature_code":"PPL",
    "gn:name":"La Cour Longue",
    "gn:population":0,
    "gn:timezone":"America/Port-au-Prince",
    "iso:country":"HT",
    "name:fra_x_preferred":[
        "La Cour Longue"
    ],
    "wof:name":"La Cour Longue",
    "wof:placetype":"locality"
},
  "geometry": {"coordinates":[-73.09650999999999,18.87674],"type":"Point"}
}