{
  "type": "Feature",
  "properties": {
    "gn:admin1_code":"15.0",
    "gn:admin2_code":"3730801.0",
    "gn:asciiname":"Gardier",
    "gn:country_code":"HT",
    "gn:dem":288,
    "gn:feature_class":"P",
    "gn:feature_code":"PPL",
    "gn:name":"Gardier",
    "gn:population":0,
    "gn:timezone":"America/Port-au-Prince",
    "iso:country":"HT",
    "name:und_x_variant":[
        "Cardier",
        "Gardier"
    ],
    "wof:name":"Gardier",
    "wof:placetype":"locality"
},
  "geometry": {"coordinates":[-73.71472,18.49639],"type":"Point"}
}