{
  "type": "Feature",
  "properties": {
    "gn:admin1_code":"11.0",
    "gn:admin2_code":"3727134.0",
    "gn:asciiname":"Tilot",
    "gn:country_code":"HT",
    "gn:dem":34,
    "gn:feature_class":"P",
    "gn:feature_code":"PPL",
    "gn:name":"Tilot",
    "gn:population":0,
    "gn:timezone":"America/Port-au-Prince",
    "iso:country":"HT",
    "wof:name":"Tilot",
    "wof:placetype":"locality"
},
  "geometry": {"coordinates":[-72.25,18.61667000000001],"type":"Point"}
}