{
  "type": "Feature",
  "properties": {
    "gn:admin1_code":"12.0",
    "gn:admin2_code":"3731094.0",
    "gn:asciiname":"Durocher",
    "gn:country_code":"HT",
    "gn:dem":59,
    "gn:feature_class":"P",
    "gn:feature_code":"PPL",
    "gn:name":"Durocher",
    "gn:population":0,
    "gn:timezone":"America/Port-au-Prince",
    "iso:country":"HT",
    "name:fra_x_preferred":[
        "Durocher"
    ],
    "wof:name":"Durocher",
    "wof:placetype":"locality"
},
  "geometry": {"coordinates":[-73.62809,18.30275],"type":"Point"}
}