{
  "type": "Feature",
  "properties": {
    "gn:admin1_code":"12.0",
    "gn:admin2_code":"3728096.0",
    "gn:asciiname":"Zombi",
    "gn:country_code":"HT",
    "gn:dem":126,
    "gn:feature_class":"P",
    "gn:feature_code":"PPL",
    "gn:name":"Zombi",
    "gn:population":0,
    "gn:timezone":"America/Port-au-Prince",
    "iso:country":"HT",
    "name:ceb_x_preferred":[
        "Zombi"
    ],
    "name:deu_x_preferred":[
        "Zombi"
    ],
    "name:fra_x_preferred":[
        "Zombi"
    ],
    "name:ind_x_preferred":[
        "Zombi"
    ],
    "name:ita_x_preferred":[
        "Zombi"
    ],
    "name:rus_x_preferred":[
        "Zombi"
    ],
    "name:slk_x_preferred":[
        "Zombi"
    ],
    "name:spa_x_preferred":[
        "Zombi"
    ],
    "name:swe_x_preferred":[
        "Zombi"
    ],
    "name:tur_x_preferred":[
        "Zombi"
    ],
    "name:ukr_x_preferred":[
        "\u0417\u043e\u043c\u0431\u0456"
    ],
    "wof:name":"Zombi",
    "wof:placetype":"locality"
},
  "geometry": {"coordinates":[-73.71481999999997,18.27083],"type":"Point"}
}