{
  "type": "Feature",
  "properties": {
    "gn:admin1_code":"13.0",
    "gn:admin2_code":"3730910.0",
    "gn:asciiname":"Mesilier",
    "gn:country_code":"HT",
    "gn:dem":292,
    "gn:feature_class":"P",
    "gn:feature_code":"PPL",
    "gn:name":"Mesilier",
    "gn:population":0,
    "gn:timezone":"America/Port-au-Prince",
    "iso:country":"HT",
    "wof:name":"Mesilier",
    "wof:placetype":"locality"
},
  "geometry": {"coordinates":[-72.86667,18.25],"type":"Point"}
}