{
  "type": "Feature",
  "properties": {
    "gn:admin1_code":"15.0",
    "gn:admin2_code":"3731122.0",
    "gn:asciiname":"Saut",
    "gn:country_code":"HT",
    "gn:dem":464,
    "gn:feature_class":"P",
    "gn:feature_code":"PPL",
    "gn:name":"Saut",
    "gn:population":0,
    "gn:timezone":"America/Port-au-Prince",
    "iso:country":"HT",
    "wof:name":"Saut",
    "wof:placetype":"locality"
},
  "geometry": {"coordinates":[-73.46666999999999,18.45],"type":"Point"}
}