{
  "type": "Feature",
  "properties": {
    "gn:admin1_code":"15.0",
    "gn:admin2_code":"3720823.0",
    "gn:asciiname":"Mare Cachiman",
    "gn:country_code":"HT",
    "gn:dem":336,
    "gn:feature_class":"P",
    "gn:feature_code":"PPL",
    "gn:name":"Mare Cachiman",
    "gn:population":0,
    "gn:timezone":"America/Port-au-Prince",
    "iso:country":"HT",
    "wof:name":"Mare Cachiman",
    "wof:placetype":"locality"
},
  "geometry": {"coordinates":[-73.31667,18.41667],"type":"Point"}
}