{
  "type": "Feature",
  "properties": {
    "gn:admin1_code":"9.0",
    "gn:admin2_code":"3731232.0",
    "gn:asciiname":"Reo",
    "gn:country_code":"HT",
    "gn:dem":26,
    "gn:feature_class":"P",
    "gn:feature_code":"PPL",
    "gn:name":"R\u00e9o",
    "gn:population":0,
    "gn:timezone":"America/Port-au-Prince",
    "iso:country":"HT",
    "name:ceb_x_preferred":[
        "Reo"
    ],
    "name:fin_x_preferred":[
        "Reo"
    ],
    "name:hye_x_preferred":[
        "\u054c\u0565\u0578"
    ],
    "name:nld_x_preferred":[
        "Reo"
    ],
    "name:por_x_preferred":[
        "Reo"
    ],
    "name:rus_x_preferred":[
        "\u0420\u0435\u043e"
    ],
    "name:spa_x_preferred":[
        "Reo"
    ],
    "name:swe_x_preferred":[
        "Reo"
    ],
    "name:ukr_x_preferred":[
        "\u0420\u0435\u043e"
    ],
    "wof:name":"Reo",
    "wof:placetype":"locality"
},
  "geometry": {"coordinates":[-72.26666999999998,19.65],"type":"Point"}
}