{
  "type": "Feature",
  "properties": {
    "gn:admin1_code":"12.0",
    "gn:admin2_code":"3728096.0",
    "gn:asciiname":"Cadet",
    "gn:country_code":"HT",
    "gn:dem":326,
    "gn:feature_class":"P",
    "gn:feature_code":"PPL",
    "gn:name":"Cadet",
    "gn:population":0,
    "gn:timezone":"America/Port-au-Prince",
    "iso:country":"HT",
    "name:bul_x_preferred":[
        "\u041a\u0430\u0434\u0435\u0442"
    ],
    "name:dan_x_preferred":[
        "Kadet"
    ],
    "name:deu_x_preferred":[
        "Kadett"
    ],
    "name:epo_x_preferred":[
        "Kadeto"
    ],
    "name:fin_x_preferred":[
        "Kadetti"
    ],
    "name:fra_x_preferred":[
        "Cadet"
    ],
    "name:gla_x_preferred":[
        "Caideat"
    ],
    "name:heb_x_preferred":[
        "\u05e6\u05d5\u05e2\u05e8"
    ],
    "name:msa_x_preferred":[
        "Kadet"
    ],
    "name:nld_x_preferred":[
        "Cadet"
    ],
    "name:pol_x_preferred":[
        "Kadet"
    ],
    "name:por_x_preferred":[
        "Cadete"
    ],
    "name:rus_x_preferred":[
        "\u041a\u0430\u0434\u0435\u0442"
    ],
    "name:spa_x_preferred":[
        "Cadete"
    ],
    "name:swe_x_preferred":[
        "Kadett"
    ],
    "name:ukr_x_preferred":[
        "\u041a\u0430\u0434\u0435\u0442"
    ],
    "name:urd_x_preferred":[
        "\u06a9\u06cc\u0688\u0679"
    ],
    "wof:name":"Cadet",
    "wof:placetype":"locality"
},
  "geometry": {"coordinates":[-73.93333,18.25],"type":"Point"}
}