{
  "type": "Feature",
  "properties": {
    "gn:admin1_code":"6.0",
    "gn:admin2_code":"3726539.0",
    "gn:asciiname":"Bastien",
    "gn:country_code":"HT",
    "gn:dem":989,
    "gn:feature_class":"P",
    "gn:feature_code":"PPL",
    "gn:name":"Bastien",
    "gn:population":0,
    "gn:timezone":"America/Port-au-Prince",
    "iso:country":"HT",
    "name:ces_x_preferred":[
        "Bastien"
    ],
    "name:deu_x_preferred":[
        "Bastien"
    ],
    "name:fra_x_preferred":[
        "Bastien"
    ],
    "name:ita_x_preferred":[
        "Bastien"
    ],
    "name:nds_x_preferred":[
        "Bastien"
    ],
    "name:ukr_x_preferred":[
        "\u0411\u0430\u0441\u0442\u044c\u0454\u043d"
    ],
    "wof:name":"Bastien",
    "wof:placetype":"locality"
},
  "geometry": {"coordinates":[-72.34338000000002,19.14629],"type":"Point"}
}