{
  "type": "Feature",
  "properties": {
    "gn:admin1_code":"15.0",
    "gn:asciiname":"Dache",
    "gn:country_code":"HT",
    "gn:dem":-9999,
    "gn:feature_class":"P",
    "gn:feature_code":"PPL",
    "gn:name":"Dache",
    "gn:population":0,
    "gn:timezone":"America/Port-au-Prince",
    "iso:country":"HT",
    "wof:name":"Dache",
    "wof:placetype":"locality"
},
  "geometry": {"coordinates":[-73.51666999999998,18.55],"type":"Point"}
}