{
  "type": "Feature",
  "properties": {
    "gn:admin1_code":"12.0",
    "gn:admin2_code":"3731094.0",
    "gn:asciiname":"Careme",
    "gn:country_code":"HT",
    "gn:dem":697,
    "gn:feature_class":"P",
    "gn:feature_code":"PPL",
    "gn:name":"Car\u00e8me",
    "gn:population":0,
    "gn:timezone":"America/Port-au-Prince",
    "iso:country":"HT",
    "name:fra_x_preferred":[
        "Car\u00eame"
    ],
    "name:und_x_variant":[
        "Car\u00e8me"
    ],
    "wof:name":"Careme",
    "wof:placetype":"locality"
},
  "geometry": {"coordinates":[-73.46548,18.30716],"type":"Point"}
}