{
  "type": "Feature",
  "properties": {
    "iso:country":"HT",
    "name:ara_x_preferred":[
        "\u0628\u0627\u0631\u062f\u0631\u064a\u0633"
    ],
    "name:ceb_x_preferred":[
        "Barad\u00e8res"
    ],
    "name:eng_x_preferred":[
        "Barad\u00e8res"
    ],
    "name:fra_x_preferred":[
        "Barrad\u00e8res"
    ],
    "name:hat_x_preferred":[
        "Barad\u00e8"
    ],
    "name:ita_x_preferred":[
        "Barad\u00e8res"
    ],
    "name:nld_x_preferred":[
        "Barad\u00e8res"
    ],
    "name:por_x_preferred":[
        "Barrad\u00e8res"
    ],
    "name:ron_x_preferred":[
        "Barrad\u00e8res"
    ],
    "name:spa_x_preferred":[
        "Barad\u00e8res"
    ],
    "name:swe_x_preferred":[
        "Barad\u00e8res"
    ],
    "name:und_x_variant":[
        "Baradaires"
    ],
    "qs:gn_country":"HT",
    "qs:gn_fcode":"PPL",
    "qs:gn_pop":1666,
    "qs:name":"Barad\u00e8res",
    "qs:name_adm0":"Ha\u00efti",
    "qs:name_adm1":"Grand 'Anse",
    "qs:photos":12,
    "qs:photos_1k":2,
    "qs:photos_9k":1,
    "qs:photos_9r":1,
    "qs:photos_all":12,
    "qs:photos_sr":1,
    "qs:placetype":"Town",
    "qs:pop_sr":"3",
    "qs:woe_adm0":23424839,
    "wd:wordcount":187,
    "wof:name":"Barad\u00e8res",
    "wof:placetype":"locality",
    "wof:population":1666
},
  "geometry": {"coordinates":[-73.63861,18.4825],"type":"Point"}
}