{
  "type": "Feature",
  "properties": {
    "gn:admin1_code":"13.0",
    "gn:asciiname":"Diembo",
    "gn:country_code":"HT",
    "gn:dem":1151,
    "gn:feature_class":"P",
    "gn:feature_code":"PPL",
    "gn:name":"Diembo",
    "gn:population":0,
    "gn:timezone":"America/Port-au-Prince",
    "iso:country":"HT",
    "wof:name":"Diembo",
    "wof:placetype":"locality"
},
  "geometry": {"coordinates":[-72.23333000000002,18.36667000000001],"type":"Point"}
}