{
  "type": "Feature",
  "properties": {
    "gn:admin1_code":"14.0",
    "gn:admin2_code":"3723592.0",
    "gn:asciiname":"Martial",
    "gn:country_code":"HT",
    "gn:dem":135,
    "gn:feature_class":"P",
    "gn:feature_code":"PPL",
    "gn:name":"Martial",
    "gn:population":0,
    "gn:timezone":"America/Port-au-Prince",
    "iso:country":"HT",
    "name:afr_x_preferred":[
        "Martialis"
    ],
    "name:ara_x_preferred":[
        "\u0645\u0627\u0631\u062a\u064a\u0627\u0644\u064a\u0633"
    ],
    "name:azb_x_preferred":[
        "\u0645\u0627\u0631\u062a\u06cc\u0627\u0644\u06cc\u0633"
    ],
    "name:bel_x_preferred":[
        "\u041c\u0430\u0440\u0446\u044b\u044f\u043b"
    ],
    "name:deu_x_preferred":[
        "Martial"
    ],
    "name:epo_x_preferred":[
        "Marcialo"
    ],
    "name:est_x_preferred":[
        "Martialis"
    ],
    "name:fas_x_preferred":[
        "\u0645\u0627\u0631\u0634\u0627\u0644"
    ],
    "name:fin_x_preferred":[
        "Martialis"
    ],
    "name:fra_x_preferred":[
        "Martial"
    ],
    "name:fur_x_preferred":[
        "Marzi\u00e2l"
    ],
    "name:glg_x_preferred":[
        "Marcial"
    ],
    "name:heb_x_preferred":[
        "\u05de\u05e8\u05d8\u05d9\u05d0\u05dc\u05d9\u05e1"
    ],
    "name:hrv_x_preferred":[
        "Marcijal"
    ],
    "name:hye_x_preferred":[
        "\u054e\u0561\u056c\u0565\u0580\u056b\u0578\u0582\u057d \u0544\u0561\u0580\u0581\u056b\u0561\u056c\u056b\u057d"
    ],
    "name:isl_x_preferred":[
        "Martialis"
    ],
    "name:jpn_x_preferred":[
        "\u30de\u30eb\u30c6\u30a3\u30a2\u30ea\u30b9"
    ],
    "name:kor_x_preferred":[
        "\ub9c8\ub974\ud2f0\uc54c\ub9ac\uc2a4"
    ],
    "name:pol_x_preferred":[
        "Marcjalis"
    ],
    "name:por_x_preferred":[
        "Marcial"
    ],
    "name:ron_x_preferred":[
        "Mar\u021bial"
    ],
    "name:sco_x_preferred":[
        "Martial"
    ],
    "name:spa_x_preferred":[
        "Marcial"
    ],
    "name:swe_x_preferred":[
        "Martialis"
    ],
    "name:zho_x_preferred":[
        "\u9a6c\u63d0\u4e9a\u5c14"
    ],
    "wof:name":"Martial",
    "wof:placetype":"locality"
},
  "geometry": {"coordinates":[-74.34999999999999,18.48333],"type":"Point"}
}