{
  "type": "Feature",
  "properties": {
    "gn:admin1_code":"6.0",
    "gn:admin2_code":"3724695.0",
    "gn:asciiname":"Nan Rouffe",
    "gn:country_code":"HT",
    "gn:dem":464,
    "gn:feature_class":"P",
    "gn:feature_code":"PPL",
    "gn:name":"Nan Rouff\u00e9",
    "gn:population":0,
    "gn:timezone":"America/Port-au-Prince",
    "iso:country":"HT",
    "wof:name":"Nan Rouffe",
    "wof:placetype":"locality"
},
  "geometry": {"coordinates":[-72.51666999999998,19.55],"type":"Point"}
}