{
  "type": "Feature",
  "properties": {
    "gn:admin1_code":"14.0",
    "gn:admin2_code":"3727381.0",
    "gn:asciiname":"Corcette",
    "gn:country_code":"HT",
    "gn:dem":455,
    "gn:feature_class":"P",
    "gn:feature_code":"PPL",
    "gn:name":"Corcette",
    "gn:population":0,
    "gn:timezone":"America/Port-au-Prince",
    "iso:country":"HT",
    "name:fra_x_preferred":[
        "Corcette"
    ],
    "wof:name":"Corcette",
    "wof:placetype":"locality"
},
  "geometry": {"coordinates":[-73.89818000000002,18.46315],"type":"Point"}
}