{
  "type": "Feature",
  "properties": {
    "gn:admin1_code":"3.0",
    "gn:admin2_code":"3717599.0",
    "gn:asciiname":"Toman",
    "gn:country_code":"HT",
    "gn:dem":532,
    "gn:feature_class":"P",
    "gn:feature_code":"PPL",
    "gn:name":"Toman",
    "gn:population":0,
    "gn:timezone":"America/Port-au-Prince",
    "iso:country":"HT",
    "wof:name":"Toman",
    "wof:placetype":"locality"
},
  "geometry": {"coordinates":[-72.68333,19.86667000000001],"type":"Point"}
}