{
  "type": "Feature",
  "properties": {
    "gn:admin1_code":"3.0",
    "gn:admin2_code":"3720764",
    "gn:asciiname":"Anse a Joseph",
    "gn:country_code":"HT",
    "gn:dem":14,
    "gn:feature_class":"P",
    "gn:feature_code":"PPL",
    "gn:name":"Anse \u00e0 Joseph",
    "gn:population":0,
    "gn:timezone":"America/Port-au-Prince",
    "iso:country":"HT",
    "wof:name":"Anse a Joseph",
    "wof:placetype":"locality"
},
  "geometry": {"coordinates":[-73.28333000000001,19.63333],"type":"Point"}
}