{
  "type": "Feature",
  "properties": {
    "gn:admin1_code":"12.0",
    "gn:admin2_code":"3728096.0",
    "gn:asciiname":"Guillaume",
    "gn:country_code":"HT",
    "gn:dem":284,
    "gn:feature_class":"P",
    "gn:feature_code":"PPL",
    "gn:name":"Guillaume",
    "gn:population":0,
    "gn:timezone":"America/Port-au-Prince",
    "iso:country":"HT",
    "wof:name":"Guillaume",
    "wof:placetype":"locality"
},
  "geometry": {"coordinates":[-73.84999999999999,18.36667000000001],"type":"Point"}
}