{
  "type": "Feature",
  "properties": {
    "gn:admin1_code":"3.0",
    "gn:admin2_code":"3720764.0",
    "gn:asciiname":"Nan Ti Mil",
    "gn:country_code":"HT",
    "gn:dem":295,
    "gn:feature_class":"P",
    "gn:feature_code":"PPL",
    "gn:name":"Nan Ti Mil",
    "gn:population":0,
    "gn:timezone":"America/Port-au-Prince",
    "iso:country":"HT",
    "name:fra_x_preferred":[
        "Nan Ti Mil"
    ],
    "wof:name":"Nan Ti Mil",
    "wof:placetype":"locality"
},
  "geometry": {"coordinates":[-73.15825,19.72762],"type":"Point"}
}