{
  "type": "Feature",
  "properties": {
    "gn:admin1_code":"11.0",
    "gn:admin2_code":"3722285.0",
    "gn:asciiname":"Gosse",
    "gn:country_code":"HT",
    "gn:dem":517,
    "gn:feature_class":"P",
    "gn:feature_code":"PPL",
    "gn:name":"Gosse",
    "gn:population":0,
    "gn:timezone":"America/Port-au-Prince",
    "iso:country":"HT",
    "name:rus_x_preferred":[
        "\u0413\u043e\u0441\u0441\u0435"
    ],
    "wof:name":"Gosse",
    "wof:placetype":"locality"
},
  "geometry": {"coordinates":[-72.78333000000001,18.35],"type":"Point"}
}