{
  "type": "Feature",
  "properties": {
    "gn:admin1_code":"15.0",
    "gn:admin2_code":"3731122.0",
    "gn:asciiname":"Ka Raymond",
    "gn:country_code":"HT",
    "gn:dem":171,
    "gn:feature_class":"P",
    "gn:feature_code":"PPL",
    "gn:name":"Ka Raymond",
    "gn:population":0,
    "gn:timezone":"America/Port-au-Prince",
    "iso:country":"HT",
    "wof:name":"Ka Raymond",
    "wof:placetype":"locality"
},
  "geometry": {"coordinates":[-73.48333000000002,18.46667],"type":"Point"}
}