{
  "type": "Feature",
  "properties": {
    "gn:admin1_code":"3.0",
    "gn:admin2_code":"3720764.0",
    "gn:asciiname":"Gode",
    "gn:country_code":"HT",
    "gn:dem":831,
    "gn:feature_class":"P",
    "gn:feature_code":"PPL",
    "gn:name":"God\u00e9",
    "gn:population":0,
    "gn:timezone":"America/Port-au-Prince",
    "iso:country":"HT",
    "name:fra_x_preferred":[
        "God\u00e9"
    ],
    "wof:name":"Gode",
    "wof:placetype":"locality"
},
  "geometry": {"coordinates":[-73.19974000000001,19.77894],"type":"Point"}
}