{
  "type": "Feature",
  "properties": {
    "gn:admin1_code":"11.0",
    "gn:admin2_code":"3727134.0",
    "gn:asciiname":"Masseau",
    "gn:country_code":"HT",
    "gn:dem":204,
    "gn:feature_class":"P",
    "gn:feature_code":"PPL",
    "gn:name":"Masseau",
    "gn:population":0,
    "gn:timezone":"America/Port-au-Prince",
    "iso:country":"HT",
    "wof:name":"Masseau",
    "wof:placetype":"locality"
},
  "geometry": {"coordinates":[-72.15000000000001,18.51667],"type":"Point"}
}