{
  "type": "Feature",
  "properties": {
    "gn:admin1_code":"13.0",
    "gn:admin2_code":"3730910.0",
    "gn:asciiname":"La Source",
    "gn:country_code":"HT",
    "gn:dem":693,
    "gn:feature_class":"P",
    "gn:feature_code":"PPL",
    "gn:name":"La Source",
    "gn:population":0,
    "gn:timezone":"America/Port-au-Prince",
    "iso:country":"HT",
    "name:ceb_x_preferred":[
        "La Source"
    ],
    "name:fra_x_preferred":[
        "La Source"
    ],
    "name:pol_x_preferred":[
        "La Source"
    ],
    "name:spa_x_preferred":[
        "La Source"
    ],
    "name:swe_x_preferred":[
        "La Source"
    ],
    "wof:name":"La Source",
    "wof:placetype":"locality"
},
  "geometry": {"coordinates":[-72.90000000000001,18.28333],"type":"Point"}
}