{
  "type": "Feature",
  "properties": {
    "gn:admin1_code":"13.0",
    "gn:admin2_code":"3730361.0",
    "gn:asciiname":"Ti Simbi",
    "gn:country_code":"HT",
    "gn:dem":1108,
    "gn:feature_class":"P",
    "gn:feature_code":"PPL",
    "gn:name":"Ti Simbi",
    "gn:population":0,
    "gn:timezone":"America/Port-au-Prince",
    "iso:country":"HT",
    "wof:name":"Ti Simbi",
    "wof:placetype":"locality"
},
  "geometry": {"coordinates":[-71.76666999999998,18.23333],"type":"Point"}
}