{
  "type": "Feature",
  "properties": {
    "gn:admin1_code":"9.0",
    "gn:admin2_code":"3717545.0",
    "gn:asciiname":"Potosuel",
    "gn:country_code":"HT",
    "gn:dem":394,
    "gn:feature_class":"P",
    "gn:feature_code":"PPL",
    "gn:name":"Potosuel",
    "gn:population":0,
    "gn:timezone":"America/Port-au-Prince",
    "iso:country":"HT",
    "name:fra_x_preferred":[
        "Potosuel"
    ],
    "wof:name":"Potosuel",
    "wof:placetype":"locality"
},
  "geometry": {"coordinates":[-72.13715999999999,19.25944],"type":"Point"}
}