{
  "type": "Feature",
  "properties": {
    "gn:admin1_code":"3.0",
    "gn:admin2_code":"3718419.0",
    "gn:asciiname":"Servily",
    "gn:country_code":"HT",
    "gn:dem":223,
    "gn:feature_class":"P",
    "gn:feature_code":"PPL",
    "gn:name":"Servily",
    "gn:population":0,
    "gn:timezone":"America/Port-au-Prince",
    "iso:country":"HT",
    "name:fra_x_preferred":[
        "Servily"
    ],
    "wof:name":"Servily",
    "wof:placetype":"locality"
},
  "geometry": {"coordinates":[-72.83356999999999,20.0605],"type":"Point"}
}