{
  "type": "Feature",
  "properties": {
    "gn:admin1_code":"6.0",
    "gn:admin2_code":"3717563.0",
    "gn:asciiname":"Dave",
    "gn:country_code":"HT",
    "gn:dem":518,
    "gn:feature_class":"P",
    "gn:feature_code":"PPL",
    "gn:name":"Dave",
    "gn:population":0,
    "gn:timezone":"America/Port-au-Prince",
    "iso:country":"HT",
    "name:ceb_x_preferred":[
        "Dave"
    ],
    "name:deu_x_preferred":[
        "Dave"
    ],
    "name:fra_x_preferred":[
        "Dave"
    ],
    "name:ita_x_preferred":[
        "Dave"
    ],
    "name:jpn_x_preferred":[
        "\u30c7\u30a4\u30f4"
    ],
    "name:kor_x_preferred":[
        "\ub370\uc774\ube0c"
    ],
    "name:nld_x_preferred":[
        "Dave"
    ],
    "name:pol_x_preferred":[
        "Dave"
    ],
    "name:por_x_preferred":[
        "Dave"
    ],
    "name:rus_x_preferred":[
        "\u0414\u0435\u0439\u0432"
    ],
    "name:swe_x_preferred":[
        "Dave"
    ],
    "name:tur_x_preferred":[
        "Dave"
    ],
    "wof:name":"Dave",
    "wof:placetype":"locality"
},
  "geometry": {"coordinates":[-72.48333000000002,19.31667],"type":"Point"}
}