{
  "type": "Feature",
  "properties": {
    "gn:admin1_code":"11.0",
    "gn:admin2_code":"3727134.0",
    "gn:asciiname":"Savanette",
    "gn:country_code":"HT",
    "gn:dem":466,
    "gn:feature_class":"P",
    "gn:feature_code":"PPL",
    "gn:name":"Savanette",
    "gn:population":0,
    "gn:timezone":"America/Port-au-Prince",
    "iso:country":"HT",
    "name:ara_x_preferred":[
        "\u0633\u0627\u0641\u0627\u0646\u064a\u062a"
    ],
    "name:ceb_x_preferred":[
        "Savanette"
    ],
    "name:fra_x_preferred":[
        "Savanette"
    ],
    "name:hat_x_preferred":[
        "Savan\u00e8t"
    ],
    "name:ita_x_preferred":[
        "Savanette"
    ],
    "name:nld_x_preferred":[
        "Savanette"
    ],
    "name:por_x_preferred":[
        "Savanette"
    ],
    "name:ron_x_preferred":[
        "Savanette"
    ],
    "name:spa_x_preferred":[
        "Savanette"
    ],
    "name:swe_x_preferred":[
        "Savanette"
    ],
    "wof:name":"Savanette",
    "wof:placetype":"locality"
},
  "geometry": {"coordinates":[-72.05,18.68333],"type":"Point"}
}