{
  "type": "Feature",
  "properties": {
    "gn:admin1_code":"11.0",
    "gn:admin2_code":"3723019.0",
    "gn:asciiname":"Pente",
    "gn:country_code":"HT",
    "gn:dem":54,
    "gn:feature_class":"P",
    "gn:feature_code":"PPL",
    "gn:name":"Pente",
    "gn:population":0,
    "gn:timezone":"America/Port-au-Prince",
    "iso:country":"HT",
    "name:deu_x_preferred":[
        "Gobang"
    ],
    "name:fra_x_preferred":[
        "Pente"
    ],
    "name:pol_x_preferred":[
        "Pente"
    ],
    "name:swe_x_preferred":[
        "Pente"
    ],
    "name:zho_x_preferred":[
        "\u7389\u653b\u68cb"
    ],
    "wof:name":"Pente",
    "wof:placetype":"locality"
},
  "geometry": {"coordinates":[-73.15000000000001,18.93333],"type":"Point"}
}