{
  "type": "Feature",
  "properties": {
    "gn:admin1_code":"6.0",
    "gn:admin2_code":"3726539.0",
    "gn:asciiname":"La Couture",
    "gn:country_code":"HT",
    "gn:dem":13,
    "gn:feature_class":"P",
    "gn:feature_code":"PPL",
    "gn:name":"La Couture",
    "gn:population":0,
    "gn:timezone":"America/Port-au-Prince",
    "iso:country":"HT",
    "name:bre_x_preferred":[
        "La Couture"
    ],
    "name:ceb_x_preferred":[
        "La Couture"
    ],
    "name:deu_x_preferred":[
        "La Couture"
    ],
    "name:fra_x_preferred":[
        "La Couture"
    ],
    "name:ita_x_preferred":[
        "La Couture"
    ],
    "name:nds_x_preferred":[
        "La Couture"
    ],
    "name:nld_x_preferred":[
        "La Couture"
    ],
    "name:pms_x_preferred":[
        "La Couture"
    ],
    "name:pol_x_preferred":[
        "La Couture"
    ],
    "name:por_x_preferred":[
        "La Couture"
    ],
    "name:slk_x_preferred":[
        "La Couture"
    ],
    "name:spa_x_preferred":[
        "La Couture"
    ],
    "name:swe_x_preferred":[
        "La Couture"
    ],
    "name:szl_x_preferred":[
        "La Couture"
    ],
    "name:ukr_x_preferred":[
        "\u041b\u0430-\u041a\u0443\u0442\u044e\u0440"
    ],
    "wof:name":"La Couture",
    "wof:placetype":"locality"
},
  "geometry": {"coordinates":[-72.55445,19.20995],"type":"Point"}
}