{
  "type": "Feature",
  "properties": {
    "gn:admin1_code":"13.0",
    "gn:admin2_code":"3723778.0",
    "gn:asciiname":"Petite Bresilienne",
    "gn:country_code":"HT",
    "gn:dem":261,
    "gn:feature_class":"P",
    "gn:feature_code":"PPL",
    "gn:name":"Petite Bresilienne",
    "gn:population":0,
    "gn:timezone":"America/Port-au-Prince",
    "iso:country":"HT",
    "wof:name":"Petite Bresilienne",
    "wof:placetype":"locality"
},
  "geometry": {"coordinates":[-72.65000000000001,18.23333],"type":"Point"}
}