{
  "type": "Feature",
  "properties": {
    "gn:admin1_code":"6.0",
    "gn:admin2_code":"3724144.0",
    "gn:asciiname":"Souqui",
    "gn:cc2":"HT",
    "gn:country_code":"HT",
    "gn:dem":313,
    "gn:feature_class":"P",
    "gn:feature_code":"PPL",
    "gn:name":"Souqui",
    "gn:population":0,
    "gn:timezone":"America/Port-au-Prince",
    "iso:country":"HT",
    "name:und_x_variant":[
        "Souti",
        "Souqui"
    ],
    "wof:name":"Souqui",
    "wof:placetype":"locality"
},
  "geometry": {"coordinates":[-72.78333000000001,19.71667],"type":"Point"}
}