{
  "type": "Feature",
  "properties": {
    "gn:admin1_code":"11.0",
    "gn:asciiname":"Boucan Ferdinand",
    "gn:country_code":"HT",
    "gn:dem":1032,
    "gn:feature_class":"P",
    "gn:feature_code":"PPL",
    "gn:name":"Boucan Ferdinand",
    "gn:population":0,
    "gn:timezone":"America/Port-au-Prince",
    "iso:country":"HT",
    "name:fra_x_preferred":[
        "Boucan Fredinand"
    ],
    "name:und_x_variant":[
        "Boucan",
        "Boucan Ferdinand"
    ],
    "wof:name":"Boucan Ferdinand",
    "wof:placetype":"locality"
},
  "geometry": {"coordinates":[-71.71333,18.33728],"type":"Point"}
}