{
  "type": "Feature",
  "properties": {
    "gn:admin1_code":"9.0",
    "gn:admin2_code":"3722122.0",
    "gn:asciiname":"La Hatte",
    "gn:country_code":"HT",
    "gn:dem":72,
    "gn:feature_class":"P",
    "gn:feature_code":"PPL",
    "gn:name":"La Hatte",
    "gn:population":0,
    "gn:timezone":"America/Port-au-Prince",
    "iso:country":"HT",
    "name:fra_x_preferred":[
        "La Hatte"
    ],
    "wof:name":"La Hatte",
    "wof:placetype":"locality"
},
  "geometry": {"coordinates":[-72.38299000000001,19.6674],"type":"Point"}
}