{
  "type": "Feature",
  "properties": {
    "gn:admin1_code":"6.0",
    "gn:admin2_code":"3724144.0",
    "gn:asciiname":"Hatte Chevalier",
    "gn:country_code":"HT",
    "gn:dem":171,
    "gn:feature_class":"P",
    "gn:feature_code":"PPL",
    "gn:name":"Hatte Chevalier",
    "gn:population":0,
    "gn:timezone":"America/Port-au-Prince",
    "iso:country":"HT",
    "name:fra_x_preferred":[
        "Hatte Chevalier"
    ],
    "wof:name":"Hatte Chevalier",
    "wof:placetype":"locality"
},
  "geometry": {"coordinates":[-72.93276,19.68205],"type":"Point"}
}