{
  "type": "Feature",
  "properties": {
    "gn:admin1_code":"7.0",
    "gn:admin2_code":"3723840.0",
    "gn:asciiname":"Haut Piege",
    "gn:country_code":"HT",
    "gn:dem":617,
    "gn:feature_class":"P",
    "gn:feature_code":"PPL",
    "gn:name":"Haut Pi\u00e8ge",
    "gn:population":0,
    "gn:timezone":"America/Port-au-Prince",
    "iso:country":"HT",
    "name:fra_x_preferred":[
        "Haut Pi\u00e8ge"
    ],
    "wof:name":"Haut Piege",
    "wof:placetype":"locality"
},
  "geometry": {"coordinates":[-72.09526,18.99223],"type":"Point"}
}