{
  "type": "Feature",
  "properties": {
    "gn:admin1_code":"12.0",
    "gn:admin2_code":"3727295.0",
    "gn:asciiname":"Rosier",
    "gn:cc2":"HT",
    "gn:country_code":"HT",
    "gn:dem":74,
    "gn:feature_class":"P",
    "gn:feature_code":"PPL",
    "gn:name":"Rosier",
    "gn:population":0,
    "gn:timezone":"America/Port-au-Prince",
    "iso:country":"HT",
    "name:deu_x_preferred":[
        "Rosier"
    ],
    "name:fra_x_preferred":[
        "Rosier"
    ],
    "name:nld_x_preferred":[
        "Rosier"
    ],
    "name:ron_x_preferred":[
        "Rosier"
    ],
    "name:rus_x_preferred":[
        "\u0420\u043e\u0437\u044c\u0435"
    ],
    "name:und_x_variant":[
        "Carre Rosie",
        "Rogier"
    ],
    "wof:name":"Rosier",
    "wof:placetype":"locality"
},
  "geometry": {"coordinates":[-73.98333000000002,18.18333],"type":"Point"}
}