{
  "type": "Feature",
  "properties": {
    "gn:admin1_code":"6.0",
    "gn:admin2_code":"3724144.0",
    "gn:asciiname":"Flervil",
    "gn:country_code":"HT",
    "gn:dem":691,
    "gn:feature_class":"P",
    "gn:feature_code":"PPL",
    "gn:name":"Flervil",
    "gn:population":0,
    "gn:timezone":"America/Port-au-Prince",
    "iso:country":"HT",
    "wof:name":"Flervil",
    "wof:placetype":"locality"
},
  "geometry": {"coordinates":[-72.65000000000001,19.75],"type":"Point"}
}