{
  "type": "Feature",
  "properties": {
    "gn:admin1_code":"6.0",
    "gn:admin2_code":"3724695.0",
    "gn:asciiname":"Bassin Dessources",
    "gn:country_code":"HT",
    "gn:dem":11,
    "gn:feature_class":"P",
    "gn:feature_code":"PPL",
    "gn:name":"Bassin Dessources",
    "gn:population":0,
    "gn:timezone":"America/Port-au-Prince",
    "iso:country":"HT",
    "wof:name":"Bassin Dessources",
    "wof:placetype":"locality"
},
  "geometry": {"coordinates":[-72.61667,19.43333],"type":"Point"}
}