{
  "type": "Feature",
  "properties": {
    "gn:admin1_code":"13.0",
    "gn:asciiname":"Gerard",
    "gn:country_code":"HT",
    "gn:dem":789,
    "gn:feature_class":"P",
    "gn:feature_code":"PPL",
    "gn:name":"G\u00e9rard",
    "gn:population":0,
    "gn:timezone":"America/Port-au-Prince",
    "iso:country":"HT",
    "wof:name":"Gerard",
    "wof:placetype":"locality"
},
  "geometry": {"coordinates":[-72.69972,18.31833],"type":"Point"}
}