{
  "type": "Feature",
  "properties": {
    "gn:admin1_code":"11.0",
    "gn:admin2_code":"3722285.0",
    "gn:asciiname":"Fond Lafleur",
    "gn:country_code":"HT",
    "gn:dem":974,
    "gn:feature_class":"P",
    "gn:feature_code":"PPL",
    "gn:name":"Fond Lafleur",
    "gn:population":0,
    "gn:timezone":"America/Port-au-Prince",
    "iso:country":"HT",
    "wof:name":"Fond Lafleur",
    "wof:placetype":"locality"
},
  "geometry": {"coordinates":[-72.76666999999998,18.33333],"type":"Point"}
}