{
  "type": "Feature",
  "properties": {
    "gn:admin1_code":"12.0",
    "gn:admin2_code":"3728096.0",
    "gn:asciiname":"Aux Palmistes",
    "gn:country_code":"HT",
    "gn:dem":9,
    "gn:feature_class":"P",
    "gn:feature_code":"PPL",
    "gn:name":"Aux Palmistes",
    "gn:population":0,
    "gn:timezone":"America/Port-au-Prince",
    "iso:country":"HT",
    "name:fra_x_preferred":[
        "Aux Palmistes"
    ],
    "wof:name":"Aux Palmistes",
    "wof:placetype":"locality"
},
  "geometry": {"coordinates":[-73.60280999999998,18.06868],"type":"Point"}
}