{
  "type": "Feature",
  "properties": {
    "gn:admin1_code":"7.0",
    "gn:admin2_code":"3723840.0",
    "gn:asciiname":"Deux Passes",
    "gn:country_code":"HT",
    "gn:dem":271,
    "gn:feature_class":"P",
    "gn:feature_code":"PPL",
    "gn:name":"Deux Passes",
    "gn:population":0,
    "gn:timezone":"America/Port-au-Prince",
    "iso:country":"HT",
    "name:und_x_variant":[
        "Deaux Passes",
        "Deux Passes"
    ],
    "wof:name":"Deux Passes",
    "wof:placetype":"locality"
},
  "geometry": {"coordinates":[-72.17783,19.19224],"type":"Point"}
}