{
  "type": "Feature",
  "properties": {
    "gn:admin1_code":"3.0",
    "gn:admin2_code":"3717599.0",
    "gn:asciiname":"Gaspard",
    "gn:country_code":"HT",
    "gn:dem":633,
    "gn:feature_class":"P",
    "gn:feature_code":"PPL",
    "gn:name":"Gaspard",
    "gn:population":0,
    "gn:timezone":"America/Port-au-Prince",
    "iso:country":"HT",
    "name:fra_x_preferred":[
        "Gaspard"
    ],
    "wof:name":"Gaspard",
    "wof:placetype":"locality"
},
  "geometry": {"coordinates":[-72.68303,19.87078],"type":"Point"}
}