{
  "type": "Feature",
  "properties": {
    "gn:admin1_code":"3.0",
    "gn:admin2_code":"3720764.0",
    "gn:asciiname":"Jeanne",
    "gn:country_code":"HT",
    "gn:dem":372,
    "gn:feature_class":"P",
    "gn:feature_code":"PPL",
    "gn:name":"Jeanne",
    "gn:population":0,
    "gn:timezone":"America/Port-au-Prince",
    "iso:country":"HT",
    "name:bre_x_preferred":[
        "Jeanne"
    ],
    "name:deu_x_preferred":[
        "Jeanne"
    ],
    "name:fra_x_preferred":[
        "Jeanne"
    ],
    "name:nld_x_preferred":[
        "Jeanne"
    ],
    "name:por_x_preferred":[
        "Jeanne"
    ],
    "name:rus_x_preferred":[
        "\u0416\u0430\u043d\u043d\u0430"
    ],
    "name:spa_x_preferred":[
        "Jeanne"
    ],
    "name:swe_x_preferred":[
        "Jeanne"
    ],
    "name:ukr_x_preferred":[
        "\u0416\u0430\u043d\u043d\u0430"
    ],
    "wof:name":"Jeanne",
    "wof:placetype":"locality"
},
  "geometry": {"coordinates":[-73.38333,19.66667],"type":"Point"}
}