{
  "type": "Feature",
  "properties": {
    "gn:admin1_code":"3.0",
    "gn:admin2_code":"3718419.0",
    "gn:asciiname":"Les Palmistes",
    "gn:country_code":"HT",
    "gn:dem":318,
    "gn:feature_class":"P",
    "gn:feature_code":"PPL",
    "gn:name":"Les Palmistes",
    "gn:population":0,
    "gn:timezone":"America/Port-au-Prince",
    "iso:country":"HT",
    "name:fra_x_preferred":[
        "Les Palmistes"
    ],
    "name:und_x_variant":[
        "Palmiste",
        "Aux Palmistes"
    ],
    "wof:name":"Les Palmistes",
    "wof:placetype":"locality"
},
  "geometry": {"coordinates":[-72.72348000000002,20.01774],"type":"Point"}
}