{
  "type": "Feature",
  "properties": {
    "gn:admin1_code":"12.0",
    "gn:admin2_code":"3728096.0",
    "gn:asciiname":"Duversin",
    "gn:country_code":"HT",
    "gn:dem":191,
    "gn:feature_class":"P",
    "gn:feature_code":"PPL",
    "gn:name":"Duversin",
    "gn:population":0,
    "gn:timezone":"America/Port-au-Prince",
    "iso:country":"HT",
    "name:und_x_variant":[
        "Duvesin",
        "Duversin"
    ],
    "wof:name":"Duversin",
    "wof:placetype":"locality"
},
  "geometry": {"coordinates":[-73.81397,18.36484],"type":"Point"}
}