{
  "type": "Feature",
  "properties": {
    "gn:admin1_code":"11.0",
    "gn:admin2_code":"3731086.0",
    "gn:asciiname":"Marotte",
    "gn:country_code":"HT",
    "gn:dem":36,
    "gn:feature_class":"P",
    "gn:feature_code":"PPL",
    "gn:name":"Marotte",
    "gn:population":0,
    "gn:timezone":"America/Port-au-Prince",
    "iso:country":"HT",
    "name:bar_x_preferred":[
        "Marottn"
    ],
    "name:deu_x_preferred":[
        "Marotte"
    ],
    "name:fra_x_preferred":[
        "Marotte"
    ],
    "name:heb_x_preferred":[
        "\u05de\u05e8\u05d5\u05d8"
    ],
    "name:nld_x_preferred":[
        "Zotskolf"
    ],
    "name:nor_x_preferred":[
        "Narresepter"
    ],
    "wof:name":"Marotte",
    "wof:placetype":"locality"
},
  "geometry": {"coordinates":[-72.57167,18.83667],"type":"Point"}
}