{
  "type": "Feature",
  "properties": {
    "gn:admin1_code":"7.0",
    "gn:asciiname":"Ravine Fontaine",
    "gn:country_code":"HT",
    "gn:dem":278,
    "gn:feature_class":"P",
    "gn:feature_code":"PPL",
    "gn:name":"Ravine Fontaine",
    "gn:population":0,
    "gn:timezone":"America/Port-au-Prince",
    "iso:country":"HT",
    "wof:name":"Ravine Fontaine",
    "wof:placetype":"locality"
},
  "geometry": {"coordinates":[-72.23333000000002,18.95],"type":"Point"}
}