{
  "type": "Feature",
  "properties": {
    "gn:admin1_code":"11.0",
    "gn:admin2_code":"3723019.0",
    "gn:asciiname":"Terre Rouge",
    "gn:country_code":"HT",
    "gn:dem":538,
    "gn:feature_class":"P",
    "gn:feature_code":"PPL",
    "gn:name":"Terre Rouge",
    "gn:population":0,
    "gn:timezone":"America/Port-au-Prince",
    "iso:country":"HT",
    "name:fra_x_preferred":[
        "Terre Rouge"
    ],
    "wof:name":"Terre Rouge",
    "wof:placetype":"locality"
},
  "geometry": {"coordinates":[-73.01236999999998,18.79565],"type":"Point"}
}