{
  "type": "Feature",
  "properties": {
    "gn:admin1_code":"11.0",
    "gn:admin2_code":"3731086.0",
    "gn:asciiname":"Ca Poule",
    "gn:country_code":"HT",
    "gn:dem":1046,
    "gn:feature_class":"P",
    "gn:feature_code":"PPL",
    "gn:name":"Ca Poule",
    "gn:population":0,
    "gn:timezone":"America/Port-au-Prince",
    "iso:country":"HT",
    "name:und_x_variant":[
        "Ka Poule",
        "Ca Poule"
    ],
    "wof:name":"Ca Poule",
    "wof:placetype":"locality"
},
  "geometry": {"coordinates":[-72.50193,18.90523],"type":"Point"}
}