{
  "type": "Feature",
  "properties": {
    "gn:admin1_code":"14.0",
    "gn:admin2_code":"3723592.0",
    "gn:asciiname":"Nan Manioc",
    "gn:country_code":"HT",
    "gn:dem":136,
    "gn:feature_class":"P",
    "gn:feature_code":"PPL",
    "gn:name":"Nan Manioc",
    "gn:population":0,
    "gn:timezone":"America/Port-au-Prince",
    "iso:country":"HT",
    "name:und_x_variant":[
        "Nan Magnioc",
        "Nan Manioc"
    ],
    "wof:name":"Nan Manioc",
    "wof:placetype":"locality"
},
  "geometry": {"coordinates":[-74.23043,18.55911],"type":"Point"}
}