{
  "type": "Feature",
  "properties": {
    "gn:admin1_code":"10.0",
    "gn:admin2_code":"3716223.0",
    "gn:asciiname":"Duro",
    "gn:country_code":"HT",
    "gn:dem":348,
    "gn:feature_class":"P",
    "gn:feature_code":"PPL",
    "gn:name":"Duro",
    "gn:population":0,
    "gn:timezone":"America/Port-au-Prince",
    "iso:country":"HT",
    "name:ceb_x_preferred":[
        "Duro"
    ],
    "name:deu_x_preferred":[
        "Duro"
    ],
    "name:fra_x_preferred":[
        "Duro"
    ],
    "name:ita_x_preferred":[
        "Duro"
    ],
    "name:rus_x_preferred":[
        "\u0414\u0443\u0440\u043e"
    ],
    "name:spa_x_preferred":[
        "Duro"
    ],
    "wof:name":"Duro",
    "wof:placetype":"locality"
},
  "geometry": {"coordinates":[-72.09999999999999,19.58333],"type":"Point"}
}