{
  "type": "Feature",
  "properties": {
    "gn:admin1_code":"6.0",
    "gn:admin2_code":"3724144.0",
    "gn:asciiname":"Trou Cordon",
    "gn:country_code":"HT",
    "gn:dem":326,
    "gn:feature_class":"P",
    "gn:feature_code":"PPL",
    "gn:name":"Trou Cordon",
    "gn:population":0,
    "gn:timezone":"America/Port-au-Prince",
    "iso:country":"HT",
    "wof:name":"Trou Cordon",
    "wof:placetype":"locality"
},
  "geometry": {"coordinates":[-72.73333000000002,19.76667],"type":"Point"}
}