{
  "type": "Feature",
  "properties": {
    "gn:admin1_code":"3.0",
    "gn:admin2_code":"3720764.0",
    "gn:asciiname":"Tete Source",
    "gn:country_code":"HT",
    "gn:dem":191,
    "gn:feature_class":"P",
    "gn:feature_code":"PPL",
    "gn:name":"T\u00eate Source",
    "gn:population":0,
    "gn:timezone":"America/Port-au-Prince",
    "iso:country":"HT",
    "name:fra_x_preferred":[
        "T\u00eate Source"
    ],
    "wof:name":"Tete Source",
    "wof:placetype":"locality"
},
  "geometry": {"coordinates":[-73.05176,19.8384],"type":"Point"}
}