{
  "type": "Feature",
  "properties": {
    "gn:admin1_code":"9.0",
    "gn:admin2_code":"3717545.0",
    "gn:asciiname":"La Cosse",
    "gn:country_code":"HT",
    "gn:dem":328,
    "gn:feature_class":"P",
    "gn:feature_code":"PPL",
    "gn:name":"La Cosse",
    "gn:population":0,
    "gn:timezone":"America/Port-au-Prince",
    "iso:country":"HT",
    "wof:name":"La Cosse",
    "wof:placetype":"locality"
},
  "geometry": {"coordinates":[-72.13333,19.33333],"type":"Point"}
}