{
  "type": "Feature",
  "properties": {
    "gn:admin1_code":"14.0",
    "gn:admin2_code":"3723592.0",
    "gn:asciiname":"Laforet",
    "gn:country_code":"HT",
    "gn:dem":113,
    "gn:feature_class":"P",
    "gn:feature_code":"PPL",
    "gn:name":"Lafor\u00eat",
    "gn:population":0,
    "gn:timezone":"America/Port-au-Prince",
    "iso:country":"HT",
    "name:jpn_x_preferred":[
        "\u30e9\u30d5\u30a9\u30fc\u30ec\u539f\u5bbf"
    ],
    "name:kor_x_preferred":[
        "\ub77c\ud3ec\ub808 \ud558\ub77c\uc8fc\ucfe0"
    ],
    "name:zho_x_preferred":[
        "Laforet\u539f\u5bbf"
    ],
    "wof:name":"Laforet",
    "wof:placetype":"locality"
},
  "geometry": {"coordinates":[-74.11667,18.55],"type":"Point"}
}