{
  "type": "Feature",
  "properties": {
    "gn:admin1_code":"11.0",
    "gn:admin2_code":"3727134.0",
    "gn:asciiname":"Bel Fond",
    "gn:country_code":"HT",
    "gn:dem":1160,
    "gn:feature_class":"P",
    "gn:feature_code":"PPL",
    "gn:name":"Bel Fond",
    "gn:population":0,
    "gn:timezone":"America/Port-au-Prince",
    "iso:country":"HT",
    "name:fra_x_preferred":[
        "Bel Fond"
    ],
    "wof:name":"Bel Fond",
    "wof:placetype":"locality"
},
  "geometry": {"coordinates":[-72.0665,18.4729],"type":"Point"}
}