{
  "type": "Feature",
  "properties": {
    "gn:admin1_code":"6.0",
    "gn:admin2_code":"3726539.0",
    "gn:asciiname":"Descareaux",
    "gn:country_code":"HT",
    "gn:dem":8,
    "gn:feature_class":"P",
    "gn:feature_code":"PPL",
    "gn:name":"Descareaux",
    "gn:population":0,
    "gn:timezone":"America/Port-au-Prince",
    "iso:country":"HT",
    "name:fra_x_preferred":[
        "Descareaux"
    ],
    "wof:name":"Descareaux",
    "wof:placetype":"locality"
},
  "geometry": {"coordinates":[-72.64960000000001,19.29895],"type":"Point"}
}