{
  "type": "Feature",
  "properties": {
    "gn:admin1_code":"3.0",
    "gn:admin2_code":"3717599.0",
    "gn:asciiname":"Fond Brule",
    "gn:country_code":"HT",
    "gn:dem":416,
    "gn:feature_class":"P",
    "gn:feature_code":"PPL",
    "gn:name":"Fond Br\u00fbl\u00e9",
    "gn:population":0,
    "gn:timezone":"America/Port-au-Prince",
    "iso:country":"HT",
    "name:fra_x_preferred":[
        "Fond Br\u00fbl\u00e9"
    ],
    "wof:name":"Fond Brule",
    "wof:placetype":"locality"
},
  "geometry": {"coordinates":[-72.67251,19.88365],"type":"Point"}
}