{
  "type": "Feature",
  "properties": {
    "gn:admin1_code":"6.0",
    "gn:asciiname":"Dahomey",
    "gn:country_code":"HT",
    "gn:dem":527,
    "gn:feature_class":"P",
    "gn:feature_code":"PPL",
    "gn:name":"Dahomey",
    "gn:population":0,
    "gn:timezone":"America/Port-au-Prince",
    "iso:country":"HT",
    "name:fra_x_preferred":[
        "Dahomey"
    ],
    "wof:name":"Dahomey",
    "wof:placetype":"locality"
},
  "geometry": {"coordinates":[-72.29179000000001,19.19822000000001],"type":"Point"}
}