{
  "type": "Feature",
  "properties": {
    "gn:admin1_code":"6.0",
    "gn:admin2_code":"3717563.0",
    "gn:asciiname":"Pare",
    "gn:country_code":"HT",
    "gn:dem":480,
    "gn:feature_class":"P",
    "gn:feature_code":"PPL",
    "gn:name":"Par\u00e9",
    "gn:population":0,
    "gn:timezone":"America/Port-au-Prince",
    "iso:country":"HT",
    "name:bel_x_preferred":[
        "\u041f\u0430\u0440\u044d"
    ],
    "name:ceb_x_preferred":[
        "Pare"
    ],
    "name:deu_x_preferred":[
        "Pare"
    ],
    "name:eus_x_preferred":[
        "Pare"
    ],
    "name:fas_x_preferred":[
        "\u067e\u0627\u0631\u0647"
    ],
    "name:fra_x_preferred":[
        "Par\u00e9"
    ],
    "name:fra_x_variant":[
        "Pare"
    ],
    "name:hye_x_preferred":[
        "\u054a\u0561\u0580\u0565"
    ],
    "name:ind_x_preferred":[
        "Pare"
    ],
    "name:ita_x_preferred":[
        "Pare"
    ],
    "name:nld_x_preferred":[
        "Pare"
    ],
    "name:por_x_preferred":[
        "Pare"
    ],
    "name:rus_x_preferred":[
        "\u041f\u0430\u0440\u0435"
    ],
    "name:swe_x_preferred":[
        "Pare"
    ],
    "name:tgl_x_preferred":[
        "Pare"
    ],
    "name:ukr_x_preferred":[
        "\u041f\u0430\u0440\u0435"
    ],
    "wof:name":"Pare",
    "wof:placetype":"locality"
},
  "geometry": {"coordinates":[-72.48009999999999,19.32467],"type":"Point"}
}