{
  "type": "Feature",
  "properties": {
    "gn:admin1_code":"12.0",
    "gn:admin2_code":"3727900.0",
    "gn:asciiname":"Nan Sevre",
    "gn:country_code":"HT",
    "gn:dem":126,
    "gn:feature_class":"P",
    "gn:feature_code":"PPL",
    "gn:name":"Nan S\u00e9vr\u00e9",
    "gn:population":0,
    "gn:timezone":"America/Port-au-Prince",
    "iso:country":"HT",
    "name:fra_x_preferred":[
        "Nan S\u00e9vr\u00e9"
    ],
    "name:und_x_variant":[
        "Sevr\u00e9",
        "Nan Sevr\u00e9"
    ],
    "wof:name":"Nan Sevre",
    "wof:placetype":"locality"
},
  "geometry": {"coordinates":[-74.29686,18.34164],"type":"Point"}
}