{
  "type": "Feature",
  "properties": {
    "gn:admin1_code":"11.0",
    "gn:admin2_code":"3718425.0",
    "gn:asciiname":"Mer Frappee",
    "gn:country_code":"HT",
    "gn:dem":25,
    "gn:feature_class":"P",
    "gn:feature_code":"PPL",
    "gn:name":"Mer Frapp\u00e9e",
    "gn:population":0,
    "gn:timezone":"America/Port-au-Prince",
    "iso:country":"HT",
    "name:fra_x_preferred":[
        "Mer Frapp\u00e9e"
    ],
    "wof:name":"Mer Frappee",
    "wof:placetype":"locality"
},
  "geometry": {"coordinates":[-72.45673000000002,18.5424],"type":"Point"}
}