{
  "type": "Feature",
  "properties": {
    "gn:admin1_code":"10.0",
    "gn:admin2_code":"3716223.0",
    "gn:asciiname":"Platon Mat",
    "gn:country_code":"HT",
    "gn:dem":563,
    "gn:feature_class":"P",
    "gn:feature_code":"PPL",
    "gn:name":"Platon Mat",
    "gn:population":0,
    "gn:timezone":"America/Port-au-Prince",
    "iso:country":"HT",
    "wof:name":"Platon Mat",
    "wof:placetype":"locality"
},
  "geometry": {"coordinates":[-72.03333000000001,19.46667],"type":"Point"}
}