{
  "type": "Feature",
  "properties": {
    "gn:admin1_code":"6.0",
    "gn:admin2_code":"3724695.0",
    "gn:asciiname":"Duvoisin",
    "gn:country_code":"HT",
    "gn:dem":697,
    "gn:feature_class":"P",
    "gn:feature_code":"PPL",
    "gn:name":"Duvoisin",
    "gn:population":0,
    "gn:timezone":"America/Port-au-Prince",
    "iso:country":"HT",
    "name:fra_x_preferred":[
        "Duvoisin"
    ],
    "wof:name":"Duvoisin",
    "wof:placetype":"locality"
},
  "geometry": {"coordinates":[-72.45187,19.42114],"type":"Point"}
}