{
  "type": "Feature",
  "properties": {
    "gn:admin1_code":"13.0",
    "gn:admin2_code":"3723778.0",
    "gn:asciiname":"Bassin Caiman",
    "gn:country_code":"HT",
    "gn:dem":48,
    "gn:feature_class":"P",
    "gn:feature_code":"PPL",
    "gn:name":"Bassin Ca\u00efman",
    "gn:population":0,
    "gn:timezone":"America/Port-au-Prince",
    "iso:country":"HT",
    "name:und_x_variant":[
        "Bassin Caimann",
        "Bassin Ca\u00efman"
    ],
    "wof:name":"Bassin Caiman",
    "wof:placetype":"locality"
},
  "geometry": {"coordinates":[-72.55086999999997,18.25834],"type":"Point"}
}