{
  "type": "Feature",
  "properties": {
    "gn:admin1_code":"6.0",
    "gn:admin2_code":"3724695.0",
    "gn:asciiname":"Decossiere",
    "gn:country_code":"HT",
    "gn:dem":326,
    "gn:feature_class":"P",
    "gn:feature_code":"PPL",
    "gn:name":"D\u00e9cossi\u00e8re",
    "gn:population":0,
    "gn:timezone":"America/Port-au-Prince",
    "iso:country":"HT",
    "name:fra_x_preferred":[
        "D\u00e9cossi\u00e8re"
    ],
    "wof:name":"Decossiere",
    "wof:placetype":"locality"
},
  "geometry": {"coordinates":[-72.70589,19.60454],"type":"Point"}
}