{
  "type": "Feature",
  "properties": {
    "gn:admin1_code":"6.0",
    "gn:admin2_code":"3726539.0",
    "gn:asciiname":"Bocozel",
    "gn:country_code":"HT",
    "gn:dem":15,
    "gn:feature_class":"P",
    "gn:feature_code":"PPL",
    "gn:name":"Bocozel",
    "gn:population":0,
    "gn:timezone":"America/Port-au-Prince",
    "iso:country":"HT",
    "name:und_x_variant":[
        "Bocozelle",
        "Bocozell",
        "Bocozel"
    ],
    "wof:name":"Bocozel",
    "wof:placetype":"locality"
},
  "geometry": {"coordinates":[-72.63956,19.20832],"type":"Point"}
}