{
  "type": "Feature",
  "properties": {
    "gn:admin1_code":"6.0",
    "gn:asciiname":"Pivereau",
    "gn:country_code":"HT",
    "gn:dem":612,
    "gn:feature_class":"P",
    "gn:feature_code":"PPL",
    "gn:name":"Pivereau",
    "gn:population":0,
    "gn:timezone":"America/Port-au-Prince",
    "iso:country":"HT",
    "wof:name":"Pivereau",
    "wof:placetype":"locality"
},
  "geometry": {"coordinates":[-72.21666999999999,19.01667],"type":"Point"}
}