{
  "type": "Feature",
  "properties": {
    "gn:admin1_code":"6.0",
    "gn:admin2_code":"3726539.0",
    "gn:asciiname":"La Hatte",
    "gn:country_code":"HT",
    "gn:dem":10,
    "gn:feature_class":"P",
    "gn:feature_code":"PPL",
    "gn:name":"La Hatte",
    "gn:population":0,
    "gn:timezone":"America/Port-au-Prince",
    "iso:country":"HT",
    "name:fra_x_preferred":[
        "La Hatte"
    ],
    "wof:name":"La Hatte",
    "wof:placetype":"locality"
},
  "geometry": {"coordinates":[-72.67171999999999,19.31648],"type":"Point"}
}