{
  "type": "Feature",
  "properties": {
    "gn:admin1_code":"9.0",
    "gn:admin2_code":"3728473.0",
    "gn:asciiname":"Clementine",
    "gn:country_code":"HT",
    "gn:dem":11,
    "gn:feature_class":"P",
    "gn:feature_code":"PPL",
    "gn:name":"Cl\u00e9mentine",
    "gn:population":0,
    "gn:timezone":"America/Port-au-Prince",
    "iso:country":"HT",
    "name:ara_x_preferred":[
        "\u0643\u0644\u064a\u0645\u0648\u0646\u062a\u064a\u0646"
    ],
    "name:bod_x_preferred":[
        "\u0f5a\u0f0b\u0f63\u0f72\u0f0b\u0f58\u0f0b\u0f46\u0f74\u0f44\u0f0b\u0f56\u0f60\u0f72\u0f0b\u0f62\u0f72\u0f42\u0f66\u0f0d"
    ],
    "name:cat_x_preferred":[
        "Clementina"
    ],
    "name:ces_x_preferred":[
        "Mandarinka klementina"
    ],
    "name:chv_x_preferred":[
        "\u041a\u043b\u0435\u043c\u0435\u043d\u0442\u0438\u043d\u0430"
    ],
    "name:cos_x_preferred":[
        "Clementina"
    ],
    "name:dan_x_preferred":[
        "Klementin"
    ],
    "name:deu_x_preferred":[
        "Clementine"
    ],
    "name:epo_x_preferred":[
        "Klementino"
    ],
    "name:est_x_preferred":[
        "Klementiin"
    ],
    "name:eus_x_preferred":[
        "Klementinondo"
    ],
    "name:fas_x_preferred":[
        "\u0646\u0627\u0631\u0646\u06af\u06cc \u06cc\u0627\u0641\u0627"
    ],
    "name:fin_x_preferred":[
        "Klementiini"
    ],
    "name:fra_x_preferred":[
        "Cl\u00e9mentine"
    ],
    "name:frr_x_preferred":[
        "Clementiin"
    ],
    "name:glg_x_preferred":[
        "Clementina"
    ],
    "name:heb_x_preferred":[
        "\u05e7\u05dc\u05de\u05e0\u05d8\u05d9\u05e0\u05d4"
    ],
    "name:koi_x_preferred":[
        "\u041a\u043b\u0435\u043c\u0435\u043d\u0442\u0438\u043d"
    ],
    "name:kom_x_preferred":[
        "\u041a\u043b\u0435\u043c\u0435\u043d\u0442\u0438\u043d"
    ],
    "name:lat_x_preferred":[
        "Clementina"
    ],
    "name:lit_x_preferred":[
        "Klementinas"
    ],
    "name:mrj_x_preferred":[
        "\u041a\u043b\u0435\u043c\u0435\u043d\u0442\u0438\u043d"
    ],
    "name:nld_x_preferred":[
        "Clementine"
    ],
    "name:nno_x_preferred":[
        "Klementin"
    ],
    "name:nor_x_preferred":[
        "Klementin"
    ],
    "name:pcd_x_preferred":[
        "Cl\u00e9mintine"
    ],
    "name:ron_x_preferred":[
        "Clementin\u0103"
    ],
    "name:rus_x_preferred":[
        "\u041a\u043b\u0435\u043c\u0435\u043d\u0442\u0438\u043d"
    ],
    "name:slv_x_preferred":[
        "Klementina"
    ],
    "name:swe_x_preferred":[
        "Clementin"
    ],
    "name:tha_x_preferred":[
        "\u0e04\u0e25\u0e35\u0e40\u0e21\u0e19\u0e44\u0e17\u0e19\u0e4c"
    ],
    "name:udm_x_preferred":[
        "\u041a\u043b\u0435\u043c\u0435\u043d\u0442\u0438\u043d"
    ],
    "name:ukr_x_preferred":[
        "\u041a\u043b\u0435\u043c\u0435\u043d\u0442\u0438\u043d"
    ],
    "name:vie_x_preferred":[
        "Clementine"
    ],
    "name:zho_x_preferred":[
        "\u514b\u91cc\u66fc\u4e01\u7ea2\u6a58"
    ],
    "wof:name":"Clementine",
    "wof:placetype":"locality"
},
  "geometry": {"coordinates":[-72.15000000000001,19.71667],"type":"Point"}
}