{
  "type": "Feature",
  "properties": {
    "gn:admin1_code":"3.0",
    "gn:admin2_code":"3718419.0",
    "gn:asciiname":"La Croix",
    "gn:country_code":"HT",
    "gn:dem":355,
    "gn:feature_class":"P",
    "gn:feature_code":"PPL",
    "gn:name":"La Croix",
    "gn:population":0,
    "gn:timezone":"America/Port-au-Prince",
    "iso:country":"HT",
    "name:fra_x_preferred":[
        "La Croix"
    ],
    "wof:name":"La Croix",
    "wof:placetype":"locality"
},
  "geometry": {"coordinates":[-72.80029999999999,19.9208],"type":"Point"}
}