{
  "type": "Feature",
  "properties": {
    "gn:admin1_code":"3.0",
    "gn:admin2_code":"3718419.0",
    "gn:asciiname":"La Croix",
    "gn:country_code":"HT",
    "gn:dem":355,
    "gn:feature_class":"P",
    "gn:feature_code":"PPL",
    "gn:name":"La Croix",
    "gn:population":0,
    "gn:timezone":"America/Port-au-Prince",
    "iso:country":"HT",
    "name:deu_x_preferred":[
        "La Croix"
    ],
    "name:eus_x_preferred":[
        "La Croix"
    ],
    "name:fra_x_preferred":[
        "La Croix"
    ],
    "name:heb_x_preferred":[
        "\u05dc\u05d4 \u05e7\u05e8\u05d5\u05d0\u05d4"
    ],
    "name:ita_x_preferred":[
        "La Croix"
    ],
    "name:lat_x_preferred":[
        "La Croix"
    ],
    "name:nld_x_preferred":[
        "La Croix"
    ],
    "name:spa_x_preferred":[
        "La Croix"
    ],
    "name:tur_x_preferred":[
        "La Croix"
    ],
    "name:zho_x_preferred":[
        "\u5341\u5b57\u67b6\u62a5"
    ],
    "wof:name":"La Croix",
    "wof:placetype":"locality"
},
  "geometry": {"coordinates":[-72.80029999999999,19.9208],"type":"Point"}
}