{
  "type": "Feature",
  "properties": {
    "gn:admin1_code":"11.0",
    "gn:admin2_code":"3718425.0",
    "gn:asciiname":"Fond Coupeau",
    "gn:country_code":"HT",
    "gn:dem":559,
    "gn:feature_class":"P",
    "gn:feature_code":"PPL",
    "gn:name":"Fond Coupeau",
    "gn:population":0,
    "gn:timezone":"America/Port-au-Prince",
    "iso:country":"HT",
    "name:fra_x_preferred":[
        "Fond Coupeau"
    ],
    "wof:name":"Fond Coupeau",
    "wof:placetype":"locality"
},
  "geometry": {"coordinates":[-72.41365,18.46499],"type":"Point"}
}