{
  "type": "Feature",
  "properties": {
    "gn:admin1_code":"7.0",
    "gn:admin2_code":"3720809.0",
    "gn:asciiname":"Belle Epee",
    "gn:country_code":"HT",
    "gn:dem":969,
    "gn:feature_class":"P",
    "gn:feature_code":"PPL",
    "gn:name":"Belle \u00c9p\u00e9e",
    "gn:population":0,
    "gn:timezone":"America/Port-au-Prince",
    "iso:country":"HT",
    "name:fra_x_preferred":[
        "Belle \u00c9p\u00e9e"
    ],
    "wof:name":"Belle Epee",
    "wof:placetype":"locality"
},
  "geometry": {"coordinates":[-72.18223,18.99434],"type":"Point"}
}