{
  "type": "Feature",
  "properties": {
    "gn:admin1_code":"12.0",
    "gn:admin2_code":"3728096.0",
    "gn:asciiname":"Nan Gouyave",
    "gn:country_code":"HT",
    "gn:dem":19,
    "gn:feature_class":"P",
    "gn:feature_code":"PPL",
    "gn:name":"Nan Gouyave",
    "gn:population":0,
    "gn:timezone":"America/Port-au-Prince",
    "iso:country":"HT",
    "wof:name":"Nan Gouyave",
    "wof:placetype":"locality"
},
  "geometry": {"coordinates":[-73.85639,18.13972],"type":"Point"}
}