{
  "type": "Feature",
  "properties": {
    "gn:admin1_code":"13.0",
    "gn:admin2_code":"3730361.0",
    "gn:asciiname":"Satorfer",
    "gn:country_code":"HT",
    "gn:dem":868,
    "gn:feature_class":"P",
    "gn:feature_code":"PPL",
    "gn:name":"Satorfer",
    "gn:population":0,
    "gn:timezone":"America/Port-au-Prince",
    "iso:country":"HT",
    "name:fra_x_preferred":[
        "Satorfer"
    ],
    "wof:name":"Satorfer",
    "wof:placetype":"locality"
},
  "geometry": {"coordinates":[-72.19291,18.26242],"type":"Point"}
}