{
  "type": "Feature",
  "properties": {
    "gn:admin1_code":"7.0",
    "gn:admin2_code":"3720809.0",
    "gn:asciiname":"Passe Pilon",
    "gn:country_code":"HT",
    "gn:dem":228,
    "gn:feature_class":"P",
    "gn:feature_code":"PPL",
    "gn:name":"Passe Pilon",
    "gn:population":0,
    "gn:timezone":"America/Port-au-Prince",
    "iso:country":"HT",
    "name:fra_x_preferred":[
        "Passe Pilon"
    ],
    "wof:name":"Passe Pilon",
    "wof:placetype":"locality"
},
  "geometry": {"coordinates":[-72.02778000000001,18.75719],"type":"Point"}
}