{
  "type": "Feature",
  "properties": {
    "gn:admin1_code":"14.0",
    "gn:admin2_code":"3723592.0",
    "gn:asciiname":"Courtois",
    "gn:country_code":"HT",
    "gn:dem":-9999,
    "gn:feature_class":"P",
    "gn:feature_code":"PPL",
    "gn:name":"Courtois",
    "gn:population":0,
    "gn:timezone":"America/Port-au-Prince",
    "iso:country":"HT",
    "name:deu_x_preferred":[
        "Courtois"
    ],
    "name:fra_x_preferred":[
        "Courtois"
    ],
    "name:ita_x_preferred":[
        "Courtois"
    ],
    "name:jpn_x_preferred":[
        "\u30af\u30eb\u30c8\u30a5\u30ef"
    ],
    "name:nds_x_preferred":[
        "Courtois"
    ],
    "name:rus_x_preferred":[
        "\u041a\u0443\u0440\u0442\u0443\u0430"
    ],
    "name:spa_x_preferred":[
        "Courtois"
    ],
    "name:tur_x_preferred":[
        "Courtois"
    ],
    "name:ukr_x_preferred":[
        "\u041a\u0443\u0440\u0442\u0443\u0430"
    ],
    "wof:name":"Courtois",
    "wof:placetype":"locality"
},
  "geometry": {"coordinates":[-74.13333,18.66667],"type":"Point"}
}