{
  "type": "Feature",
  "properties": {
    "gn:admin1_code":"6.0",
    "gn:admin2_code":"3726539.0",
    "gn:asciiname":"Pothenot",
    "gn:country_code":"HT",
    "gn:dem":14,
    "gn:feature_class":"P",
    "gn:feature_code":"PPL",
    "gn:name":"Pothenot",
    "gn:population":0,
    "gn:timezone":"America/Port-au-Prince",
    "iso:country":"HT",
    "name:fra_x_preferred":[
        "Pothenot"
    ],
    "wof:name":"Pothenot",
    "wof:placetype":"locality"
},
  "geometry": {"coordinates":[-72.63975000000001,19.23319],"type":"Point"}
}