{
  "type": "Feature",
  "properties": {
    "gn:admin1_code":"11.0",
    "gn:admin2_code":"3718425.0",
    "gn:asciiname":"Cadrien",
    "gn:country_code":"HT",
    "gn:dem":920,
    "gn:feature_class":"P",
    "gn:feature_code":"PPL",
    "gn:name":"Cadrien",
    "gn:population":0,
    "gn:timezone":"America/Port-au-Prince",
    "iso:country":"HT",
    "wof:name":"Cadrien",
    "wof:placetype":"locality"
},
  "geometry": {"coordinates":[-72.26666999999998,18.38333],"type":"Point"}
}