{
  "type": "Feature",
  "properties": {
    "gn:admin1_code":"3.0",
    "gn:admin2_code":"3720764.0",
    "gn:asciiname":"George Callebassier",
    "gn:country_code":"HT",
    "gn:dem":101,
    "gn:feature_class":"P",
    "gn:feature_code":"PPL",
    "gn:name":"George Callebassier",
    "gn:population":0,
    "gn:timezone":"America/Port-au-Prince",
    "iso:country":"HT",
    "name:fra_x_preferred":[
        "George Callebassier"
    ],
    "wof:name":"George Callebassier",
    "wof:placetype":"locality"
},
  "geometry": {"coordinates":[-73.2426,19.69652],"type":"Point"}
}