{
  "type": "Feature",
  "properties": {
    "gn:admin1_code":"6.0",
    "gn:admin2_code":"3724144.0",
    "gn:asciiname":"Nan Nicotte",
    "gn:country_code":"HT",
    "gn:dem":473,
    "gn:feature_class":"P",
    "gn:feature_code":"PPL",
    "gn:name":"Nan Nicotte",
    "gn:population":0,
    "gn:timezone":"America/Port-au-Prince",
    "iso:country":"HT",
    "name:fra_x_preferred":[
        "Nan Nicotte"
    ],
    "wof:name":"Nan Nicotte",
    "wof:placetype":"locality"
},
  "geometry": {"coordinates":[-72.79014000000002,19.60985],"type":"Point"}
}