{
  "type": "Feature",
  "properties": {
    "gn:admin1_code":"3.0",
    "gn:admin2_code":"3717599.0",
    "gn:asciiname":"Liquette",
    "gn:country_code":"HT",
    "gn:dem":139,
    "gn:feature_class":"P",
    "gn:feature_code":"PPL",
    "gn:name":"Liquette",
    "gn:population":0,
    "gn:timezone":"America/Port-au-Prince",
    "iso:country":"HT",
    "name:fra_x_preferred":[
        "Liquette"
    ],
    "wof:name":"Liquette",
    "wof:placetype":"locality"
},
  "geometry": {"coordinates":[-72.65846999999999,19.89915],"type":"Point"}
}