{
  "type": "Feature",
  "properties": {
    "gn:admin1_code":"7.0",
    "gn:admin2_code":"3720809.0",
    "gn:asciiname":"Barbin",
    "gn:country_code":"HT",
    "gn:dem":549,
    "gn:feature_class":"P",
    "gn:feature_code":"PPL",
    "gn:name":"Barbin",
    "gn:population":0,
    "gn:timezone":"America/Port-au-Prince",
    "iso:country":"HT",
    "name:azb_x_preferred":[
        "\u0628\u0627\u0631\u0628\u06cc\u0646"
    ],
    "name:aze_x_preferred":[
        "Barbin"
    ],
    "name:fas_x_preferred":[
        "\u0628\u0627\u0631\u0628\u06cc\u0646"
    ],
    "name:msa_x_preferred":[
        "Barbin"
    ],
    "name:ukr_x_preferred":[
        "\u0411\u0430\u0440\u0431\u0456\u043d"
    ],
    "wof:name":"Barbin",
    "wof:placetype":"locality"
},
  "geometry": {"coordinates":[-72.26666999999998,18.83333],"type":"Point"}
}