{
  "type": "Feature",
  "properties": {
    "gn:admin1_code":"9.0",
    "gn:admin2_code":"3717545.0",
    "gn:asciiname":"Nan Citron",
    "gn:country_code":"HT",
    "gn:dem":860,
    "gn:feature_class":"P",
    "gn:feature_code":"PPL",
    "gn:name":"Nan Citron",
    "gn:population":0,
    "gn:timezone":"America/Port-au-Prince",
    "iso:country":"HT",
    "wof:name":"Nan Citron",
    "wof:placetype":"locality"
},
  "geometry": {"coordinates":[-72.15000000000001,19.43333],"type":"Point"}
}