{
  "type": "Feature",
  "properties": {
    "gn:admin1_code":"3.0",
    "gn:admin2_code":"3718419.0",
    "gn:asciiname":"Tete Rochelle",
    "gn:country_code":"HT",
    "gn:dem":158,
    "gn:feature_class":"P",
    "gn:feature_code":"PPL",
    "gn:name":"T\u00eate Rochelle",
    "gn:population":0,
    "gn:timezone":"America/Port-au-Prince",
    "iso:country":"HT",
    "name:fra_x_preferred":[
        "T\u00eate Rochelle"
    ],
    "wof:name":"Tete Rochelle",
    "wof:placetype":"locality"
},
  "geometry": {"coordinates":[-72.74728,20.04443],"type":"Point"}
}