{
  "type": "Feature",
  "properties": {
    "gn:admin1_code":"12.0",
    "gn:admin2_code":"3718404.0",
    "gn:asciiname":"Mauras",
    "gn:country_code":"HT",
    "gn:dem":197,
    "gn:feature_class":"P",
    "gn:feature_code":"PPL",
    "gn:name":"Mauras",
    "gn:population":0,
    "gn:timezone":"America/Port-au-Prince",
    "iso:country":"HT",
    "wof:name":"Mauras",
    "wof:placetype":"locality"
},
  "geometry": {"coordinates":[-73.92860999999998,18.15944],"type":"Point"}
}