{
  "type": "Feature",
  "properties": {
    "gn:admin1_code":"6.0",
    "gn:admin2_code":"3724695.0",
    "gn:asciiname":"Le Tiro",
    "gn:cc2":"HT",
    "gn:country_code":"HT",
    "gn:dem":29,
    "gn:feature_class":"P",
    "gn:feature_code":"PPL",
    "gn:name":"Le Tiro",
    "gn:population":0,
    "gn:timezone":"America/Port-au-Prince",
    "iso:country":"HT",
    "name:und_x_variant":[
        "Tiro",
        "Le Tiro"
    ],
    "wof:name":"Le Tiro",
    "wof:placetype":"locality"
},
  "geometry": {"coordinates":[-72.61667,19.46667],"type":"Point"}
}