{
  "type": "Feature",
  "properties": {
    "gn:admin1_code":"6.0",
    "gn:admin2_code":"3724695.0",
    "gn:asciiname":"Funel",
    "gn:cc2":"HT",
    "gn:country_code":"HT",
    "gn:dem":136,
    "gn:feature_class":"P",
    "gn:feature_code":"PPL",
    "gn:name":"Funel",
    "gn:population":0,
    "gn:timezone":"America/Port-au-Prince",
    "iso:country":"HT",
    "name:und_x_variant":[
        "Fr\u00e9nel",
        "Funel"
    ],
    "wof:name":"Funel",
    "wof:placetype":"locality"
},
  "geometry": {"coordinates":[-72.61667,19.55],"type":"Point"}
}