{
  "type": "Feature",
  "properties": {
    "gn:admin1_code":"3.0",
    "gn:admin2_code":"3720764.0",
    "gn:asciiname":"Fond Amadou",
    "gn:country_code":"HT",
    "gn:dem":288,
    "gn:feature_class":"P",
    "gn:feature_code":"PPL",
    "gn:name":"Fond Amadou",
    "gn:population":0,
    "gn:timezone":"America/Port-au-Prince",
    "iso:country":"HT",
    "name:und_x_variant":[
        "Fond Amadon",
        "Fond Amadou"
    ],
    "wof:name":"Fond Amadou",
    "wof:placetype":"locality"
},
  "geometry": {"coordinates":[-73.23298,19.84136],"type":"Point"}
}