{
  "type": "Feature",
  "properties": {
    "gn:admin1_code":"3.0",
    "gn:admin2_code":"3720764.0",
    "gn:asciiname":"Labelle",
    "gn:cc2":"HT",
    "gn:country_code":"HT",
    "gn:dem":354,
    "gn:feature_class":"P",
    "gn:feature_code":"PPL",
    "gn:name":"Labelle",
    "gn:population":0,
    "gn:timezone":"America/Port-au-Prince",
    "iso:country":"HT",
    "name:ita_x_preferred":[
        "Labelle"
    ],
    "name:nld_x_preferred":[
        "Labelle"
    ],
    "name:por_x_preferred":[
        "Labelle"
    ],
    "name:rus_x_preferred":[
        "LaBelle"
    ],
    "name:spa_x_preferred":[
        "LaBelle"
    ],
    "name:swe_x_preferred":[
        "Labelle"
    ],
    "name:und_x_variant":[
        "La Belley"
    ],
    "wof:name":"Labelle",
    "wof:placetype":"locality"
},
  "geometry": {"coordinates":[-73.13944000000002,19.75083],"type":"Point"}
}