{
  "type": "Feature",
  "properties": {
    "gn:admin1_code":"14.0",
    "gn:admin2_code":"3731116.0",
    "gn:asciiname":"Litisse",
    "gn:country_code":"HT",
    "gn:dem":166,
    "gn:feature_class":"P",
    "gn:feature_code":"PPL",
    "gn:name":"Litisse",
    "gn:population":0,
    "gn:timezone":"America/Port-au-Prince",
    "iso:country":"HT",
    "wof:name":"Litisse",
    "wof:placetype":"locality"
},
  "geometry": {"coordinates":[-74.43333,18.45],"type":"Point"}
}