{
  "type": "Feature",
  "properties": {
    "gn:admin1_code":"13.0",
    "gn:admin2_code":"3730910.0",
    "gn:asciiname":"Bodor",
    "gn:country_code":"HT",
    "gn:dem":264,
    "gn:feature_class":"P",
    "gn:feature_code":"PPL",
    "gn:name":"Bodor",
    "gn:population":0,
    "gn:timezone":"America/Port-au-Prince",
    "iso:country":"HT",
    "name:fra_x_preferred":[
        "Bodor"
    ],
    "wof:name":"Bodor",
    "wof:placetype":"locality"
},
  "geometry": {"coordinates":[-72.66833000000003,18.2125],"type":"Point"}
}