{
  "type": "Feature",
  "properties": {
    "gn:admin1_code":"3.0",
    "gn:asciiname":"Lanoix",
    "gn:country_code":"HT",
    "gn:dem":86,
    "gn:feature_class":"P",
    "gn:feature_code":"PPL",
    "gn:name":"Lanoix",
    "gn:population":0,
    "gn:timezone":"America/Port-au-Prince",
    "iso:country":"HT",
    "name:und_x_variant":[
        "La Croix"
    ],
    "wof:name":"Lanoix",
    "wof:placetype":"locality"
},
  "geometry": {"coordinates":[-72.60769999999999,19.84817],"type":"Point"}
}