{
  "type": "Feature",
  "properties": {
    "gn:admin1_code":"9.0",
    "gn:admin2_code":"3728473.0",
    "gn:asciiname":"Nandon",
    "gn:country_code":"HT",
    "gn:dem":9,
    "gn:feature_class":"P",
    "gn:feature_code":"PPL",
    "gn:name":"Nandon",
    "gn:population":0,
    "gn:timezone":"America/Port-au-Prince",
    "iso:country":"HT",
    "wof:name":"Nandon",
    "wof:placetype":"locality"
},
  "geometry": {"coordinates":[-72.16667,19.73333],"type":"Point"}
}