{
  "type": "Feature",
  "properties": {
    "gn:admin1_code":"12.0",
    "gn:asciiname":"Sous Fort",
    "gn:country_code":"HT",
    "gn:dem":50,
    "gn:feature_class":"P",
    "gn:feature_code":"PPL",
    "gn:name":"Sous Fort",
    "gn:population":0,
    "gn:timezone":"America/Port-au-Prince",
    "iso:country":"HT",
    "wof:name":"Sous Fort",
    "wof:placetype":"locality"
},
  "geometry": {"coordinates":[-72.98333000000002,18.18333],"type":"Point"}
}