{
  "type": "Feature",
  "properties": {
    "gn:admin1_code":"13.0",
    "gn:admin2_code":"3723778.0",
    "gn:asciiname":"La Gosseline",
    "gn:country_code":"HT",
    "gn:dem":309,
    "gn:feature_class":"P",
    "gn:feature_code":"PPL",
    "gn:name":"La Gosseline",
    "gn:population":0,
    "gn:timezone":"America/Port-au-Prince",
    "iso:country":"HT",
    "name:fra_x_preferred":[
        "La Gosseline"
    ],
    "name:und_x_variant":[
        "Fond Gosseline"
    ],
    "wof:name":"La Gosseline",
    "wof:placetype":"locality"
},
  "geometry": {"coordinates":[-72.43543000000003,18.35455],"type":"Point"}
}