{
  "type": "Feature",
  "properties": {
    "gn:admin1_code":"11.0",
    "gn:admin2_code":"3722285.0",
    "gn:asciiname":"Dejean",
    "gn:country_code":"HT",
    "gn:dem":581,
    "gn:feature_class":"P",
    "gn:feature_code":"PPL",
    "gn:name":"D\u00e9jean",
    "gn:population":0,
    "gn:timezone":"America/Port-au-Prince",
    "iso:country":"HT",
    "wof:name":"Dejean",
    "wof:placetype":"locality"
},
  "geometry": {"coordinates":[-72.53333000000001,18.41667],"type":"Point"}
}