{
  "type": "Feature",
  "properties": {
    "gn:admin1_code":"15.0",
    "gn:asciiname":"Saint-Michel du Sud",
    "gn:country_code":"HT",
    "gn:dem":242,
    "gn:feature_class":"P",
    "gn:feature_code":"PPL",
    "gn:name":"Saint-Michel du Sud",
    "gn:population":0,
    "gn:timezone":"America/Port-au-Prince",
    "iso:country":"HT",
    "name:fra_x_preferred":[
        "Saint-Michel du Sud"
    ],
    "wof:name":"Saint-Michel du Sud",
    "wof:placetype":"locality"
},
  "geometry": {"coordinates":[-73.11671,18.37321],"type":"Point"}
}