{
  "type": "Feature",
  "properties": {
    "gn:admin1_code":"3.0",
    "gn:asciiname":"Etrier Femme",
    "gn:country_code":"HT",
    "gn:dem":-9999,
    "gn:feature_class":"P",
    "gn:feature_code":"PPL",
    "gn:name":"\u00c9trier Femme",
    "gn:population":0,
    "gn:timezone":"America/Port-au-Prince",
    "iso:country":"HT",
    "wof:name":"Etrier Femme",
    "wof:placetype":"locality"
},
  "geometry": {"coordinates":[-72.83333,19.95],"type":"Point"}
}