{
  "type": "Feature",
  "properties": {
    "gn:admin1_code":"6.0",
    "gn:admin2_code":"3724695.0",
    "gn:asciiname":"Cabia",
    "gn:country_code":"HT",
    "gn:dem":538,
    "gn:feature_class":"P",
    "gn:feature_code":"PPL",
    "gn:name":"Cabia",
    "gn:population":0,
    "gn:timezone":"America/Port-au-Prince",
    "iso:country":"HT",
    "wof:name":"Cabia",
    "wof:placetype":"locality"
},
  "geometry": {"coordinates":[-72.40000000000001,19.43333],"type":"Point"}
}