{
  "type": "Feature",
  "properties": {
    "gn:admin1_code":"14.0",
    "gn:admin2_code":"3731116.0",
    "gn:asciiname":"Balandier",
    "gn:country_code":"HT",
    "gn:dem":72,
    "gn:feature_class":"P",
    "gn:feature_code":"PPL",
    "gn:name":"Balandier",
    "gn:population":0,
    "gn:timezone":"America/Port-au-Prince",
    "iso:country":"HT",
    "wof:name":"Balandier",
    "wof:placetype":"locality"
},
  "geometry": {"coordinates":[-74.38333,18.61667000000001],"type":"Point"}
}